Workbook

Sheet Summ
H1: 45689 | AO1: 45717 | BY1: 45748 | DG1: Feb,Mar & Apr 2025 | DN1: 45778 | EX1: 45809 | GG1: 45839 | HQ1: May, Jun & Jul 2025
A2: Sl.No | B2: Name of Products | C2: Actual rate | D2: Sale price | E2: Comm(20%) | F2: Discount | H2: 1 | I2: 2 | J2: 3 | K2: 4 | L2: 5 | M2: 6 | N2: 7 | O2: 8 | P2: 9 | Q2: 10 | R2: 11 | S2: 12 | T2: 13 | U2: 14 | V2: 15 | W2: 16 | X2: 17 | Y2: 18 | Z2: 19 | AA2: 20 | AB2: 21 | AC2: 22 | AD2: 23 | AE2: 24 | AF2: 25 | AG2: 26 | AH2: 27 | AI2: 28 | AJ2: Total Qty | AK2: Total Amount | AL2: Total Comm | AM2: Total Payable | AO2: 1 | AP2: 2 | AQ2: 3 | AR2: 4 | AS2: 5 | AT2: 6 | AU2: 7 | AV2: 8 | AW2: 9 | AX2: 10 | AY2: 11 | AZ2: 12 | BA2: 13 | BB2: 14 | BC2: 15 | BD2: 16 | BE2: 17 | BF2: 18 | BG2: 19 | BH2: 20 | BI2: 21 | BJ2: 22 | BK2: 23 | BL2: 24 | BM2: 25 | BN2: 26 | BO2: 27 | BP2: 28 | BQ2: 29 | BR2: 30 | BS2: 31 | BT2: Total Qty | BU2: Total Amount | BV2: Total Comm | BW2: Total Payable | BY2: 1 | BZ2: 2 | CA2: 3 | CB2: 4 | CC2: 5 | CD2: 6 | CE2: 7 | CF2: 8 | CG2: 9 | CH2: 10 | CI2: 11 | CJ2: 12 | CK2: 13 | CL2: 14 | CM2: 15 | CN2: 16 | CO2: 17 | CP2: 18 | CQ2: 19 | CR2: 20 | CS2: 21 | CT2: 22 | CU2: 23 | CV2: 24 | CW2: 25 | CX2: 26 | CY2: 27 | CZ2: 28 | DA2: 29 | DB2: 30 | DC2: Total Qty | DD2: Total Amount | DE2: Total Comm | DF2: Total Payable | DG2: QTY of F,M&A | DH2: Actual rate | DI2: Sale price | DJ2: Comm(20%) | DK2: Discount | DL2: Amount | DN2: 1 | DO2: 2 | DP2: 3 | DQ2: 4 | DR2: 5 | DS2: 6 | DT2: 7 | DU2: 8 | DV2: 9 | DW2: 10 | DX2: 11 | DY2: 12 | DZ2: 13 | EA2: 14 | EB2: 15 | EC2: 16 | ED2: 17 | EE2: 18 | EF2: 19 | EG2: 20 | EH2: 21 | EI2: 22 | EJ2: 23 | EK2: 24 | EL2: 25 | EM2: 26 | EN2: 27 | EO2: 28 | EP2: 29 | EQ2: 30 | ER2: 31 | ES2: Total Qty | ET2: Total Amount | EU2: Total Comm | EV2: Total Payable | EX2: 1 | EY2: 2 | EZ2: 3 | FA2: 4 | FB2: 5 | FC2: 6 | FD2: 7 | FE2: 8 | FF2: 9 | FG2: 10 | FH2: 11 | FI2: 12 | FJ2: 13 | FK2: 14 | FL2: 15 | FM2: 16 | FN2: 17 | FO2: 18 | FP2: 19 | FQ2: 20 | FR2: 21 | FS2: 22 | FT2: 23 | FU2: 24 | FV2: 25 | FW2: 26 | FX2: 27 | FY2: 28 | FZ2: 29 | GA2: 30 | GB2: Total Qty | GC2: Total Amount | GD2: Total Comm | GE2: Total Payable | GG2: 1 | GH2: 2 | GI2: 3 | GJ2: 4 | GK2: 5 | GL2: 6 | GM2: 7 | GN2: 8 | GO2: 9 | GP2: 10 | GQ2: 11 | GR2: 12 | GS2: 13 | GT2: 14 | GU2: 15 | GV2: 16 | GW2: 17 | GX2: 18 | GY2: 19 | GZ2: 20 | HA2: 21 | HB2: 22 | HC2: 23 | HD2: 24 | HE2: 25 | HF2: 26 | HG2: 27 | HH2: 28 | HI2: 29 | HJ2: 30 | HK2: 31 | HL2: Total Qty | HM2: Total Amount | HN2: Total Comm | HO2: Total Payable | HQ2: QTY of M,J&J | HR2: Actual rate | HS2: Sale price | HT2: Comm(20%) | HU2: Discount | HV2: Amount | IN2: Total Qty | IO2: Total Amount | IP2: Total Comm | IQ2: Total Payable
A3: 1 | B3: Safflower and Cinamon Tea | C3: 300 | D3: 360 | E3: =D3-C3 -> 60 | F3: 10% Discount on every 80 boxes | I3: =PHLY!I3 -> 0 | J3: =PHLY!J3 -> 0 | K3: =PHLY!K3 -> 0 | L3: =PHLY!L3 -> 0 | M3: =PHLY!M3 -> 0 | N3: =PHLY!N3 -> 0 | O3: =PHLY!O3 -> 0 | P3: =PHLY!P3 -> 0 | ... AM3: =PHLY!AM3 -> 0 | AO3: =WANG!H3+PUNA!H3+GELA!H3+ZEMG!H3+TRON!H3+BUMA!H3+SARA!H3+TSIR!H3+DGNA!H3+PANG!H3+DPLA!H3+SJKA!H3+LUNT!H3+SAMC!H3+PHUA!H3+SAMA!H3+GMTU!H3+PHLY!AO3 -> 0 | AP3: =WANG!I3+PUNA!I3+GELA!I3+ZEMG!I3+TRON!I3+BUMA!I3+SARA!I3+TSIR!I3+DGNA!I3+PANG!I3+DPLA!I3+SJKA!I3+LUNT!I3+SAMC!I3+PHUA!I3+SAMA!I3+GMTU!I3+PHLY!AP3 -> 0 | AQ3: =WANG!J3+PUNA!J3+GELA!J3+ZEMG!J3+TRON!J3+BUMA!J3+SARA!J3+TSIR!J3+DGNA!J3+PANG!J3+DPLA!J3+SJKA!J3+LUNT!J3+SAMC!J3+PHUA!J3+SAMA!J3+GMTU!J3+PHLY!AQ3 -> 0 | AR3: =WANG!K3+PUNA!K3+GELA!K3+ZEMG!K3+TRON!K3+BUMA!K3+SARA!K3+TSIR!K3+DGNA!K3+PANG!K3+DPLA!K3+SJKA!K3+LUNT!K3+SAMC!K3+PHUA!K3+SAMA!K3+GMTU!K3+PHLY!AR3 -> 1 | AS3: =WANG!L3+PUNA!L3+GELA!L3+ZEMG!L3+TRON!L3+BUMA!L3+SARA!L3+TSIR!L3+DGNA!L3+PANG!L3+DPLA!L3+SJKA!L3+LUNT!L3+SAMC!L3+PHUA!L3+SAMA!L3+GMTU!L3+PHLY!AS3 -> 0 | AT3: =WANG!M3+PUNA!M3+GELA!M3+ZEMG!M3+TRON!M3+BUMA!M3+SARA!M3+TSIR!M3+DGNA!M3+PANG!M3+DPLA!M3+SJKA!M3+LUNT!M3+SAMC!M3+PHUA!M3+SAMA!M3+GMTU!M3+PHLY!AT3 -> 0 | AU3: =WANG!N3+PUNA!N3+GELA!N3+ZEMG!N3+TRON!N3+BUMA!N3+SARA!N3+TSIR!N3+DGNA!N3+PANG!N3+DPLA!N3+SJKA!N3+LUNT!N3+SAMC!N3+PHUA!N3+SAMA!N3+GMTU!N3+PHLY!AU3 -> 1 | AV3: =WANG!O3+PUNA!O3+GELA!O3+ZEMG!O3+TRON!O3+BUMA!O3+SARA!O3+TSIR!O3+DGNA!O3+PANG!O3+DPLA!O3+SJKA!O3+LUNT!O3+SAMC!O3+PHUA!O3+SAMA!O3+GMTU!O3+PHLY!AV3 -> 0 | ... BW3: =WANG!AP3+PUNA!AP3+GELA!AP3+ZEMG!AP3+TRON!AP3+BUMA!AP3+SARA!AP3+TSIR!AP3+DGNA!AP3+PANG!AP3+DPLA!AP3+SJKA!AP3+LUNT!AP3+SAMC!AP3+PHUA!AP3+SAMA!AP3+GMTU!AP3+PHLY!BW3 -> 10800 | BY3: =HAA!H3+WANG!AR3+PUNA!AR3+GASA!H3+GELA!AR3+ZEMG!AR3+TRON!AR3+BUMA!AR3+SARA!AR3+TSIR!AR3+DGNA!AR3+PANG!AR3+DPLA!AR3+SJKA!AR3+TRAG!H3+LUNT!AR3+WRMG!H3+NGLM!H3+SAMC!AR3+PHUA!AR3+GEDU!H3+SAMA!AR3+TCHG!H3+GMTU!AR3+PHLY!BY3 -> 3 | BZ3: =HAA!I3+WANG!AS3+PUNA!AS3+GASA!I3+GELA!AS3+ZEMG!AS3+TRON!AS3+BUMA!AS3+SARA!AS3+TSIR!AS3+DGNA!AS3+PANG!AS3+DPLA!AS3+SJKA!AS3+TRAG!I3+LUNT!AS3+WRMG!I3+NGLM!I3+SAMC!AS3+PHUA!AS3+GEDU!I3+SAMA!AS3+TCHG!I3+GMTU!AS3+PHLY!BZ3 -> 0 | CA3: =HAA!J3+WANG!AT3+PUNA!AT3+GASA!J3+GELA!AT3+ZEMG!AT3+TRON!AT3+BUMA!AT3+SARA!AT3+TSIR!AT3+DGNA!AT3+PANG!AT3+DPLA!AT3+SJKA!AT3+TRAG!J3+LUNT!AT3+WRMG!J3+NGLM!J3+SAMC!AT3+PHUA!AT3+GEDU!J3+SAMA!AT3+TCHG!J3+GMTU!AT3+PHLY!CA3 -> 2 | CB3: =HAA!K3+WANG!AU3+PUNA!AU3+GASA!K3+GELA!AU3+ZEMG!AU3+TRON!AU3+BUMA!AU3+SARA!AU3+TSIR!AU3+DGNA!AU3+PANG!AU3+DPLA!AU3+SJKA!AU3+TRAG!K3+LUNT!AU3+WRMG!K3+NGLM!K3+SAMC!AU3+PHUA!AU3+GEDU!K3+SAMA!AU3+TCHG!K3+GMTU!AU3+PHLY!CB3 -> 0 | CC3: =HAA!L3+WANG!AV3+PUNA!AV3+GASA!L3+GELA!AV3+ZEMG!AV3+TRON!AV3+BUMA!AV3+SARA!AV3+TSIR!AV3+DGNA!AV3+PANG!AV3+DPLA!AV3+SJKA!AV3+TRAG!L3+LUNT!AV3+WRMG!L3+NGLM!L3+SAMC!AV3+PHUA!AV3+GEDU!L3+SAMA!AV3+TCHG!L3+GMTU!AV3+PHLY!CC3 -> 0 | CD3: =HAA!M3+WANG!AW3+PUNA!AW3+GASA!M3+GELA!AW3+ZEMG!AW3+TRON!AW3+BUMA!AW3+SARA!AW3+TSIR!AW3+DGNA!AW3+PANG!AW3+DPLA!AW3+SJKA!AW3+TRAG!M3+LUNT!AW3+WRMG!M3+NGLM!M3+SAMC!AW3+PHUA!AW3+GEDU!M3+SAMA!AW3+TCHG!M3+GMTU!AW3+PHLY!CD3 -> 0 | CE3: =HAA!N3+WANG!AX3+PUNA!AX3+GASA!N3+GELA!AX3+ZEMG!AX3+TRON!AX3+BUMA!AX3+SARA!AX3+TSIR!AX3+DGNA!AX3+PANG!AX3+DPLA!AX3+SJKA!AX3+TRAG!N3+LUNT!AX3+WRMG!N3+NGLM!N3+SAMC!AX3+PHUA!AX3+GEDU!N3+SAMA!AX3+TCHG!N3+GMTU!AX3+PHLY!CE3 -> 1 | CF3: =HAA!O3+WANG!AY3+PUNA!AY3+GASA!O3+GELA!AY3+ZEMG!AY3+TRON!AY3+BUMA!AY3+SARA!AY3+TSIR!AY3+DGNA!AY3+PANG!AY3+DPLA!AY3+SJKA!AY3+TRAG!O3+LUNT!AY3+WRMG!O3+NGLM!O3+SAMC!AY3+PHUA!AY3+GEDU!O3+SAMA!AY3+TCHG!O3+GMTU!AY3+PHLY!CF3 -> 1 | ... DF3: =HAA!AO3+WANG!BY3+PUNA!BY3+GASA!AO3+GELA!BY3+ZEMG!BY3+TRON!BY3+BUMA!BY3+SARA!BY3+TSIR!BY3+DGNA!BY3+PANG!BY3+DPLA!BY3+SJKA!BY3+TRAG!AO3+LUNT!BY3+WRMG!AO3+NGLM!AO3+SAMC!BY3+PHUA!BY3+GEDU!AO3+SAMA!BY3+TCHG!AO3+GMTU!BY3+PHLY!DF3 -> 11400 | DG3: =AJ3+BT3+DC3 -> 74 | DH3: =C3*DG3 -> 22200 | DI3: =D3*DG3 -> 26640 | DJ3: =E3*DG3 -> 4440 | DK3: 30 | DL3: =DG3*DK3 -> 2220 | DN3: =PARO!H3+HAA!AQ3+WANG!CA3+PUNA!CA3+GASA!AQ3+GELA!CA3+ZEMG!CA3+TRON!CA3+BUMA!CA3+SARA!CA3+TSIR!CA3+DGNA!CA3+PANG!CA3+DPLA!CA3+SJKA!CA3+TRAG!AQ3+MONA!H3+LUNT!CA3+TYSE!H3+PEMA!H3+KNLG!H3+RJNG!H3+WRMG!AQ3+DUSM!H3+GYPG!H3+NGLM!AQ3+SAMC!CA3+PHUA!CA3+TSMA!H3+GEDU!AQ3+SAMA!CA3+TCHG!AQ3+GMTU!CA3+LHAM!H3+PHLY!DH3 -> 0 | DO3: =PARO!I3+HAA!AR3+WANG!CB3+PUNA!CB3+GASA!AR3+GELA!CB3+ZEMG!CB3+TRON!CB3+BUMA!CB3+SARA!CB3+TSIR!CB3+DGNA!CB3+PANG!CB3+DPLA!CB3+SJKA!CB3+TRAG!AR3+MONA!I3+LUNT!CB3+TYSE!I3+PEMA!I3+KNLG!I3+RJNG!I3+WRMG!AR3+DUSM!I3+GYPG!I3+NGLM!AR3+SAMC!CB3+PHUA!CB3+TSMA!I3+GEDU!AR3+SAMA!CB3+TCHG!AR3+GMTU!CB3+LHAM!I3+PHLY!DI3 -> 0 | DP3: =PARO!J3+HAA!AS3+WANG!CC3+PUNA!CC3+GASA!AS3+GELA!CC3+ZEMG!CC3+TRON!CC3+BUMA!CC3+SARA!CC3+TSIR!CC3+DGNA!CC3+PANG!CC3+DPLA!CC3+SJKA!CC3+TRAG!AS3+MONA!J3+LUNT!CC3+TYSE!J3+PEMA!J3+KNLG!J3+RJNG!J3+WRMG!AS3+DUSM!J3+GYPG!J3+NGLM!AS3+SAMC!CC3+PHUA!CC3+TSMA!J3+GEDU!AS3+SAMA!CC3+TCHG!AS3+GMTU!CC3+LHAM!J3+PHLY!DJ3 -> 0 | DQ3: =PARO!K3+HAA!AT3+WANG!CD3+PUNA!CD3+GASA!AT3+GELA!CD3+ZEMG!CD3+TRON!CD3+BUMA!CD3+SARA!CD3+TSIR!CD3+DGNA!CD3+PANG!CD3+DPLA!CD3+SJKA!CD3+TRAG!AT3+MONA!K3+LUNT!CD3+TYSE!K3+PEMA!K3+KNLG!K3+RJNG!K3+WRMG!AT3+DUSM!K3+GYPG!K3+NGLM!AT3+SAMC!CD3+PHUA!CD3+TSMA!K3+GEDU!AT3+SAMA!CD3+TCHG!AT3+GMTU!CD3+LHAM!K3+PHLY!DK3 -> 0 | DR3: =PARO!L3+HAA!AU3+WANG!CE3+PUNA!CE3+GASA!AU3+GELA!CE3+ZEMG!CE3+TRON!CE3+BUMA!CE3+SARA!CE3+TSIR!CE3+DGNA!CE3+PANG!CE3+DPLA!CE3+SJKA!CE3+TRAG!AU3+MONA!L3+LUNT!CE3+TYSE!L3+PEMA!L3+KNLG!L3+RJNG!L3+WRMG!AU3+DUSM!L3+GYPG!L3+NGLM!AU3+SAMC!CE3+PHUA!CE3+TSMA!L3+GEDU!AU3+SAMA!CE3+TCHG!AU3+GMTU!CE3+LHAM!L3+PHLY!DL3 -> 3 | DS3: =PARO!M3+HAA!AV3+WANG!CF3+PUNA!CF3+GASA!AV3+GELA!CF3+ZEMG!CF3+TRON!CF3+BUMA!CF3+SARA!CF3+TSIR!CF3+DGNA!CF3+PANG!CF3+DPLA!CF3+SJKA!CF3+TRAG!AV3+MONA!M3+LUNT!CF3+TYSE!M3+PEMA!M3+KNLG!M3+RJNG!M3+WRMG!AV3+DUSM!M3+GYPG!M3+NGLM!AV3+SAMC!CF3+PHUA!CF3+TSMA!M3+GEDU!AV3+SAMA!CF3+TCHG!AV3+GMTU!CF3+LHAM!M3+PHLY!DM3 -> 12 | DT3: =PARO!N3+HAA!AW3+WANG!CG3+PUNA!CG3+GASA!AW3+GELA!CG3+ZEMG!CG3+TRON!CG3+BUMA!CG3+SARA!CG3+TSIR!CG3+DGNA!CG3+PANG!CG3+DPLA!CG3+SJKA!CG3+TRAG!AW3+MONA!N3+LUNT!CG3+TYSE!N3+PEMA!N3+KNLG!N3+RJNG!N3+WRMG!AW3+DUSM!N3+GYPG!N3+NGLM!AW3+SAMC!CG3+PHUA!CG3+TSMA!N3+GEDU!AW3+SAMA!CG3+TCHG!AW3+GMTU!CG3+LHAM!N3+PHLY!DN3 -> 0 | DU3: =PARO!O3+HAA!AX3+WANG!CH3+PUNA!CH3+GASA!AX3+GELA!CH3+ZEMG!CH3+TRON!CH3+BUMA!CH3+SARA!CH3+TSIR!CH3+DGNA!CH3+PANG!CH3+DPLA!CH3+SJKA!CH3+TRAG!AX3+MONA!O3+LUNT!CH3+TYSE!O3+PEMA!O3+KNLG!O3+RJNG!O3+WRMG!AX3+DUSM!O3+GYPG!O3+NGLM!AX3+SAMC!CH3+PHUA!CH3+TSMA!O3+GEDU!AX3+SAMA!CH3+TCHG!AX3+GMTU!CH3+LHAM!O3+PHLY!DO3 -> 0 | ... EV3: =PARO!AP3+HAA!BY3+WANG!DI3+PUNA!DI3+GASA!BY3+GELA!DI3+ZEMG!DI3+TRON!DI3+BUMA!DI3+SARA!DI3+TSIR!DI3+DGNA!DI3+PANG!DI3+DPLA!DI3+SJKA!DI3+TRAG!BY3+MONA!AP3+LUNT!DI3+TYSE!AP3+PEMA!AP3+KNLG!AP3+RJNG!AP3+WRMG!BY3+DUSM!AP3+GYPG!AP3+NGLM!BY3+SAMC!DI3+PHUA!DI3+TSMA!AP3+GEDU!BY3+SAMA!DI3+TCHG!BY3+GMTU!DI3+LHAM!AP3+PHLY!EP3 -> 9300 | EX3: =PARO!AR3+HAA!CA3+WANG!DK3+PUNA!DK3+GASA!CA3+GELA!DK3+ZEMG!DK3+TRON!DK3+BUMA!DK3+SARA!DK3+TSIR!DK3+DGNA!DK3+PANG!DK3+DPLA!DK3+SJKA!DK3+TRAG!CA3+MONA!AR3+LUNT!DK3+TYSE!AR3+PEMA!AR3+KNLG!AR3+RJNG!AR3+WRMG!CA3+DUSM!AR3+GYPG!AR3+NGLM!CA3+SAMC!DK3+PHUA!DK3+TSMA!AR3+GEDU!CA3+SAMA!DK3+TCHG!CA3+GMTU!DK3+LHAM!AR3+PHLY!ER3 -> 0 | EY3: =PARO!AS3+HAA!CB3+WANG!DL3+PUNA!DL3+GASA!CB3+GELA!DL3+ZEMG!DL3+TRON!DL3+BUMA!DL3+SARA!DL3+TSIR!DL3+DGNA!DL3+PANG!DL3+DPLA!DL3+SJKA!DL3+TRAG!CB3+MONA!AS3+LUNT!DL3+TYSE!AS3+PEMA!AS3+KNLG!AS3+RJNG!AS3+WRMG!CB3+DUSM!AS3+GYPG!AS3+NGLM!CB3+SAMC!DL3+PHUA!DL3+TSMA!AS3+GEDU!CB3+SAMA!DL3+TCHG!CB3+GMTU!DL3+LHAM!AS3+PHLY!ES3 -> 0 | EZ3: =PARO!AT3+HAA!CC3+WANG!DM3+PUNA!DM3+GASA!CC3+GELA!DM3+ZEMG!DM3+TRON!DM3+BUMA!DM3+SARA!DM3+TSIR!DM3+DGNA!DM3+PANG!DM3+DPLA!DM3+SJKA!DM3+TRAG!CC3+MONA!AT3+LUNT!DM3+TYSE!AT3+PEMA!AT3+KNLG!AT3+RJNG!AT3+WRMG!CC3+DUSM!AT3+GYPG!AT3+NGLM!CC3+SAMC!DM3+PHUA!DM3+TSMA!AT3+GEDU!CC3+SAMA!DM3+TCHG!CC3+GMTU!DM3+LHAM!AT3+PHLY!ET3 -> 2 | FA3: =PARO!AU3+HAA!CD3+WANG!DN3+PUNA!DN3+GASA!CD3+GELA!DN3+ZEMG!DN3+TRON!DN3+BUMA!DN3+SARA!DN3+TSIR!DN3+DGNA!DN3+PANG!DN3+DPLA!DN3+SJKA!DN3+TRAG!CD3+MONA!AU3+LUNT!DN3+TYSE!AU3+PEMA!AU3+KNLG!AU3+RJNG!AU3+WRMG!CD3+DUSM!AU3+GYPG!AU3+NGLM!CD3+SAMC!DN3+PHUA!DN3+TSMA!AU3+GEDU!CD3+SAMA!DN3+TCHG!CD3+GMTU!DN3+LHAM!AU3+PHLY!EU3 -> 2 | FB3: =PARO!AV3+HAA!CE3+WANG!DO3+PUNA!DO3+GASA!CE3+GELA!DO3+ZEMG!DO3+TRON!DO3+BUMA!DO3+SARA!DO3+TSIR!DO3+DGNA!DO3+PANG!DO3+DPLA!DO3+SJKA!DO3+TRAG!CE3+MONA!AV3+LUNT!DO3+TYSE!AV3+PEMA!AV3+KNLG!AV3+RJNG!AV3+WRMG!CE3+DUSM!AV3+GYPG!AV3+NGLM!CE3+SAMC!DO3+PHUA!DO3+TSMA!AV3+GEDU!CE3+SAMA!DO3+TCHG!CE3+GMTU!DO3+LHAM!AV3+PHLY!EV3 -> 2 | FC3: =PARO!AW3+HAA!CF3+WANG!DP3+PUNA!DP3+GASA!CF3+GELA!DP3+ZEMG!DP3+TRON!DP3+BUMA!DP3+SARA!DP3+TSIR!DP3+DGNA!DP3+PANG!DP3+DPLA!DP3+SJKA!DP3+TRAG!CF3+MONA!AW3+LUNT!DP3+TYSE!AW3+PEMA!AW3+KNLG!AW3+RJNG!AW3+WRMG!CF3+DUSM!AW3+GYPG!AW3+NGLM!CF3+SAMC!DP3+PHUA!DP3+TSMA!AW3+GEDU!CF3+SAMA!DP3+TCHG!CF3+GMTU!DP3+LHAM!AW3+PHLY!EW3 -> 0 | FD3: =PARO!AX3+HAA!CG3+WANG!DQ3+PUNA!DQ3+GASA!CG3+GELA!DQ3+ZEMG!DQ3+TRON!DQ3+BUMA!DQ3+SARA!DQ3+TSIR!DQ3+DGNA!DQ3+PANG!DQ3+DPLA!DQ3+SJKA!DQ3+TRAG!CG3+MONA!AX3+LUNT!DQ3+TYSE!AX3+PEMA!AX3+KNLG!AX3+RJNG!AX3+WRMG!CG3+DUSM!AX3+GYPG!AX3+NGLM!CG3+SAMC!DQ3+PHUA!DQ3+TSMA!AX3+GEDU!CG3+SAMA!DQ3+TCHG!CG3+GMTU!DQ3+LHAM!AX3+PHLY!EX3 -> 7 | FE3: =PARO!AY3+HAA!CH3+WANG!DR3+PUNA!DR3+GASA!CH3+GELA!DR3+ZEMG!DR3+TRON!DR3+BUMA!DR3+SARA!DR3+TSIR!DR3+DGNA!DR3+PANG!DR3+DPLA!DR3+SJKA!DR3+TRAG!CH3+MONA!AY3+LUNT!DR3+TYSE!AY3+PEMA!AY3+KNLG!AY3+RJNG!AY3+WRMG!CH3+DUSM!AY3+GYPG!AY3+NGLM!CH3+SAMC!DR3+PHUA!DR3+TSMA!AY3+GEDU!CH3+SAMA!DR3+TCHG!CH3+GMTU!DR3+LHAM!AY3+PHLY!EY3 -> 0 | ... GA3: =PARO!BU3+HAA!DD3+WANG!EN3+PUNA!EN3+GASA!DD3+GELA!EN3+ZEMG!EN3+TRON!EN3+BUMA!EN3+SARA!EN3+TSIR!EN3+DGNA!EN3+PANG!EN3+DPLA!EN3+SJKA!EN3+TRAG!DD3+MONA!BU3+LUNT!EN3+TYSE!BU3+PEMA!BU3+KNLG!BU3+RJNG!BU3+WRMG!DD3+DUSM!BU3+GYPG!BU3+NGLM!DD3+SAMC!EN3+PHUA!EN3+TSMA!BU3+GEDU!DD3+SAMA!EN3+TCHG!DD3+GMTU!EN3+LHAM!BU3+PHLY!FU3 -> 0 | GB3: =PARO!BV3+HAA!DE3+WANG!EO3+PUNA!EO3+GASA!DE3+GELA!EO3+ZEMG!EO3+TRON!EO3+BUMA!EO3+SARA!EO3+TSIR!EO3+DGNA!EO3+PANG!EO3+DPLA!EO3+SJKA!EO3+TRAG!DE3+MONA!BW3+LUNT!EO3+TYSE!BW3+PEMA!BW3+KNLG!BW3+RJNG!BV3+WRMG!DE3+DUSM!BW3+GYPG!BW3+NGLM!DE3+SAMC!EO3+PHUA!EO3+TSMA!BV3+GEDU!DE3+SAMA!EO3+TCHG!DE3+GMTU!EO3+LHAM!BV3+PHLY!FV3 -> 26 | GC3: =PARO!BW3+HAA!DF3+WANG!EP3+PUNA!EP3+GASA!DF3+GELA!EP3+ZEMG!EP3+TRON!EP3+BUMA!EP3+SARA!EP3+TSIR!EP3+DGNA!EP3+PANG!EP3+DPLA!EP3+SJKA!EP3+TRAG!DF3+MONA!BX3+LUNT!EP3+TYSE!BX3+PEMA!BX3+KNLG!BX3+RJNG!BW3+WRMG!DF3+DUSM!BX3+GYPG!BX3+NGLM!DF3+SAMC!EP3+PHUA!EP3+TSMA!BW3+GEDU!DF3+SAMA!EP3+TCHG!DF3+GMTU!EP3+LHAM!BW3+PHLY!FW3 -> 9360 | GD3: =PARO!BX3+HAA!DG3+WANG!EQ3+PUNA!EQ3+GASA!DG3+GELA!EQ3+ZEMG!EQ3+TRON!EQ3+BUMA!EQ3+SARA!EQ3+TSIR!EQ3+DGNA!EQ3+PANG!EQ3+DPLA!EQ3+SJKA!EQ3+TRAG!DG3+MONA!BY3+LUNT!EQ3+TYSE!BY3+PEMA!BY3+KNLG!BY3+RJNG!BX3+WRMG!DG3+DUSM!BY3+GYPG!BY3+NGLM!DG3+SAMC!EQ3+PHUA!EQ3+TSMA!BX3+GEDU!DG3+SAMA!EQ3+TCHG!DG3+GMTU!EQ3+LHAM!BX3+PHLY!FX3 -> 1560 | GE3: =PARO!BY3+HAA!DH3+WANG!ER3+PUNA!ER3+GASA!DH3+GELA!ER3+ZEMG!ER3+TRON!ER3+BUMA!ER3+SARA!ER3+TSIR!ER3+DGNA!ER3+PANG!ER3+DPLA!ER3+SJKA!ER3+TRAG!DH3+MONA!BZ3+LUNT!ER3+TYSE!BZ3+PEMA!BZ3+KNLG!BZ3+RJNG!BY3+WRMG!DH3+DUSM!BZ3+GYPG!BZ3+NGLM!DH3+SAMC!ER3+PHUA!ER3+TSMA!BY3+GEDU!DH3+SAMA!ER3+TCHG!DH3+GMTU!ER3+LHAM!BY3+PHLY!FY3 -> 7800 | GG3: =PARO!CA3+HAA!DJ3+WANG!ET3+PUNA!ET3+GASA!DJ3+GELA!ET3+ZEMG!ET3+TRON!ET3+BUMA!ET3+SARA!ET3+TSIR!ET3+DGNA!ET3+PANG!ET3+DPLA!ET3+SJKA!ET3+TRAG!DJ3+MONA!CB3+LUNT!ET3+TYSE!CB3+PEMA!CB3+KNLG!CB3+RJNG!CA3+WRMG!DJ3+DUSM!CB3+GYPG!CB3+NGLM!DJ3+SAMC!ET3+PHUA!ET3+TSMA!CA3+GEDU!DJ3+SAMA!ET3+TCHG!DJ3+GMTU!ET3+LHAM!CA3+PHLY!GA3 -> 0 | GH3: =PARO!CB3+HAA!DK3+WANG!EU3+PUNA!EU3+GASA!DK3+GELA!EU3+ZEMG!EU3+TRON!EU3+BUMA!EU3+SARA!EU3+TSIR!EU3+DGNA!EU3+PANG!EU3+DPLA!EU3+SJKA!EU3+TRAG!DK3+MONA!CC3+LUNT!EU3+TYSE!CC3+PEMA!CC3+KNLG!CC3+RJNG!CB3+WRMG!DK3+DUSM!CC3+GYPG!CC3+NGLM!DK3+SAMC!EU3+PHUA!EU3+TSMA!CB3+GEDU!DK3+SAMA!EU3+TCHG!DK3+GMTU!EU3+LHAM!CB3+PHLY!GB3 -> 0 | GI3: =PARO!CC3+HAA!DL3+WANG!EV3+PUNA!EV3+GASA!DL3+GELA!EV3+ZEMG!EV3+TRON!EV3+BUMA!EV3+SARA!EV3+TSIR!EV3+DGNA!EV3+PANG!EV3+DPLA!EV3+SJKA!EV3+TRAG!DL3+MONA!CD3+LUNT!EV3+TYSE!CD3+PEMA!CD3+KNLG!CD3+RJNG!CC3+WRMG!DL3+DUSM!CD3+GYPG!CD3+NGLM!DL3+SAMC!EV3+PHUA!EV3+TSMA!CC3+GEDU!DL3+SAMA!EV3+TCHG!DL3+GMTU!EV3+LHAM!CC3+PHLY!GC3 -> 2 | GJ3: =PARO!CD3+HAA!DM3+WANG!EW3+PUNA!EW3+GASA!DM3+GELA!EW3+ZEMG!EW3+TRON!EW3+BUMA!EW3+SARA!EW3+TSIR!EW3+DGNA!EW3+PANG!EW3+DPLA!EW3+SJKA!EW3+TRAG!DM3+MONA!CE3+LUNT!EW3+TYSE!CE3+PEMA!CE3+KNLG!CE3+RJNG!CD3+WRMG!DM3+DUSM!CE3+GYPG!CE3+NGLM!DM3+SAMC!EW3+PHUA!EW3+TSMA!CD3+GEDU!DM3+SAMA!EW3+TCHG!DM3+GMTU!EW3+LHAM!CD3+PHLY!GD3 -> 2 | GK3: =PARO!CE3+HAA!DN3+WANG!EX3+PUNA!EX3+GASA!DN3+GELA!EX3+ZEMG!EX3+TRON!EX3+BUMA!EX3+SARA!EX3+TSIR!EX3+DGNA!EX3+PANG!EX3+DPLA!EX3+SJKA!EX3+TRAG!DN3+MONA!CF3+LUNT!EX3+TYSE!CF3+PEMA!CF3+KNLG!CF3+RJNG!CE3+WRMG!DN3+DUSM!CF3+GYPG!CF3+NGLM!DN3+SAMC!EX3+PHUA!EX3+TSMA!CE3+GEDU!DN3+SAMA!EX3+TCHG!DN3+GMTU!EX3+LHAM!CE3+PHLY!GE3 -> 0 | GL3: =PARO!CF3+HAA!DO3+WANG!EY3+PUNA!EY3+GASA!DO3+GELA!EY3+ZEMG!EY3+TRON!EY3+BUMA!EY3+SARA!EY3+TSIR!EY3+DGNA!EY3+PANG!EY3+DPLA!EY3+SJKA!EY3+TRAG!DO3+MONA!CG3+LUNT!EY3+TYSE!CG3+PEMA!CG3+KNLG!CG3+RJNG!CF3+WRMG!DO3+DUSM!CG3+GYPG!CG3+NGLM!DO3+SAMC!EY3+PHUA!EY3+TSMA!CF3+GEDU!DO3+SAMA!EY3+TCHG!DO3+GMTU!EY3+LHAM!CF3+PHLY!GF3 -> 0 | GM3: =PARO!CG3+HAA!DP3+WANG!EZ3+PUNA!EZ3+GASA!DP3+GELA!EZ3+ZEMG!EZ3+TRON!EZ3+BUMA!EZ3+SARA!EZ3+TSIR!EZ3+DGNA!EZ3+PANG!EZ3+DPLA!EZ3+SJKA!EZ3+TRAG!DP3+MONA!CH3+LUNT!EZ3+TYSE!CH3+PEMA!CH3+KNLG!CH3+RJNG!CG3+WRMG!DP3+DUSM!CH3+GYPG!CH3+NGLM!DP3+SAMC!EZ3+PHUA!EZ3+TSMA!CG3+GEDU!DP3+SAMA!EZ3+TCHG!DP3+GMTU!EZ3+LHAM!CG3+PHLY!GG3 -> 0 | GN3: =PARO!CH3+HAA!DQ3+WANG!FA3+PUNA!FA3+GASA!DQ3+GELA!FA3+ZEMG!FA3+TRON!FA3+BUMA!FA3+SARA!FA3+TSIR!FA3+DGNA!FA3+PANG!FA3+DPLA!FA3+SJKA!FA3+TRAG!DQ3+MONA!CI3+LUNT!FA3+TYSE!CI3+PEMA!CI3+KNLG!CI3+RJNG!CH3+WRMG!DQ3+DUSM!CI3+GYPG!CI3+NGLM!DQ3+SAMC!FA3+PHUA!FA3+TSMA!CH3+GEDU!DQ3+SAMA!FA3+TCHG!DQ3+GMTU!FA3+LHAM!CH3+PHLY!GH3 -> 0 | ... HO3: =PARO!DI3+HAA!ER3+WANG!GB3+PUNA!GB3+GASA!ER3+GELA!GB3+ZEMG!GB3+TRON!GB3+BUMA!GB3+SARA!GB3+TSIR!GB3+DGNA!GB3+PANG!GB3+DPLA!GB3+SJKA!GB3+TRAG!ER3+MONA!DJ3+LUNT!GB3+TYSE!DJ3+PEMA!DJ3+KNLG!DJ3+RJNG!DI3+WRMG!ER3+DUSM!DJ3+GYPG!DJ3+NGLM!ER3+SAMC!GB3+PHUA!GB3+TSMA!DI3+GEDU!ER3+SAMA!GB3+TCHG!ER3+GMTU!GB3+LHAM!DI3+PHLY!HI3 -> 3900 | HQ3: =ES3+GB3+HL3 -> 70 | HR3: =C3*HQ3 -> 21000 | HS3: =D3*HQ3 -> 25200 | HT3: =E3*HQ3 -> 4200 | HU3: 30 | HV3: =HQ3*HU3 -> 2100 | IN3: =AJ3+BT3+DC3+ES3+GB3+HL3 -> 144 | IO3: =AK3+BU3+DD3+ET3+GC3+HM3 -> 51840 | IP3: =AL3+BV3+DE3+EU3+GD3+HN3 -> 8640 | IQ3: =AM3+BW3+DF3+EV3+GE3+HO3 -> 43200 | IR3: =SUM(IN3:IN6) -> 566
A4: 2 | B4: Himalayan Gooseberry tea | C4: 300 | D4: 360 | E4: =D4-C4 -> 60 | I4: =PHLY!I4 -> 0 | J4: =PHLY!J4 -> 0 | K4: =PHLY!K4 -> 0 | L4: =PHLY!L4 -> 0 | M4: =PHLY!M4 -> 0 | N4: =PHLY!N4 -> 0 | O4: =PHLY!O4 -> 0 | P4: =PHLY!P4 -> 0 | ... AM4: =PHLY!AM4 -> 600 | AO4: =WANG!H4+PUNA!H4+GELA!H4+ZEMG!H4+TRON!H4+BUMA!H4+SARA!H4+TSIR!H4+DGNA!H4+PANG!H4+DPLA!H4+SJKA!H4+LUNT!H4+SAMC!H4+PHUA!H4+SAMA!H4+GMTU!H4+PHLY!AO4 -> 0 | AP4: =WANG!I4+PUNA!I4+GELA!I4+ZEMG!I4+TRON!I4+BUMA!I4+SARA!I4+TSIR!I4+DGNA!I4+PANG!I4+DPLA!I4+SJKA!I4+LUNT!I4+SAMC!I4+PHUA!I4+SAMA!I4+GMTU!I4+PHLY!AP4 -> 0 | AQ4: =WANG!J4+PUNA!J4+GELA!J4+ZEMG!J4+TRON!J4+BUMA!J4+SARA!J4+TSIR!J4+DGNA!J4+PANG!J4+DPLA!J4+SJKA!J4+LUNT!J4+SAMC!J4+PHUA!J4+SAMA!J4+GMTU!J4+PHLY!AQ4 -> 0 | AR4: =WANG!K4+PUNA!K4+GELA!K4+ZEMG!K4+TRON!K4+BUMA!K4+SARA!K4+TSIR!K4+DGNA!K4+PANG!K4+DPLA!K4+SJKA!K4+LUNT!K4+SAMC!K4+PHUA!K4+SAMA!K4+GMTU!K4+PHLY!AR4 -> 0 | AS4: =WANG!L4+PUNA!L4+GELA!L4+ZEMG!L4+TRON!L4+BUMA!L4+SARA!L4+TSIR!L4+DGNA!L4+PANG!L4+DPLA!L4+SJKA!L4+LUNT!L4+SAMC!L4+PHUA!L4+SAMA!L4+GMTU!L4+PHLY!AS4 -> 1 | AT4: =WANG!M4+PUNA!M4+GELA!M4+ZEMG!M4+TRON!M4+BUMA!M4+SARA!M4+TSIR!M4+DGNA!M4+PANG!M4+DPLA!M4+SJKA!M4+LUNT!M4+SAMC!M4+PHUA!M4+SAMA!M4+GMTU!M4+PHLY!AT4 -> 0 | AU4: =WANG!N4+PUNA!N4+GELA!N4+ZEMG!N4+TRON!N4+BUMA!N4+SARA!N4+TSIR!N4+DGNA!N4+PANG!N4+DPLA!N4+SJKA!N4+LUNT!N4+SAMC!N4+PHUA!N4+SAMA!N4+GMTU!N4+PHLY!AU4 -> 3 | AV4: =WANG!O4+PUNA!O4+GELA!O4+ZEMG!O4+TRON!O4+BUMA!O4+SARA!O4+TSIR!O4+DGNA!O4+PANG!O4+DPLA!O4+SJKA!O4+LUNT!O4+SAMC!O4+PHUA!O4+SAMA!O4+GMTU!O4+PHLY!AV4 -> 0 | ... BW4: =WANG!AP4+PUNA!AP4+GELA!AP4+ZEMG!AP4+TRON!AP4+BUMA!AP4+SARA!AP4+TSIR!AP4+DGNA!AP4+PANG!AP4+DPLA!AP4+SJKA!AP4+LUNT!AP4+SAMC!AP4+PHUA!AP4+SAMA!AP4+GMTU!AP4+PHLY!BW4 -> 13800 | BY4: =HAA!H4+WANG!AR4+PUNA!AR4+GASA!H4+GELA!AR4+ZEMG!AR4+TRON!AR4+BUMA!AR4+SARA!AR4+TSIR!AR4+DGNA!AR4+PANG!AR4+DPLA!AR4+SJKA!AR4+TRAG!H4+LUNT!AR4+WRMG!H4+NGLM!H4+SAMC!AR4+PHUA!AR4+GEDU!H4+SAMA!AR4+TCHG!H4+GMTU!AR4+PHLY!BY4 -> 0 | BZ4: =HAA!I4+WANG!AS4+PUNA!AS4+GASA!I4+GELA!AS4+ZEMG!AS4+TRON!AS4+BUMA!AS4+SARA!AS4+TSIR!AS4+DGNA!AS4+PANG!AS4+DPLA!AS4+SJKA!AS4+TRAG!I4+LUNT!AS4+WRMG!I4+NGLM!I4+SAMC!AS4+PHUA!AS4+GEDU!I4+SAMA!AS4+TCHG!I4+GMTU!AS4+PHLY!BZ4 -> 0 | CA4: =HAA!J4+WANG!AT4+PUNA!AT4+GASA!J4+GELA!AT4+ZEMG!AT4+TRON!AT4+BUMA!AT4+SARA!AT4+TSIR!AT4+DGNA!AT4+PANG!AT4+DPLA!AT4+SJKA!AT4+TRAG!J4+LUNT!AT4+WRMG!J4+NGLM!J4+SAMC!AT4+PHUA!AT4+GEDU!J4+SAMA!AT4+TCHG!J4+GMTU!AT4+PHLY!CA4 -> 0 | CB4: =HAA!K4+WANG!AU4+PUNA!AU4+GASA!K4+GELA!AU4+ZEMG!AU4+TRON!AU4+BUMA!AU4+SARA!AU4+TSIR!AU4+DGNA!AU4+PANG!AU4+DPLA!AU4+SJKA!AU4+TRAG!K4+LUNT!AU4+WRMG!K4+NGLM!K4+SAMC!AU4+PHUA!AU4+GEDU!K4+SAMA!AU4+TCHG!K4+GMTU!AU4+PHLY!CB4 -> 1 | CC4: =HAA!L4+WANG!AV4+PUNA!AV4+GASA!L4+GELA!AV4+ZEMG!AV4+TRON!AV4+BUMA!AV4+SARA!AV4+TSIR!AV4+DGNA!AV4+PANG!AV4+DPLA!AV4+SJKA!AV4+TRAG!L4+LUNT!AV4+WRMG!L4+NGLM!L4+SAMC!AV4+PHUA!AV4+GEDU!L4+SAMA!AV4+TCHG!L4+GMTU!AV4+PHLY!CC4 -> 0 | CD4: =HAA!M4+WANG!AW4+PUNA!AW4+GASA!M4+GELA!AW4+ZEMG!AW4+TRON!AW4+BUMA!AW4+SARA!AW4+TSIR!AW4+DGNA!AW4+PANG!AW4+DPLA!AW4+SJKA!AW4+TRAG!M4+LUNT!AW4+WRMG!M4+NGLM!M4+SAMC!AW4+PHUA!AW4+GEDU!M4+SAMA!AW4+TCHG!M4+GMTU!AW4+PHLY!CD4 -> 0 | CE4: =HAA!N4+WANG!AX4+PUNA!AX4+GASA!N4+GELA!AX4+ZEMG!AX4+TRON!AX4+BUMA!AX4+SARA!AX4+TSIR!AX4+DGNA!AX4+PANG!AX4+DPLA!AX4+SJKA!AX4+TRAG!N4+LUNT!AX4+WRMG!N4+NGLM!N4+SAMC!AX4+PHUA!AX4+GEDU!N4+SAMA!AX4+TCHG!N4+GMTU!AX4+PHLY!CE4 -> 0 | CF4: =HAA!O4+WANG!AY4+PUNA!AY4+GASA!O4+GELA!AY4+ZEMG!AY4+TRON!AY4+BUMA!AY4+SARA!AY4+TSIR!AY4+DGNA!AY4+PANG!AY4+DPLA!AY4+SJKA!AY4+TRAG!O4+LUNT!AY4+WRMG!O4+NGLM!O4+SAMC!AY4+PHUA!AY4+GEDU!O4+SAMA!AY4+TCHG!O4+GMTU!AY4+PHLY!CF4 -> 1 | ... DF4: =HAA!AO4+WANG!BY4+PUNA!BY4+GASA!AO4+GELA!BY4+ZEMG!BY4+TRON!BY4+BUMA!BY4+SARA!BY4+TSIR!BY4+DGNA!BY4+PANG!BY4+DPLA!BY4+SJKA!BY4+TRAG!AO4+LUNT!BY4+WRMG!AO4+NGLM!AO4+SAMC!BY4+PHUA!BY4+GEDU!AO4+SAMA!BY4+TCHG!AO4+GMTU!BY4+PHLY!DF4 -> 12900 | DG4: =AJ4+BT4+DC4 -> 91 | DH4: =C4*DG4 -> 27300 | DI4: =D4*DG4 -> 32760 | DJ4: =E4*DG4 -> 5460 | DK4: 30 | DL4: =DG4*DK4 -> 2730 | DN4: =PARO!H4+HAA!AQ4+WANG!CA4+PUNA!CA4+GASA!AQ4+GELA!CA4+ZEMG!CA4+TRON!CA4+BUMA!CA4+SARA!CA4+TSIR!CA4+DGNA!CA4+PANG!CA4+DPLA!CA4+SJKA!CA4+TRAG!AQ4+MONA!H4+LUNT!CA4+TYSE!H4+PEMA!H4+KNLG!H4+RJNG!H4+WRMG!AQ4+DUSM!H4+GYPG!H4+NGLM!AQ4+SAMC!CA4+PHUA!CA4+TSMA!H4+GEDU!AQ4+SAMA!CA4+TCHG!AQ4+GMTU!CA4+LHAM!H4+PHLY!DH4 -> 0 | DO4: =PARO!I4+HAA!AR4+WANG!CB4+PUNA!CB4+GASA!AR4+GELA!CB4+ZEMG!CB4+TRON!CB4+BUMA!CB4+SARA!CB4+TSIR!CB4+DGNA!CB4+PANG!CB4+DPLA!CB4+SJKA!CB4+TRAG!AR4+MONA!I4+LUNT!CB4+TYSE!I4+PEMA!I4+KNLG!I4+RJNG!I4+WRMG!AR4+DUSM!I4+GYPG!I4+NGLM!AR4+SAMC!CB4+PHUA!CB4+TSMA!I4+GEDU!AR4+SAMA!CB4+TCHG!AR4+GMTU!CB4+LHAM!I4+PHLY!DI4 -> 0 | DP4: =PARO!J4+HAA!AS4+WANG!CC4+PUNA!CC4+GASA!AS4+GELA!CC4+ZEMG!CC4+TRON!CC4+BUMA!CC4+SARA!CC4+TSIR!CC4+DGNA!CC4+PANG!CC4+DPLA!CC4+SJKA!CC4+TRAG!AS4+MONA!J4+LUNT!CC4+TYSE!J4+PEMA!J4+KNLG!J4+RJNG!J4+WRMG!AS4+DUSM!J4+GYPG!J4+NGLM!AS4+SAMC!CC4+PHUA!CC4+TSMA!J4+GEDU!AS4+SAMA!CC4+TCHG!AS4+GMTU!CC4+LHAM!J4+PHLY!DJ4 -> 0 | DQ4: =PARO!K4+HAA!AT4+WANG!CD4+PUNA!CD4+GASA!AT4+GELA!CD4+ZEMG!CD4+TRON!CD4+BUMA!CD4+SARA!CD4+TSIR!CD4+DGNA!CD4+PANG!CD4+DPLA!CD4+SJKA!CD4+TRAG!AT4+MONA!K4+LUNT!CD4+TYSE!K4+PEMA!K4+KNLG!K4+RJNG!K4+WRMG!AT4+DUSM!K4+GYPG!K4+NGLM!AT4+SAMC!CD4+PHUA!CD4+TSMA!K4+GEDU!AT4+SAMA!CD4+TCHG!AT4+GMTU!CD4+LHAM!K4+PHLY!DK4 -> 0 | DR4: =PARO!L4+HAA!AU4+WANG!CE4+PUNA!CE4+GASA!AU4+GELA!CE4+ZEMG!CE4+TRON!CE4+BUMA!CE4+SARA!CE4+TSIR!CE4+DGNA!CE4+PANG!CE4+DPLA!CE4+SJKA!CE4+TRAG!AU4+MONA!L4+LUNT!CE4+TYSE!L4+PEMA!L4+KNLG!L4+RJNG!L4+WRMG!AU4+DUSM!L4+GYPG!L4+NGLM!AU4+SAMC!CE4+PHUA!CE4+TSMA!L4+GEDU!AU4+SAMA!CE4+TCHG!AU4+GMTU!CE4+LHAM!L4+PHLY!DL4 -> 1 | DS4: =PARO!M4+HAA!AV4+WANG!CF4+PUNA!CF4+GASA!AV4+GELA!CF4+ZEMG!CF4+TRON!CF4+BUMA!CF4+SARA!CF4+TSIR!CF4+DGNA!CF4+PANG!CF4+DPLA!CF4+SJKA!CF4+TRAG!AV4+MONA!M4+LUNT!CF4+TYSE!M4+PEMA!M4+KNLG!M4+RJNG!M4+WRMG!AV4+DUSM!M4+GYPG!M4+NGLM!AV4+SAMC!CF4+PHUA!CF4+TSMA!M4+GEDU!AV4+SAMA!CF4+TCHG!AV4+GMTU!CF4+LHAM!M4+PHLY!DM4 -> 10 | DT4: =PARO!N4+HAA!AW4+WANG!CG4+PUNA!CG4+GASA!AW4+GELA!CG4+ZEMG!CG4+TRON!CG4+BUMA!CG4+SARA!CG4+TSIR!CG4+DGNA!CG4+PANG!CG4+DPLA!CG4+SJKA!CG4+TRAG!AW4+MONA!N4+LUNT!CG4+TYSE!N4+PEMA!N4+KNLG!N4+RJNG!N4+WRMG!AW4+DUSM!N4+GYPG!N4+NGLM!AW4+SAMC!CG4+PHUA!CG4+TSMA!N4+GEDU!AW4+SAMA!CG4+TCHG!AW4+GMTU!CG4+LHAM!N4+PHLY!DN4 -> 2 | DU4: =PARO!O4+HAA!AX4+WANG!CH4+PUNA!CH4+GASA!AX4+GELA!CH4+ZEMG!CH4+TRON!CH4+BUMA!CH4+SARA!CH4+TSIR!CH4+DGNA!CH4+PANG!CH4+DPLA!CH4+SJKA!CH4+TRAG!AX4+MONA!O4+LUNT!CH4+TYSE!O4+PEMA!O4+KNLG!O4+RJNG!O4+WRMG!AX4+DUSM!O4+GYPG!O4+NGLM!AX4+SAMC!CH4+PHUA!CH4+TSMA!O4+GEDU!AX4+SAMA!CH4+TCHG!AX4+GMTU!CH4+LHAM!O4+PHLY!DO4 -> 2 | ... EV4: =PARO!AP4+HAA!BY4+WANG!DI4+PUNA!DI4+GASA!BY4+GELA!DI4+ZEMG!DI4+TRON!DI4+BUMA!DI4+SARA!DI4+TSIR!DI4+DGNA!DI4+PANG!DI4+DPLA!DI4+SJKA!DI4+TRAG!BY4+MONA!AP4+LUNT!DI4+TYSE!AP4+PEMA!AP4+KNLG!AP4+RJNG!AP4+WRMG!BY4+DUSM!AP4+GYPG!AP4+NGLM!BY4+SAMC!DI4+PHUA!DI4+TSMA!AP4+GEDU!BY4+SAMA!DI4+TCHG!BY4+GMTU!DI4+LHAM!AP4+PHLY!EP4 -> 8400 | EX4: =PARO!AR4+HAA!CA4+WANG!DK4+PUNA!DK4+GASA!CA4+GELA!DK4+ZEMG!DK4+TRON!DK4+BUMA!DK4+SARA!DK4+TSIR!DK4+DGNA!DK4+PANG!DK4+DPLA!DK4+SJKA!DK4+TRAG!CA4+MONA!AR4+LUNT!DK4+TYSE!AR4+PEMA!AR4+KNLG!AR4+RJNG!AR4+WRMG!CA4+DUSM!AR4+GYPG!AR4+NGLM!CA4+SAMC!DK4+PHUA!DK4+TSMA!AR4+GEDU!CA4+SAMA!DK4+TCHG!CA4+GMTU!DK4+LHAM!AR4+PHLY!ER4 -> 0 | EY4: =PARO!AS4+HAA!CB4+WANG!DL4+PUNA!DL4+GASA!CB4+GELA!DL4+ZEMG!DL4+TRON!DL4+BUMA!DL4+SARA!DL4+TSIR!DL4+DGNA!DL4+PANG!DL4+DPLA!DL4+SJKA!DL4+TRAG!CB4+MONA!AS4+LUNT!DL4+TYSE!AS4+PEMA!AS4+KNLG!AS4+RJNG!AS4+WRMG!CB4+DUSM!AS4+GYPG!AS4+NGLM!CB4+SAMC!DL4+PHUA!DL4+TSMA!AS4+GEDU!CB4+SAMA!DL4+TCHG!CB4+GMTU!DL4+LHAM!AS4+PHLY!ES4 -> 0 | EZ4: =PARO!AT4+HAA!CC4+WANG!DM4+PUNA!DM4+GASA!CC4+GELA!DM4+ZEMG!DM4+TRON!DM4+BUMA!DM4+SARA!DM4+TSIR!DM4+DGNA!DM4+PANG!DM4+DPLA!DM4+SJKA!DM4+TRAG!CC4+MONA!AT4+LUNT!DM4+TYSE!AT4+PEMA!AT4+KNLG!AT4+RJNG!AT4+WRMG!CC4+DUSM!AT4+GYPG!AT4+NGLM!CC4+SAMC!DM4+PHUA!DM4+TSMA!AT4+GEDU!CC4+SAMA!DM4+TCHG!CC4+GMTU!DM4+LHAM!AT4+PHLY!ET4 -> 1 | FA4: =PARO!AU4+HAA!CD4+WANG!DN4+PUNA!DN4+GASA!CD4+GELA!DN4+ZEMG!DN4+TRON!DN4+BUMA!DN4+SARA!DN4+TSIR!DN4+DGNA!DN4+PANG!DN4+DPLA!DN4+SJKA!DN4+TRAG!CD4+MONA!AU4+LUNT!DN4+TYSE!AU4+PEMA!AU4+KNLG!AU4+RJNG!AU4+WRMG!CD4+DUSM!AU4+GYPG!AU4+NGLM!CD4+SAMC!DN4+PHUA!DN4+TSMA!AU4+GEDU!CD4+SAMA!DN4+TCHG!CD4+GMTU!DN4+LHAM!AU4+PHLY!EU4 -> 2 | FB4: =PARO!AV4+HAA!CE4+WANG!DO4+PUNA!DO4+GASA!CE4+GELA!DO4+ZEMG!DO4+TRON!DO4+BUMA!DO4+SARA!DO4+TSIR!DO4+DGNA!DO4+PANG!DO4+DPLA!DO4+SJKA!DO4+TRAG!CE4+MONA!AV4+LUNT!DO4+TYSE!AV4+PEMA!AV4+KNLG!AV4+RJNG!AV4+WRMG!CE4+DUSM!AV4+GYPG!AV4+NGLM!CE4+SAMC!DO4+PHUA!DO4+TSMA!AV4+GEDU!CE4+SAMA!DO4+TCHG!CE4+GMTU!DO4+LHAM!AV4+PHLY!EV4 -> 0 | FC4: =PARO!AW4+HAA!CF4+WANG!DP4+PUNA!DP4+GASA!CF4+GELA!DP4+ZEMG!DP4+TRON!DP4+BUMA!DP4+SARA!DP4+TSIR!DP4+DGNA!DP4+PANG!DP4+DPLA!DP4+SJKA!DP4+TRAG!CF4+MONA!AW4+LUNT!DP4+TYSE!AW4+PEMA!AW4+KNLG!AW4+RJNG!AW4+WRMG!CF4+DUSM!AW4+GYPG!AW4+NGLM!CF4+SAMC!DP4+PHUA!DP4+TSMA!AW4+GEDU!CF4+SAMA!DP4+TCHG!CF4+GMTU!DP4+LHAM!AW4+PHLY!EW4 -> 0 | FD4: =PARO!AX4+HAA!CG4+WANG!DQ4+PUNA!DQ4+GASA!CG4+GELA!DQ4+ZEMG!DQ4+TRON!DQ4+BUMA!DQ4+SARA!DQ4+TSIR!DQ4+DGNA!DQ4+PANG!DQ4+DPLA!DQ4+SJKA!DQ4+TRAG!CG4+MONA!AX4+LUNT!DQ4+TYSE!AX4+PEMA!AX4+KNLG!AX4+RJNG!AX4+WRMG!CG4+DUSM!AX4+GYPG!AX4+NGLM!CG4+SAMC!DQ4+PHUA!DQ4+TSMA!AX4+GEDU!CG4+SAMA!DQ4+TCHG!CG4+GMTU!DQ4+LHAM!AX4+PHLY!EX4 -> 4 | FE4: =PARO!AY4+HAA!CH4+WANG!DR4+PUNA!DR4+GASA!CH4+GELA!DR4+ZEMG!DR4+TRON!DR4+BUMA!DR4+SARA!DR4+TSIR!DR4+DGNA!DR4+PANG!DR4+DPLA!DR4+SJKA!DR4+TRAG!CH4+MONA!AY4+LUNT!DR4+TYSE!AY4+PEMA!AY4+KNLG!AY4+RJNG!AY4+WRMG!CH4+DUSM!AY4+GYPG!AY4+NGLM!CH4+SAMC!DR4+PHUA!DR4+TSMA!AY4+GEDU!CH4+SAMA!DR4+TCHG!CH4+GMTU!DR4+LHAM!AY4+PHLY!EY4 -> 0 | ... GA4: =PARO!BU4+HAA!DD4+WANG!EN4+PUNA!EN4+GASA!DD4+GELA!EN4+ZEMG!EN4+TRON!EN4+BUMA!EN4+SARA!EN4+TSIR!EN4+DGNA!EN4+PANG!EN4+DPLA!EN4+SJKA!EN4+TRAG!DD4+MONA!BU4+LUNT!EN4+TYSE!BU4+PEMA!BU4+KNLG!BU4+RJNG!BU4+WRMG!DD4+DUSM!BU4+GYPG!BU4+NGLM!DD4+SAMC!EN4+PHUA!EN4+TSMA!BU4+GEDU!DD4+SAMA!EN4+TCHG!DD4+GMTU!EN4+LHAM!BU4+PHLY!FU4 -> 0 | GB4: =PARO!BV4+HAA!DE4+WANG!EO4+PUNA!EO4+GASA!DE4+GELA!EO4+ZEMG!EO4+TRON!EO4+BUMA!EO4+SARA!EO4+TSIR!EO4+DGNA!EO4+PANG!EO4+DPLA!EO4+SJKA!EO4+TRAG!DE4+MONA!BW4+LUNT!EO4+TYSE!BW4+PEMA!BW4+KNLG!BW4+RJNG!BV4+WRMG!DE4+DUSM!BW4+GYPG!BW4+NGLM!DE4+SAMC!EO4+PHUA!EO4+TSMA!BV4+GEDU!DE4+SAMA!EO4+TCHG!DE4+GMTU!EO4+LHAM!BV4+PHLY!FV4 -> 23 | GC4: =PARO!BW4+HAA!DF4+WANG!EP4+PUNA!EP4+GASA!DF4+GELA!EP4+ZEMG!EP4+TRON!EP4+BUMA!EP4+SARA!EP4+TSIR!EP4+DGNA!EP4+PANG!EP4+DPLA!EP4+SJKA!EP4+TRAG!DF4+MONA!BX4+LUNT!EP4+TYSE!BX4+PEMA!BX4+KNLG!BX4+RJNG!BW4+WRMG!DF4+DUSM!BX4+GYPG!BX4+NGLM!DF4+SAMC!EP4+PHUA!EP4+TSMA!BW4+GEDU!DF4+SAMA!EP4+TCHG!DF4+GMTU!EP4+LHAM!BW4+PHLY!FW4 -> 8280 | GD4: =PARO!BX4+HAA!DG4+WANG!EQ4+PUNA!EQ4+GASA!DG4+GELA!EQ4+ZEMG!EQ4+TRON!EQ4+BUMA!EQ4+SARA!EQ4+TSIR!EQ4+DGNA!EQ4+PANG!EQ4+DPLA!EQ4+SJKA!EQ4+TRAG!DG4+MONA!BY4+LUNT!EQ4+TYSE!BY4+PEMA!BY4+KNLG!BY4+RJNG!BX4+WRMG!DG4+DUSM!BY4+GYPG!BY4+NGLM!DG4+SAMC!EQ4+PHUA!EQ4+TSMA!BX4+GEDU!DG4+SAMA!EQ4+TCHG!DG4+GMTU!EQ4+LHAM!BX4+PHLY!FX4 -> 1380 | GE4: =PARO!BY4+HAA!DH4+WANG!ER4+PUNA!ER4+GASA!DH4+GELA!ER4+ZEMG!ER4+TRON!ER4+BUMA!ER4+SARA!ER4+TSIR!ER4+DGNA!ER4+PANG!ER4+DPLA!ER4+SJKA!ER4+TRAG!DH4+MONA!BZ4+LUNT!ER4+TYSE!BZ4+PEMA!BZ4+KNLG!BZ4+RJNG!BY4+WRMG!DH4+DUSM!BZ4+GYPG!BZ4+NGLM!DH4+SAMC!ER4+PHUA!ER4+TSMA!BY4+GEDU!DH4+SAMA!ER4+TCHG!DH4+GMTU!ER4+LHAM!BY4+PHLY!FY4 -> 6900 | GG4: =PARO!CA4+HAA!DJ4+WANG!ET4+PUNA!ET4+GASA!DJ4+GELA!ET4+ZEMG!ET4+TRON!ET4+BUMA!ET4+SARA!ET4+TSIR!ET4+DGNA!ET4+PANG!ET4+DPLA!ET4+SJKA!ET4+TRAG!DJ4+MONA!CB4+LUNT!ET4+TYSE!CB4+PEMA!CB4+KNLG!CB4+RJNG!CA4+WRMG!DJ4+DUSM!CB4+GYPG!CB4+NGLM!DJ4+SAMC!ET4+PHUA!ET4+TSMA!CA4+GEDU!DJ4+SAMA!ET4+TCHG!DJ4+GMTU!ET4+LHAM!CA4+PHLY!GA4 -> 0 | GH4: =PARO!CB4+HAA!DK4+WANG!EU4+PUNA!EU4+GASA!DK4+GELA!EU4+ZEMG!EU4+TRON!EU4+BUMA!EU4+SARA!EU4+TSIR!EU4+DGNA!EU4+PANG!EU4+DPLA!EU4+SJKA!EU4+TRAG!DK4+MONA!CC4+LUNT!EU4+TYSE!CC4+PEMA!CC4+KNLG!CC4+RJNG!CB4+WRMG!DK4+DUSM!CC4+GYPG!CC4+NGLM!DK4+SAMC!EU4+PHUA!EU4+TSMA!CB4+GEDU!DK4+SAMA!EU4+TCHG!DK4+GMTU!EU4+LHAM!CB4+PHLY!GB4 -> 0 | GI4: =PARO!CC4+HAA!DL4+WANG!EV4+PUNA!EV4+GASA!DL4+GELA!EV4+ZEMG!EV4+TRON!EV4+BUMA!EV4+SARA!EV4+TSIR!EV4+DGNA!EV4+PANG!EV4+DPLA!EV4+SJKA!EV4+TRAG!DL4+MONA!CD4+LUNT!EV4+TYSE!CD4+PEMA!CD4+KNLG!CD4+RJNG!CC4+WRMG!DL4+DUSM!CD4+GYPG!CD4+NGLM!DL4+SAMC!EV4+PHUA!EV4+TSMA!CC4+GEDU!DL4+SAMA!EV4+TCHG!DL4+GMTU!EV4+LHAM!CC4+PHLY!GC4 -> 1 | GJ4: =PARO!CD4+HAA!DM4+WANG!EW4+PUNA!EW4+GASA!DM4+GELA!EW4+ZEMG!EW4+TRON!EW4+BUMA!EW4+SARA!EW4+TSIR!EW4+DGNA!EW4+PANG!EW4+DPLA!EW4+SJKA!EW4+TRAG!DM4+MONA!CE4+LUNT!EW4+TYSE!CE4+PEMA!CE4+KNLG!CE4+RJNG!CD4+WRMG!DM4+DUSM!CE4+GYPG!CE4+NGLM!DM4+SAMC!EW4+PHUA!EW4+TSMA!CD4+GEDU!DM4+SAMA!EW4+TCHG!DM4+GMTU!EW4+LHAM!CD4+PHLY!GD4 -> 0 | GK4: =PARO!CE4+HAA!DN4+WANG!EX4+PUNA!EX4+GASA!DN4+GELA!EX4+ZEMG!EX4+TRON!EX4+BUMA!EX4+SARA!EX4+TSIR!EX4+DGNA!EX4+PANG!EX4+DPLA!EX4+SJKA!EX4+TRAG!DN4+MONA!CF4+LUNT!EX4+TYSE!CF4+PEMA!CF4+KNLG!CF4+RJNG!CE4+WRMG!DN4+DUSM!CF4+GYPG!CF4+NGLM!DN4+SAMC!EX4+PHUA!EX4+TSMA!CE4+GEDU!DN4+SAMA!EX4+TCHG!DN4+GMTU!EX4+LHAM!CE4+PHLY!GE4 -> 0 | GL4: =PARO!CF4+HAA!DO4+WANG!EY4+PUNA!EY4+GASA!DO4+GELA!EY4+ZEMG!EY4+TRON!EY4+BUMA!EY4+SARA!EY4+TSIR!EY4+DGNA!EY4+PANG!EY4+DPLA!EY4+SJKA!EY4+TRAG!DO4+MONA!CG4+LUNT!EY4+TYSE!CG4+PEMA!CG4+KNLG!CG4+RJNG!CF4+WRMG!DO4+DUSM!CG4+GYPG!CG4+NGLM!DO4+SAMC!EY4+PHUA!EY4+TSMA!CF4+GEDU!DO4+SAMA!EY4+TCHG!DO4+GMTU!EY4+LHAM!CF4+PHLY!GF4 -> 0 | GM4: =PARO!CG4+HAA!DP4+WANG!EZ4+PUNA!EZ4+GASA!DP4+GELA!EZ4+ZEMG!EZ4+TRON!EZ4+BUMA!EZ4+SARA!EZ4+TSIR!EZ4+DGNA!EZ4+PANG!EZ4+DPLA!EZ4+SJKA!EZ4+TRAG!DP4+MONA!CH4+LUNT!EZ4+TYSE!CH4+PEMA!CH4+KNLG!CH4+RJNG!CG4+WRMG!DP4+DUSM!CH4+GYPG!CH4+NGLM!DP4+SAMC!EZ4+PHUA!EZ4+TSMA!CG4+GEDU!DP4+SAMA!EZ4+TCHG!DP4+GMTU!EZ4+LHAM!CG4+PHLY!GG4 -> 0 | GN4: =PARO!CH4+HAA!DQ4+WANG!FA4+PUNA!FA4+GASA!DQ4+GELA!FA4+ZEMG!FA4+TRON!FA4+BUMA!FA4+SARA!FA4+TSIR!FA4+DGNA!FA4+PANG!FA4+DPLA!FA4+SJKA!FA4+TRAG!DQ4+MONA!CI4+LUNT!FA4+TYSE!CI4+PEMA!CI4+KNLG!CI4+RJNG!CH4+WRMG!DQ4+DUSM!CI4+GYPG!CI4+NGLM!DQ4+SAMC!FA4+PHUA!FA4+TSMA!CH4+GEDU!DQ4+SAMA!FA4+TCHG!DQ4+GMTU!FA4+LHAM!CH4+PHLY!GH4 -> 0 | ... HO4: =PARO!DI4+HAA!ER4+WANG!GB4+PUNA!GB4+GASA!ER4+GELA!GB4+ZEMG!GB4+TRON!GB4+BUMA!GB4+SARA!GB4+TSIR!GB4+DGNA!GB4+PANG!GB4+DPLA!GB4+SJKA!GB4+TRAG!ER4+MONA!DJ4+LUNT!GB4+TYSE!DJ4+PEMA!DJ4+KNLG!DJ4+RJNG!DI4+WRMG!ER4+DUSM!DJ4+GYPG!DJ4+NGLM!ER4+SAMC!GB4+PHUA!GB4+TSMA!DI4+GEDU!ER4+SAMA!GB4+TCHG!ER4+GMTU!GB4+LHAM!DI4+PHLY!HI4 -> 2400 | HQ4: =ES4+GB4+HL4 -> 59 | HR4: =C4*HQ4 -> 17700 | HS4: =D4*HQ4 -> 21240 | HT4: =E4*HQ4 -> 3540 | HU4: 30 | HV4: =HQ4*HU4 -> 1770 | IN4: =AJ4+BT4+DC4+ES4+GB4+HL4 -> 150 | IO4: =AK4+BU4+DD4+ET4+GC4+HM4 -> 54000 | IP4: =AL4+BV4+DE4+EU4+GD4+HN4 -> 9000 | IQ4: =AM4+BW4+DF4+EV4+GE4+HO4 -> 45000 | IR4: =IR3/80 -> 7.075
A5: 3 | B5: Tumeric and Cinnamon tea | C5: 300 | D5: 360 | E5: =D5-C5 -> 60 | H5: =PHLY!H5 -> 0 | I5: =PHLY!I5 -> 0 | J5: =PHLY!J5 -> 0 | K5: =PHLY!K5 -> 0 | L5: =PHLY!L5 -> 0 | M5: =PHLY!M5 -> 0 | N5: =PHLY!N5 -> 0 | O5: =PHLY!O5 -> 0 | ... AM5: =PHLY!AM5 -> 0 | AO5: =WANG!H5+PUNA!H5+GELA!H5+ZEMG!H5+TRON!H5+BUMA!H5+SARA!H5+TSIR!H5+DGNA!H5+PANG!H5+DPLA!H5+SJKA!H5+LUNT!H5+SAMC!H5+PHUA!H5+SAMA!H5+GMTU!H5+PHLY!AO5 -> 0 | AP5: =WANG!I5+PUNA!I5+GELA!I5+ZEMG!I5+TRON!I5+BUMA!I5+SARA!I5+TSIR!I5+DGNA!I5+PANG!I5+DPLA!I5+SJKA!I5+LUNT!I5+SAMC!I5+PHUA!I5+SAMA!I5+GMTU!I5+PHLY!AP5 -> 0 | AQ5: =WANG!J5+PUNA!J5+GELA!J5+ZEMG!J5+TRON!J5+BUMA!J5+SARA!J5+TSIR!J5+DGNA!J5+PANG!J5+DPLA!J5+SJKA!J5+LUNT!J5+SAMC!J5+PHUA!J5+SAMA!J5+GMTU!J5+PHLY!AQ5 -> 0 | AR5: =WANG!K5+PUNA!K5+GELA!K5+ZEMG!K5+TRON!K5+BUMA!K5+SARA!K5+TSIR!K5+DGNA!K5+PANG!K5+DPLA!K5+SJKA!K5+LUNT!K5+SAMC!K5+PHUA!K5+SAMA!K5+GMTU!K5+PHLY!AR5 -> 0 | AS5: =WANG!L5+PUNA!L5+GELA!L5+ZEMG!L5+TRON!L5+BUMA!L5+SARA!L5+TSIR!L5+DGNA!L5+PANG!L5+DPLA!L5+SJKA!L5+LUNT!L5+SAMC!L5+PHUA!L5+SAMA!L5+GMTU!L5+PHLY!AS5 -> 2 | AT5: =WANG!M5+PUNA!M5+GELA!M5+ZEMG!M5+TRON!M5+BUMA!M5+SARA!M5+TSIR!M5+DGNA!M5+PANG!M5+DPLA!M5+SJKA!M5+LUNT!M5+SAMC!M5+PHUA!M5+SAMA!M5+GMTU!M5+PHLY!AT5 -> 0 | AU5: =WANG!N5+PUNA!N5+GELA!N5+ZEMG!N5+TRON!N5+BUMA!N5+SARA!N5+TSIR!N5+DGNA!N5+PANG!N5+DPLA!N5+SJKA!N5+LUNT!N5+SAMC!N5+PHUA!N5+SAMA!N5+GMTU!N5+PHLY!AU5 -> 3 | AV5: =WANG!O5+PUNA!O5+GELA!O5+ZEMG!O5+TRON!O5+BUMA!O5+SARA!O5+TSIR!O5+DGNA!O5+PANG!O5+DPLA!O5+SJKA!O5+LUNT!O5+SAMC!O5+PHUA!O5+SAMA!O5+GMTU!O5+PHLY!AV5 -> 0 | ... BW5: =WANG!AP5+PUNA!AP5+GELA!AP5+ZEMG!AP5+TRON!AP5+BUMA!AP5+SARA!AP5+TSIR!AP5+DGNA!AP5+PANG!AP5+DPLA!AP5+SJKA!AP5+LUNT!AP5+SAMC!AP5+PHUA!AP5+SAMA!AP5+GMTU!AP5+PHLY!BW5 -> 10800 | BY5: =HAA!H5+WANG!AR5+PUNA!AR5+GASA!H5+GELA!AR5+ZEMG!AR5+TRON!AR5+BUMA!AR5+SARA!AR5+TSIR!AR5+DGNA!AR5+PANG!AR5+DPLA!AR5+SJKA!AR5+TRAG!H5+LUNT!AR5+WRMG!H5+NGLM!H5+SAMC!AR5+PHUA!AR5+GEDU!H5+SAMA!AR5+TCHG!H5+GMTU!AR5+PHLY!BY5 -> 3 | BZ5: =HAA!I5+WANG!AS5+PUNA!AS5+GASA!I5+GELA!AS5+ZEMG!AS5+TRON!AS5+BUMA!AS5+SARA!AS5+TSIR!AS5+DGNA!AS5+PANG!AS5+DPLA!AS5+SJKA!AS5+TRAG!I5+LUNT!AS5+WRMG!I5+NGLM!I5+SAMC!AS5+PHUA!AS5+GEDU!I5+SAMA!AS5+TCHG!I5+GMTU!AS5+PHLY!BZ5 -> 4 | CA5: =HAA!J5+WANG!AT5+PUNA!AT5+GASA!J5+GELA!AT5+ZEMG!AT5+TRON!AT5+BUMA!AT5+SARA!AT5+TSIR!AT5+DGNA!AT5+PANG!AT5+DPLA!AT5+SJKA!AT5+TRAG!J5+LUNT!AT5+WRMG!J5+NGLM!J5+SAMC!AT5+PHUA!AT5+GEDU!J5+SAMA!AT5+TCHG!J5+GMTU!AT5+PHLY!CA5 -> 3 | CB5: =HAA!K5+WANG!AU5+PUNA!AU5+GASA!K5+GELA!AU5+ZEMG!AU5+TRON!AU5+BUMA!AU5+SARA!AU5+TSIR!AU5+DGNA!AU5+PANG!AU5+DPLA!AU5+SJKA!AU5+TRAG!K5+LUNT!AU5+WRMG!K5+NGLM!K5+SAMC!AU5+PHUA!AU5+GEDU!K5+SAMA!AU5+TCHG!K5+GMTU!AU5+PHLY!CB5 -> 2 | CC5: =HAA!L5+WANG!AV5+PUNA!AV5+GASA!L5+GELA!AV5+ZEMG!AV5+TRON!AV5+BUMA!AV5+SARA!AV5+TSIR!AV5+DGNA!AV5+PANG!AV5+DPLA!AV5+SJKA!AV5+TRAG!L5+LUNT!AV5+WRMG!L5+NGLM!L5+SAMC!AV5+PHUA!AV5+GEDU!L5+SAMA!AV5+TCHG!L5+GMTU!AV5+PHLY!CC5 -> 0 | CD5: =HAA!M5+WANG!AW5+PUNA!AW5+GASA!M5+GELA!AW5+ZEMG!AW5+TRON!AW5+BUMA!AW5+SARA!AW5+TSIR!AW5+DGNA!AW5+PANG!AW5+DPLA!AW5+SJKA!AW5+TRAG!M5+LUNT!AW5+WRMG!M5+NGLM!M5+SAMC!AW5+PHUA!AW5+GEDU!M5+SAMA!AW5+TCHG!M5+GMTU!AW5+PHLY!CD5 -> 0 | CE5: =HAA!N5+WANG!AX5+PUNA!AX5+GASA!N5+GELA!AX5+ZEMG!AX5+TRON!AX5+BUMA!AX5+SARA!AX5+TSIR!AX5+DGNA!AX5+PANG!AX5+DPLA!AX5+SJKA!AX5+TRAG!N5+LUNT!AX5+WRMG!N5+NGLM!N5+SAMC!AX5+PHUA!AX5+GEDU!N5+SAMA!AX5+TCHG!N5+GMTU!AX5+PHLY!CE5 -> 1 | CF5: =HAA!O5+WANG!AY5+PUNA!AY5+GASA!O5+GELA!AY5+ZEMG!AY5+TRON!AY5+BUMA!AY5+SARA!AY5+TSIR!AY5+DGNA!AY5+PANG!AY5+DPLA!AY5+SJKA!AY5+TRAG!O5+LUNT!AY5+WRMG!O5+NGLM!O5+SAMC!AY5+PHUA!AY5+GEDU!O5+SAMA!AY5+TCHG!O5+GMTU!AY5+PHLY!CF5 -> 0 | ... DF5: =HAA!AO5+WANG!BY5+PUNA!BY5+GASA!AO5+GELA!BY5+ZEMG!BY5+TRON!BY5+BUMA!BY5+SARA!BY5+TSIR!BY5+DGNA!BY5+PANG!BY5+DPLA!BY5+SJKA!BY5+TRAG!AO5+LUNT!BY5+WRMG!AO5+NGLM!AO5+SAMC!BY5+PHUA!BY5+GEDU!AO5+SAMA!BY5+TCHG!AO5+GMTU!BY5+PHLY!DF5 -> 21000 | DG5: =AJ5+BT5+DC5 -> 106 | DH5: =C5*DG5 -> 31800 | DI5: =D5*DG5 -> 38160 | DJ5: =E5*DG5 -> 6360 | DK5: 30 | DL5: =DG5*DK5 -> 3180 | DN5: =PARO!H5+HAA!AQ5+WANG!CA5+PUNA!CA5+GASA!AQ5+GELA!CA5+ZEMG!CA5+TRON!CA5+BUMA!CA5+SARA!CA5+TSIR!CA5+DGNA!CA5+PANG!CA5+DPLA!CA5+SJKA!CA5+TRAG!AQ5+MONA!H5+LUNT!CA5+TYSE!H5+PEMA!H5+KNLG!H5+RJNG!H5+WRMG!AQ5+DUSM!H5+GYPG!H5+NGLM!AQ5+SAMC!CA5+PHUA!CA5+TSMA!H5+GEDU!AQ5+SAMA!CA5+TCHG!AQ5+GMTU!CA5+LHAM!H5+PHLY!DH5 -> 1 | DO5: =PARO!I5+HAA!AR5+WANG!CB5+PUNA!CB5+GASA!AR5+GELA!CB5+ZEMG!CB5+TRON!CB5+BUMA!CB5+SARA!CB5+TSIR!CB5+DGNA!CB5+PANG!CB5+DPLA!CB5+SJKA!CB5+TRAG!AR5+MONA!I5+LUNT!CB5+TYSE!I5+PEMA!I5+KNLG!I5+RJNG!I5+WRMG!AR5+DUSM!I5+GYPG!I5+NGLM!AR5+SAMC!CB5+PHUA!CB5+TSMA!I5+GEDU!AR5+SAMA!CB5+TCHG!AR5+GMTU!CB5+LHAM!I5+PHLY!DI5 -> 0 | DP5: =PARO!J5+HAA!AS5+WANG!CC5+PUNA!CC5+GASA!AS5+GELA!CC5+ZEMG!CC5+TRON!CC5+BUMA!CC5+SARA!CC5+TSIR!CC5+DGNA!CC5+PANG!CC5+DPLA!CC5+SJKA!CC5+TRAG!AS5+MONA!J5+LUNT!CC5+TYSE!J5+PEMA!J5+KNLG!J5+RJNG!J5+WRMG!AS5+DUSM!J5+GYPG!J5+NGLM!AS5+SAMC!CC5+PHUA!CC5+TSMA!J5+GEDU!AS5+SAMA!CC5+TCHG!AS5+GMTU!CC5+LHAM!J5+PHLY!DJ5 -> 0 | DQ5: =PARO!K5+HAA!AT5+WANG!CD5+PUNA!CD5+GASA!AT5+GELA!CD5+ZEMG!CD5+TRON!CD5+BUMA!CD5+SARA!CD5+TSIR!CD5+DGNA!CD5+PANG!CD5+DPLA!CD5+SJKA!CD5+TRAG!AT5+MONA!K5+LUNT!CD5+TYSE!K5+PEMA!K5+KNLG!K5+RJNG!K5+WRMG!AT5+DUSM!K5+GYPG!K5+NGLM!AT5+SAMC!CD5+PHUA!CD5+TSMA!K5+GEDU!AT5+SAMA!CD5+TCHG!AT5+GMTU!CD5+LHAM!K5+PHLY!DK5 -> 0 | DR5: =PARO!L5+HAA!AU5+WANG!CE5+PUNA!CE5+GASA!AU5+GELA!CE5+ZEMG!CE5+TRON!CE5+BUMA!CE5+SARA!CE5+TSIR!CE5+DGNA!CE5+PANG!CE5+DPLA!CE5+SJKA!CE5+TRAG!AU5+MONA!L5+LUNT!CE5+TYSE!L5+PEMA!L5+KNLG!L5+RJNG!L5+WRMG!AU5+DUSM!L5+GYPG!L5+NGLM!AU5+SAMC!CE5+PHUA!CE5+TSMA!L5+GEDU!AU5+SAMA!CE5+TCHG!AU5+GMTU!CE5+LHAM!L5+PHLY!DL5 -> 1 | DS5: =PARO!M5+HAA!AV5+WANG!CF5+PUNA!CF5+GASA!AV5+GELA!CF5+ZEMG!CF5+TRON!CF5+BUMA!CF5+SARA!CF5+TSIR!CF5+DGNA!CF5+PANG!CF5+DPLA!CF5+SJKA!CF5+TRAG!AV5+MONA!M5+LUNT!CF5+TYSE!M5+PEMA!M5+KNLG!M5+RJNG!M5+WRMG!AV5+DUSM!M5+GYPG!M5+NGLM!AV5+SAMC!CF5+PHUA!CF5+TSMA!M5+GEDU!AV5+SAMA!CF5+TCHG!AV5+GMTU!CF5+LHAM!M5+PHLY!DM5 -> 15 | DT5: =PARO!N5+HAA!AW5+WANG!CG5+PUNA!CG5+GASA!AW5+GELA!CG5+ZEMG!CG5+TRON!CG5+BUMA!CG5+SARA!CG5+TSIR!CG5+DGNA!CG5+PANG!CG5+DPLA!CG5+SJKA!CG5+TRAG!AW5+MONA!N5+LUNT!CG5+TYSE!N5+PEMA!N5+KNLG!N5+RJNG!N5+WRMG!AW5+DUSM!N5+GYPG!N5+NGLM!AW5+SAMC!CG5+PHUA!CG5+TSMA!N5+GEDU!AW5+SAMA!CG5+TCHG!AW5+GMTU!CG5+LHAM!N5+PHLY!DN5 -> 1 | DU5: =PARO!O5+HAA!AX5+WANG!CH5+PUNA!CH5+GASA!AX5+GELA!CH5+ZEMG!CH5+TRON!CH5+BUMA!CH5+SARA!CH5+TSIR!CH5+DGNA!CH5+PANG!CH5+DPLA!CH5+SJKA!CH5+TRAG!AX5+MONA!O5+LUNT!CH5+TYSE!O5+PEMA!O5+KNLG!O5+RJNG!O5+WRMG!AX5+DUSM!O5+GYPG!O5+NGLM!AX5+SAMC!CH5+PHUA!CH5+TSMA!O5+GEDU!AX5+SAMA!CH5+TCHG!AX5+GMTU!CH5+LHAM!O5+PHLY!DO5 -> 0 | ... EV5: =PARO!AP5+HAA!BY5+WANG!DI5+PUNA!DI5+GASA!BY5+GELA!DI5+ZEMG!DI5+TRON!DI5+BUMA!DI5+SARA!DI5+TSIR!DI5+DGNA!DI5+PANG!DI5+DPLA!DI5+SJKA!DI5+TRAG!BY5+MONA!AP5+LUNT!DI5+TYSE!AP5+PEMA!AP5+KNLG!AP5+RJNG!AP5+WRMG!BY5+DUSM!AP5+GYPG!AP5+NGLM!BY5+SAMC!DI5+PHUA!DI5+TSMA!AP5+GEDU!BY5+SAMA!DI5+TCHG!BY5+GMTU!DI5+LHAM!AP5+PHLY!EP5 -> 12000 | EX5: =PARO!AR5+HAA!CA5+WANG!DK5+PUNA!DK5+GASA!CA5+GELA!DK5+ZEMG!DK5+TRON!DK5+BUMA!DK5+SARA!DK5+TSIR!DK5+DGNA!DK5+PANG!DK5+DPLA!DK5+SJKA!DK5+TRAG!CA5+MONA!AR5+LUNT!DK5+TYSE!AR5+PEMA!AR5+KNLG!AR5+RJNG!AR5+WRMG!CA5+DUSM!AR5+GYPG!AR5+NGLM!CA5+SAMC!DK5+PHUA!DK5+TSMA!AR5+GEDU!CA5+SAMA!DK5+TCHG!CA5+GMTU!DK5+LHAM!AR5+PHLY!ER5 -> 0 | EY5: =PARO!AS5+HAA!CB5+WANG!DL5+PUNA!DL5+GASA!CB5+GELA!DL5+ZEMG!DL5+TRON!DL5+BUMA!DL5+SARA!DL5+TSIR!DL5+DGNA!DL5+PANG!DL5+DPLA!DL5+SJKA!DL5+TRAG!CB5+MONA!AS5+LUNT!DL5+TYSE!AS5+PEMA!AS5+KNLG!AS5+RJNG!AS5+WRMG!CB5+DUSM!AS5+GYPG!AS5+NGLM!CB5+SAMC!DL5+PHUA!DL5+TSMA!AS5+GEDU!CB5+SAMA!DL5+TCHG!CB5+GMTU!DL5+LHAM!AS5+PHLY!ES5 -> 0 | EZ5: =PARO!AT5+HAA!CC5+WANG!DM5+PUNA!DM5+GASA!CC5+GELA!DM5+ZEMG!DM5+TRON!DM5+BUMA!DM5+SARA!DM5+TSIR!DM5+DGNA!DM5+PANG!DM5+DPLA!DM5+SJKA!DM5+TRAG!CC5+MONA!AT5+LUNT!DM5+TYSE!AT5+PEMA!AT5+KNLG!AT5+RJNG!AT5+WRMG!CC5+DUSM!AT5+GYPG!AT5+NGLM!CC5+SAMC!DM5+PHUA!DM5+TSMA!AT5+GEDU!CC5+SAMA!DM5+TCHG!CC5+GMTU!DM5+LHAM!AT5+PHLY!ET5 -> 1 | FA5: =PARO!AU5+HAA!CD5+WANG!DN5+PUNA!DN5+GASA!CD5+GELA!DN5+ZEMG!DN5+TRON!DN5+BUMA!DN5+SARA!DN5+TSIR!DN5+DGNA!DN5+PANG!DN5+DPLA!DN5+SJKA!DN5+TRAG!CD5+MONA!AU5+LUNT!DN5+TYSE!AU5+PEMA!AU5+KNLG!AU5+RJNG!AU5+WRMG!CD5+DUSM!AU5+GYPG!AU5+NGLM!CD5+SAMC!DN5+PHUA!DN5+TSMA!AU5+GEDU!CD5+SAMA!DN5+TCHG!CD5+GMTU!DN5+LHAM!AU5+PHLY!EU5 -> 3 | FB5: =PARO!AV5+HAA!CE5+WANG!DO5+PUNA!DO5+GASA!CE5+GELA!DO5+ZEMG!DO5+TRON!DO5+BUMA!DO5+SARA!DO5+TSIR!DO5+DGNA!DO5+PANG!DO5+DPLA!DO5+SJKA!DO5+TRAG!CE5+MONA!AV5+LUNT!DO5+TYSE!AV5+PEMA!AV5+KNLG!AV5+RJNG!AV5+WRMG!CE5+DUSM!AV5+GYPG!AV5+NGLM!CE5+SAMC!DO5+PHUA!DO5+TSMA!AV5+GEDU!CE5+SAMA!DO5+TCHG!CE5+GMTU!DO5+LHAM!AV5+PHLY!EV5 -> 2 | FC5: =PARO!AW5+HAA!CF5+WANG!DP5+PUNA!DP5+GASA!CF5+GELA!DP5+ZEMG!DP5+TRON!DP5+BUMA!DP5+SARA!DP5+TSIR!DP5+DGNA!DP5+PANG!DP5+DPLA!DP5+SJKA!DP5+TRAG!CF5+MONA!AW5+LUNT!DP5+TYSE!AW5+PEMA!AW5+KNLG!AW5+RJNG!AW5+WRMG!CF5+DUSM!AW5+GYPG!AW5+NGLM!CF5+SAMC!DP5+PHUA!DP5+TSMA!AW5+GEDU!CF5+SAMA!DP5+TCHG!CF5+GMTU!DP5+LHAM!AW5+PHLY!EW5 -> 1 | FD5: =PARO!AX5+HAA!CG5+WANG!DQ5+PUNA!DQ5+GASA!CG5+GELA!DQ5+ZEMG!DQ5+TRON!DQ5+BUMA!DQ5+SARA!DQ5+TSIR!DQ5+DGNA!DQ5+PANG!DQ5+DPLA!DQ5+SJKA!DQ5+TRAG!CG5+MONA!AX5+LUNT!DQ5+TYSE!AX5+PEMA!AX5+KNLG!AX5+RJNG!AX5+WRMG!CG5+DUSM!AX5+GYPG!AX5+NGLM!CG5+SAMC!DQ5+PHUA!DQ5+TSMA!AX5+GEDU!CG5+SAMA!DQ5+TCHG!CG5+GMTU!DQ5+LHAM!AX5+PHLY!EX5 -> 2 | FE5: =PARO!AY5+HAA!CH5+WANG!DR5+PUNA!DR5+GASA!CH5+GELA!DR5+ZEMG!DR5+TRON!DR5+BUMA!DR5+SARA!DR5+TSIR!DR5+DGNA!DR5+PANG!DR5+DPLA!DR5+SJKA!DR5+TRAG!CH5+MONA!AY5+LUNT!DR5+TYSE!AY5+PEMA!AY5+KNLG!AY5+RJNG!AY5+WRMG!CH5+DUSM!AY5+GYPG!AY5+NGLM!CH5+SAMC!DR5+PHUA!DR5+TSMA!AY5+GEDU!CH5+SAMA!DR5+TCHG!CH5+GMTU!DR5+LHAM!AY5+PHLY!EY5 -> 0 | ... GA5: =PARO!BU5+HAA!DD5+WANG!EN5+PUNA!EN5+GASA!DD5+GELA!EN5+ZEMG!EN5+TRON!EN5+BUMA!EN5+SARA!EN5+TSIR!EN5+DGNA!EN5+PANG!EN5+DPLA!EN5+SJKA!EN5+TRAG!DD5+MONA!BU5+LUNT!EN5+TYSE!BU5+PEMA!BU5+KNLG!BU5+RJNG!BU5+WRMG!DD5+DUSM!BU5+GYPG!BU5+NGLM!DD5+SAMC!EN5+PHUA!EN5+TSMA!BU5+GEDU!DD5+SAMA!EN5+TCHG!DD5+GMTU!EN5+LHAM!BU5+PHLY!FU5 -> 0 | GB5: =PARO!BV5+HAA!DE5+WANG!EO5+PUNA!EO5+GASA!DE5+GELA!EO5+ZEMG!EO5+TRON!EO5+BUMA!EO5+SARA!EO5+TSIR!EO5+DGNA!EO5+PANG!EO5+DPLA!EO5+SJKA!EO5+TRAG!DE5+MONA!BW5+LUNT!EO5+TYSE!BW5+PEMA!BW5+KNLG!BW5+RJNG!BV5+WRMG!DE5+DUSM!BW5+GYPG!BW5+NGLM!DE5+SAMC!EO5+PHUA!EO5+TSMA!BV5+GEDU!DE5+SAMA!EO5+TCHG!DE5+GMTU!EO5+LHAM!BV5+PHLY!FV5 -> 17 | GC5: =PARO!BW5+HAA!DF5+WANG!EP5+PUNA!EP5+GASA!DF5+GELA!EP5+ZEMG!EP5+TRON!EP5+BUMA!EP5+SARA!EP5+TSIR!EP5+DGNA!EP5+PANG!EP5+DPLA!EP5+SJKA!EP5+TRAG!DF5+MONA!BX5+LUNT!EP5+TYSE!BX5+PEMA!BX5+KNLG!BX5+RJNG!BW5+WRMG!DF5+DUSM!BX5+GYPG!BX5+NGLM!DF5+SAMC!EP5+PHUA!EP5+TSMA!BW5+GEDU!DF5+SAMA!EP5+TCHG!DF5+GMTU!EP5+LHAM!BW5+PHLY!FW5 -> 6120 | GD5: =PARO!BX5+HAA!DG5+WANG!EQ5+PUNA!EQ5+GASA!DG5+GELA!EQ5+ZEMG!EQ5+TRON!EQ5+BUMA!EQ5+SARA!EQ5+TSIR!EQ5+DGNA!EQ5+PANG!EQ5+DPLA!EQ5+SJKA!EQ5+TRAG!DG5+MONA!BY5+LUNT!EQ5+TYSE!BY5+PEMA!BY5+KNLG!BY5+RJNG!BX5+WRMG!DG5+DUSM!BY5+GYPG!BY5+NGLM!DG5+SAMC!EQ5+PHUA!EQ5+TSMA!BX5+GEDU!DG5+SAMA!EQ5+TCHG!DG5+GMTU!EQ5+LHAM!BX5+PHLY!FX5 -> 1020 | GE5: =PARO!BY5+HAA!DH5+WANG!ER5+PUNA!ER5+GASA!DH5+GELA!ER5+ZEMG!ER5+TRON!ER5+BUMA!ER5+SARA!ER5+TSIR!ER5+DGNA!ER5+PANG!ER5+DPLA!ER5+SJKA!ER5+TRAG!DH5+MONA!BZ5+LUNT!ER5+TYSE!BZ5+PEMA!BZ5+KNLG!BZ5+RJNG!BY5+WRMG!DH5+DUSM!BZ5+GYPG!BZ5+NGLM!DH5+SAMC!ER5+PHUA!ER5+TSMA!BY5+GEDU!DH5+SAMA!ER5+TCHG!DH5+GMTU!ER5+LHAM!BY5+PHLY!FY5 -> 5100 | GG5: =PARO!CA5+HAA!DJ5+WANG!ET5+PUNA!ET5+GASA!DJ5+GELA!ET5+ZEMG!ET5+TRON!ET5+BUMA!ET5+SARA!ET5+TSIR!ET5+DGNA!ET5+PANG!ET5+DPLA!ET5+SJKA!ET5+TRAG!DJ5+MONA!CB5+LUNT!ET5+TYSE!CB5+PEMA!CB5+KNLG!CB5+RJNG!CA5+WRMG!DJ5+DUSM!CB5+GYPG!CB5+NGLM!DJ5+SAMC!ET5+PHUA!ET5+TSMA!CA5+GEDU!DJ5+SAMA!ET5+TCHG!DJ5+GMTU!ET5+LHAM!CA5+PHLY!GA5 -> 0 | GH5: =PARO!CB5+HAA!DK5+WANG!EU5+PUNA!EU5+GASA!DK5+GELA!EU5+ZEMG!EU5+TRON!EU5+BUMA!EU5+SARA!EU5+TSIR!EU5+DGNA!EU5+PANG!EU5+DPLA!EU5+SJKA!EU5+TRAG!DK5+MONA!CC5+LUNT!EU5+TYSE!CC5+PEMA!CC5+KNLG!CC5+RJNG!CB5+WRMG!DK5+DUSM!CC5+GYPG!CC5+NGLM!DK5+SAMC!EU5+PHUA!EU5+TSMA!CB5+GEDU!DK5+SAMA!EU5+TCHG!DK5+GMTU!EU5+LHAM!CB5+PHLY!GB5 -> 0 | GI5: =PARO!CC5+HAA!DL5+WANG!EV5+PUNA!EV5+GASA!DL5+GELA!EV5+ZEMG!EV5+TRON!EV5+BUMA!EV5+SARA!EV5+TSIR!EV5+DGNA!EV5+PANG!EV5+DPLA!EV5+SJKA!EV5+TRAG!DL5+MONA!CD5+LUNT!EV5+TYSE!CD5+PEMA!CD5+KNLG!CD5+RJNG!CC5+WRMG!DL5+DUSM!CD5+GYPG!CD5+NGLM!DL5+SAMC!EV5+PHUA!EV5+TSMA!CC5+GEDU!DL5+SAMA!EV5+TCHG!DL5+GMTU!EV5+LHAM!CC5+PHLY!GC5 -> 0 | GJ5: =PARO!CD5+HAA!DM5+WANG!EW5+PUNA!EW5+GASA!DM5+GELA!EW5+ZEMG!EW5+TRON!EW5+BUMA!EW5+SARA!EW5+TSIR!EW5+DGNA!EW5+PANG!EW5+DPLA!EW5+SJKA!EW5+TRAG!DM5+MONA!CE5+LUNT!EW5+TYSE!CE5+PEMA!CE5+KNLG!CE5+RJNG!CD5+WRMG!DM5+DUSM!CE5+GYPG!CE5+NGLM!DM5+SAMC!EW5+PHUA!EW5+TSMA!CD5+GEDU!DM5+SAMA!EW5+TCHG!DM5+GMTU!EW5+LHAM!CD5+PHLY!GD5 -> 8 | GK5: =PARO!CE5+HAA!DN5+WANG!EX5+PUNA!EX5+GASA!DN5+GELA!EX5+ZEMG!EX5+TRON!EX5+BUMA!EX5+SARA!EX5+TSIR!EX5+DGNA!EX5+PANG!EX5+DPLA!EX5+SJKA!EX5+TRAG!DN5+MONA!CF5+LUNT!EX5+TYSE!CF5+PEMA!CF5+KNLG!CF5+RJNG!CE5+WRMG!DN5+DUSM!CF5+GYPG!CF5+NGLM!DN5+SAMC!EX5+PHUA!EX5+TSMA!CE5+GEDU!DN5+SAMA!EX5+TCHG!DN5+GMTU!EX5+LHAM!CE5+PHLY!GE5 -> 0 | GL5: =PARO!CF5+HAA!DO5+WANG!EY5+PUNA!EY5+GASA!DO5+GELA!EY5+ZEMG!EY5+TRON!EY5+BUMA!EY5+SARA!EY5+TSIR!EY5+DGNA!EY5+PANG!EY5+DPLA!EY5+SJKA!EY5+TRAG!DO5+MONA!CG5+LUNT!EY5+TYSE!CG5+PEMA!CG5+KNLG!CG5+RJNG!CF5+WRMG!DO5+DUSM!CG5+GYPG!CG5+NGLM!DO5+SAMC!EY5+PHUA!EY5+TSMA!CF5+GEDU!DO5+SAMA!EY5+TCHG!DO5+GMTU!EY5+LHAM!CF5+PHLY!GF5 -> 0 | GM5: =PARO!CG5+HAA!DP5+WANG!EZ5+PUNA!EZ5+GASA!DP5+GELA!EZ5+ZEMG!EZ5+TRON!EZ5+BUMA!EZ5+SARA!EZ5+TSIR!EZ5+DGNA!EZ5+PANG!EZ5+DPLA!EZ5+SJKA!EZ5+TRAG!DP5+MONA!CH5+LUNT!EZ5+TYSE!CH5+PEMA!CH5+KNLG!CH5+RJNG!CG5+WRMG!DP5+DUSM!CH5+GYPG!CH5+NGLM!DP5+SAMC!EZ5+PHUA!EZ5+TSMA!CG5+GEDU!DP5+SAMA!EZ5+TCHG!DP5+GMTU!EZ5+LHAM!CG5+PHLY!GG5 -> 1 | GN5: =PARO!CH5+HAA!DQ5+WANG!FA5+PUNA!FA5+GASA!DQ5+GELA!FA5+ZEMG!FA5+TRON!FA5+BUMA!FA5+SARA!FA5+TSIR!FA5+DGNA!FA5+PANG!FA5+DPLA!FA5+SJKA!FA5+TRAG!DQ5+MONA!CI5+LUNT!FA5+TYSE!CI5+PEMA!CI5+KNLG!CI5+RJNG!CH5+WRMG!DQ5+DUSM!CI5+GYPG!CI5+NGLM!DQ5+SAMC!FA5+PHUA!FA5+TSMA!CH5+GEDU!DQ5+SAMA!FA5+TCHG!DQ5+GMTU!FA5+LHAM!CH5+PHLY!GH5 -> 0 | ... HO5: =PARO!DI5+HAA!ER5+WANG!GB5+PUNA!GB5+GASA!ER5+GELA!GB5+ZEMG!GB5+TRON!GB5+BUMA!GB5+SARA!GB5+TSIR!GB5+DGNA!GB5+PANG!GB5+DPLA!GB5+SJKA!GB5+TRAG!ER5+MONA!DJ5+LUNT!GB5+TYSE!DJ5+PEMA!DJ5+KNLG!DJ5+RJNG!DI5+WRMG!ER5+DUSM!DJ5+GYPG!DJ5+NGLM!ER5+SAMC!GB5+PHUA!GB5+TSMA!DI5+GEDU!ER5+SAMA!GB5+TCHG!ER5+GMTU!GB5+LHAM!DI5+PHLY!HI5 -> 6900 | HQ5: =ES5+GB5+HL5 -> 80 | HR5: =C5*HQ5 -> 24000 | HS5: =D5*HQ5 -> 28800 | HT5: =E5*HQ5 -> 4800 | HU5: 30 | HV5: =HQ5*HU5 -> 2400 | IN5: =AJ5+BT5+DC5+ES5+GB5+HL5 -> 186 | IO5: =AK5+BU5+DD5+ET5+GC5+HM5 -> 66960 | IP5: =AL5+BV5+DE5+EU5+GD5+HN5 -> 11160 | IQ5: =AM5+BW5+DF5+EV5+GE5+HO5 -> 55800
A6: 4 | B6: Cordyceps Happiness Tea | C6: 995 | D6: 1194 | E6: =D6-C6 -> 199 | F6: No Discount | H6: =PHLY!H6 -> 0 | I6: =PHLY!I6 -> 0 | J6: =PHLY!J6 -> 0 | K6: =PHLY!K6 -> 0 | L6: =PHLY!L6 -> 0 | M6: =PHLY!M6 -> 0 | N6: =PHLY!N6 -> 0 | O6: =PHLY!O6 -> 0 | ... AM6: =PHLY!AM6 -> 995 | AO6: =WANG!H6+PUNA!H6+GELA!H6+ZEMG!H6+TRON!H6+BUMA!H6+SARA!H6+TSIR!H6+DGNA!H6+PANG!H6+DPLA!H6+SJKA!H6+LUNT!H6+SAMC!H6+PHUA!H6+SAMA!H6+GMTU!H6+PHLY!AO6 -> 0 | AP6: =WANG!I6+PUNA!I6+GELA!I6+ZEMG!I6+TRON!I6+BUMA!I6+SARA!I6+TSIR!I6+DGNA!I6+PANG!I6+DPLA!I6+SJKA!I6+LUNT!I6+SAMC!I6+PHUA!I6+SAMA!I6+GMTU!I6+PHLY!AP6 -> 0 | AQ6: =WANG!J6+PUNA!J6+GELA!J6+ZEMG!J6+TRON!J6+BUMA!J6+SARA!J6+TSIR!J6+DGNA!J6+PANG!J6+DPLA!J6+SJKA!J6+LUNT!J6+SAMC!J6+PHUA!J6+SAMA!J6+GMTU!J6+PHLY!AQ6 -> 0 | AR6: =WANG!K6+PUNA!K6+GELA!K6+ZEMG!K6+TRON!K6+BUMA!K6+SARA!K6+TSIR!K6+DGNA!K6+PANG!K6+DPLA!K6+SJKA!K6+LUNT!K6+SAMC!K6+PHUA!K6+SAMA!K6+GMTU!K6+PHLY!AR6 -> 0 | AS6: =WANG!L6+PUNA!L6+GELA!L6+ZEMG!L6+TRON!L6+BUMA!L6+SARA!L6+TSIR!L6+DGNA!L6+PANG!L6+DPLA!L6+SJKA!L6+LUNT!L6+SAMC!L6+PHUA!L6+SAMA!L6+GMTU!L6+PHLY!AS6 -> 1 | AT6: =WANG!M6+PUNA!M6+GELA!M6+ZEMG!M6+TRON!M6+BUMA!M6+SARA!M6+TSIR!M6+DGNA!M6+PANG!M6+DPLA!M6+SJKA!M6+LUNT!M6+SAMC!M6+PHUA!M6+SAMA!M6+GMTU!M6+PHLY!AT6 -> 0 | AU6: =WANG!N6+PUNA!N6+GELA!N6+ZEMG!N6+TRON!N6+BUMA!N6+SARA!N6+TSIR!N6+DGNA!N6+PANG!N6+DPLA!N6+SJKA!N6+LUNT!N6+SAMC!N6+PHUA!N6+SAMA!N6+GMTU!N6+PHLY!AU6 -> 0 | AV6: =WANG!O6+PUNA!O6+GELA!O6+ZEMG!O6+TRON!O6+BUMA!O6+SARA!O6+TSIR!O6+DGNA!O6+PANG!O6+DPLA!O6+SJKA!O6+LUNT!O6+SAMC!O6+PHUA!O6+SAMA!O6+GMTU!O6+PHLY!AV6 -> 0 | ... BW6: =WANG!AP6+PUNA!AP6+GELA!AP6+ZEMG!AP6+TRON!AP6+BUMA!AP6+SARA!AP6+TSIR!AP6+DGNA!AP6+PANG!AP6+DPLA!AP6+SJKA!AP6+LUNT!AP6+SAMC!AP6+PHUA!AP6+SAMA!AP6+GMTU!AP6+PHLY!BW6 -> 14925 | BY6: =HAA!H6+WANG!AR6+PUNA!AR6+GASA!H6+GELA!AR6+ZEMG!AR6+TRON!AR6+BUMA!AR6+SARA!AR6+TSIR!AR6+DGNA!AR6+PANG!AR6+DPLA!AR6+SJKA!AR6+TRAG!H6+LUNT!AR6+WRMG!H6+NGLM!H6+SAMC!AR6+PHUA!AR6+GEDU!H6+SAMA!AR6+TCHG!H6+GMTU!AR6+PHLY!BY6 -> 0 | BZ6: =HAA!I6+WANG!AS6+PUNA!AS6+GASA!I6+GELA!AS6+ZEMG!AS6+TRON!AS6+BUMA!AS6+SARA!AS6+TSIR!AS6+DGNA!AS6+PANG!AS6+DPLA!AS6+SJKA!AS6+TRAG!I6+LUNT!AS6+WRMG!I6+NGLM!I6+SAMC!AS6+PHUA!AS6+GEDU!I6+SAMA!AS6+TCHG!I6+GMTU!AS6+PHLY!BZ6 -> 1 | CA6: =HAA!J6+WANG!AT6+PUNA!AT6+GASA!J6+GELA!AT6+ZEMG!AT6+TRON!AT6+BUMA!AT6+SARA!AT6+TSIR!AT6+DGNA!AT6+PANG!AT6+DPLA!AT6+SJKA!AT6+TRAG!J6+LUNT!AT6+WRMG!J6+NGLM!J6+SAMC!AT6+PHUA!AT6+GEDU!J6+SAMA!AT6+TCHG!J6+GMTU!AT6+PHLY!CA6 -> 2 | CB6: =HAA!K6+WANG!AU6+PUNA!AU6+GASA!K6+GELA!AU6+ZEMG!AU6+TRON!AU6+BUMA!AU6+SARA!AU6+TSIR!AU6+DGNA!AU6+PANG!AU6+DPLA!AU6+SJKA!AU6+TRAG!K6+LUNT!AU6+WRMG!K6+NGLM!K6+SAMC!AU6+PHUA!AU6+GEDU!K6+SAMA!AU6+TCHG!K6+GMTU!AU6+PHLY!CB6 -> 0 | CC6: =HAA!L6+WANG!AV6+PUNA!AV6+GASA!L6+GELA!AV6+ZEMG!AV6+TRON!AV6+BUMA!AV6+SARA!AV6+TSIR!AV6+DGNA!AV6+PANG!AV6+DPLA!AV6+SJKA!AV6+TRAG!L6+LUNT!AV6+WRMG!L6+NGLM!L6+SAMC!AV6+PHUA!AV6+GEDU!L6+SAMA!AV6+TCHG!L6+GMTU!AV6+PHLY!CC6 -> 0 | CD6: =HAA!M6+WANG!AW6+PUNA!AW6+GASA!M6+GELA!AW6+ZEMG!AW6+TRON!AW6+BUMA!AW6+SARA!AW6+TSIR!AW6+DGNA!AW6+PANG!AW6+DPLA!AW6+SJKA!AW6+TRAG!M6+LUNT!AW6+WRMG!M6+NGLM!M6+SAMC!AW6+PHUA!AW6+GEDU!M6+SAMA!AW6+TCHG!M6+GMTU!AW6+PHLY!CD6 -> 0 | CE6: =HAA!N6+WANG!AX6+PUNA!AX6+GASA!N6+GELA!AX6+ZEMG!AX6+TRON!AX6+BUMA!AX6+SARA!AX6+TSIR!AX6+DGNA!AX6+PANG!AX6+DPLA!AX6+SJKA!AX6+TRAG!N6+LUNT!AX6+WRMG!N6+NGLM!N6+SAMC!AX6+PHUA!AX6+GEDU!N6+SAMA!AX6+TCHG!N6+GMTU!AX6+PHLY!CE6 -> 0 | CF6: =HAA!O6+WANG!AY6+PUNA!AY6+GASA!O6+GELA!AY6+ZEMG!AY6+TRON!AY6+BUMA!AY6+SARA!AY6+TSIR!AY6+DGNA!AY6+PANG!AY6+DPLA!AY6+SJKA!AY6+TRAG!O6+LUNT!AY6+WRMG!O6+NGLM!O6+SAMC!AY6+PHUA!AY6+GEDU!O6+SAMA!AY6+TCHG!O6+GMTU!AY6+PHLY!CF6 -> 0 | ... DF6: =HAA!AO6+WANG!BY6+PUNA!BY6+GASA!AO6+GELA!BY6+ZEMG!BY6+TRON!BY6+BUMA!BY6+SARA!BY6+TSIR!BY6+DGNA!BY6+PANG!BY6+DPLA!BY6+SJKA!BY6+TRAG!AO6+LUNT!BY6+WRMG!AO6+NGLM!AO6+SAMC!BY6+PHUA!BY6+GEDU!AO6+SAMA!BY6+TCHG!AO6+GMTU!BY6+PHLY!DF6 -> 30845 | DG6: =AJ6+BT6+DC6 -> 47 | DH6: =C6*DG6 -> 46765 | DI6: =D6*DG6 -> 56118 | DJ6: =E6*DG6 -> 9353 | DN6: =PARO!H6+HAA!AQ6+WANG!CA6+PUNA!CA6+GASA!AQ6+GELA!CA6+ZEMG!CA6+TRON!CA6+BUMA!CA6+SARA!CA6+TSIR!CA6+DGNA!CA6+PANG!CA6+DPLA!CA6+SJKA!CA6+TRAG!AQ6+MONA!H6+LUNT!CA6+TYSE!H6+PEMA!H6+KNLG!H6+RJNG!H6+WRMG!AQ6+DUSM!H6+GYPG!H6+NGLM!AQ6+SAMC!CA6+PHUA!CA6+TSMA!H6+GEDU!AQ6+SAMA!CA6+TCHG!AQ6+GMTU!CA6+LHAM!H6+PHLY!DH6 -> 0 | DO6: =PARO!I6+HAA!AR6+WANG!CB6+PUNA!CB6+GASA!AR6+GELA!CB6+ZEMG!CB6+TRON!CB6+BUMA!CB6+SARA!CB6+TSIR!CB6+DGNA!CB6+PANG!CB6+DPLA!CB6+SJKA!CB6+TRAG!AR6+MONA!I6+LUNT!CB6+TYSE!I6+PEMA!I6+KNLG!I6+RJNG!I6+WRMG!AR6+DUSM!I6+GYPG!I6+NGLM!AR6+SAMC!CB6+PHUA!CB6+TSMA!I6+GEDU!AR6+SAMA!CB6+TCHG!AR6+GMTU!CB6+LHAM!I6+PHLY!DI6 -> 0 | DP6: =PARO!J6+HAA!AS6+WANG!CC6+PUNA!CC6+GASA!AS6+GELA!CC6+ZEMG!CC6+TRON!CC6+BUMA!CC6+SARA!CC6+TSIR!CC6+DGNA!CC6+PANG!CC6+DPLA!CC6+SJKA!CC6+TRAG!AS6+MONA!J6+LUNT!CC6+TYSE!J6+PEMA!J6+KNLG!J6+RJNG!J6+WRMG!AS6+DUSM!J6+GYPG!J6+NGLM!AS6+SAMC!CC6+PHUA!CC6+TSMA!J6+GEDU!AS6+SAMA!CC6+TCHG!AS6+GMTU!CC6+LHAM!J6+PHLY!DJ6 -> 0 | DQ6: =PARO!K6+HAA!AT6+WANG!CD6+PUNA!CD6+GASA!AT6+GELA!CD6+ZEMG!CD6+TRON!CD6+BUMA!CD6+SARA!CD6+TSIR!CD6+DGNA!CD6+PANG!CD6+DPLA!CD6+SJKA!CD6+TRAG!AT6+MONA!K6+LUNT!CD6+TYSE!K6+PEMA!K6+KNLG!K6+RJNG!K6+WRMG!AT6+DUSM!K6+GYPG!K6+NGLM!AT6+SAMC!CD6+PHUA!CD6+TSMA!K6+GEDU!AT6+SAMA!CD6+TCHG!AT6+GMTU!CD6+LHAM!K6+PHLY!DK6 -> 0 | DR6: =PARO!L6+HAA!AU6+WANG!CE6+PUNA!CE6+GASA!AU6+GELA!CE6+ZEMG!CE6+TRON!CE6+BUMA!CE6+SARA!CE6+TSIR!CE6+DGNA!CE6+PANG!CE6+DPLA!CE6+SJKA!CE6+TRAG!AU6+MONA!L6+LUNT!CE6+TYSE!L6+PEMA!L6+KNLG!L6+RJNG!L6+WRMG!AU6+DUSM!L6+GYPG!L6+NGLM!AU6+SAMC!CE6+PHUA!CE6+TSMA!L6+GEDU!AU6+SAMA!CE6+TCHG!AU6+GMTU!CE6+LHAM!L6+PHLY!DL6 -> 2 | DS6: =PARO!M6+HAA!AV6+WANG!CF6+PUNA!CF6+GASA!AV6+GELA!CF6+ZEMG!CF6+TRON!CF6+BUMA!CF6+SARA!CF6+TSIR!CF6+DGNA!CF6+PANG!CF6+DPLA!CF6+SJKA!CF6+TRAG!AV6+MONA!M6+LUNT!CF6+TYSE!M6+PEMA!M6+KNLG!M6+RJNG!M6+WRMG!AV6+DUSM!M6+GYPG!M6+NGLM!AV6+SAMC!CF6+PHUA!CF6+TSMA!M6+GEDU!AV6+SAMA!CF6+TCHG!AV6+GMTU!CF6+LHAM!M6+PHLY!DM6 -> 3 | DT6: =PARO!N6+HAA!AW6+WANG!CG6+PUNA!CG6+GASA!AW6+GELA!CG6+ZEMG!CG6+TRON!CG6+BUMA!CG6+SARA!CG6+TSIR!CG6+DGNA!CG6+PANG!CG6+DPLA!CG6+SJKA!CG6+TRAG!AW6+MONA!N6+LUNT!CG6+TYSE!N6+PEMA!N6+KNLG!N6+RJNG!N6+WRMG!AW6+DUSM!N6+GYPG!N6+NGLM!AW6+SAMC!CG6+PHUA!CG6+TSMA!N6+GEDU!AW6+SAMA!CG6+TCHG!AW6+GMTU!CG6+LHAM!N6+PHLY!DN6 -> 0 | DU6: =PARO!O6+HAA!AX6+WANG!CH6+PUNA!CH6+GASA!AX6+GELA!CH6+ZEMG!CH6+TRON!CH6+BUMA!CH6+SARA!CH6+TSIR!CH6+DGNA!CH6+PANG!CH6+DPLA!CH6+SJKA!CH6+TRAG!AX6+MONA!O6+LUNT!CH6+TYSE!O6+PEMA!O6+KNLG!O6+RJNG!O6+WRMG!AX6+DUSM!O6+GYPG!O6+NGLM!AX6+SAMC!CH6+PHUA!CH6+TSMA!O6+GEDU!AX6+SAMA!CH6+TCHG!AX6+GMTU!CH6+LHAM!O6+PHLY!DO6 -> 6 | ... EV6: =PARO!AP6+HAA!BY6+WANG!DI6+PUNA!DI6+GASA!BY6+GELA!DI6+ZEMG!DI6+TRON!DI6+BUMA!DI6+SARA!DI6+TSIR!DI6+DGNA!DI6+PANG!DI6+DPLA!DI6+SJKA!DI6+TRAG!BY6+MONA!AP6+LUNT!DI6+TYSE!AP6+PEMA!AP6+KNLG!AP6+RJNG!AP6+WRMG!BY6+DUSM!AP6+GYPG!AP6+NGLM!BY6+SAMC!DI6+PHUA!DI6+TSMA!AP6+GEDU!BY6+SAMA!DI6+TCHG!BY6+GMTU!DI6+LHAM!AP6+PHLY!EP6 -> 21890 | EX6: =PARO!AR6+HAA!CA6+WANG!DK6+PUNA!DK6+GASA!CA6+GELA!DK6+ZEMG!DK6+TRON!DK6+BUMA!DK6+SARA!DK6+TSIR!DK6+DGNA!DK6+PANG!DK6+DPLA!DK6+SJKA!DK6+TRAG!CA6+MONA!AR6+LUNT!DK6+TYSE!AR6+PEMA!AR6+KNLG!AR6+RJNG!AR6+WRMG!CA6+DUSM!AR6+GYPG!AR6+NGLM!CA6+SAMC!DK6+PHUA!DK6+TSMA!AR6+GEDU!CA6+SAMA!DK6+TCHG!CA6+GMTU!DK6+LHAM!AR6+PHLY!ER6 -> 0 | EY6: =PARO!AS6+HAA!CB6+WANG!DL6+PUNA!DL6+GASA!CB6+GELA!DL6+ZEMG!DL6+TRON!DL6+BUMA!DL6+SARA!DL6+TSIR!DL6+DGNA!DL6+PANG!DL6+DPLA!DL6+SJKA!DL6+TRAG!CB6+MONA!AS6+LUNT!DL6+TYSE!AS6+PEMA!AS6+KNLG!AS6+RJNG!AS6+WRMG!CB6+DUSM!AS6+GYPG!AS6+NGLM!CB6+SAMC!DL6+PHUA!DL6+TSMA!AS6+GEDU!CB6+SAMA!DL6+TCHG!CB6+GMTU!DL6+LHAM!AS6+PHLY!ES6 -> 0 | EZ6: =PARO!AT6+HAA!CC6+WANG!DM6+PUNA!DM6+GASA!CC6+GELA!DM6+ZEMG!DM6+TRON!DM6+BUMA!DM6+SARA!DM6+TSIR!DM6+DGNA!DM6+PANG!DM6+DPLA!DM6+SJKA!DM6+TRAG!CC6+MONA!AT6+LUNT!DM6+TYSE!AT6+PEMA!AT6+KNLG!AT6+RJNG!AT6+WRMG!CC6+DUSM!AT6+GYPG!AT6+NGLM!CC6+SAMC!DM6+PHUA!DM6+TSMA!AT6+GEDU!CC6+SAMA!DM6+TCHG!CC6+GMTU!DM6+LHAM!AT6+PHLY!ET6 -> 0 | FA6: =PARO!AU6+HAA!CD6+WANG!DN6+PUNA!DN6+GASA!CD6+GELA!DN6+ZEMG!DN6+TRON!DN6+BUMA!DN6+SARA!DN6+TSIR!DN6+DGNA!DN6+PANG!DN6+DPLA!DN6+SJKA!DN6+TRAG!CD6+MONA!AU6+LUNT!DN6+TYSE!AU6+PEMA!AU6+KNLG!AU6+RJNG!AU6+WRMG!CD6+DUSM!AU6+GYPG!AU6+NGLM!CD6+SAMC!DN6+PHUA!DN6+TSMA!AU6+GEDU!CD6+SAMA!DN6+TCHG!CD6+GMTU!DN6+LHAM!AU6+PHLY!EU6 -> 0 | FB6: =PARO!AV6+HAA!CE6+WANG!DO6+PUNA!DO6+GASA!CE6+GELA!DO6+ZEMG!DO6+TRON!DO6+BUMA!DO6+SARA!DO6+TSIR!DO6+DGNA!DO6+PANG!DO6+DPLA!DO6+SJKA!DO6+TRAG!CE6+MONA!AV6+LUNT!DO6+TYSE!AV6+PEMA!AV6+KNLG!AV6+RJNG!AV6+WRMG!CE6+DUSM!AV6+GYPG!AV6+NGLM!CE6+SAMC!DO6+PHUA!DO6+TSMA!AV6+GEDU!CE6+SAMA!DO6+TCHG!CE6+GMTU!DO6+LHAM!AV6+PHLY!EV6 -> 0 | FC6: =PARO!AW6+HAA!CF6+WANG!DP6+PUNA!DP6+GASA!CF6+GELA!DP6+ZEMG!DP6+TRON!DP6+BUMA!DP6+SARA!DP6+TSIR!DP6+DGNA!DP6+PANG!DP6+DPLA!DP6+SJKA!DP6+TRAG!CF6+MONA!AW6+LUNT!DP6+TYSE!AW6+PEMA!AW6+KNLG!AW6+RJNG!AW6+WRMG!CF6+DUSM!AW6+GYPG!AW6+NGLM!CF6+SAMC!DP6+PHUA!DP6+TSMA!AW6+GEDU!CF6+SAMA!DP6+TCHG!CF6+GMTU!DP6+LHAM!AW6+PHLY!EW6 -> 0 | FD6: =PARO!AX6+HAA!CG6+WANG!DQ6+PUNA!DQ6+GASA!CG6+GELA!DQ6+ZEMG!DQ6+TRON!DQ6+BUMA!DQ6+SARA!DQ6+TSIR!DQ6+DGNA!DQ6+PANG!DQ6+DPLA!DQ6+SJKA!DQ6+TRAG!CG6+MONA!AX6+LUNT!DQ6+TYSE!AX6+PEMA!AX6+KNLG!AX6+RJNG!AX6+WRMG!CG6+DUSM!AX6+GYPG!AX6+NGLM!CG6+SAMC!DQ6+PHUA!DQ6+TSMA!AX6+GEDU!CG6+SAMA!DQ6+TCHG!CG6+GMTU!DQ6+LHAM!AX6+PHLY!EX6 -> 5 | FE6: =PARO!AY6+HAA!CH6+WANG!DR6+PUNA!DR6+GASA!CH6+GELA!DR6+ZEMG!DR6+TRON!DR6+BUMA!DR6+SARA!DR6+TSIR!DR6+DGNA!DR6+PANG!DR6+DPLA!DR6+SJKA!DR6+TRAG!CH6+MONA!AY6+LUNT!DR6+TYSE!AY6+PEMA!AY6+KNLG!AY6+RJNG!AY6+WRMG!CH6+DUSM!AY6+GYPG!AY6+NGLM!CH6+SAMC!DR6+PHUA!DR6+TSMA!AY6+GEDU!CH6+SAMA!DR6+TCHG!CH6+GMTU!DR6+LHAM!AY6+PHLY!EY6 -> 0 | ... GA6: =PARO!BU6+HAA!DD6+WANG!EN6+PUNA!EN6+GASA!DD6+GELA!EN6+ZEMG!EN6+TRON!EN6+BUMA!EN6+SARA!EN6+TSIR!EN6+DGNA!EN6+PANG!EN6+DPLA!EN6+SJKA!EN6+TRAG!DD6+MONA!BU6+LUNT!EN6+TYSE!BU6+PEMA!BU6+KNLG!BU6+RJNG!BU6+WRMG!DD6+DUSM!BU6+GYPG!BU6+NGLM!DD6+SAMC!EN6+PHUA!EN6+TSMA!BU6+GEDU!DD6+SAMA!EN6+TCHG!DD6+GMTU!EN6+LHAM!BU6+PHLY!FU6 -> 0 | GB6: =PARO!BV6+HAA!DE6+WANG!EO6+PUNA!EO6+GASA!DE6+GELA!EO6+ZEMG!EO6+TRON!EO6+BUMA!EO6+SARA!EO6+TSIR!EO6+DGNA!EO6+PANG!EO6+DPLA!EO6+SJKA!EO6+TRAG!DE6+MONA!BW6+LUNT!EO6+TYSE!BW6+PEMA!BW6+KNLG!BW6+RJNG!BV6+WRMG!DE6+DUSM!BW6+GYPG!BW6+NGLM!DE6+SAMC!EO6+PHUA!EO6+TSMA!BV6+GEDU!DE6+SAMA!EO6+TCHG!DE6+GMTU!EO6+LHAM!BV6+PHLY!FV6 -> 13 | GC6: =PARO!BW6+HAA!DF6+WANG!EP6+PUNA!EP6+GASA!DF6+GELA!EP6+ZEMG!EP6+TRON!EP6+BUMA!EP6+SARA!EP6+TSIR!EP6+DGNA!EP6+PANG!EP6+DPLA!EP6+SJKA!EP6+TRAG!DF6+MONA!BX6+LUNT!EP6+TYSE!BX6+PEMA!BX6+KNLG!BX6+RJNG!BW6+WRMG!DF6+DUSM!BX6+GYPG!BX6+NGLM!DF6+SAMC!EP6+PHUA!EP6+TSMA!BW6+GEDU!DF6+SAMA!EP6+TCHG!DF6+GMTU!EP6+LHAM!BW6+PHLY!FW6 -> 15522 | GD6: =PARO!BX6+HAA!DG6+WANG!EQ6+PUNA!EQ6+GASA!DG6+GELA!EQ6+ZEMG!EQ6+TRON!EQ6+BUMA!EQ6+SARA!EQ6+TSIR!EQ6+DGNA!EQ6+PANG!EQ6+DPLA!EQ6+SJKA!EQ6+TRAG!DG6+MONA!BY6+LUNT!EQ6+TYSE!BY6+PEMA!BY6+KNLG!BY6+RJNG!BX6+WRMG!DG6+DUSM!BY6+GYPG!BY6+NGLM!DG6+SAMC!EQ6+PHUA!EQ6+TSMA!BX6+GEDU!DG6+SAMA!EQ6+TCHG!DG6+GMTU!EQ6+LHAM!BX6+PHLY!FX6 -> 2587 | GE6: =PARO!BY6+HAA!DH6+WANG!ER6+PUNA!ER6+GASA!DH6+GELA!ER6+ZEMG!ER6+TRON!ER6+BUMA!ER6+SARA!ER6+TSIR!ER6+DGNA!ER6+PANG!ER6+DPLA!ER6+SJKA!ER6+TRAG!DH6+MONA!BZ6+LUNT!ER6+TYSE!BZ6+PEMA!BZ6+KNLG!BZ6+RJNG!BY6+WRMG!DH6+DUSM!BZ6+GYPG!BZ6+NGLM!DH6+SAMC!ER6+PHUA!ER6+TSMA!BY6+GEDU!DH6+SAMA!ER6+TCHG!DH6+GMTU!ER6+LHAM!BY6+PHLY!FY6 -> 12935 | GG6: =PARO!CA6+HAA!DJ6+WANG!ET6+PUNA!ET6+GASA!DJ6+GELA!ET6+ZEMG!ET6+TRON!ET6+BUMA!ET6+SARA!ET6+TSIR!ET6+DGNA!ET6+PANG!ET6+DPLA!ET6+SJKA!ET6+TRAG!DJ6+MONA!CB6+LUNT!ET6+TYSE!CB6+PEMA!CB6+KNLG!CB6+RJNG!CA6+WRMG!DJ6+DUSM!CB6+GYPG!CB6+NGLM!DJ6+SAMC!ET6+PHUA!ET6+TSMA!CA6+GEDU!DJ6+SAMA!ET6+TCHG!DJ6+GMTU!ET6+LHAM!CA6+PHLY!GA6 -> 0 | GH6: =PARO!CB6+HAA!DK6+WANG!EU6+PUNA!EU6+GASA!DK6+GELA!EU6+ZEMG!EU6+TRON!EU6+BUMA!EU6+SARA!EU6+TSIR!EU6+DGNA!EU6+PANG!EU6+DPLA!EU6+SJKA!EU6+TRAG!DK6+MONA!CC6+LUNT!EU6+TYSE!CC6+PEMA!CC6+KNLG!CC6+RJNG!CB6+WRMG!DK6+DUSM!CC6+GYPG!CC6+NGLM!DK6+SAMC!EU6+PHUA!EU6+TSMA!CB6+GEDU!DK6+SAMA!EU6+TCHG!DK6+GMTU!EU6+LHAM!CB6+PHLY!GB6 -> 2 | GI6: =PARO!CC6+HAA!DL6+WANG!EV6+PUNA!EV6+GASA!DL6+GELA!EV6+ZEMG!EV6+TRON!EV6+BUMA!EV6+SARA!EV6+TSIR!EV6+DGNA!EV6+PANG!EV6+DPLA!EV6+SJKA!EV6+TRAG!DL6+MONA!CD6+LUNT!EV6+TYSE!CD6+PEMA!CD6+KNLG!CD6+RJNG!CC6+WRMG!DL6+DUSM!CD6+GYPG!CD6+NGLM!DL6+SAMC!EV6+PHUA!EV6+TSMA!CC6+GEDU!DL6+SAMA!EV6+TCHG!DL6+GMTU!EV6+LHAM!CC6+PHLY!GC6 -> 0 | GJ6: =PARO!CD6+HAA!DM6+WANG!EW6+PUNA!EW6+GASA!DM6+GELA!EW6+ZEMG!EW6+TRON!EW6+BUMA!EW6+SARA!EW6+TSIR!EW6+DGNA!EW6+PANG!EW6+DPLA!EW6+SJKA!EW6+TRAG!DM6+MONA!CE6+LUNT!EW6+TYSE!CE6+PEMA!CE6+KNLG!CE6+RJNG!CD6+WRMG!DM6+DUSM!CE6+GYPG!CE6+NGLM!DM6+SAMC!EW6+PHUA!EW6+TSMA!CD6+GEDU!DM6+SAMA!EW6+TCHG!DM6+GMTU!EW6+LHAM!CD6+PHLY!GD6 -> 1 | GK6: =PARO!CE6+HAA!DN6+WANG!EX6+PUNA!EX6+GASA!DN6+GELA!EX6+ZEMG!EX6+TRON!EX6+BUMA!EX6+SARA!EX6+TSIR!EX6+DGNA!EX6+PANG!EX6+DPLA!EX6+SJKA!EX6+TRAG!DN6+MONA!CF6+LUNT!EX6+TYSE!CF6+PEMA!CF6+KNLG!CF6+RJNG!CE6+WRMG!DN6+DUSM!CF6+GYPG!CF6+NGLM!DN6+SAMC!EX6+PHUA!EX6+TSMA!CE6+GEDU!DN6+SAMA!EX6+TCHG!DN6+GMTU!EX6+LHAM!CE6+PHLY!GE6 -> 0 | GL6: =PARO!CF6+HAA!DO6+WANG!EY6+PUNA!EY6+GASA!DO6+GELA!EY6+ZEMG!EY6+TRON!EY6+BUMA!EY6+SARA!EY6+TSIR!EY6+DGNA!EY6+PANG!EY6+DPLA!EY6+SJKA!EY6+TRAG!DO6+MONA!CG6+LUNT!EY6+TYSE!CG6+PEMA!CG6+KNLG!CG6+RJNG!CF6+WRMG!DO6+DUSM!CG6+GYPG!CG6+NGLM!DO6+SAMC!EY6+PHUA!EY6+TSMA!CF6+GEDU!DO6+SAMA!EY6+TCHG!DO6+GMTU!EY6+LHAM!CF6+PHLY!GF6 -> 0 | GM6: =PARO!CG6+HAA!DP6+WANG!EZ6+PUNA!EZ6+GASA!DP6+GELA!EZ6+ZEMG!EZ6+TRON!EZ6+BUMA!EZ6+SARA!EZ6+TSIR!EZ6+DGNA!EZ6+PANG!EZ6+DPLA!EZ6+SJKA!EZ6+TRAG!DP6+MONA!CH6+LUNT!EZ6+TYSE!CH6+PEMA!CH6+KNLG!CH6+RJNG!CG6+WRMG!DP6+DUSM!CH6+GYPG!CH6+NGLM!DP6+SAMC!EZ6+PHUA!EZ6+TSMA!CG6+GEDU!DP6+SAMA!EZ6+TCHG!DP6+GMTU!EZ6+LHAM!CG6+PHLY!GG6 -> 0 | GN6: =PARO!CH6+HAA!DQ6+WANG!FA6+PUNA!FA6+GASA!DQ6+GELA!FA6+ZEMG!FA6+TRON!FA6+BUMA!FA6+SARA!FA6+TSIR!FA6+DGNA!FA6+PANG!FA6+DPLA!FA6+SJKA!FA6+TRAG!DQ6+MONA!CI6+LUNT!FA6+TYSE!CI6+PEMA!CI6+KNLG!CI6+RJNG!CH6+WRMG!DQ6+DUSM!CI6+GYPG!CI6+NGLM!DQ6+SAMC!FA6+PHUA!FA6+TSMA!CH6+GEDU!DQ6+SAMA!FA6+TCHG!DQ6+GMTU!FA6+LHAM!CH6+PHLY!GH6 -> 0 | ... HO6: =PARO!DI6+HAA!ER6+WANG!GB6+PUNA!GB6+GASA!ER6+GELA!GB6+ZEMG!GB6+TRON!GB6+BUMA!GB6+SARA!GB6+TSIR!GB6+DGNA!GB6+PANG!GB6+DPLA!GB6+SJKA!GB6+TRAG!ER6+MONA!DJ6+LUNT!GB6+TYSE!DJ6+PEMA!DJ6+KNLG!DJ6+RJNG!DI6+WRMG!ER6+DUSM!DJ6+GYPG!DJ6+NGLM!ER6+SAMC!GB6+PHUA!GB6+TSMA!DI6+GEDU!ER6+SAMA!GB6+TCHG!ER6+GMTU!GB6+LHAM!DI6+PHLY!HI6 -> 3980 | HQ6: =ES6+GB6+HL6 -> 39 | HR6: =C6*HQ6 -> 38805 | HS6: =D6*HQ6 -> 46566 | HT6: =E6*HQ6 -> 7761 | IN6: =AJ6+BT6+DC6+ES6+GB6+HL6 -> 86 | IO6: =AK6+BU6+DD6+ET6+GC6+HM6 -> 102684 | IP6: =AL6+BV6+DE6+EU6+GD6+HN6 -> 17114 | IQ6: =AM6+BW6+DF6+EV6+GE6+HO6 -> 85570
A7: 5 | B7: CordyPlus | C7: 3500 | D7: 4200 | E7: =D7-C7 -> 700 | H7: =PHLY!H7 -> 0 | I7: =PHLY!I7 -> 0 | J7: =PHLY!J7 -> 0 | K7: =PHLY!K7 -> 0 | L7: =PHLY!L7 -> 0 | M7: =PHLY!M7 -> 0 | N7: =PHLY!N7 -> 0 | O7: =PHLY!O7 -> 0 | ... AM7: =PHLY!AM7 -> 0 | AO7: =WANG!H7+PUNA!H7+GELA!H7+ZEMG!H7+TRON!H7+BUMA!H7+SARA!H7+TSIR!H7+DGNA!H7+PANG!H7+DPLA!H7+SJKA!H7+LUNT!H7+SAMC!H7+PHUA!H7+SAMA!H7+GMTU!H7+PHLY!AO7 -> 0 | AP7: =WANG!I7+PUNA!I7+GELA!I7+ZEMG!I7+TRON!I7+BUMA!I7+SARA!I7+TSIR!I7+DGNA!I7+PANG!I7+DPLA!I7+SJKA!I7+LUNT!I7+SAMC!I7+PHUA!I7+SAMA!I7+GMTU!I7+PHLY!AP7 -> 0 | AQ7: =WANG!J7+PUNA!J7+GELA!J7+ZEMG!J7+TRON!J7+BUMA!J7+SARA!J7+TSIR!J7+DGNA!J7+PANG!J7+DPLA!J7+SJKA!J7+LUNT!J7+SAMC!J7+PHUA!J7+SAMA!J7+GMTU!J7+PHLY!AQ7 -> 0 | AR7: =WANG!K7+PUNA!K7+GELA!K7+ZEMG!K7+TRON!K7+BUMA!K7+SARA!K7+TSIR!K7+DGNA!K7+PANG!K7+DPLA!K7+SJKA!K7+LUNT!K7+SAMC!K7+PHUA!K7+SAMA!K7+GMTU!K7+PHLY!AR7 -> 0 | AS7: =WANG!L7+PUNA!L7+GELA!L7+ZEMG!L7+TRON!L7+BUMA!L7+SARA!L7+TSIR!L7+DGNA!L7+PANG!L7+DPLA!L7+SJKA!L7+LUNT!L7+SAMC!L7+PHUA!L7+SAMA!L7+GMTU!L7+PHLY!AS7 -> 0 | AT7: =WANG!M7+PUNA!M7+GELA!M7+ZEMG!M7+TRON!M7+BUMA!M7+SARA!M7+TSIR!M7+DGNA!M7+PANG!M7+DPLA!M7+SJKA!M7+LUNT!M7+SAMC!M7+PHUA!M7+SAMA!M7+GMTU!M7+PHLY!AT7 -> 0 | AU7: =WANG!N7+PUNA!N7+GELA!N7+ZEMG!N7+TRON!N7+BUMA!N7+SARA!N7+TSIR!N7+DGNA!N7+PANG!N7+DPLA!N7+SJKA!N7+LUNT!N7+SAMC!N7+PHUA!N7+SAMA!N7+GMTU!N7+PHLY!AU7 -> 0 | AV7: =WANG!O7+PUNA!O7+GELA!O7+ZEMG!O7+TRON!O7+BUMA!O7+SARA!O7+TSIR!O7+DGNA!O7+PANG!O7+DPLA!O7+SJKA!O7+LUNT!O7+SAMC!O7+PHUA!O7+SAMA!O7+GMTU!O7+PHLY!AV7 -> 0 | ... BW7: =WANG!AP7+PUNA!AP7+GELA!AP7+ZEMG!AP7+TRON!AP7+BUMA!AP7+SARA!AP7+TSIR!AP7+DGNA!AP7+PANG!AP7+DPLA!AP7+SJKA!AP7+LUNT!AP7+SAMC!AP7+PHUA!AP7+SAMA!AP7+GMTU!AP7+PHLY!BW7 -> 0 | BY7: =HAA!H7+WANG!AR7+PUNA!AR7+GASA!H7+GELA!AR7+ZEMG!AR7+TRON!AR7+BUMA!AR7+SARA!AR7+TSIR!AR7+DGNA!AR7+PANG!AR7+DPLA!AR7+SJKA!AR7+TRAG!H7+LUNT!AR7+WRMG!H7+NGLM!H7+SAMC!AR7+PHUA!AR7+GEDU!H7+SAMA!AR7+TCHG!H7+GMTU!AR7+PHLY!BY7 -> 0 | BZ7: =HAA!I7+WANG!AS7+PUNA!AS7+GASA!I7+GELA!AS7+ZEMG!AS7+TRON!AS7+BUMA!AS7+SARA!AS7+TSIR!AS7+DGNA!AS7+PANG!AS7+DPLA!AS7+SJKA!AS7+TRAG!I7+LUNT!AS7+WRMG!I7+NGLM!I7+SAMC!AS7+PHUA!AS7+GEDU!I7+SAMA!AS7+TCHG!I7+GMTU!AS7+PHLY!BZ7 -> 0 | CA7: =HAA!J7+WANG!AT7+PUNA!AT7+GASA!J7+GELA!AT7+ZEMG!AT7+TRON!AT7+BUMA!AT7+SARA!AT7+TSIR!AT7+DGNA!AT7+PANG!AT7+DPLA!AT7+SJKA!AT7+TRAG!J7+LUNT!AT7+WRMG!J7+NGLM!J7+SAMC!AT7+PHUA!AT7+GEDU!J7+SAMA!AT7+TCHG!J7+GMTU!AT7+PHLY!CA7 -> 0 | CB7: =HAA!K7+WANG!AU7+PUNA!AU7+GASA!K7+GELA!AU7+ZEMG!AU7+TRON!AU7+BUMA!AU7+SARA!AU7+TSIR!AU7+DGNA!AU7+PANG!AU7+DPLA!AU7+SJKA!AU7+TRAG!K7+LUNT!AU7+WRMG!K7+NGLM!K7+SAMC!AU7+PHUA!AU7+GEDU!K7+SAMA!AU7+TCHG!K7+GMTU!AU7+PHLY!CB7 -> 0 | CC7: =HAA!L7+WANG!AV7+PUNA!AV7+GASA!L7+GELA!AV7+ZEMG!AV7+TRON!AV7+BUMA!AV7+SARA!AV7+TSIR!AV7+DGNA!AV7+PANG!AV7+DPLA!AV7+SJKA!AV7+TRAG!L7+LUNT!AV7+WRMG!L7+NGLM!L7+SAMC!AV7+PHUA!AV7+GEDU!L7+SAMA!AV7+TCHG!L7+GMTU!AV7+PHLY!CC7 -> 0 | CD7: =HAA!M7+WANG!AW7+PUNA!AW7+GASA!M7+GELA!AW7+ZEMG!AW7+TRON!AW7+BUMA!AW7+SARA!AW7+TSIR!AW7+DGNA!AW7+PANG!AW7+DPLA!AW7+SJKA!AW7+TRAG!M7+LUNT!AW7+WRMG!M7+NGLM!M7+SAMC!AW7+PHUA!AW7+GEDU!M7+SAMA!AW7+TCHG!M7+GMTU!AW7+PHLY!CD7 -> 0 | CE7: =HAA!N7+WANG!AX7+PUNA!AX7+GASA!N7+GELA!AX7+ZEMG!AX7+TRON!AX7+BUMA!AX7+SARA!AX7+TSIR!AX7+DGNA!AX7+PANG!AX7+DPLA!AX7+SJKA!AX7+TRAG!N7+LUNT!AX7+WRMG!N7+NGLM!N7+SAMC!AX7+PHUA!AX7+GEDU!N7+SAMA!AX7+TCHG!N7+GMTU!AX7+PHLY!CE7 -> 0 | CF7: =HAA!O7+WANG!AY7+PUNA!AY7+GASA!O7+GELA!AY7+ZEMG!AY7+TRON!AY7+BUMA!AY7+SARA!AY7+TSIR!AY7+DGNA!AY7+PANG!AY7+DPLA!AY7+SJKA!AY7+TRAG!O7+LUNT!AY7+WRMG!O7+NGLM!O7+SAMC!AY7+PHUA!AY7+GEDU!O7+SAMA!AY7+TCHG!O7+GMTU!AY7+PHLY!CF7 -> 0 | ... DF7: =HAA!AO7+WANG!BY7+PUNA!BY7+GASA!AO7+GELA!BY7+ZEMG!BY7+TRON!BY7+BUMA!BY7+SARA!BY7+TSIR!BY7+DGNA!BY7+PANG!BY7+DPLA!BY7+SJKA!BY7+TRAG!AO7+LUNT!BY7+WRMG!AO7+NGLM!AO7+SAMC!BY7+PHUA!BY7+GEDU!AO7+SAMA!BY7+TCHG!AO7+GMTU!BY7+PHLY!DF7 -> 3500 | DG7: =AJ7+BT7+DC7 -> 1 | DH7: =C7*DG7 -> 3500 | DI7: =D7*DG7 -> 4200 | DJ7: =E7*DG7 -> 700 | DN7: =PARO!H7+HAA!AQ7+WANG!CA7+PUNA!CA7+GASA!AQ7+GELA!CA7+ZEMG!CA7+TRON!CA7+BUMA!CA7+SARA!CA7+TSIR!CA7+DGNA!CA7+PANG!CA7+DPLA!CA7+SJKA!CA7+TRAG!AQ7+MONA!H7+LUNT!CA7+TYSE!H7+PEMA!H7+KNLG!H7+RJNG!H7+WRMG!AQ7+DUSM!H7+GYPG!H7+NGLM!AQ7+SAMC!CA7+PHUA!CA7+TSMA!H7+GEDU!AQ7+SAMA!CA7+TCHG!AQ7+GMTU!CA7+LHAM!H7+PHLY!DH7 -> 0 | DO7: =PARO!I7+HAA!AR7+WANG!CB7+PUNA!CB7+GASA!AR7+GELA!CB7+ZEMG!CB7+TRON!CB7+BUMA!CB7+SARA!CB7+TSIR!CB7+DGNA!CB7+PANG!CB7+DPLA!CB7+SJKA!CB7+TRAG!AR7+MONA!I7+LUNT!CB7+TYSE!I7+PEMA!I7+KNLG!I7+RJNG!I7+WRMG!AR7+DUSM!I7+GYPG!I7+NGLM!AR7+SAMC!CB7+PHUA!CB7+TSMA!I7+GEDU!AR7+SAMA!CB7+TCHG!AR7+GMTU!CB7+LHAM!I7+PHLY!DI7 -> 0 | DP7: =PARO!J7+HAA!AS7+WANG!CC7+PUNA!CC7+GASA!AS7+GELA!CC7+ZEMG!CC7+TRON!CC7+BUMA!CC7+SARA!CC7+TSIR!CC7+DGNA!CC7+PANG!CC7+DPLA!CC7+SJKA!CC7+TRAG!AS7+MONA!J7+LUNT!CC7+TYSE!J7+PEMA!J7+KNLG!J7+RJNG!J7+WRMG!AS7+DUSM!J7+GYPG!J7+NGLM!AS7+SAMC!CC7+PHUA!CC7+TSMA!J7+GEDU!AS7+SAMA!CC7+TCHG!AS7+GMTU!CC7+LHAM!J7+PHLY!DJ7 -> 0 | DQ7: =PARO!K7+HAA!AT7+WANG!CD7+PUNA!CD7+GASA!AT7+GELA!CD7+ZEMG!CD7+TRON!CD7+BUMA!CD7+SARA!CD7+TSIR!CD7+DGNA!CD7+PANG!CD7+DPLA!CD7+SJKA!CD7+TRAG!AT7+MONA!K7+LUNT!CD7+TYSE!K7+PEMA!K7+KNLG!K7+RJNG!K7+WRMG!AT7+DUSM!K7+GYPG!K7+NGLM!AT7+SAMC!CD7+PHUA!CD7+TSMA!K7+GEDU!AT7+SAMA!CD7+TCHG!AT7+GMTU!CD7+LHAM!K7+PHLY!DK7 -> 0 | DR7: =PARO!L7+HAA!AU7+WANG!CE7+PUNA!CE7+GASA!AU7+GELA!CE7+ZEMG!CE7+TRON!CE7+BUMA!CE7+SARA!CE7+TSIR!CE7+DGNA!CE7+PANG!CE7+DPLA!CE7+SJKA!CE7+TRAG!AU7+MONA!L7+LUNT!CE7+TYSE!L7+PEMA!L7+KNLG!L7+RJNG!L7+WRMG!AU7+DUSM!L7+GYPG!L7+NGLM!AU7+SAMC!CE7+PHUA!CE7+TSMA!L7+GEDU!AU7+SAMA!CE7+TCHG!AU7+GMTU!CE7+LHAM!L7+PHLY!DL7 -> 0 | DS7: =PARO!M7+HAA!AV7+WANG!CF7+PUNA!CF7+GASA!AV7+GELA!CF7+ZEMG!CF7+TRON!CF7+BUMA!CF7+SARA!CF7+TSIR!CF7+DGNA!CF7+PANG!CF7+DPLA!CF7+SJKA!CF7+TRAG!AV7+MONA!M7+LUNT!CF7+TYSE!M7+PEMA!M7+KNLG!M7+RJNG!M7+WRMG!AV7+DUSM!M7+GYPG!M7+NGLM!AV7+SAMC!CF7+PHUA!CF7+TSMA!M7+GEDU!AV7+SAMA!CF7+TCHG!AV7+GMTU!CF7+LHAM!M7+PHLY!DM7 -> 0 | DT7: =PARO!N7+HAA!AW7+WANG!CG7+PUNA!CG7+GASA!AW7+GELA!CG7+ZEMG!CG7+TRON!CG7+BUMA!CG7+SARA!CG7+TSIR!CG7+DGNA!CG7+PANG!CG7+DPLA!CG7+SJKA!CG7+TRAG!AW7+MONA!N7+LUNT!CG7+TYSE!N7+PEMA!N7+KNLG!N7+RJNG!N7+WRMG!AW7+DUSM!N7+GYPG!N7+NGLM!AW7+SAMC!CG7+PHUA!CG7+TSMA!N7+GEDU!AW7+SAMA!CG7+TCHG!AW7+GMTU!CG7+LHAM!N7+PHLY!DN7 -> 0 | DU7: =PARO!O7+HAA!AX7+WANG!CH7+PUNA!CH7+GASA!AX7+GELA!CH7+ZEMG!CH7+TRON!CH7+BUMA!CH7+SARA!CH7+TSIR!CH7+DGNA!CH7+PANG!CH7+DPLA!CH7+SJKA!CH7+TRAG!AX7+MONA!O7+LUNT!CH7+TYSE!O7+PEMA!O7+KNLG!O7+RJNG!O7+WRMG!AX7+DUSM!O7+GYPG!O7+NGLM!AX7+SAMC!CH7+PHUA!CH7+TSMA!O7+GEDU!AX7+SAMA!CH7+TCHG!AX7+GMTU!CH7+LHAM!O7+PHLY!DO7 -> 0 | ... EV7: =PARO!AP7+HAA!BY7+WANG!DI7+PUNA!DI7+GASA!BY7+GELA!DI7+ZEMG!DI7+TRON!DI7+BUMA!DI7+SARA!DI7+TSIR!DI7+DGNA!DI7+PANG!DI7+DPLA!DI7+SJKA!DI7+TRAG!BY7+MONA!AP7+LUNT!DI7+TYSE!AP7+PEMA!AP7+KNLG!AP7+RJNG!AP7+WRMG!BY7+DUSM!AP7+GYPG!AP7+NGLM!BY7+SAMC!DI7+PHUA!DI7+TSMA!AP7+GEDU!BY7+SAMA!DI7+TCHG!BY7+GMTU!DI7+LHAM!AP7+PHLY!EP7 -> 0 | EX7: =PARO!AR7+HAA!CA7+WANG!DK7+PUNA!DK7+GASA!CA7+GELA!DK7+ZEMG!DK7+TRON!DK7+BUMA!DK7+SARA!DK7+TSIR!DK7+DGNA!DK7+PANG!DK7+DPLA!DK7+SJKA!DK7+TRAG!CA7+MONA!AR7+LUNT!DK7+TYSE!AR7+PEMA!AR7+KNLG!AR7+RJNG!AR7+WRMG!CA7+DUSM!AR7+GYPG!AR7+NGLM!CA7+SAMC!DK7+PHUA!DK7+TSMA!AR7+GEDU!CA7+SAMA!DK7+TCHG!CA7+GMTU!DK7+LHAM!AR7+PHLY!ER7 -> 0 | EY7: =PARO!AS7+HAA!CB7+WANG!DL7+PUNA!DL7+GASA!CB7+GELA!DL7+ZEMG!DL7+TRON!DL7+BUMA!DL7+SARA!DL7+TSIR!DL7+DGNA!DL7+PANG!DL7+DPLA!DL7+SJKA!DL7+TRAG!CB7+MONA!AS7+LUNT!DL7+TYSE!AS7+PEMA!AS7+KNLG!AS7+RJNG!AS7+WRMG!CB7+DUSM!AS7+GYPG!AS7+NGLM!CB7+SAMC!DL7+PHUA!DL7+TSMA!AS7+GEDU!CB7+SAMA!DL7+TCHG!CB7+GMTU!DL7+LHAM!AS7+PHLY!ES7 -> 0 | EZ7: =PARO!AT7+HAA!CC7+WANG!DM7+PUNA!DM7+GASA!CC7+GELA!DM7+ZEMG!DM7+TRON!DM7+BUMA!DM7+SARA!DM7+TSIR!DM7+DGNA!DM7+PANG!DM7+DPLA!DM7+SJKA!DM7+TRAG!CC7+MONA!AT7+LUNT!DM7+TYSE!AT7+PEMA!AT7+KNLG!AT7+RJNG!AT7+WRMG!CC7+DUSM!AT7+GYPG!AT7+NGLM!CC7+SAMC!DM7+PHUA!DM7+TSMA!AT7+GEDU!CC7+SAMA!DM7+TCHG!CC7+GMTU!DM7+LHAM!AT7+PHLY!ET7 -> 0 | FA7: =PARO!AU7+HAA!CD7+WANG!DN7+PUNA!DN7+GASA!CD7+GELA!DN7+ZEMG!DN7+TRON!DN7+BUMA!DN7+SARA!DN7+TSIR!DN7+DGNA!DN7+PANG!DN7+DPLA!DN7+SJKA!DN7+TRAG!CD7+MONA!AU7+LUNT!DN7+TYSE!AU7+PEMA!AU7+KNLG!AU7+RJNG!AU7+WRMG!CD7+DUSM!AU7+GYPG!AU7+NGLM!CD7+SAMC!DN7+PHUA!DN7+TSMA!AU7+GEDU!CD7+SAMA!DN7+TCHG!CD7+GMTU!DN7+LHAM!AU7+PHLY!EU7 -> 0 | FB7: =PARO!AV7+HAA!CE7+WANG!DO7+PUNA!DO7+GASA!CE7+GELA!DO7+ZEMG!DO7+TRON!DO7+BUMA!DO7+SARA!DO7+TSIR!DO7+DGNA!DO7+PANG!DO7+DPLA!DO7+SJKA!DO7+TRAG!CE7+MONA!AV7+LUNT!DO7+TYSE!AV7+PEMA!AV7+KNLG!AV7+RJNG!AV7+WRMG!CE7+DUSM!AV7+GYPG!AV7+NGLM!CE7+SAMC!DO7+PHUA!DO7+TSMA!AV7+GEDU!CE7+SAMA!DO7+TCHG!CE7+GMTU!DO7+LHAM!AV7+PHLY!EV7 -> 0 | FC7: =PARO!AW7+HAA!CF7+WANG!DP7+PUNA!DP7+GASA!CF7+GELA!DP7+ZEMG!DP7+TRON!DP7+BUMA!DP7+SARA!DP7+TSIR!DP7+DGNA!DP7+PANG!DP7+DPLA!DP7+SJKA!DP7+TRAG!CF7+MONA!AW7+LUNT!DP7+TYSE!AW7+PEMA!AW7+KNLG!AW7+RJNG!AW7+WRMG!CF7+DUSM!AW7+GYPG!AW7+NGLM!CF7+SAMC!DP7+PHUA!DP7+TSMA!AW7+GEDU!CF7+SAMA!DP7+TCHG!CF7+GMTU!DP7+LHAM!AW7+PHLY!EW7 -> 0 | FD7: =PARO!AX7+HAA!CG7+WANG!DQ7+PUNA!DQ7+GASA!CG7+GELA!DQ7+ZEMG!DQ7+TRON!DQ7+BUMA!DQ7+SARA!DQ7+TSIR!DQ7+DGNA!DQ7+PANG!DQ7+DPLA!DQ7+SJKA!DQ7+TRAG!CG7+MONA!AX7+LUNT!DQ7+TYSE!AX7+PEMA!AX7+KNLG!AX7+RJNG!AX7+WRMG!CG7+DUSM!AX7+GYPG!AX7+NGLM!CG7+SAMC!DQ7+PHUA!DQ7+TSMA!AX7+GEDU!CG7+SAMA!DQ7+TCHG!CG7+GMTU!DQ7+LHAM!AX7+PHLY!EX7 -> 0 | FE7: =PARO!AY7+HAA!CH7+WANG!DR7+PUNA!DR7+GASA!CH7+GELA!DR7+ZEMG!DR7+TRON!DR7+BUMA!DR7+SARA!DR7+TSIR!DR7+DGNA!DR7+PANG!DR7+DPLA!DR7+SJKA!DR7+TRAG!CH7+MONA!AY7+LUNT!DR7+TYSE!AY7+PEMA!AY7+KNLG!AY7+RJNG!AY7+WRMG!CH7+DUSM!AY7+GYPG!AY7+NGLM!CH7+SAMC!DR7+PHUA!DR7+TSMA!AY7+GEDU!CH7+SAMA!DR7+TCHG!CH7+GMTU!DR7+LHAM!AY7+PHLY!EY7 -> 0 | ... GA7: =PARO!BU7+HAA!DD7+WANG!EN7+PUNA!EN7+GASA!DD7+GELA!EN7+ZEMG!EN7+TRON!EN7+BUMA!EN7+SARA!EN7+TSIR!EN7+DGNA!EN7+PANG!EN7+DPLA!EN7+SJKA!EN7+TRAG!DD7+MONA!BU7+LUNT!EN7+TYSE!BU7+PEMA!BU7+KNLG!BU7+RJNG!BU7+WRMG!DD7+DUSM!BU7+GYPG!BU7+NGLM!DD7+SAMC!EN7+PHUA!EN7+TSMA!BU7+GEDU!DD7+SAMA!EN7+TCHG!DD7+GMTU!EN7+LHAM!BU7+PHLY!FU7 -> 0 | GB7: =PARO!BV7+HAA!DE7+WANG!EO7+PUNA!EO7+GASA!DE7+GELA!EO7+ZEMG!EO7+TRON!EO7+BUMA!EO7+SARA!EO7+TSIR!EO7+DGNA!EO7+PANG!EO7+DPLA!EO7+SJKA!EO7+TRAG!DE7+MONA!BW7+LUNT!EO7+TYSE!BW7+PEMA!BW7+KNLG!BW7+RJNG!BV7+WRMG!DE7+DUSM!BW7+GYPG!BW7+NGLM!DE7+SAMC!EO7+PHUA!EO7+TSMA!BV7+GEDU!DE7+SAMA!EO7+TCHG!DE7+GMTU!EO7+LHAM!BV7+PHLY!FV7 -> 0 | GC7: =PARO!BW7+HAA!DF7+WANG!EP7+PUNA!EP7+GASA!DF7+GELA!EP7+ZEMG!EP7+TRON!EP7+BUMA!EP7+SARA!EP7+TSIR!EP7+DGNA!EP7+PANG!EP7+DPLA!EP7+SJKA!EP7+TRAG!DF7+MONA!BX7+LUNT!EP7+TYSE!BX7+PEMA!BX7+KNLG!BX7+RJNG!BW7+WRMG!DF7+DUSM!BX7+GYPG!BX7+NGLM!DF7+SAMC!EP7+PHUA!EP7+TSMA!BW7+GEDU!DF7+SAMA!EP7+TCHG!DF7+GMTU!EP7+LHAM!BW7+PHLY!FW7 -> 0 | GD7: =PARO!BX7+HAA!DG7+WANG!EQ7+PUNA!EQ7+GASA!DG7+GELA!EQ7+ZEMG!EQ7+TRON!EQ7+BUMA!EQ7+SARA!EQ7+TSIR!EQ7+DGNA!EQ7+PANG!EQ7+DPLA!EQ7+SJKA!EQ7+TRAG!DG7+MONA!BY7+LUNT!EQ7+TYSE!BY7+PEMA!BY7+KNLG!BY7+RJNG!BX7+WRMG!DG7+DUSM!BY7+GYPG!BY7+NGLM!DG7+SAMC!EQ7+PHUA!EQ7+TSMA!BX7+GEDU!DG7+SAMA!EQ7+TCHG!DG7+GMTU!EQ7+LHAM!BX7+PHLY!FX7 -> 0 | GE7: =PARO!BY7+HAA!DH7+WANG!ER7+PUNA!ER7+GASA!DH7+GELA!ER7+ZEMG!ER7+TRON!ER7+BUMA!ER7+SARA!ER7+TSIR!ER7+DGNA!ER7+PANG!ER7+DPLA!ER7+SJKA!ER7+TRAG!DH7+MONA!BZ7+LUNT!ER7+TYSE!BZ7+PEMA!BZ7+KNLG!BZ7+RJNG!BY7+WRMG!DH7+DUSM!BZ7+GYPG!BZ7+NGLM!DH7+SAMC!ER7+PHUA!ER7+TSMA!BY7+GEDU!DH7+SAMA!ER7+TCHG!DH7+GMTU!ER7+LHAM!BY7+PHLY!FY7 -> 0 | GG7: =PARO!CA7+HAA!DJ7+WANG!ET7+PUNA!ET7+GASA!DJ7+GELA!ET7+ZEMG!ET7+TRON!ET7+BUMA!ET7+SARA!ET7+TSIR!ET7+DGNA!ET7+PANG!ET7+DPLA!ET7+SJKA!ET7+TRAG!DJ7+MONA!CB7+LUNT!ET7+TYSE!CB7+PEMA!CB7+KNLG!CB7+RJNG!CA7+WRMG!DJ7+DUSM!CB7+GYPG!CB7+NGLM!DJ7+SAMC!ET7+PHUA!ET7+TSMA!CA7+GEDU!DJ7+SAMA!ET7+TCHG!DJ7+GMTU!ET7+LHAM!CA7+PHLY!GA7 -> 0 | GH7: =PARO!CB7+HAA!DK7+WANG!EU7+PUNA!EU7+GASA!DK7+GELA!EU7+ZEMG!EU7+TRON!EU7+BUMA!EU7+SARA!EU7+TSIR!EU7+DGNA!EU7+PANG!EU7+DPLA!EU7+SJKA!EU7+TRAG!DK7+MONA!CC7+LUNT!EU7+TYSE!CC7+PEMA!CC7+KNLG!CC7+RJNG!CB7+WRMG!DK7+DUSM!CC7+GYPG!CC7+NGLM!DK7+SAMC!EU7+PHUA!EU7+TSMA!CB7+GEDU!DK7+SAMA!EU7+TCHG!DK7+GMTU!EU7+LHAM!CB7+PHLY!GB7 -> 0 | GI7: =PARO!CC7+HAA!DL7+WANG!EV7+PUNA!EV7+GASA!DL7+GELA!EV7+ZEMG!EV7+TRON!EV7+BUMA!EV7+SARA!EV7+TSIR!EV7+DGNA!EV7+PANG!EV7+DPLA!EV7+SJKA!EV7+TRAG!DL7+MONA!CD7+LUNT!EV7+TYSE!CD7+PEMA!CD7+KNLG!CD7+RJNG!CC7+WRMG!DL7+DUSM!CD7+GYPG!CD7+NGLM!DL7+SAMC!EV7+PHUA!EV7+TSMA!CC7+GEDU!DL7+SAMA!EV7+TCHG!DL7+GMTU!EV7+LHAM!CC7+PHLY!GC7 -> 0 | GJ7: =PARO!CD7+HAA!DM7+WANG!EW7+PUNA!EW7+GASA!DM7+GELA!EW7+ZEMG!EW7+TRON!EW7+BUMA!EW7+SARA!EW7+TSIR!EW7+DGNA!EW7+PANG!EW7+DPLA!EW7+SJKA!EW7+TRAG!DM7+MONA!CE7+LUNT!EW7+TYSE!CE7+PEMA!CE7+KNLG!CE7+RJNG!CD7+WRMG!DM7+DUSM!CE7+GYPG!CE7+NGLM!DM7+SAMC!EW7+PHUA!EW7+TSMA!CD7+GEDU!DM7+SAMA!EW7+TCHG!DM7+GMTU!EW7+LHAM!CD7+PHLY!GD7 -> 0 | GK7: =PARO!CE7+HAA!DN7+WANG!EX7+PUNA!EX7+GASA!DN7+GELA!EX7+ZEMG!EX7+TRON!EX7+BUMA!EX7+SARA!EX7+TSIR!EX7+DGNA!EX7+PANG!EX7+DPLA!EX7+SJKA!EX7+TRAG!DN7+MONA!CF7+LUNT!EX7+TYSE!CF7+PEMA!CF7+KNLG!CF7+RJNG!CE7+WRMG!DN7+DUSM!CF7+GYPG!CF7+NGLM!DN7+SAMC!EX7+PHUA!EX7+TSMA!CE7+GEDU!DN7+SAMA!EX7+TCHG!DN7+GMTU!EX7+LHAM!CE7+PHLY!GE7 -> 0 | GL7: =PARO!CF7+HAA!DO7+WANG!EY7+PUNA!EY7+GASA!DO7+GELA!EY7+ZEMG!EY7+TRON!EY7+BUMA!EY7+SARA!EY7+TSIR!EY7+DGNA!EY7+PANG!EY7+DPLA!EY7+SJKA!EY7+TRAG!DO7+MONA!CG7+LUNT!EY7+TYSE!CG7+PEMA!CG7+KNLG!CG7+RJNG!CF7+WRMG!DO7+DUSM!CG7+GYPG!CG7+NGLM!DO7+SAMC!EY7+PHUA!EY7+TSMA!CF7+GEDU!DO7+SAMA!EY7+TCHG!DO7+GMTU!EY7+LHAM!CF7+PHLY!GF7 -> 0 | GM7: =PARO!CG7+HAA!DP7+WANG!EZ7+PUNA!EZ7+GASA!DP7+GELA!EZ7+ZEMG!EZ7+TRON!EZ7+BUMA!EZ7+SARA!EZ7+TSIR!EZ7+DGNA!EZ7+PANG!EZ7+DPLA!EZ7+SJKA!EZ7+TRAG!DP7+MONA!CH7+LUNT!EZ7+TYSE!CH7+PEMA!CH7+KNLG!CH7+RJNG!CG7+WRMG!DP7+DUSM!CH7+GYPG!CH7+NGLM!DP7+SAMC!EZ7+PHUA!EZ7+TSMA!CG7+GEDU!DP7+SAMA!EZ7+TCHG!DP7+GMTU!EZ7+LHAM!CG7+PHLY!GG7 -> 0 | GN7: =PARO!CH7+HAA!DQ7+WANG!FA7+PUNA!FA7+GASA!DQ7+GELA!FA7+ZEMG!FA7+TRON!FA7+BUMA!FA7+SARA!FA7+TSIR!FA7+DGNA!FA7+PANG!FA7+DPLA!FA7+SJKA!FA7+TRAG!DQ7+MONA!CI7+LUNT!FA7+TYSE!CI7+PEMA!CI7+KNLG!CI7+RJNG!CH7+WRMG!DQ7+DUSM!CI7+GYPG!CI7+NGLM!DQ7+SAMC!FA7+PHUA!FA7+TSMA!CH7+GEDU!DQ7+SAMA!FA7+TCHG!DQ7+GMTU!FA7+LHAM!CH7+PHLY!GH7 -> 0 | ... HO7: =PARO!DI7+HAA!ER7+WANG!GB7+PUNA!GB7+GASA!ER7+GELA!GB7+ZEMG!GB7+TRON!GB7+BUMA!GB7+SARA!GB7+TSIR!GB7+DGNA!GB7+PANG!GB7+DPLA!GB7+SJKA!GB7+TRAG!ER7+MONA!DJ7+LUNT!GB7+TYSE!DJ7+PEMA!DJ7+KNLG!DJ7+RJNG!DI7+WRMG!ER7+DUSM!DJ7+GYPG!DJ7+NGLM!ER7+SAMC!GB7+PHUA!GB7+TSMA!DI7+GEDU!ER7+SAMA!GB7+TCHG!ER7+GMTU!GB7+LHAM!DI7+PHLY!HI7 -> 0 | HQ7: =ES7+GB7+HL7 -> 0 | HR7: =C7*HQ7 -> 0 | HS7: =D7*HQ7 -> 0 | HT7: =E7*HQ7 -> 0 | IN7: =AJ7+BT7+DC7+ES7+GB7+HL7 -> 1 | IO7: =AK7+BU7+DD7+ET7+GC7+HM7 -> 4200 | IP7: =AL7+BV7+DE7+EU7+GD7+HN7 -> 700 | IQ7: =AM7+BW7+DF7+EV7+GE7+HO7 -> 3500 | IR7: =SUM(IN7:IN17) -> 1499
A8: 6 | B8: CordyACTIVE | C8: 3520 | D8: 4224 | E8: =D8-C8 -> 704 | H8: =PHLY!H8 -> 0 | I8: =PHLY!I8 -> 0 | J8: =PHLY!J8 -> 0 | K8: =PHLY!K8 -> 0 | L8: =PHLY!L8 -> 0 | M8: =PHLY!M8 -> 0 | N8: =PHLY!N8 -> 0 | O8: =PHLY!O8 -> 0 | ... AM8: =PHLY!AM8 -> 0 | AO8: =WANG!H8+PUNA!H8+GELA!H8+ZEMG!H8+TRON!H8+BUMA!H8+SARA!H8+TSIR!H8+DGNA!H8+PANG!H8+DPLA!H8+SJKA!H8+LUNT!H8+SAMC!H8+PHUA!H8+SAMA!H8+GMTU!H8+PHLY!AO8 -> 0 | AP8: =WANG!I8+PUNA!I8+GELA!I8+ZEMG!I8+TRON!I8+BUMA!I8+SARA!I8+TSIR!I8+DGNA!I8+PANG!I8+DPLA!I8+SJKA!I8+LUNT!I8+SAMC!I8+PHUA!I8+SAMA!I8+GMTU!I8+PHLY!AP8 -> 0 | AQ8: =WANG!J8+PUNA!J8+GELA!J8+ZEMG!J8+TRON!J8+BUMA!J8+SARA!J8+TSIR!J8+DGNA!J8+PANG!J8+DPLA!J8+SJKA!J8+LUNT!J8+SAMC!J8+PHUA!J8+SAMA!J8+GMTU!J8+PHLY!AQ8 -> 0 | AR8: =WANG!K8+PUNA!K8+GELA!K8+ZEMG!K8+TRON!K8+BUMA!K8+SARA!K8+TSIR!K8+DGNA!K8+PANG!K8+DPLA!K8+SJKA!K8+LUNT!K8+SAMC!K8+PHUA!K8+SAMA!K8+GMTU!K8+PHLY!AR8 -> 0 | AS8: =WANG!L8+PUNA!L8+GELA!L8+ZEMG!L8+TRON!L8+BUMA!L8+SARA!L8+TSIR!L8+DGNA!L8+PANG!L8+DPLA!L8+SJKA!L8+LUNT!L8+SAMC!L8+PHUA!L8+SAMA!L8+GMTU!L8+PHLY!AS8 -> 0 | AT8: =WANG!M8+PUNA!M8+GELA!M8+ZEMG!M8+TRON!M8+BUMA!M8+SARA!M8+TSIR!M8+DGNA!M8+PANG!M8+DPLA!M8+SJKA!M8+LUNT!M8+SAMC!M8+PHUA!M8+SAMA!M8+GMTU!M8+PHLY!AT8 -> 0 | AU8: =WANG!N8+PUNA!N8+GELA!N8+ZEMG!N8+TRON!N8+BUMA!N8+SARA!N8+TSIR!N8+DGNA!N8+PANG!N8+DPLA!N8+SJKA!N8+LUNT!N8+SAMC!N8+PHUA!N8+SAMA!N8+GMTU!N8+PHLY!AU8 -> 0 | AV8: =WANG!O8+PUNA!O8+GELA!O8+ZEMG!O8+TRON!O8+BUMA!O8+SARA!O8+TSIR!O8+DGNA!O8+PANG!O8+DPLA!O8+SJKA!O8+LUNT!O8+SAMC!O8+PHUA!O8+SAMA!O8+GMTU!O8+PHLY!AV8 -> 0 | ... BW8: =WANG!AP8+PUNA!AP8+GELA!AP8+ZEMG!AP8+TRON!AP8+BUMA!AP8+SARA!AP8+TSIR!AP8+DGNA!AP8+PANG!AP8+DPLA!AP8+SJKA!AP8+LUNT!AP8+SAMC!AP8+PHUA!AP8+SAMA!AP8+GMTU!AP8+PHLY!BW8 -> 0 | BY8: =HAA!H8+WANG!AR8+PUNA!AR8+GASA!H8+GELA!AR8+ZEMG!AR8+TRON!AR8+BUMA!AR8+SARA!AR8+TSIR!AR8+DGNA!AR8+PANG!AR8+DPLA!AR8+SJKA!AR8+TRAG!H8+LUNT!AR8+WRMG!H8+NGLM!H8+SAMC!AR8+PHUA!AR8+GEDU!H8+SAMA!AR8+TCHG!H8+GMTU!AR8+PHLY!BY8 -> 0 | BZ8: =HAA!I8+WANG!AS8+PUNA!AS8+GASA!I8+GELA!AS8+ZEMG!AS8+TRON!AS8+BUMA!AS8+SARA!AS8+TSIR!AS8+DGNA!AS8+PANG!AS8+DPLA!AS8+SJKA!AS8+TRAG!I8+LUNT!AS8+WRMG!I8+NGLM!I8+SAMC!AS8+PHUA!AS8+GEDU!I8+SAMA!AS8+TCHG!I8+GMTU!AS8+PHLY!BZ8 -> 0 | CA8: =HAA!J8+WANG!AT8+PUNA!AT8+GASA!J8+GELA!AT8+ZEMG!AT8+TRON!AT8+BUMA!AT8+SARA!AT8+TSIR!AT8+DGNA!AT8+PANG!AT8+DPLA!AT8+SJKA!AT8+TRAG!J8+LUNT!AT8+WRMG!J8+NGLM!J8+SAMC!AT8+PHUA!AT8+GEDU!J8+SAMA!AT8+TCHG!J8+GMTU!AT8+PHLY!CA8 -> 0 | CB8: =HAA!K8+WANG!AU8+PUNA!AU8+GASA!K8+GELA!AU8+ZEMG!AU8+TRON!AU8+BUMA!AU8+SARA!AU8+TSIR!AU8+DGNA!AU8+PANG!AU8+DPLA!AU8+SJKA!AU8+TRAG!K8+LUNT!AU8+WRMG!K8+NGLM!K8+SAMC!AU8+PHUA!AU8+GEDU!K8+SAMA!AU8+TCHG!K8+GMTU!AU8+PHLY!CB8 -> 0 | CC8: =HAA!L8+WANG!AV8+PUNA!AV8+GASA!L8+GELA!AV8+ZEMG!AV8+TRON!AV8+BUMA!AV8+SARA!AV8+TSIR!AV8+DGNA!AV8+PANG!AV8+DPLA!AV8+SJKA!AV8+TRAG!L8+LUNT!AV8+WRMG!L8+NGLM!L8+SAMC!AV8+PHUA!AV8+GEDU!L8+SAMA!AV8+TCHG!L8+GMTU!AV8+PHLY!CC8 -> 0 | CD8: =HAA!M8+WANG!AW8+PUNA!AW8+GASA!M8+GELA!AW8+ZEMG!AW8+TRON!AW8+BUMA!AW8+SARA!AW8+TSIR!AW8+DGNA!AW8+PANG!AW8+DPLA!AW8+SJKA!AW8+TRAG!M8+LUNT!AW8+WRMG!M8+NGLM!M8+SAMC!AW8+PHUA!AW8+GEDU!M8+SAMA!AW8+TCHG!M8+GMTU!AW8+PHLY!CD8 -> 0 | CE8: =HAA!N8+WANG!AX8+PUNA!AX8+GASA!N8+GELA!AX8+ZEMG!AX8+TRON!AX8+BUMA!AX8+SARA!AX8+TSIR!AX8+DGNA!AX8+PANG!AX8+DPLA!AX8+SJKA!AX8+TRAG!N8+LUNT!AX8+WRMG!N8+NGLM!N8+SAMC!AX8+PHUA!AX8+GEDU!N8+SAMA!AX8+TCHG!N8+GMTU!AX8+PHLY!CE8 -> 0 | CF8: =HAA!O8+WANG!AY8+PUNA!AY8+GASA!O8+GELA!AY8+ZEMG!AY8+TRON!AY8+BUMA!AY8+SARA!AY8+TSIR!AY8+DGNA!AY8+PANG!AY8+DPLA!AY8+SJKA!AY8+TRAG!O8+LUNT!AY8+WRMG!O8+NGLM!O8+SAMC!AY8+PHUA!AY8+GEDU!O8+SAMA!AY8+TCHG!O8+GMTU!AY8+PHLY!CF8 -> 0 | ... DF8: =HAA!AO8+WANG!BY8+PUNA!BY8+GASA!AO8+GELA!BY8+ZEMG!BY8+TRON!BY8+BUMA!BY8+SARA!BY8+TSIR!BY8+DGNA!BY8+PANG!BY8+DPLA!BY8+SJKA!BY8+TRAG!AO8+LUNT!BY8+WRMG!AO8+NGLM!AO8+SAMC!BY8+PHUA!BY8+GEDU!AO8+SAMA!BY8+TCHG!AO8+GMTU!BY8+PHLY!DF8 -> 7040 | DG8: =AJ8+BT8+DC8 -> 2 | DH8: =C8*DG8 -> 7040 | DI8: =D8*DG8 -> 8448 | DJ8: =E8*DG8 -> 1408 | DN8: =PARO!H8+HAA!AQ8+WANG!CA8+PUNA!CA8+GASA!AQ8+GELA!CA8+ZEMG!CA8+TRON!CA8+BUMA!CA8+SARA!CA8+TSIR!CA8+DGNA!CA8+PANG!CA8+DPLA!CA8+SJKA!CA8+TRAG!AQ8+MONA!H8+LUNT!CA8+TYSE!H8+PEMA!H8+KNLG!H8+RJNG!H8+WRMG!AQ8+DUSM!H8+GYPG!H8+NGLM!AQ8+SAMC!CA8+PHUA!CA8+TSMA!H8+GEDU!AQ8+SAMA!CA8+TCHG!AQ8+GMTU!CA8+LHAM!H8+PHLY!DH8 -> 0 | DO8: =PARO!I8+HAA!AR8+WANG!CB8+PUNA!CB8+GASA!AR8+GELA!CB8+ZEMG!CB8+TRON!CB8+BUMA!CB8+SARA!CB8+TSIR!CB8+DGNA!CB8+PANG!CB8+DPLA!CB8+SJKA!CB8+TRAG!AR8+MONA!I8+LUNT!CB8+TYSE!I8+PEMA!I8+KNLG!I8+RJNG!I8+WRMG!AR8+DUSM!I8+GYPG!I8+NGLM!AR8+SAMC!CB8+PHUA!CB8+TSMA!I8+GEDU!AR8+SAMA!CB8+TCHG!AR8+GMTU!CB8+LHAM!I8+PHLY!DI8 -> 0 | DP8: =PARO!J8+HAA!AS8+WANG!CC8+PUNA!CC8+GASA!AS8+GELA!CC8+ZEMG!CC8+TRON!CC8+BUMA!CC8+SARA!CC8+TSIR!CC8+DGNA!CC8+PANG!CC8+DPLA!CC8+SJKA!CC8+TRAG!AS8+MONA!J8+LUNT!CC8+TYSE!J8+PEMA!J8+KNLG!J8+RJNG!J8+WRMG!AS8+DUSM!J8+GYPG!J8+NGLM!AS8+SAMC!CC8+PHUA!CC8+TSMA!J8+GEDU!AS8+SAMA!CC8+TCHG!AS8+GMTU!CC8+LHAM!J8+PHLY!DJ8 -> 0 | DQ8: =PARO!K8+HAA!AT8+WANG!CD8+PUNA!CD8+GASA!AT8+GELA!CD8+ZEMG!CD8+TRON!CD8+BUMA!CD8+SARA!CD8+TSIR!CD8+DGNA!CD8+PANG!CD8+DPLA!CD8+SJKA!CD8+TRAG!AT8+MONA!K8+LUNT!CD8+TYSE!K8+PEMA!K8+KNLG!K8+RJNG!K8+WRMG!AT8+DUSM!K8+GYPG!K8+NGLM!AT8+SAMC!CD8+PHUA!CD8+TSMA!K8+GEDU!AT8+SAMA!CD8+TCHG!AT8+GMTU!CD8+LHAM!K8+PHLY!DK8 -> 0 | DR8: =PARO!L8+HAA!AU8+WANG!CE8+PUNA!CE8+GASA!AU8+GELA!CE8+ZEMG!CE8+TRON!CE8+BUMA!CE8+SARA!CE8+TSIR!CE8+DGNA!CE8+PANG!CE8+DPLA!CE8+SJKA!CE8+TRAG!AU8+MONA!L8+LUNT!CE8+TYSE!L8+PEMA!L8+KNLG!L8+RJNG!L8+WRMG!AU8+DUSM!L8+GYPG!L8+NGLM!AU8+SAMC!CE8+PHUA!CE8+TSMA!L8+GEDU!AU8+SAMA!CE8+TCHG!AU8+GMTU!CE8+LHAM!L8+PHLY!DL8 -> 0 | DS8: =PARO!M8+HAA!AV8+WANG!CF8+PUNA!CF8+GASA!AV8+GELA!CF8+ZEMG!CF8+TRON!CF8+BUMA!CF8+SARA!CF8+TSIR!CF8+DGNA!CF8+PANG!CF8+DPLA!CF8+SJKA!CF8+TRAG!AV8+MONA!M8+LUNT!CF8+TYSE!M8+PEMA!M8+KNLG!M8+RJNG!M8+WRMG!AV8+DUSM!M8+GYPG!M8+NGLM!AV8+SAMC!CF8+PHUA!CF8+TSMA!M8+GEDU!AV8+SAMA!CF8+TCHG!AV8+GMTU!CF8+LHAM!M8+PHLY!DM8 -> 0 | DT8: =PARO!N8+HAA!AW8+WANG!CG8+PUNA!CG8+GASA!AW8+GELA!CG8+ZEMG!CG8+TRON!CG8+BUMA!CG8+SARA!CG8+TSIR!CG8+DGNA!CG8+PANG!CG8+DPLA!CG8+SJKA!CG8+TRAG!AW8+MONA!N8+LUNT!CG8+TYSE!N8+PEMA!N8+KNLG!N8+RJNG!N8+WRMG!AW8+DUSM!N8+GYPG!N8+NGLM!AW8+SAMC!CG8+PHUA!CG8+TSMA!N8+GEDU!AW8+SAMA!CG8+TCHG!AW8+GMTU!CG8+LHAM!N8+PHLY!DN8 -> 0 | DU8: =PARO!O8+HAA!AX8+WANG!CH8+PUNA!CH8+GASA!AX8+GELA!CH8+ZEMG!CH8+TRON!CH8+BUMA!CH8+SARA!CH8+TSIR!CH8+DGNA!CH8+PANG!CH8+DPLA!CH8+SJKA!CH8+TRAG!AX8+MONA!O8+LUNT!CH8+TYSE!O8+PEMA!O8+KNLG!O8+RJNG!O8+WRMG!AX8+DUSM!O8+GYPG!O8+NGLM!AX8+SAMC!CH8+PHUA!CH8+TSMA!O8+GEDU!AX8+SAMA!CH8+TCHG!AX8+GMTU!CH8+LHAM!O8+PHLY!DO8 -> 0 | ... EV8: =PARO!AP8+HAA!BY8+WANG!DI8+PUNA!DI8+GASA!BY8+GELA!DI8+ZEMG!DI8+TRON!DI8+BUMA!DI8+SARA!DI8+TSIR!DI8+DGNA!DI8+PANG!DI8+DPLA!DI8+SJKA!DI8+TRAG!BY8+MONA!AP8+LUNT!DI8+TYSE!AP8+PEMA!AP8+KNLG!AP8+RJNG!AP8+WRMG!BY8+DUSM!AP8+GYPG!AP8+NGLM!BY8+SAMC!DI8+PHUA!DI8+TSMA!AP8+GEDU!BY8+SAMA!DI8+TCHG!BY8+GMTU!DI8+LHAM!AP8+PHLY!EP8 -> 0 | EX8: =PARO!AR8+HAA!CA8+WANG!DK8+PUNA!DK8+GASA!CA8+GELA!DK8+ZEMG!DK8+TRON!DK8+BUMA!DK8+SARA!DK8+TSIR!DK8+DGNA!DK8+PANG!DK8+DPLA!DK8+SJKA!DK8+TRAG!CA8+MONA!AR8+LUNT!DK8+TYSE!AR8+PEMA!AR8+KNLG!AR8+RJNG!AR8+WRMG!CA8+DUSM!AR8+GYPG!AR8+NGLM!CA8+SAMC!DK8+PHUA!DK8+TSMA!AR8+GEDU!CA8+SAMA!DK8+TCHG!CA8+GMTU!DK8+LHAM!AR8+PHLY!ER8 -> 0 | EY8: =PARO!AS8+HAA!CB8+WANG!DL8+PUNA!DL8+GASA!CB8+GELA!DL8+ZEMG!DL8+TRON!DL8+BUMA!DL8+SARA!DL8+TSIR!DL8+DGNA!DL8+PANG!DL8+DPLA!DL8+SJKA!DL8+TRAG!CB8+MONA!AS8+LUNT!DL8+TYSE!AS8+PEMA!AS8+KNLG!AS8+RJNG!AS8+WRMG!CB8+DUSM!AS8+GYPG!AS8+NGLM!CB8+SAMC!DL8+PHUA!DL8+TSMA!AS8+GEDU!CB8+SAMA!DL8+TCHG!CB8+GMTU!DL8+LHAM!AS8+PHLY!ES8 -> 0 | EZ8: =PARO!AT8+HAA!CC8+WANG!DM8+PUNA!DM8+GASA!CC8+GELA!DM8+ZEMG!DM8+TRON!DM8+BUMA!DM8+SARA!DM8+TSIR!DM8+DGNA!DM8+PANG!DM8+DPLA!DM8+SJKA!DM8+TRAG!CC8+MONA!AT8+LUNT!DM8+TYSE!AT8+PEMA!AT8+KNLG!AT8+RJNG!AT8+WRMG!CC8+DUSM!AT8+GYPG!AT8+NGLM!CC8+SAMC!DM8+PHUA!DM8+TSMA!AT8+GEDU!CC8+SAMA!DM8+TCHG!CC8+GMTU!DM8+LHAM!AT8+PHLY!ET8 -> 0 | FA8: =PARO!AU8+HAA!CD8+WANG!DN8+PUNA!DN8+GASA!CD8+GELA!DN8+ZEMG!DN8+TRON!DN8+BUMA!DN8+SARA!DN8+TSIR!DN8+DGNA!DN8+PANG!DN8+DPLA!DN8+SJKA!DN8+TRAG!CD8+MONA!AU8+LUNT!DN8+TYSE!AU8+PEMA!AU8+KNLG!AU8+RJNG!AU8+WRMG!CD8+DUSM!AU8+GYPG!AU8+NGLM!CD8+SAMC!DN8+PHUA!DN8+TSMA!AU8+GEDU!CD8+SAMA!DN8+TCHG!CD8+GMTU!DN8+LHAM!AU8+PHLY!EU8 -> 0 | FB8: =PARO!AV8+HAA!CE8+WANG!DO8+PUNA!DO8+GASA!CE8+GELA!DO8+ZEMG!DO8+TRON!DO8+BUMA!DO8+SARA!DO8+TSIR!DO8+DGNA!DO8+PANG!DO8+DPLA!DO8+SJKA!DO8+TRAG!CE8+MONA!AV8+LUNT!DO8+TYSE!AV8+PEMA!AV8+KNLG!AV8+RJNG!AV8+WRMG!CE8+DUSM!AV8+GYPG!AV8+NGLM!CE8+SAMC!DO8+PHUA!DO8+TSMA!AV8+GEDU!CE8+SAMA!DO8+TCHG!CE8+GMTU!DO8+LHAM!AV8+PHLY!EV8 -> 0 | FC8: =PARO!AW8+HAA!CF8+WANG!DP8+PUNA!DP8+GASA!CF8+GELA!DP8+ZEMG!DP8+TRON!DP8+BUMA!DP8+SARA!DP8+TSIR!DP8+DGNA!DP8+PANG!DP8+DPLA!DP8+SJKA!DP8+TRAG!CF8+MONA!AW8+LUNT!DP8+TYSE!AW8+PEMA!AW8+KNLG!AW8+RJNG!AW8+WRMG!CF8+DUSM!AW8+GYPG!AW8+NGLM!CF8+SAMC!DP8+PHUA!DP8+TSMA!AW8+GEDU!CF8+SAMA!DP8+TCHG!CF8+GMTU!DP8+LHAM!AW8+PHLY!EW8 -> 0 | FD8: =PARO!AX8+HAA!CG8+WANG!DQ8+PUNA!DQ8+GASA!CG8+GELA!DQ8+ZEMG!DQ8+TRON!DQ8+BUMA!DQ8+SARA!DQ8+TSIR!DQ8+DGNA!DQ8+PANG!DQ8+DPLA!DQ8+SJKA!DQ8+TRAG!CG8+MONA!AX8+LUNT!DQ8+TYSE!AX8+PEMA!AX8+KNLG!AX8+RJNG!AX8+WRMG!CG8+DUSM!AX8+GYPG!AX8+NGLM!CG8+SAMC!DQ8+PHUA!DQ8+TSMA!AX8+GEDU!CG8+SAMA!DQ8+TCHG!CG8+GMTU!DQ8+LHAM!AX8+PHLY!EX8 -> 0 | FE8: =PARO!AY8+HAA!CH8+WANG!DR8+PUNA!DR8+GASA!CH8+GELA!DR8+ZEMG!DR8+TRON!DR8+BUMA!DR8+SARA!DR8+TSIR!DR8+DGNA!DR8+PANG!DR8+DPLA!DR8+SJKA!DR8+TRAG!CH8+MONA!AY8+LUNT!DR8+TYSE!AY8+PEMA!AY8+KNLG!AY8+RJNG!AY8+WRMG!CH8+DUSM!AY8+GYPG!AY8+NGLM!CH8+SAMC!DR8+PHUA!DR8+TSMA!AY8+GEDU!CH8+SAMA!DR8+TCHG!CH8+GMTU!DR8+LHAM!AY8+PHLY!EY8 -> 0 | ... GA8: =PARO!BU8+HAA!DD8+WANG!EN8+PUNA!EN8+GASA!DD8+GELA!EN8+ZEMG!EN8+TRON!EN8+BUMA!EN8+SARA!EN8+TSIR!EN8+DGNA!EN8+PANG!EN8+DPLA!EN8+SJKA!EN8+TRAG!DD8+MONA!BU8+LUNT!EN8+TYSE!BU8+PEMA!BU8+KNLG!BU8+RJNG!BU8+WRMG!DD8+DUSM!BU8+GYPG!BU8+NGLM!DD8+SAMC!EN8+PHUA!EN8+TSMA!BU8+GEDU!DD8+SAMA!EN8+TCHG!DD8+GMTU!EN8+LHAM!BU8+PHLY!FU8 -> 0 | GB8: =PARO!BV8+HAA!DE8+WANG!EO8+PUNA!EO8+GASA!DE8+GELA!EO8+ZEMG!EO8+TRON!EO8+BUMA!EO8+SARA!EO8+TSIR!EO8+DGNA!EO8+PANG!EO8+DPLA!EO8+SJKA!EO8+TRAG!DE8+MONA!BW8+LUNT!EO8+TYSE!BW8+PEMA!BW8+KNLG!BW8+RJNG!BV8+WRMG!DE8+DUSM!BW8+GYPG!BW8+NGLM!DE8+SAMC!EO8+PHUA!EO8+TSMA!BV8+GEDU!DE8+SAMA!EO8+TCHG!DE8+GMTU!EO8+LHAM!BV8+PHLY!FV8 -> 1 | GC8: =PARO!BW8+HAA!DF8+WANG!EP8+PUNA!EP8+GASA!DF8+GELA!EP8+ZEMG!EP8+TRON!EP8+BUMA!EP8+SARA!EP8+TSIR!EP8+DGNA!EP8+PANG!EP8+DPLA!EP8+SJKA!EP8+TRAG!DF8+MONA!BX8+LUNT!EP8+TYSE!BX8+PEMA!BX8+KNLG!BX8+RJNG!BW8+WRMG!DF8+DUSM!BX8+GYPG!BX8+NGLM!DF8+SAMC!EP8+PHUA!EP8+TSMA!BW8+GEDU!DF8+SAMA!EP8+TCHG!DF8+GMTU!EP8+LHAM!BW8+PHLY!FW8 -> 4224 | GD8: =PARO!BX8+HAA!DG8+WANG!EQ8+PUNA!EQ8+GASA!DG8+GELA!EQ8+ZEMG!EQ8+TRON!EQ8+BUMA!EQ8+SARA!EQ8+TSIR!EQ8+DGNA!EQ8+PANG!EQ8+DPLA!EQ8+SJKA!EQ8+TRAG!DG8+MONA!BY8+LUNT!EQ8+TYSE!BY8+PEMA!BY8+KNLG!BY8+RJNG!BX8+WRMG!DG8+DUSM!BY8+GYPG!BY8+NGLM!DG8+SAMC!EQ8+PHUA!EQ8+TSMA!BX8+GEDU!DG8+SAMA!EQ8+TCHG!DG8+GMTU!EQ8+LHAM!BX8+PHLY!FX8 -> 704 | GE8: =PARO!BY8+HAA!DH8+WANG!ER8+PUNA!ER8+GASA!DH8+GELA!ER8+ZEMG!ER8+TRON!ER8+BUMA!ER8+SARA!ER8+TSIR!ER8+DGNA!ER8+PANG!ER8+DPLA!ER8+SJKA!ER8+TRAG!DH8+MONA!BZ8+LUNT!ER8+TYSE!BZ8+PEMA!BZ8+KNLG!BZ8+RJNG!BY8+WRMG!DH8+DUSM!BZ8+GYPG!BZ8+NGLM!DH8+SAMC!ER8+PHUA!ER8+TSMA!BY8+GEDU!DH8+SAMA!ER8+TCHG!DH8+GMTU!ER8+LHAM!BY8+PHLY!FY8 -> 3520 | GG8: =PARO!CA8+HAA!DJ8+WANG!ET8+PUNA!ET8+GASA!DJ8+GELA!ET8+ZEMG!ET8+TRON!ET8+BUMA!ET8+SARA!ET8+TSIR!ET8+DGNA!ET8+PANG!ET8+DPLA!ET8+SJKA!ET8+TRAG!DJ8+MONA!CB8+LUNT!ET8+TYSE!CB8+PEMA!CB8+KNLG!CB8+RJNG!CA8+WRMG!DJ8+DUSM!CB8+GYPG!CB8+NGLM!DJ8+SAMC!ET8+PHUA!ET8+TSMA!CA8+GEDU!DJ8+SAMA!ET8+TCHG!DJ8+GMTU!ET8+LHAM!CA8+PHLY!GA8 -> 0 | GH8: =PARO!CB8+HAA!DK8+WANG!EU8+PUNA!EU8+GASA!DK8+GELA!EU8+ZEMG!EU8+TRON!EU8+BUMA!EU8+SARA!EU8+TSIR!EU8+DGNA!EU8+PANG!EU8+DPLA!EU8+SJKA!EU8+TRAG!DK8+MONA!CC8+LUNT!EU8+TYSE!CC8+PEMA!CC8+KNLG!CC8+RJNG!CB8+WRMG!DK8+DUSM!CC8+GYPG!CC8+NGLM!DK8+SAMC!EU8+PHUA!EU8+TSMA!CB8+GEDU!DK8+SAMA!EU8+TCHG!DK8+GMTU!EU8+LHAM!CB8+PHLY!GB8 -> 0 | GI8: =PARO!CC8+HAA!DL8+WANG!EV8+PUNA!EV8+GASA!DL8+GELA!EV8+ZEMG!EV8+TRON!EV8+BUMA!EV8+SARA!EV8+TSIR!EV8+DGNA!EV8+PANG!EV8+DPLA!EV8+SJKA!EV8+TRAG!DL8+MONA!CD8+LUNT!EV8+TYSE!CD8+PEMA!CD8+KNLG!CD8+RJNG!CC8+WRMG!DL8+DUSM!CD8+GYPG!CD8+NGLM!DL8+SAMC!EV8+PHUA!EV8+TSMA!CC8+GEDU!DL8+SAMA!EV8+TCHG!DL8+GMTU!EV8+LHAM!CC8+PHLY!GC8 -> 0 | GJ8: =PARO!CD8+HAA!DM8+WANG!EW8+PUNA!EW8+GASA!DM8+GELA!EW8+ZEMG!EW8+TRON!EW8+BUMA!EW8+SARA!EW8+TSIR!EW8+DGNA!EW8+PANG!EW8+DPLA!EW8+SJKA!EW8+TRAG!DM8+MONA!CE8+LUNT!EW8+TYSE!CE8+PEMA!CE8+KNLG!CE8+RJNG!CD8+WRMG!DM8+DUSM!CE8+GYPG!CE8+NGLM!DM8+SAMC!EW8+PHUA!EW8+TSMA!CD8+GEDU!DM8+SAMA!EW8+TCHG!DM8+GMTU!EW8+LHAM!CD8+PHLY!GD8 -> 1 | GK8: =PARO!CE8+HAA!DN8+WANG!EX8+PUNA!EX8+GASA!DN8+GELA!EX8+ZEMG!EX8+TRON!EX8+BUMA!EX8+SARA!EX8+TSIR!EX8+DGNA!EX8+PANG!EX8+DPLA!EX8+SJKA!EX8+TRAG!DN8+MONA!CF8+LUNT!EX8+TYSE!CF8+PEMA!CF8+KNLG!CF8+RJNG!CE8+WRMG!DN8+DUSM!CF8+GYPG!CF8+NGLM!DN8+SAMC!EX8+PHUA!EX8+TSMA!CE8+GEDU!DN8+SAMA!EX8+TCHG!DN8+GMTU!EX8+LHAM!CE8+PHLY!GE8 -> 0 | GL8: =PARO!CF8+HAA!DO8+WANG!EY8+PUNA!EY8+GASA!DO8+GELA!EY8+ZEMG!EY8+TRON!EY8+BUMA!EY8+SARA!EY8+TSIR!EY8+DGNA!EY8+PANG!EY8+DPLA!EY8+SJKA!EY8+TRAG!DO8+MONA!CG8+LUNT!EY8+TYSE!CG8+PEMA!CG8+KNLG!CG8+RJNG!CF8+WRMG!DO8+DUSM!CG8+GYPG!CG8+NGLM!DO8+SAMC!EY8+PHUA!EY8+TSMA!CF8+GEDU!DO8+SAMA!EY8+TCHG!DO8+GMTU!EY8+LHAM!CF8+PHLY!GF8 -> 0 | GM8: =PARO!CG8+HAA!DP8+WANG!EZ8+PUNA!EZ8+GASA!DP8+GELA!EZ8+ZEMG!EZ8+TRON!EZ8+BUMA!EZ8+SARA!EZ8+TSIR!EZ8+DGNA!EZ8+PANG!EZ8+DPLA!EZ8+SJKA!EZ8+TRAG!DP8+MONA!CH8+LUNT!EZ8+TYSE!CH8+PEMA!CH8+KNLG!CH8+RJNG!CG8+WRMG!DP8+DUSM!CH8+GYPG!CH8+NGLM!DP8+SAMC!EZ8+PHUA!EZ8+TSMA!CG8+GEDU!DP8+SAMA!EZ8+TCHG!DP8+GMTU!EZ8+LHAM!CG8+PHLY!GG8 -> 0 | GN8: =PARO!CH8+HAA!DQ8+WANG!FA8+PUNA!FA8+GASA!DQ8+GELA!FA8+ZEMG!FA8+TRON!FA8+BUMA!FA8+SARA!FA8+TSIR!FA8+DGNA!FA8+PANG!FA8+DPLA!FA8+SJKA!FA8+TRAG!DQ8+MONA!CI8+LUNT!FA8+TYSE!CI8+PEMA!CI8+KNLG!CI8+RJNG!CH8+WRMG!DQ8+DUSM!CI8+GYPG!CI8+NGLM!DQ8+SAMC!FA8+PHUA!FA8+TSMA!CH8+GEDU!DQ8+SAMA!FA8+TCHG!DQ8+GMTU!FA8+LHAM!CH8+PHLY!GH8 -> 0 | ... HO8: =PARO!DI8+HAA!ER8+WANG!GB8+PUNA!GB8+GASA!ER8+GELA!GB8+ZEMG!GB8+TRON!GB8+BUMA!GB8+SARA!GB8+TSIR!GB8+DGNA!GB8+PANG!GB8+DPLA!GB8+SJKA!GB8+TRAG!ER8+MONA!DJ8+LUNT!GB8+TYSE!DJ8+PEMA!DJ8+KNLG!DJ8+RJNG!DI8+WRMG!ER8+DUSM!DJ8+GYPG!DJ8+NGLM!ER8+SAMC!GB8+PHUA!GB8+TSMA!DI8+GEDU!ER8+SAMA!GB8+TCHG!ER8+GMTU!GB8+LHAM!DI8+PHLY!HI8 -> 3520 | HQ8: =ES8+GB8+HL8 -> 2 | HR8: =C8*HQ8 -> 7040 | HS8: =D8*HQ8 -> 8448 | HT8: =E8*HQ8 -> 1408 | IN8: =AJ8+BT8+DC8+ES8+GB8+HL8 -> 4 | IO8: =AK8+BU8+DD8+ET8+GC8+HM8 -> 16896 | IP8: =AL8+BV8+DE8+EU8+GD8+HN8 -> 2816 | IQ8: =AM8+BW8+DF8+EV8+GE8+HO8 -> 14080 | IR8: =IR7/20 -> 74.95
A9: 7 | B9: Yungwa Tumeric capsule | C9: 500 | D9: 600 | E9: =D9-C9 -> 100 | F9: 5% Discount on every 25 boxes / packets | H9: =PHLY!H9 -> 0 | I9: =PHLY!I9 -> 0 | J9: =PHLY!J9 -> 0 | K9: =PHLY!K9 -> 0 | L9: =PHLY!L9 -> 0 | M9: =PHLY!M9 -> 0 | N9: =PHLY!N9 -> 0 | O9: =PHLY!O9 -> 0 | ... AM9: =PHLY!AM9 -> 0 | AO9: =WANG!H9+PUNA!H9+GELA!H9+ZEMG!H9+TRON!H9+BUMA!H9+SARA!H9+TSIR!H9+DGNA!H9+PANG!H9+DPLA!H9+SJKA!H9+LUNT!H9+SAMC!H9+PHUA!H9+SAMA!H9+GMTU!H9+PHLY!AO9 -> 0 | AP9: =WANG!I9+PUNA!I9+GELA!I9+ZEMG!I9+TRON!I9+BUMA!I9+SARA!I9+TSIR!I9+DGNA!I9+PANG!I9+DPLA!I9+SJKA!I9+LUNT!I9+SAMC!I9+PHUA!I9+SAMA!I9+GMTU!I9+PHLY!AP9 -> 0 | AQ9: =WANG!J9+PUNA!J9+GELA!J9+ZEMG!J9+TRON!J9+BUMA!J9+SARA!J9+TSIR!J9+DGNA!J9+PANG!J9+DPLA!J9+SJKA!J9+LUNT!J9+SAMC!J9+PHUA!J9+SAMA!J9+GMTU!J9+PHLY!AQ9 -> 0 | AR9: =WANG!K9+PUNA!K9+GELA!K9+ZEMG!K9+TRON!K9+BUMA!K9+SARA!K9+TSIR!K9+DGNA!K9+PANG!K9+DPLA!K9+SJKA!K9+LUNT!K9+SAMC!K9+PHUA!K9+SAMA!K9+GMTU!K9+PHLY!AR9 -> 0 | AS9: =WANG!L9+PUNA!L9+GELA!L9+ZEMG!L9+TRON!L9+BUMA!L9+SARA!L9+TSIR!L9+DGNA!L9+PANG!L9+DPLA!L9+SJKA!L9+LUNT!L9+SAMC!L9+PHUA!L9+SAMA!L9+GMTU!L9+PHLY!AS9 -> 0 | AT9: =WANG!M9+PUNA!M9+GELA!M9+ZEMG!M9+TRON!M9+BUMA!M9+SARA!M9+TSIR!M9+DGNA!M9+PANG!M9+DPLA!M9+SJKA!M9+LUNT!M9+SAMC!M9+PHUA!M9+SAMA!M9+GMTU!M9+PHLY!AT9 -> 0 | AU9: =WANG!N9+PUNA!N9+GELA!N9+ZEMG!N9+TRON!N9+BUMA!N9+SARA!N9+TSIR!N9+DGNA!N9+PANG!N9+DPLA!N9+SJKA!N9+LUNT!N9+SAMC!N9+PHUA!N9+SAMA!N9+GMTU!N9+PHLY!AU9 -> 1 | AV9: =WANG!O9+PUNA!O9+GELA!O9+ZEMG!O9+TRON!O9+BUMA!O9+SARA!O9+TSIR!O9+DGNA!O9+PANG!O9+DPLA!O9+SJKA!O9+LUNT!O9+SAMC!O9+PHUA!O9+SAMA!O9+GMTU!O9+PHLY!AV9 -> 0 | ... BW9: =WANG!AP9+PUNA!AP9+GELA!AP9+ZEMG!AP9+TRON!AP9+BUMA!AP9+SARA!AP9+TSIR!AP9+DGNA!AP9+PANG!AP9+DPLA!AP9+SJKA!AP9+LUNT!AP9+SAMC!AP9+PHUA!AP9+SAMA!AP9+GMTU!AP9+PHLY!BW9 -> 7500 | BY9: =HAA!H9+WANG!AR9+PUNA!AR9+GASA!H9+GELA!AR9+ZEMG!AR9+TRON!AR9+BUMA!AR9+SARA!AR9+TSIR!AR9+DGNA!AR9+PANG!AR9+DPLA!AR9+SJKA!AR9+TRAG!H9+LUNT!AR9+WRMG!H9+NGLM!H9+SAMC!AR9+PHUA!AR9+GEDU!H9+SAMA!AR9+TCHG!H9+GMTU!AR9+PHLY!BY9 -> 0 | BZ9: =HAA!I9+WANG!AS9+PUNA!AS9+GASA!I9+GELA!AS9+ZEMG!AS9+TRON!AS9+BUMA!AS9+SARA!AS9+TSIR!AS9+DGNA!AS9+PANG!AS9+DPLA!AS9+SJKA!AS9+TRAG!I9+LUNT!AS9+WRMG!I9+NGLM!I9+SAMC!AS9+PHUA!AS9+GEDU!I9+SAMA!AS9+TCHG!I9+GMTU!AS9+PHLY!BZ9 -> 0 | CA9: =HAA!J9+WANG!AT9+PUNA!AT9+GASA!J9+GELA!AT9+ZEMG!AT9+TRON!AT9+BUMA!AT9+SARA!AT9+TSIR!AT9+DGNA!AT9+PANG!AT9+DPLA!AT9+SJKA!AT9+TRAG!J9+LUNT!AT9+WRMG!J9+NGLM!J9+SAMC!AT9+PHUA!AT9+GEDU!J9+SAMA!AT9+TCHG!J9+GMTU!AT9+PHLY!CA9 -> 0 | CB9: =HAA!K9+WANG!AU9+PUNA!AU9+GASA!K9+GELA!AU9+ZEMG!AU9+TRON!AU9+BUMA!AU9+SARA!AU9+TSIR!AU9+DGNA!AU9+PANG!AU9+DPLA!AU9+SJKA!AU9+TRAG!K9+LUNT!AU9+WRMG!K9+NGLM!K9+SAMC!AU9+PHUA!AU9+GEDU!K9+SAMA!AU9+TCHG!K9+GMTU!AU9+PHLY!CB9 -> 0 | CC9: =HAA!L9+WANG!AV9+PUNA!AV9+GASA!L9+GELA!AV9+ZEMG!AV9+TRON!AV9+BUMA!AV9+SARA!AV9+TSIR!AV9+DGNA!AV9+PANG!AV9+DPLA!AV9+SJKA!AV9+TRAG!L9+LUNT!AV9+WRMG!L9+NGLM!L9+SAMC!AV9+PHUA!AV9+GEDU!L9+SAMA!AV9+TCHG!L9+GMTU!AV9+PHLY!CC9 -> 0 | CD9: =HAA!M9+WANG!AW9+PUNA!AW9+GASA!M9+GELA!AW9+ZEMG!AW9+TRON!AW9+BUMA!AW9+SARA!AW9+TSIR!AW9+DGNA!AW9+PANG!AW9+DPLA!AW9+SJKA!AW9+TRAG!M9+LUNT!AW9+WRMG!M9+NGLM!M9+SAMC!AW9+PHUA!AW9+GEDU!M9+SAMA!AW9+TCHG!M9+GMTU!AW9+PHLY!CD9 -> 0 | CE9: =HAA!N9+WANG!AX9+PUNA!AX9+GASA!N9+GELA!AX9+ZEMG!AX9+TRON!AX9+BUMA!AX9+SARA!AX9+TSIR!AX9+DGNA!AX9+PANG!AX9+DPLA!AX9+SJKA!AX9+TRAG!N9+LUNT!AX9+WRMG!N9+NGLM!N9+SAMC!AX9+PHUA!AX9+GEDU!N9+SAMA!AX9+TCHG!N9+GMTU!AX9+PHLY!CE9 -> 0 | CF9: =HAA!O9+WANG!AY9+PUNA!AY9+GASA!O9+GELA!AY9+ZEMG!AY9+TRON!AY9+BUMA!AY9+SARA!AY9+TSIR!AY9+DGNA!AY9+PANG!AY9+DPLA!AY9+SJKA!AY9+TRAG!O9+LUNT!AY9+WRMG!O9+NGLM!O9+SAMC!AY9+PHUA!AY9+GEDU!O9+SAMA!AY9+TCHG!O9+GMTU!AY9+PHLY!CF9 -> 0 | ... DF9: =HAA!AO9+WANG!BY9+PUNA!BY9+GASA!AO9+GELA!BY9+ZEMG!BY9+TRON!BY9+BUMA!BY9+SARA!BY9+TSIR!BY9+DGNA!BY9+PANG!BY9+DPLA!BY9+SJKA!BY9+TRAG!AO9+LUNT!BY9+WRMG!AO9+NGLM!AO9+SAMC!BY9+PHUA!BY9+GEDU!AO9+SAMA!BY9+TCHG!AO9+GMTU!BY9+PHLY!DF9 -> 2000 | DG9: =AJ9+BT9+DC9 -> 19 | DH9: =C9*DG9 -> 9500 | DI9: =D9*DG9 -> 11400 | DJ9: =E9*DG9 -> 1900 | DK9: 25 | DL9: =DG9*DK9 -> 475 | DN9: =PARO!H9+HAA!AQ9+WANG!CA9+PUNA!CA9+GASA!AQ9+GELA!CA9+ZEMG!CA9+TRON!CA9+BUMA!CA9+SARA!CA9+TSIR!CA9+DGNA!CA9+PANG!CA9+DPLA!CA9+SJKA!CA9+TRAG!AQ9+MONA!H9+LUNT!CA9+TYSE!H9+PEMA!H9+KNLG!H9+RJNG!H9+WRMG!AQ9+DUSM!H9+GYPG!H9+NGLM!AQ9+SAMC!CA9+PHUA!CA9+TSMA!H9+GEDU!AQ9+SAMA!CA9+TCHG!AQ9+GMTU!CA9+LHAM!H9+PHLY!DH9 -> 0 | DO9: =PARO!I9+HAA!AR9+WANG!CB9+PUNA!CB9+GASA!AR9+GELA!CB9+ZEMG!CB9+TRON!CB9+BUMA!CB9+SARA!CB9+TSIR!CB9+DGNA!CB9+PANG!CB9+DPLA!CB9+SJKA!CB9+TRAG!AR9+MONA!I9+LUNT!CB9+TYSE!I9+PEMA!I9+KNLG!I9+RJNG!I9+WRMG!AR9+DUSM!I9+GYPG!I9+NGLM!AR9+SAMC!CB9+PHUA!CB9+TSMA!I9+GEDU!AR9+SAMA!CB9+TCHG!AR9+GMTU!CB9+LHAM!I9+PHLY!DI9 -> 0 | DP9: =PARO!J9+HAA!AS9+WANG!CC9+PUNA!CC9+GASA!AS9+GELA!CC9+ZEMG!CC9+TRON!CC9+BUMA!CC9+SARA!CC9+TSIR!CC9+DGNA!CC9+PANG!CC9+DPLA!CC9+SJKA!CC9+TRAG!AS9+MONA!J9+LUNT!CC9+TYSE!J9+PEMA!J9+KNLG!J9+RJNG!J9+WRMG!AS9+DUSM!J9+GYPG!J9+NGLM!AS9+SAMC!CC9+PHUA!CC9+TSMA!J9+GEDU!AS9+SAMA!CC9+TCHG!AS9+GMTU!CC9+LHAM!J9+PHLY!DJ9 -> 0 | DQ9: =PARO!K9+HAA!AT9+WANG!CD9+PUNA!CD9+GASA!AT9+GELA!CD9+ZEMG!CD9+TRON!CD9+BUMA!CD9+SARA!CD9+TSIR!CD9+DGNA!CD9+PANG!CD9+DPLA!CD9+SJKA!CD9+TRAG!AT9+MONA!K9+LUNT!CD9+TYSE!K9+PEMA!K9+KNLG!K9+RJNG!K9+WRMG!AT9+DUSM!K9+GYPG!K9+NGLM!AT9+SAMC!CD9+PHUA!CD9+TSMA!K9+GEDU!AT9+SAMA!CD9+TCHG!AT9+GMTU!CD9+LHAM!K9+PHLY!DK9 -> 0 | DR9: =PARO!L9+HAA!AU9+WANG!CE9+PUNA!CE9+GASA!AU9+GELA!CE9+ZEMG!CE9+TRON!CE9+BUMA!CE9+SARA!CE9+TSIR!CE9+DGNA!CE9+PANG!CE9+DPLA!CE9+SJKA!CE9+TRAG!AU9+MONA!L9+LUNT!CE9+TYSE!L9+PEMA!L9+KNLG!L9+RJNG!L9+WRMG!AU9+DUSM!L9+GYPG!L9+NGLM!AU9+SAMC!CE9+PHUA!CE9+TSMA!L9+GEDU!AU9+SAMA!CE9+TCHG!AU9+GMTU!CE9+LHAM!L9+PHLY!DL9 -> 0 | DS9: =PARO!M9+HAA!AV9+WANG!CF9+PUNA!CF9+GASA!AV9+GELA!CF9+ZEMG!CF9+TRON!CF9+BUMA!CF9+SARA!CF9+TSIR!CF9+DGNA!CF9+PANG!CF9+DPLA!CF9+SJKA!CF9+TRAG!AV9+MONA!M9+LUNT!CF9+TYSE!M9+PEMA!M9+KNLG!M9+RJNG!M9+WRMG!AV9+DUSM!M9+GYPG!M9+NGLM!AV9+SAMC!CF9+PHUA!CF9+TSMA!M9+GEDU!AV9+SAMA!CF9+TCHG!AV9+GMTU!CF9+LHAM!M9+PHLY!DM9 -> 1 | DT9: =PARO!N9+HAA!AW9+WANG!CG9+PUNA!CG9+GASA!AW9+GELA!CG9+ZEMG!CG9+TRON!CG9+BUMA!CG9+SARA!CG9+TSIR!CG9+DGNA!CG9+PANG!CG9+DPLA!CG9+SJKA!CG9+TRAG!AW9+MONA!N9+LUNT!CG9+TYSE!N9+PEMA!N9+KNLG!N9+RJNG!N9+WRMG!AW9+DUSM!N9+GYPG!N9+NGLM!AW9+SAMC!CG9+PHUA!CG9+TSMA!N9+GEDU!AW9+SAMA!CG9+TCHG!AW9+GMTU!CG9+LHAM!N9+PHLY!DN9 -> 0 | DU9: =PARO!O9+HAA!AX9+WANG!CH9+PUNA!CH9+GASA!AX9+GELA!CH9+ZEMG!CH9+TRON!CH9+BUMA!CH9+SARA!CH9+TSIR!CH9+DGNA!CH9+PANG!CH9+DPLA!CH9+SJKA!CH9+TRAG!AX9+MONA!O9+LUNT!CH9+TYSE!O9+PEMA!O9+KNLG!O9+RJNG!O9+WRMG!AX9+DUSM!O9+GYPG!O9+NGLM!AX9+SAMC!CH9+PHUA!CH9+TSMA!O9+GEDU!AX9+SAMA!CH9+TCHG!AX9+GMTU!CH9+LHAM!O9+PHLY!DO9 -> 1 | ... EV9: =PARO!AP9+HAA!BY9+WANG!DI9+PUNA!DI9+GASA!BY9+GELA!DI9+ZEMG!DI9+TRON!DI9+BUMA!DI9+SARA!DI9+TSIR!DI9+DGNA!DI9+PANG!DI9+DPLA!DI9+SJKA!DI9+TRAG!BY9+MONA!AP9+LUNT!DI9+TYSE!AP9+PEMA!AP9+KNLG!AP9+RJNG!AP9+WRMG!BY9+DUSM!AP9+GYPG!AP9+NGLM!BY9+SAMC!DI9+PHUA!DI9+TSMA!AP9+GEDU!BY9+SAMA!DI9+TCHG!BY9+GMTU!DI9+LHAM!AP9+PHLY!EP9 -> 4000 | EX9: =PARO!AR9+HAA!CA9+WANG!DK9+PUNA!DK9+GASA!CA9+GELA!DK9+ZEMG!DK9+TRON!DK9+BUMA!DK9+SARA!DK9+TSIR!DK9+DGNA!DK9+PANG!DK9+DPLA!DK9+SJKA!DK9+TRAG!CA9+MONA!AR9+LUNT!DK9+TYSE!AR9+PEMA!AR9+KNLG!AR9+RJNG!AR9+WRMG!CA9+DUSM!AR9+GYPG!AR9+NGLM!CA9+SAMC!DK9+PHUA!DK9+TSMA!AR9+GEDU!CA9+SAMA!DK9+TCHG!CA9+GMTU!DK9+LHAM!AR9+PHLY!ER9 -> 0 | EY9: =PARO!AS9+HAA!CB9+WANG!DL9+PUNA!DL9+GASA!CB9+GELA!DL9+ZEMG!DL9+TRON!DL9+BUMA!DL9+SARA!DL9+TSIR!DL9+DGNA!DL9+PANG!DL9+DPLA!DL9+SJKA!DL9+TRAG!CB9+MONA!AS9+LUNT!DL9+TYSE!AS9+PEMA!AS9+KNLG!AS9+RJNG!AS9+WRMG!CB9+DUSM!AS9+GYPG!AS9+NGLM!CB9+SAMC!DL9+PHUA!DL9+TSMA!AS9+GEDU!CB9+SAMA!DL9+TCHG!CB9+GMTU!DL9+LHAM!AS9+PHLY!ES9 -> 0 | EZ9: =PARO!AT9+HAA!CC9+WANG!DM9+PUNA!DM9+GASA!CC9+GELA!DM9+ZEMG!DM9+TRON!DM9+BUMA!DM9+SARA!DM9+TSIR!DM9+DGNA!DM9+PANG!DM9+DPLA!DM9+SJKA!DM9+TRAG!CC9+MONA!AT9+LUNT!DM9+TYSE!AT9+PEMA!AT9+KNLG!AT9+RJNG!AT9+WRMG!CC9+DUSM!AT9+GYPG!AT9+NGLM!CC9+SAMC!DM9+PHUA!DM9+TSMA!AT9+GEDU!CC9+SAMA!DM9+TCHG!CC9+GMTU!DM9+LHAM!AT9+PHLY!ET9 -> 0 | FA9: =PARO!AU9+HAA!CD9+WANG!DN9+PUNA!DN9+GASA!CD9+GELA!DN9+ZEMG!DN9+TRON!DN9+BUMA!DN9+SARA!DN9+TSIR!DN9+DGNA!DN9+PANG!DN9+DPLA!DN9+SJKA!DN9+TRAG!CD9+MONA!AU9+LUNT!DN9+TYSE!AU9+PEMA!AU9+KNLG!AU9+RJNG!AU9+WRMG!CD9+DUSM!AU9+GYPG!AU9+NGLM!CD9+SAMC!DN9+PHUA!DN9+TSMA!AU9+GEDU!CD9+SAMA!DN9+TCHG!CD9+GMTU!DN9+LHAM!AU9+PHLY!EU9 -> 0 | FB9: =PARO!AV9+HAA!CE9+WANG!DO9+PUNA!DO9+GASA!CE9+GELA!DO9+ZEMG!DO9+TRON!DO9+BUMA!DO9+SARA!DO9+TSIR!DO9+DGNA!DO9+PANG!DO9+DPLA!DO9+SJKA!DO9+TRAG!CE9+MONA!AV9+LUNT!DO9+TYSE!AV9+PEMA!AV9+KNLG!AV9+RJNG!AV9+WRMG!CE9+DUSM!AV9+GYPG!AV9+NGLM!CE9+SAMC!DO9+PHUA!DO9+TSMA!AV9+GEDU!CE9+SAMA!DO9+TCHG!CE9+GMTU!DO9+LHAM!AV9+PHLY!EV9 -> 0 | FC9: =PARO!AW9+HAA!CF9+WANG!DP9+PUNA!DP9+GASA!CF9+GELA!DP9+ZEMG!DP9+TRON!DP9+BUMA!DP9+SARA!DP9+TSIR!DP9+DGNA!DP9+PANG!DP9+DPLA!DP9+SJKA!DP9+TRAG!CF9+MONA!AW9+LUNT!DP9+TYSE!AW9+PEMA!AW9+KNLG!AW9+RJNG!AW9+WRMG!CF9+DUSM!AW9+GYPG!AW9+NGLM!CF9+SAMC!DP9+PHUA!DP9+TSMA!AW9+GEDU!CF9+SAMA!DP9+TCHG!CF9+GMTU!DP9+LHAM!AW9+PHLY!EW9 -> 0 | FD9: =PARO!AX9+HAA!CG9+WANG!DQ9+PUNA!DQ9+GASA!CG9+GELA!DQ9+ZEMG!DQ9+TRON!DQ9+BUMA!DQ9+SARA!DQ9+TSIR!DQ9+DGNA!DQ9+PANG!DQ9+DPLA!DQ9+SJKA!DQ9+TRAG!CG9+MONA!AX9+LUNT!DQ9+TYSE!AX9+PEMA!AX9+KNLG!AX9+RJNG!AX9+WRMG!CG9+DUSM!AX9+GYPG!AX9+NGLM!CG9+SAMC!DQ9+PHUA!DQ9+TSMA!AX9+GEDU!CG9+SAMA!DQ9+TCHG!CG9+GMTU!DQ9+LHAM!AX9+PHLY!EX9 -> 0 | FE9: =PARO!AY9+HAA!CH9+WANG!DR9+PUNA!DR9+GASA!CH9+GELA!DR9+ZEMG!DR9+TRON!DR9+BUMA!DR9+SARA!DR9+TSIR!DR9+DGNA!DR9+PANG!DR9+DPLA!DR9+SJKA!DR9+TRAG!CH9+MONA!AY9+LUNT!DR9+TYSE!AY9+PEMA!AY9+KNLG!AY9+RJNG!AY9+WRMG!CH9+DUSM!AY9+GYPG!AY9+NGLM!CH9+SAMC!DR9+PHUA!DR9+TSMA!AY9+GEDU!CH9+SAMA!DR9+TCHG!CH9+GMTU!DR9+LHAM!AY9+PHLY!EY9 -> 0 | ... GA9: =PARO!BU9+HAA!DD9+WANG!EN9+PUNA!EN9+GASA!DD9+GELA!EN9+ZEMG!EN9+TRON!EN9+BUMA!EN9+SARA!EN9+TSIR!EN9+DGNA!EN9+PANG!EN9+DPLA!EN9+SJKA!EN9+TRAG!DD9+MONA!BU9+LUNT!EN9+TYSE!BU9+PEMA!BU9+KNLG!BU9+RJNG!BU9+WRMG!DD9+DUSM!BU9+GYPG!BU9+NGLM!DD9+SAMC!EN9+PHUA!EN9+TSMA!BU9+GEDU!DD9+SAMA!EN9+TCHG!DD9+GMTU!EN9+LHAM!BU9+PHLY!FU9 -> 0 | GB9: =PARO!BV9+HAA!DE9+WANG!EO9+PUNA!EO9+GASA!DE9+GELA!EO9+ZEMG!EO9+TRON!EO9+BUMA!EO9+SARA!EO9+TSIR!EO9+DGNA!EO9+PANG!EO9+DPLA!EO9+SJKA!EO9+TRAG!DE9+MONA!BW9+LUNT!EO9+TYSE!BW9+PEMA!BW9+KNLG!BW9+RJNG!BV9+WRMG!DE9+DUSM!BW9+GYPG!BW9+NGLM!DE9+SAMC!EO9+PHUA!EO9+TSMA!BV9+GEDU!DE9+SAMA!EO9+TCHG!DE9+GMTU!EO9+LHAM!BV9+PHLY!FV9 -> 9 | GC9: =PARO!BW9+HAA!DF9+WANG!EP9+PUNA!EP9+GASA!DF9+GELA!EP9+ZEMG!EP9+TRON!EP9+BUMA!EP9+SARA!EP9+TSIR!EP9+DGNA!EP9+PANG!EP9+DPLA!EP9+SJKA!EP9+TRAG!DF9+MONA!BX9+LUNT!EP9+TYSE!BX9+PEMA!BX9+KNLG!BX9+RJNG!BW9+WRMG!DF9+DUSM!BX9+GYPG!BX9+NGLM!DF9+SAMC!EP9+PHUA!EP9+TSMA!BW9+GEDU!DF9+SAMA!EP9+TCHG!DF9+GMTU!EP9+LHAM!BW9+PHLY!FW9 -> 5400 | GD9: =PARO!BX9+HAA!DG9+WANG!EQ9+PUNA!EQ9+GASA!DG9+GELA!EQ9+ZEMG!EQ9+TRON!EQ9+BUMA!EQ9+SARA!EQ9+TSIR!EQ9+DGNA!EQ9+PANG!EQ9+DPLA!EQ9+SJKA!EQ9+TRAG!DG9+MONA!BY9+LUNT!EQ9+TYSE!BY9+PEMA!BY9+KNLG!BY9+RJNG!BX9+WRMG!DG9+DUSM!BY9+GYPG!BY9+NGLM!DG9+SAMC!EQ9+PHUA!EQ9+TSMA!BX9+GEDU!DG9+SAMA!EQ9+TCHG!DG9+GMTU!EQ9+LHAM!BX9+PHLY!FX9 -> 900 | GE9: =PARO!BY9+HAA!DH9+WANG!ER9+PUNA!ER9+GASA!DH9+GELA!ER9+ZEMG!ER9+TRON!ER9+BUMA!ER9+SARA!ER9+TSIR!ER9+DGNA!ER9+PANG!ER9+DPLA!ER9+SJKA!ER9+TRAG!DH9+MONA!BZ9+LUNT!ER9+TYSE!BZ9+PEMA!BZ9+KNLG!BZ9+RJNG!BY9+WRMG!DH9+DUSM!BZ9+GYPG!BZ9+NGLM!DH9+SAMC!ER9+PHUA!ER9+TSMA!BY9+GEDU!DH9+SAMA!ER9+TCHG!DH9+GMTU!ER9+LHAM!BY9+PHLY!FY9 -> 4500 | GG9: =PARO!CA9+HAA!DJ9+WANG!ET9+PUNA!ET9+GASA!DJ9+GELA!ET9+ZEMG!ET9+TRON!ET9+BUMA!ET9+SARA!ET9+TSIR!ET9+DGNA!ET9+PANG!ET9+DPLA!ET9+SJKA!ET9+TRAG!DJ9+MONA!CB9+LUNT!ET9+TYSE!CB9+PEMA!CB9+KNLG!CB9+RJNG!CA9+WRMG!DJ9+DUSM!CB9+GYPG!CB9+NGLM!DJ9+SAMC!ET9+PHUA!ET9+TSMA!CA9+GEDU!DJ9+SAMA!ET9+TCHG!DJ9+GMTU!ET9+LHAM!CA9+PHLY!GA9 -> 0 | GH9: =PARO!CB9+HAA!DK9+WANG!EU9+PUNA!EU9+GASA!DK9+GELA!EU9+ZEMG!EU9+TRON!EU9+BUMA!EU9+SARA!EU9+TSIR!EU9+DGNA!EU9+PANG!EU9+DPLA!EU9+SJKA!EU9+TRAG!DK9+MONA!CC9+LUNT!EU9+TYSE!CC9+PEMA!CC9+KNLG!CC9+RJNG!CB9+WRMG!DK9+DUSM!CC9+GYPG!CC9+NGLM!DK9+SAMC!EU9+PHUA!EU9+TSMA!CB9+GEDU!DK9+SAMA!EU9+TCHG!DK9+GMTU!EU9+LHAM!CB9+PHLY!GB9 -> 0 | GI9: =PARO!CC9+HAA!DL9+WANG!EV9+PUNA!EV9+GASA!DL9+GELA!EV9+ZEMG!EV9+TRON!EV9+BUMA!EV9+SARA!EV9+TSIR!EV9+DGNA!EV9+PANG!EV9+DPLA!EV9+SJKA!EV9+TRAG!DL9+MONA!CD9+LUNT!EV9+TYSE!CD9+PEMA!CD9+KNLG!CD9+RJNG!CC9+WRMG!DL9+DUSM!CD9+GYPG!CD9+NGLM!DL9+SAMC!EV9+PHUA!EV9+TSMA!CC9+GEDU!DL9+SAMA!EV9+TCHG!DL9+GMTU!EV9+LHAM!CC9+PHLY!GC9 -> 0 | GJ9: =PARO!CD9+HAA!DM9+WANG!EW9+PUNA!EW9+GASA!DM9+GELA!EW9+ZEMG!EW9+TRON!EW9+BUMA!EW9+SARA!EW9+TSIR!EW9+DGNA!EW9+PANG!EW9+DPLA!EW9+SJKA!EW9+TRAG!DM9+MONA!CE9+LUNT!EW9+TYSE!CE9+PEMA!CE9+KNLG!CE9+RJNG!CD9+WRMG!DM9+DUSM!CE9+GYPG!CE9+NGLM!DM9+SAMC!EW9+PHUA!EW9+TSMA!CD9+GEDU!DM9+SAMA!EW9+TCHG!DM9+GMTU!EW9+LHAM!CD9+PHLY!GD9 -> 0 | GK9: =PARO!CE9+HAA!DN9+WANG!EX9+PUNA!EX9+GASA!DN9+GELA!EX9+ZEMG!EX9+TRON!EX9+BUMA!EX9+SARA!EX9+TSIR!EX9+DGNA!EX9+PANG!EX9+DPLA!EX9+SJKA!EX9+TRAG!DN9+MONA!CF9+LUNT!EX9+TYSE!CF9+PEMA!CF9+KNLG!CF9+RJNG!CE9+WRMG!DN9+DUSM!CF9+GYPG!CF9+NGLM!DN9+SAMC!EX9+PHUA!EX9+TSMA!CE9+GEDU!DN9+SAMA!EX9+TCHG!DN9+GMTU!EX9+LHAM!CE9+PHLY!GE9 -> 0 | GL9: =PARO!CF9+HAA!DO9+WANG!EY9+PUNA!EY9+GASA!DO9+GELA!EY9+ZEMG!EY9+TRON!EY9+BUMA!EY9+SARA!EY9+TSIR!EY9+DGNA!EY9+PANG!EY9+DPLA!EY9+SJKA!EY9+TRAG!DO9+MONA!CG9+LUNT!EY9+TYSE!CG9+PEMA!CG9+KNLG!CG9+RJNG!CF9+WRMG!DO9+DUSM!CG9+GYPG!CG9+NGLM!DO9+SAMC!EY9+PHUA!EY9+TSMA!CF9+GEDU!DO9+SAMA!EY9+TCHG!DO9+GMTU!EY9+LHAM!CF9+PHLY!GF9 -> 0 | GM9: =PARO!CG9+HAA!DP9+WANG!EZ9+PUNA!EZ9+GASA!DP9+GELA!EZ9+ZEMG!EZ9+TRON!EZ9+BUMA!EZ9+SARA!EZ9+TSIR!EZ9+DGNA!EZ9+PANG!EZ9+DPLA!EZ9+SJKA!EZ9+TRAG!DP9+MONA!CH9+LUNT!EZ9+TYSE!CH9+PEMA!CH9+KNLG!CH9+RJNG!CG9+WRMG!DP9+DUSM!CH9+GYPG!CH9+NGLM!DP9+SAMC!EZ9+PHUA!EZ9+TSMA!CG9+GEDU!DP9+SAMA!EZ9+TCHG!DP9+GMTU!EZ9+LHAM!CG9+PHLY!GG9 -> 0 | GN9: =PARO!CH9+HAA!DQ9+WANG!FA9+PUNA!FA9+GASA!DQ9+GELA!FA9+ZEMG!FA9+TRON!FA9+BUMA!FA9+SARA!FA9+TSIR!FA9+DGNA!FA9+PANG!FA9+DPLA!FA9+SJKA!FA9+TRAG!DQ9+MONA!CI9+LUNT!FA9+TYSE!CI9+PEMA!CI9+KNLG!CI9+RJNG!CH9+WRMG!DQ9+DUSM!CI9+GYPG!CI9+NGLM!DQ9+SAMC!FA9+PHUA!FA9+TSMA!CH9+GEDU!DQ9+SAMA!FA9+TCHG!DQ9+GMTU!FA9+LHAM!CH9+PHLY!GH9 -> 0 | ... HO9: =PARO!DI9+HAA!ER9+WANG!GB9+PUNA!GB9+GASA!ER9+GELA!GB9+ZEMG!GB9+TRON!GB9+BUMA!GB9+SARA!GB9+TSIR!GB9+DGNA!GB9+PANG!GB9+DPLA!GB9+SJKA!GB9+TRAG!ER9+MONA!DJ9+LUNT!GB9+TYSE!DJ9+PEMA!DJ9+KNLG!DJ9+RJNG!DI9+WRMG!ER9+DUSM!DJ9+GYPG!DJ9+NGLM!ER9+SAMC!GB9+PHUA!GB9+TSMA!DI9+GEDU!ER9+SAMA!GB9+TCHG!ER9+GMTU!GB9+LHAM!DI9+PHLY!HI9 -> 1500 | HQ9: =ES9+GB9+HL9 -> 20 | HR9: =C9*HQ9 -> 10000 | HS9: =D9*HQ9 -> 12000 | HT9: =E9*HQ9 -> 2000 | HU9: 25 | HV9: =HQ9*HU9 -> 500 | IN9: =AJ9+BT9+DC9+ES9+GB9+HL9 -> 39 | IO9: =AK9+BU9+DD9+ET9+GC9+HM9 -> 23400 | IP9: =AL9+BV9+DE9+EU9+GD9+HN9 -> 3900 | IQ9: =AM9+BW9+DF9+EV9+GE9+HO9 -> 19500
A10: 8 | B10: Natural Shilajit Miniral Pitch | C10: 1300 | D10: 1560 | E10: =D10-C10 -> 260 | F10: No Discount | H10: =PHLY!H10 -> 0 | I10: =PHLY!I10 -> 0 | J10: =PHLY!J10 -> 0 | K10: =PHLY!K10 -> 0 | L10: =PHLY!L10 -> 0 | M10: =PHLY!M10 -> 0 | N10: =PHLY!N10 -> 0 | O10: =PHLY!O10 -> 0 | ... AM10: =PHLY!AM10 -> 0 | AO10: =WANG!H10+PUNA!H10+GELA!H10+ZEMG!H10+TRON!H10+BUMA!H10+SARA!H10+TSIR!H10+DGNA!H10+PANG!H10+DPLA!H10+SJKA!H10+LUNT!H10+SAMC!H10+PHUA!H10+SAMA!H10+GMTU!H10+PHLY!AO10 -> 0 | AP10: =WANG!I10+PUNA!I10+GELA!I10+ZEMG!I10+TRON!I10+BUMA!I10+SARA!I10+TSIR!I10+DGNA!I10+PANG!I10+DPLA!I10+SJKA!I10+LUNT!I10+SAMC!I10+PHUA!I10+SAMA!I10+GMTU!I10+PHLY!AP10 -> 0 | AQ10: =WANG!J10+PUNA!J10+GELA!J10+ZEMG!J10+TRON!J10+BUMA!J10+SARA!J10+TSIR!J10+DGNA!J10+PANG!J10+DPLA!J10+SJKA!J10+LUNT!J10+SAMC!J10+PHUA!J10+SAMA!J10+GMTU!J10+PHLY!AQ10 -> 0 | AR10: =WANG!K10+PUNA!K10+GELA!K10+ZEMG!K10+TRON!K10+BUMA!K10+SARA!K10+TSIR!K10+DGNA!K10+PANG!K10+DPLA!K10+SJKA!K10+LUNT!K10+SAMC!K10+PHUA!K10+SAMA!K10+GMTU!K10+PHLY!AR10 -> 0 | AS10: =WANG!L10+PUNA!L10+GELA!L10+ZEMG!L10+TRON!L10+BUMA!L10+SARA!L10+TSIR!L10+DGNA!L10+PANG!L10+DPLA!L10+SJKA!L10+LUNT!L10+SAMC!L10+PHUA!L10+SAMA!L10+GMTU!L10+PHLY!AS10 -> 1 | AT10: =WANG!M10+PUNA!M10+GELA!M10+ZEMG!M10+TRON!M10+BUMA!M10+SARA!M10+TSIR!M10+DGNA!M10+PANG!M10+DPLA!M10+SJKA!M10+LUNT!M10+SAMC!M10+PHUA!M10+SAMA!M10+GMTU!M10+PHLY!AT10 -> 0 | AU10: =WANG!N10+PUNA!N10+GELA!N10+ZEMG!N10+TRON!N10+BUMA!N10+SARA!N10+TSIR!N10+DGNA!N10+PANG!N10+DPLA!N10+SJKA!N10+LUNT!N10+SAMC!N10+PHUA!N10+SAMA!N10+GMTU!N10+PHLY!AU10 -> 0 | AV10: =WANG!O10+PUNA!O10+GELA!O10+ZEMG!O10+TRON!O10+BUMA!O10+SARA!O10+TSIR!O10+DGNA!O10+PANG!O10+DPLA!O10+SJKA!O10+LUNT!O10+SAMC!O10+PHUA!O10+SAMA!O10+GMTU!O10+PHLY!AV10 -> 0 | ... BW10: =WANG!AP10+PUNA!AP10+GELA!AP10+ZEMG!AP10+TRON!AP10+BUMA!AP10+SARA!AP10+TSIR!AP10+DGNA!AP10+PANG!AP10+DPLA!AP10+SJKA!AP10+LUNT!AP10+SAMC!AP10+PHUA!AP10+SAMA!AP10+GMTU!AP10+PHLY!BW10 -> 20800 | BY10: =HAA!H10+WANG!AR10+PUNA!AR10+GASA!H10+GELA!AR10+ZEMG!AR10+TRON!AR10+BUMA!AR10+SARA!AR10+TSIR!AR10+DGNA!AR10+PANG!AR10+DPLA!AR10+SJKA!AR10+TRAG!H10+LUNT!AR10+WRMG!H10+NGLM!H10+SAMC!AR10+PHUA!AR10+GEDU!H10+SAMA!AR10+TCHG!H10+GMTU!AR10+PHLY!BY10 -> 0 | BZ10: =HAA!I10+WANG!AS10+PUNA!AS10+GASA!I10+GELA!AS10+ZEMG!AS10+TRON!AS10+BUMA!AS10+SARA!AS10+TSIR!AS10+DGNA!AS10+PANG!AS10+DPLA!AS10+SJKA!AS10+TRAG!I10+LUNT!AS10+WRMG!I10+NGLM!I10+SAMC!AS10+PHUA!AS10+GEDU!I10+SAMA!AS10+TCHG!I10+GMTU!AS10+PHLY!BZ10 -> 1 | CA10: =HAA!J10+WANG!AT10+PUNA!AT10+GASA!J10+GELA!AT10+ZEMG!AT10+TRON!AT10+BUMA!AT10+SARA!AT10+TSIR!AT10+DGNA!AT10+PANG!AT10+DPLA!AT10+SJKA!AT10+TRAG!J10+LUNT!AT10+WRMG!J10+NGLM!J10+SAMC!AT10+PHUA!AT10+GEDU!J10+SAMA!AT10+TCHG!J10+GMTU!AT10+PHLY!CA10 -> 1 | CB10: =HAA!K10+WANG!AU10+PUNA!AU10+GASA!K10+GELA!AU10+ZEMG!AU10+TRON!AU10+BUMA!AU10+SARA!AU10+TSIR!AU10+DGNA!AU10+PANG!AU10+DPLA!AU10+SJKA!AU10+TRAG!K10+LUNT!AU10+WRMG!K10+NGLM!K10+SAMC!AU10+PHUA!AU10+GEDU!K10+SAMA!AU10+TCHG!K10+GMTU!AU10+PHLY!CB10 -> 1 | CC10: =HAA!L10+WANG!AV10+PUNA!AV10+GASA!L10+GELA!AV10+ZEMG!AV10+TRON!AV10+BUMA!AV10+SARA!AV10+TSIR!AV10+DGNA!AV10+PANG!AV10+DPLA!AV10+SJKA!AV10+TRAG!L10+LUNT!AV10+WRMG!L10+NGLM!L10+SAMC!AV10+PHUA!AV10+GEDU!L10+SAMA!AV10+TCHG!L10+GMTU!AV10+PHLY!CC10 -> 0 | CD10: =HAA!M10+WANG!AW10+PUNA!AW10+GASA!M10+GELA!AW10+ZEMG!AW10+TRON!AW10+BUMA!AW10+SARA!AW10+TSIR!AW10+DGNA!AW10+PANG!AW10+DPLA!AW10+SJKA!AW10+TRAG!M10+LUNT!AW10+WRMG!M10+NGLM!M10+SAMC!AW10+PHUA!AW10+GEDU!M10+SAMA!AW10+TCHG!M10+GMTU!AW10+PHLY!CD10 -> 0 | CE10: =HAA!N10+WANG!AX10+PUNA!AX10+GASA!N10+GELA!AX10+ZEMG!AX10+TRON!AX10+BUMA!AX10+SARA!AX10+TSIR!AX10+DGNA!AX10+PANG!AX10+DPLA!AX10+SJKA!AX10+TRAG!N10+LUNT!AX10+WRMG!N10+NGLM!N10+SAMC!AX10+PHUA!AX10+GEDU!N10+SAMA!AX10+TCHG!N10+GMTU!AX10+PHLY!CE10 -> 1 | CF10: =HAA!O10+WANG!AY10+PUNA!AY10+GASA!O10+GELA!AY10+ZEMG!AY10+TRON!AY10+BUMA!AY10+SARA!AY10+TSIR!AY10+DGNA!AY10+PANG!AY10+DPLA!AY10+SJKA!AY10+TRAG!O10+LUNT!AY10+WRMG!O10+NGLM!O10+SAMC!AY10+PHUA!AY10+GEDU!O10+SAMA!AY10+TCHG!O10+GMTU!AY10+PHLY!CF10 -> 0 | ... DF10: =HAA!AO10+WANG!BY10+PUNA!BY10+GASA!AO10+GELA!BY10+ZEMG!BY10+TRON!BY10+BUMA!BY10+SARA!BY10+TSIR!BY10+DGNA!BY10+PANG!BY10+DPLA!BY10+SJKA!BY10+TRAG!AO10+LUNT!BY10+WRMG!AO10+NGLM!AO10+SAMC!BY10+PHUA!BY10+GEDU!AO10+SAMA!BY10+TCHG!AO10+GMTU!BY10+PHLY!DF10 -> 27300 | DG10: =AJ10+BT10+DC10 -> 37 | DH10: =C10*DG10 -> 48100 | DI10: =D10*DG10 -> 57720 | DJ10: =E10*DG10 -> 9620 | DN10: =PARO!H10+HAA!AQ10+WANG!CA10+PUNA!CA10+GASA!AQ10+GELA!CA10+ZEMG!CA10+TRON!CA10+BUMA!CA10+SARA!CA10+TSIR!CA10+DGNA!CA10+PANG!CA10+DPLA!CA10+SJKA!CA10+TRAG!AQ10+MONA!H10+LUNT!CA10+TYSE!H10+PEMA!H10+KNLG!H10+RJNG!H10+WRMG!AQ10+DUSM!H10+GYPG!H10+NGLM!AQ10+SAMC!CA10+PHUA!CA10+TSMA!H10+GEDU!AQ10+SAMA!CA10+TCHG!AQ10+GMTU!CA10+LHAM!H10+PHLY!DH10 -> 0 | DO10: =PARO!I10+HAA!AR10+WANG!CB10+PUNA!CB10+GASA!AR10+GELA!CB10+ZEMG!CB10+TRON!CB10+BUMA!CB10+SARA!CB10+TSIR!CB10+DGNA!CB10+PANG!CB10+DPLA!CB10+SJKA!CB10+TRAG!AR10+MONA!I10+LUNT!CB10+TYSE!I10+PEMA!I10+KNLG!I10+RJNG!I10+WRMG!AR10+DUSM!I10+GYPG!I10+NGLM!AR10+SAMC!CB10+PHUA!CB10+TSMA!I10+GEDU!AR10+SAMA!CB10+TCHG!AR10+GMTU!CB10+LHAM!I10+PHLY!DI10 -> 0 | DP10: =PARO!J10+HAA!AS10+WANG!CC10+PUNA!CC10+GASA!AS10+GELA!CC10+ZEMG!CC10+TRON!CC10+BUMA!CC10+SARA!CC10+TSIR!CC10+DGNA!CC10+PANG!CC10+DPLA!CC10+SJKA!CC10+TRAG!AS10+MONA!J10+LUNT!CC10+TYSE!J10+PEMA!J10+KNLG!J10+RJNG!J10+WRMG!AS10+DUSM!J10+GYPG!J10+NGLM!AS10+SAMC!CC10+PHUA!CC10+TSMA!J10+GEDU!AS10+SAMA!CC10+TCHG!AS10+GMTU!CC10+LHAM!J10+PHLY!DJ10 -> 0 | DQ10: =PARO!K10+HAA!AT10+WANG!CD10+PUNA!CD10+GASA!AT10+GELA!CD10+ZEMG!CD10+TRON!CD10+BUMA!CD10+SARA!CD10+TSIR!CD10+DGNA!CD10+PANG!CD10+DPLA!CD10+SJKA!CD10+TRAG!AT10+MONA!K10+LUNT!CD10+TYSE!K10+PEMA!K10+KNLG!K10+RJNG!K10+WRMG!AT10+DUSM!K10+GYPG!K10+NGLM!AT10+SAMC!CD10+PHUA!CD10+TSMA!K10+GEDU!AT10+SAMA!CD10+TCHG!AT10+GMTU!CD10+LHAM!K10+PHLY!DK10 -> 0 | DR10: =PARO!L10+HAA!AU10+WANG!CE10+PUNA!CE10+GASA!AU10+GELA!CE10+ZEMG!CE10+TRON!CE10+BUMA!CE10+SARA!CE10+TSIR!CE10+DGNA!CE10+PANG!CE10+DPLA!CE10+SJKA!CE10+TRAG!AU10+MONA!L10+LUNT!CE10+TYSE!L10+PEMA!L10+KNLG!L10+RJNG!L10+WRMG!AU10+DUSM!L10+GYPG!L10+NGLM!AU10+SAMC!CE10+PHUA!CE10+TSMA!L10+GEDU!AU10+SAMA!CE10+TCHG!AU10+GMTU!CE10+LHAM!L10+PHLY!DL10 -> 2 | DS10: =PARO!M10+HAA!AV10+WANG!CF10+PUNA!CF10+GASA!AV10+GELA!CF10+ZEMG!CF10+TRON!CF10+BUMA!CF10+SARA!CF10+TSIR!CF10+DGNA!CF10+PANG!CF10+DPLA!CF10+SJKA!CF10+TRAG!AV10+MONA!M10+LUNT!CF10+TYSE!M10+PEMA!M10+KNLG!M10+RJNG!M10+WRMG!AV10+DUSM!M10+GYPG!M10+NGLM!AV10+SAMC!CF10+PHUA!CF10+TSMA!M10+GEDU!AV10+SAMA!CF10+TCHG!AV10+GMTU!CF10+LHAM!M10+PHLY!DM10 -> 0 | DT10: =PARO!N10+HAA!AW10+WANG!CG10+PUNA!CG10+GASA!AW10+GELA!CG10+ZEMG!CG10+TRON!CG10+BUMA!CG10+SARA!CG10+TSIR!CG10+DGNA!CG10+PANG!CG10+DPLA!CG10+SJKA!CG10+TRAG!AW10+MONA!N10+LUNT!CG10+TYSE!N10+PEMA!N10+KNLG!N10+RJNG!N10+WRMG!AW10+DUSM!N10+GYPG!N10+NGLM!AW10+SAMC!CG10+PHUA!CG10+TSMA!N10+GEDU!AW10+SAMA!CG10+TCHG!AW10+GMTU!CG10+LHAM!N10+PHLY!DN10 -> 0 | DU10: =PARO!O10+HAA!AX10+WANG!CH10+PUNA!CH10+GASA!AX10+GELA!CH10+ZEMG!CH10+TRON!CH10+BUMA!CH10+SARA!CH10+TSIR!CH10+DGNA!CH10+PANG!CH10+DPLA!CH10+SJKA!CH10+TRAG!AX10+MONA!O10+LUNT!CH10+TYSE!O10+PEMA!O10+KNLG!O10+RJNG!O10+WRMG!AX10+DUSM!O10+GYPG!O10+NGLM!AX10+SAMC!CH10+PHUA!CH10+TSMA!O10+GEDU!AX10+SAMA!CH10+TCHG!AX10+GMTU!CH10+LHAM!O10+PHLY!DO10 -> 0 | ... EV10: =PARO!AP10+HAA!BY10+WANG!DI10+PUNA!DI10+GASA!BY10+GELA!DI10+ZEMG!DI10+TRON!DI10+BUMA!DI10+SARA!DI10+TSIR!DI10+DGNA!DI10+PANG!DI10+DPLA!DI10+SJKA!DI10+TRAG!BY10+MONA!AP10+LUNT!DI10+TYSE!AP10+PEMA!AP10+KNLG!AP10+RJNG!AP10+WRMG!BY10+DUSM!AP10+GYPG!AP10+NGLM!BY10+SAMC!DI10+PHUA!DI10+TSMA!AP10+GEDU!BY10+SAMA!DI10+TCHG!BY10+GMTU!DI10+LHAM!AP10+PHLY!EP10 -> 18200 | EX10: =PARO!AR10+HAA!CA10+WANG!DK10+PUNA!DK10+GASA!CA10+GELA!DK10+ZEMG!DK10+TRON!DK10+BUMA!DK10+SARA!DK10+TSIR!DK10+DGNA!DK10+PANG!DK10+DPLA!DK10+SJKA!DK10+TRAG!CA10+MONA!AR10+LUNT!DK10+TYSE!AR10+PEMA!AR10+KNLG!AR10+RJNG!AR10+WRMG!CA10+DUSM!AR10+GYPG!AR10+NGLM!CA10+SAMC!DK10+PHUA!DK10+TSMA!AR10+GEDU!CA10+SAMA!DK10+TCHG!CA10+GMTU!DK10+LHAM!AR10+PHLY!ER10 -> 0 | EY10: =PARO!AS10+HAA!CB10+WANG!DL10+PUNA!DL10+GASA!CB10+GELA!DL10+ZEMG!DL10+TRON!DL10+BUMA!DL10+SARA!DL10+TSIR!DL10+DGNA!DL10+PANG!DL10+DPLA!DL10+SJKA!DL10+TRAG!CB10+MONA!AS10+LUNT!DL10+TYSE!AS10+PEMA!AS10+KNLG!AS10+RJNG!AS10+WRMG!CB10+DUSM!AS10+GYPG!AS10+NGLM!CB10+SAMC!DL10+PHUA!DL10+TSMA!AS10+GEDU!CB10+SAMA!DL10+TCHG!CB10+GMTU!DL10+LHAM!AS10+PHLY!ES10 -> 0 | EZ10: =PARO!AT10+HAA!CC10+WANG!DM10+PUNA!DM10+GASA!CC10+GELA!DM10+ZEMG!DM10+TRON!DM10+BUMA!DM10+SARA!DM10+TSIR!DM10+DGNA!DM10+PANG!DM10+DPLA!DM10+SJKA!DM10+TRAG!CC10+MONA!AT10+LUNT!DM10+TYSE!AT10+PEMA!AT10+KNLG!AT10+RJNG!AT10+WRMG!CC10+DUSM!AT10+GYPG!AT10+NGLM!CC10+SAMC!DM10+PHUA!DM10+TSMA!AT10+GEDU!CC10+SAMA!DM10+TCHG!CC10+GMTU!DM10+LHAM!AT10+PHLY!ET10 -> 0 | FA10: =PARO!AU10+HAA!CD10+WANG!DN10+PUNA!DN10+GASA!CD10+GELA!DN10+ZEMG!DN10+TRON!DN10+BUMA!DN10+SARA!DN10+TSIR!DN10+DGNA!DN10+PANG!DN10+DPLA!DN10+SJKA!DN10+TRAG!CD10+MONA!AU10+LUNT!DN10+TYSE!AU10+PEMA!AU10+KNLG!AU10+RJNG!AU10+WRMG!CD10+DUSM!AU10+GYPG!AU10+NGLM!CD10+SAMC!DN10+PHUA!DN10+TSMA!AU10+GEDU!CD10+SAMA!DN10+TCHG!CD10+GMTU!DN10+LHAM!AU10+PHLY!EU10 -> 0 | FB10: =PARO!AV10+HAA!CE10+WANG!DO10+PUNA!DO10+GASA!CE10+GELA!DO10+ZEMG!DO10+TRON!DO10+BUMA!DO10+SARA!DO10+TSIR!DO10+DGNA!DO10+PANG!DO10+DPLA!DO10+SJKA!DO10+TRAG!CE10+MONA!AV10+LUNT!DO10+TYSE!AV10+PEMA!AV10+KNLG!AV10+RJNG!AV10+WRMG!CE10+DUSM!AV10+GYPG!AV10+NGLM!CE10+SAMC!DO10+PHUA!DO10+TSMA!AV10+GEDU!CE10+SAMA!DO10+TCHG!CE10+GMTU!DO10+LHAM!AV10+PHLY!EV10 -> 2 | FC10: =PARO!AW10+HAA!CF10+WANG!DP10+PUNA!DP10+GASA!CF10+GELA!DP10+ZEMG!DP10+TRON!DP10+BUMA!DP10+SARA!DP10+TSIR!DP10+DGNA!DP10+PANG!DP10+DPLA!DP10+SJKA!DP10+TRAG!CF10+MONA!AW10+LUNT!DP10+TYSE!AW10+PEMA!AW10+KNLG!AW10+RJNG!AW10+WRMG!CF10+DUSM!AW10+GYPG!AW10+NGLM!CF10+SAMC!DP10+PHUA!DP10+TSMA!AW10+GEDU!CF10+SAMA!DP10+TCHG!CF10+GMTU!DP10+LHAM!AW10+PHLY!EW10 -> 0 | FD10: =PARO!AX10+HAA!CG10+WANG!DQ10+PUNA!DQ10+GASA!CG10+GELA!DQ10+ZEMG!DQ10+TRON!DQ10+BUMA!DQ10+SARA!DQ10+TSIR!DQ10+DGNA!DQ10+PANG!DQ10+DPLA!DQ10+SJKA!DQ10+TRAG!CG10+MONA!AX10+LUNT!DQ10+TYSE!AX10+PEMA!AX10+KNLG!AX10+RJNG!AX10+WRMG!CG10+DUSM!AX10+GYPG!AX10+NGLM!CG10+SAMC!DQ10+PHUA!DQ10+TSMA!AX10+GEDU!CG10+SAMA!DQ10+TCHG!CG10+GMTU!DQ10+LHAM!AX10+PHLY!EX10 -> 1 | FE10: =PARO!AY10+HAA!CH10+WANG!DR10+PUNA!DR10+GASA!CH10+GELA!DR10+ZEMG!DR10+TRON!DR10+BUMA!DR10+SARA!DR10+TSIR!DR10+DGNA!DR10+PANG!DR10+DPLA!DR10+SJKA!DR10+TRAG!CH10+MONA!AY10+LUNT!DR10+TYSE!AY10+PEMA!AY10+KNLG!AY10+RJNG!AY10+WRMG!CH10+DUSM!AY10+GYPG!AY10+NGLM!CH10+SAMC!DR10+PHUA!DR10+TSMA!AY10+GEDU!CH10+SAMA!DR10+TCHG!CH10+GMTU!DR10+LHAM!AY10+PHLY!EY10 -> 0 | ... GA10: =PARO!BU10+HAA!DD10+WANG!EN10+PUNA!EN10+GASA!DD10+GELA!EN10+ZEMG!EN10+TRON!EN10+BUMA!EN10+SARA!EN10+TSIR!EN10+DGNA!EN10+PANG!EN10+DPLA!EN10+SJKA!EN10+TRAG!DD10+MONA!BU10+LUNT!EN10+TYSE!BU10+PEMA!BU10+KNLG!BU10+RJNG!BU10+WRMG!DD10+DUSM!BU10+GYPG!BU10+NGLM!DD10+SAMC!EN10+PHUA!EN10+TSMA!BU10+GEDU!DD10+SAMA!EN10+TCHG!DD10+GMTU!EN10+LHAM!BU10+PHLY!FU10 -> 1 | GB10: =PARO!BV10+HAA!DE10+WANG!EO10+PUNA!EO10+GASA!DE10+GELA!EO10+ZEMG!EO10+TRON!EO10+BUMA!EO10+SARA!EO10+TSIR!EO10+DGNA!EO10+PANG!EO10+DPLA!EO10+SJKA!EO10+TRAG!DE10+MONA!BW10+LUNT!EO10+TYSE!BW10+PEMA!BW10+KNLG!BW10+RJNG!BV10+WRMG!DE10+DUSM!BW10+GYPG!BW10+NGLM!DE10+SAMC!EO10+PHUA!EO10+TSMA!BV10+GEDU!DE10+SAMA!EO10+TCHG!DE10+GMTU!EO10+LHAM!BV10+PHLY!FV10 -> 19 | GC10: =PARO!BW10+HAA!DF10+WANG!EP10+PUNA!EP10+GASA!DF10+GELA!EP10+ZEMG!EP10+TRON!EP10+BUMA!EP10+SARA!EP10+TSIR!EP10+DGNA!EP10+PANG!EP10+DPLA!EP10+SJKA!EP10+TRAG!DF10+MONA!BX10+LUNT!EP10+TYSE!BX10+PEMA!BX10+KNLG!BX10+RJNG!BW10+WRMG!DF10+DUSM!BX10+GYPG!BX10+NGLM!DF10+SAMC!EP10+PHUA!EP10+TSMA!BW10+GEDU!DF10+SAMA!EP10+TCHG!DF10+GMTU!EP10+LHAM!BW10+PHLY!FW10 -> 29640 | GD10: =PARO!BX10+HAA!DG10+WANG!EQ10+PUNA!EQ10+GASA!DG10+GELA!EQ10+ZEMG!EQ10+TRON!EQ10+BUMA!EQ10+SARA!EQ10+TSIR!EQ10+DGNA!EQ10+PANG!EQ10+DPLA!EQ10+SJKA!EQ10+TRAG!DG10+MONA!BY10+LUNT!EQ10+TYSE!BY10+PEMA!BY10+KNLG!BY10+RJNG!BX10+WRMG!DG10+DUSM!BY10+GYPG!BY10+NGLM!DG10+SAMC!EQ10+PHUA!EQ10+TSMA!BX10+GEDU!DG10+SAMA!EQ10+TCHG!DG10+GMTU!EQ10+LHAM!BX10+PHLY!FX10 -> 4940 | GE10: =PARO!BY10+HAA!DH10+WANG!ER10+PUNA!ER10+GASA!DH10+GELA!ER10+ZEMG!ER10+TRON!ER10+BUMA!ER10+SARA!ER10+TSIR!ER10+DGNA!ER10+PANG!ER10+DPLA!ER10+SJKA!ER10+TRAG!DH10+MONA!BZ10+LUNT!ER10+TYSE!BZ10+PEMA!BZ10+KNLG!BZ10+RJNG!BY10+WRMG!DH10+DUSM!BZ10+GYPG!BZ10+NGLM!DH10+SAMC!ER10+PHUA!ER10+TSMA!BY10+GEDU!DH10+SAMA!ER10+TCHG!DH10+GMTU!ER10+LHAM!BY10+PHLY!FY10 -> 24700 | GG10: =PARO!CA10+HAA!DJ10+WANG!ET10+PUNA!ET10+GASA!DJ10+GELA!ET10+ZEMG!ET10+TRON!ET10+BUMA!ET10+SARA!ET10+TSIR!ET10+DGNA!ET10+PANG!ET10+DPLA!ET10+SJKA!ET10+TRAG!DJ10+MONA!CB10+LUNT!ET10+TYSE!CB10+PEMA!CB10+KNLG!CB10+RJNG!CA10+WRMG!DJ10+DUSM!CB10+GYPG!CB10+NGLM!DJ10+SAMC!ET10+PHUA!ET10+TSMA!CA10+GEDU!DJ10+SAMA!ET10+TCHG!DJ10+GMTU!ET10+LHAM!CA10+PHLY!GA10 -> 0 | GH10: =PARO!CB10+HAA!DK10+WANG!EU10+PUNA!EU10+GASA!DK10+GELA!EU10+ZEMG!EU10+TRON!EU10+BUMA!EU10+SARA!EU10+TSIR!EU10+DGNA!EU10+PANG!EU10+DPLA!EU10+SJKA!EU10+TRAG!DK10+MONA!CC10+LUNT!EU10+TYSE!CC10+PEMA!CC10+KNLG!CC10+RJNG!CB10+WRMG!DK10+DUSM!CC10+GYPG!CC10+NGLM!DK10+SAMC!EU10+PHUA!EU10+TSMA!CB10+GEDU!DK10+SAMA!EU10+TCHG!DK10+GMTU!EU10+LHAM!CB10+PHLY!GB10 -> 0 | GI10: =PARO!CC10+HAA!DL10+WANG!EV10+PUNA!EV10+GASA!DL10+GELA!EV10+ZEMG!EV10+TRON!EV10+BUMA!EV10+SARA!EV10+TSIR!EV10+DGNA!EV10+PANG!EV10+DPLA!EV10+SJKA!EV10+TRAG!DL10+MONA!CD10+LUNT!EV10+TYSE!CD10+PEMA!CD10+KNLG!CD10+RJNG!CC10+WRMG!DL10+DUSM!CD10+GYPG!CD10+NGLM!DL10+SAMC!EV10+PHUA!EV10+TSMA!CC10+GEDU!DL10+SAMA!EV10+TCHG!DL10+GMTU!EV10+LHAM!CC10+PHLY!GC10 -> 1 | GJ10: =PARO!CD10+HAA!DM10+WANG!EW10+PUNA!EW10+GASA!DM10+GELA!EW10+ZEMG!EW10+TRON!EW10+BUMA!EW10+SARA!EW10+TSIR!EW10+DGNA!EW10+PANG!EW10+DPLA!EW10+SJKA!EW10+TRAG!DM10+MONA!CE10+LUNT!EW10+TYSE!CE10+PEMA!CE10+KNLG!CE10+RJNG!CD10+WRMG!DM10+DUSM!CE10+GYPG!CE10+NGLM!DM10+SAMC!EW10+PHUA!EW10+TSMA!CD10+GEDU!DM10+SAMA!EW10+TCHG!DM10+GMTU!EW10+LHAM!CD10+PHLY!GD10 -> 2 | GK10: =PARO!CE10+HAA!DN10+WANG!EX10+PUNA!EX10+GASA!DN10+GELA!EX10+ZEMG!EX10+TRON!EX10+BUMA!EX10+SARA!EX10+TSIR!EX10+DGNA!EX10+PANG!EX10+DPLA!EX10+SJKA!EX10+TRAG!DN10+MONA!CF10+LUNT!EX10+TYSE!CF10+PEMA!CF10+KNLG!CF10+RJNG!CE10+WRMG!DN10+DUSM!CF10+GYPG!CF10+NGLM!DN10+SAMC!EX10+PHUA!EX10+TSMA!CE10+GEDU!DN10+SAMA!EX10+TCHG!DN10+GMTU!EX10+LHAM!CE10+PHLY!GE10 -> 0 | GL10: =PARO!CF10+HAA!DO10+WANG!EY10+PUNA!EY10+GASA!DO10+GELA!EY10+ZEMG!EY10+TRON!EY10+BUMA!EY10+SARA!EY10+TSIR!EY10+DGNA!EY10+PANG!EY10+DPLA!EY10+SJKA!EY10+TRAG!DO10+MONA!CG10+LUNT!EY10+TYSE!CG10+PEMA!CG10+KNLG!CG10+RJNG!CF10+WRMG!DO10+DUSM!CG10+GYPG!CG10+NGLM!DO10+SAMC!EY10+PHUA!EY10+TSMA!CF10+GEDU!DO10+SAMA!EY10+TCHG!DO10+GMTU!EY10+LHAM!CF10+PHLY!GF10 -> 0 | GM10: =PARO!CG10+HAA!DP10+WANG!EZ10+PUNA!EZ10+GASA!DP10+GELA!EZ10+ZEMG!EZ10+TRON!EZ10+BUMA!EZ10+SARA!EZ10+TSIR!EZ10+DGNA!EZ10+PANG!EZ10+DPLA!EZ10+SJKA!EZ10+TRAG!DP10+MONA!CH10+LUNT!EZ10+TYSE!CH10+PEMA!CH10+KNLG!CH10+RJNG!CG10+WRMG!DP10+DUSM!CH10+GYPG!CH10+NGLM!DP10+SAMC!EZ10+PHUA!EZ10+TSMA!CG10+GEDU!DP10+SAMA!EZ10+TCHG!DP10+GMTU!EZ10+LHAM!CG10+PHLY!GG10 -> 0 | GN10: =PARO!CH10+HAA!DQ10+WANG!FA10+PUNA!FA10+GASA!DQ10+GELA!FA10+ZEMG!FA10+TRON!FA10+BUMA!FA10+SARA!FA10+TSIR!FA10+DGNA!FA10+PANG!FA10+DPLA!FA10+SJKA!FA10+TRAG!DQ10+MONA!CI10+LUNT!FA10+TYSE!CI10+PEMA!CI10+KNLG!CI10+RJNG!CH10+WRMG!DQ10+DUSM!CI10+GYPG!CI10+NGLM!DQ10+SAMC!FA10+PHUA!FA10+TSMA!CH10+GEDU!DQ10+SAMA!FA10+TCHG!DQ10+GMTU!FA10+LHAM!CH10+PHLY!GH10 -> 0 | ... HO10: =PARO!DI10+HAA!ER10+WANG!GB10+PUNA!GB10+GASA!ER10+GELA!GB10+ZEMG!GB10+TRON!GB10+BUMA!GB10+SARA!GB10+TSIR!GB10+DGNA!GB10+PANG!GB10+DPLA!GB10+SJKA!GB10+TRAG!ER10+MONA!DJ10+LUNT!GB10+TYSE!DJ10+PEMA!DJ10+KNLG!DJ10+RJNG!DI10+WRMG!ER10+DUSM!DJ10+GYPG!DJ10+NGLM!ER10+SAMC!GB10+PHUA!GB10+TSMA!DI10+GEDU!ER10+SAMA!GB10+TCHG!ER10+GMTU!GB10+LHAM!DI10+PHLY!HI10 -> 3900 | HQ10: =ES10+GB10+HL10 -> 36 | HR10: =C10*HQ10 -> 46800 | HS10: =D10*HQ10 -> 56160 | HT10: =E10*HQ10 -> 9360 | IN10: =AJ10+BT10+DC10+ES10+GB10+HL10 -> 73 | IO10: =AK10+BU10+DD10+ET10+GC10+HM10 -> 113880 | IP10: =AL10+BV10+DE10+EU10+GD10+HN10 -> 18980 | IQ10: =AM10+BW10+DF10+EV10+GE10+HO10 -> 94900
A11: 9 | B11: Black Tumeric | C11: 480 | D11: 576 | E11: =D11-C11 -> 96 | F11: 5% Discount on every 25 boxes / packets | H11: =PHLY!H11 -> 0 | I11: =PHLY!I11 -> 0 | J11: =PHLY!J11 -> 0 | K11: =PHLY!K11 -> 0 | L11: =PHLY!L11 -> 0 | M11: =PHLY!M11 -> 0 | N11: =PHLY!N11 -> 0 | O11: =PHLY!O11 -> 0 | ... AM11: =PHLY!AM11 -> 0 | AO11: =WANG!H11+PUNA!H11+GELA!H11+ZEMG!H11+TRON!H11+BUMA!H11+SARA!H11+TSIR!H11+DGNA!H11+PANG!H11+DPLA!H11+SJKA!H11+LUNT!H11+SAMC!H11+PHUA!H11+SAMA!H11+GMTU!H11+PHLY!AO11 -> 0 | AP11: =WANG!I11+PUNA!I11+GELA!I11+ZEMG!I11+TRON!I11+BUMA!I11+SARA!I11+TSIR!I11+DGNA!I11+PANG!I11+DPLA!I11+SJKA!I11+LUNT!I11+SAMC!I11+PHUA!I11+SAMA!I11+GMTU!I11+PHLY!AP11 -> 0 | AQ11: =WANG!J11+PUNA!J11+GELA!J11+ZEMG!J11+TRON!J11+BUMA!J11+SARA!J11+TSIR!J11+DGNA!J11+PANG!J11+DPLA!J11+SJKA!J11+LUNT!J11+SAMC!J11+PHUA!J11+SAMA!J11+GMTU!J11+PHLY!AQ11 -> 0 | AR11: =WANG!K11+PUNA!K11+GELA!K11+ZEMG!K11+TRON!K11+BUMA!K11+SARA!K11+TSIR!K11+DGNA!K11+PANG!K11+DPLA!K11+SJKA!K11+LUNT!K11+SAMC!K11+PHUA!K11+SAMA!K11+GMTU!K11+PHLY!AR11 -> 0 | AS11: =WANG!L11+PUNA!L11+GELA!L11+ZEMG!L11+TRON!L11+BUMA!L11+SARA!L11+TSIR!L11+DGNA!L11+PANG!L11+DPLA!L11+SJKA!L11+LUNT!L11+SAMC!L11+PHUA!L11+SAMA!L11+GMTU!L11+PHLY!AS11 -> 1 | AT11: =WANG!M11+PUNA!M11+GELA!M11+ZEMG!M11+TRON!M11+BUMA!M11+SARA!M11+TSIR!M11+DGNA!M11+PANG!M11+DPLA!M11+SJKA!M11+LUNT!M11+SAMC!M11+PHUA!M11+SAMA!M11+GMTU!M11+PHLY!AT11 -> 1 | AU11: =WANG!N11+PUNA!N11+GELA!N11+ZEMG!N11+TRON!N11+BUMA!N11+SARA!N11+TSIR!N11+DGNA!N11+PANG!N11+DPLA!N11+SJKA!N11+LUNT!N11+SAMC!N11+PHUA!N11+SAMA!N11+GMTU!N11+PHLY!AU11 -> 1 | AV11: =WANG!O11+PUNA!O11+GELA!O11+ZEMG!O11+TRON!O11+BUMA!O11+SARA!O11+TSIR!O11+DGNA!O11+PANG!O11+DPLA!O11+SJKA!O11+LUNT!O11+SAMC!O11+PHUA!O11+SAMA!O11+GMTU!O11+PHLY!AV11 -> 0 | ... BW11: =WANG!AP11+PUNA!AP11+GELA!AP11+ZEMG!AP11+TRON!AP11+BUMA!AP11+SARA!AP11+TSIR!AP11+DGNA!AP11+PANG!AP11+DPLA!AP11+SJKA!AP11+LUNT!AP11+SAMC!AP11+PHUA!AP11+SAMA!AP11+GMTU!AP11+PHLY!BW11 -> 12960 | BY11: =HAA!H11+WANG!AR11+PUNA!AR11+GASA!H11+GELA!AR11+ZEMG!AR11+TRON!AR11+BUMA!AR11+SARA!AR11+TSIR!AR11+DGNA!AR11+PANG!AR11+DPLA!AR11+SJKA!AR11+TRAG!H11+LUNT!AR11+WRMG!H11+NGLM!H11+SAMC!AR11+PHUA!AR11+GEDU!H11+SAMA!AR11+TCHG!H11+GMTU!AR11+PHLY!BY11 -> 0 | BZ11: =HAA!I11+WANG!AS11+PUNA!AS11+GASA!I11+GELA!AS11+ZEMG!AS11+TRON!AS11+BUMA!AS11+SARA!AS11+TSIR!AS11+DGNA!AS11+PANG!AS11+DPLA!AS11+SJKA!AS11+TRAG!I11+LUNT!AS11+WRMG!I11+NGLM!I11+SAMC!AS11+PHUA!AS11+GEDU!I11+SAMA!AS11+TCHG!I11+GMTU!AS11+PHLY!BZ11 -> 0 | CA11: =HAA!J11+WANG!AT11+PUNA!AT11+GASA!J11+GELA!AT11+ZEMG!AT11+TRON!AT11+BUMA!AT11+SARA!AT11+TSIR!AT11+DGNA!AT11+PANG!AT11+DPLA!AT11+SJKA!AT11+TRAG!J11+LUNT!AT11+WRMG!J11+NGLM!J11+SAMC!AT11+PHUA!AT11+GEDU!J11+SAMA!AT11+TCHG!J11+GMTU!AT11+PHLY!CA11 -> 0 | CB11: =HAA!K11+WANG!AU11+PUNA!AU11+GASA!K11+GELA!AU11+ZEMG!AU11+TRON!AU11+BUMA!AU11+SARA!AU11+TSIR!AU11+DGNA!AU11+PANG!AU11+DPLA!AU11+SJKA!AU11+TRAG!K11+LUNT!AU11+WRMG!K11+NGLM!K11+SAMC!AU11+PHUA!AU11+GEDU!K11+SAMA!AU11+TCHG!K11+GMTU!AU11+PHLY!CB11 -> 3 | CC11: =HAA!L11+WANG!AV11+PUNA!AV11+GASA!L11+GELA!AV11+ZEMG!AV11+TRON!AV11+BUMA!AV11+SARA!AV11+TSIR!AV11+DGNA!AV11+PANG!AV11+DPLA!AV11+SJKA!AV11+TRAG!L11+LUNT!AV11+WRMG!L11+NGLM!L11+SAMC!AV11+PHUA!AV11+GEDU!L11+SAMA!AV11+TCHG!L11+GMTU!AV11+PHLY!CC11 -> 0 | CD11: =HAA!M11+WANG!AW11+PUNA!AW11+GASA!M11+GELA!AW11+ZEMG!AW11+TRON!AW11+BUMA!AW11+SARA!AW11+TSIR!AW11+DGNA!AW11+PANG!AW11+DPLA!AW11+SJKA!AW11+TRAG!M11+LUNT!AW11+WRMG!M11+NGLM!M11+SAMC!AW11+PHUA!AW11+GEDU!M11+SAMA!AW11+TCHG!M11+GMTU!AW11+PHLY!CD11 -> 0 | CE11: =HAA!N11+WANG!AX11+PUNA!AX11+GASA!N11+GELA!AX11+ZEMG!AX11+TRON!AX11+BUMA!AX11+SARA!AX11+TSIR!AX11+DGNA!AX11+PANG!AX11+DPLA!AX11+SJKA!AX11+TRAG!N11+LUNT!AX11+WRMG!N11+NGLM!N11+SAMC!AX11+PHUA!AX11+GEDU!N11+SAMA!AX11+TCHG!N11+GMTU!AX11+PHLY!CE11 -> 1 | CF11: =HAA!O11+WANG!AY11+PUNA!AY11+GASA!O11+GELA!AY11+ZEMG!AY11+TRON!AY11+BUMA!AY11+SARA!AY11+TSIR!AY11+DGNA!AY11+PANG!AY11+DPLA!AY11+SJKA!AY11+TRAG!O11+LUNT!AY11+WRMG!O11+NGLM!O11+SAMC!AY11+PHUA!AY11+GEDU!O11+SAMA!AY11+TCHG!O11+GMTU!AY11+PHLY!CF11 -> 1 | ... DF11: =HAA!AO11+WANG!BY11+PUNA!BY11+GASA!AO11+GELA!BY11+ZEMG!BY11+TRON!BY11+BUMA!BY11+SARA!BY11+TSIR!BY11+DGNA!BY11+PANG!BY11+DPLA!BY11+SJKA!BY11+TRAG!AO11+LUNT!BY11+WRMG!AO11+NGLM!AO11+SAMC!BY11+PHUA!BY11+GEDU!AO11+SAMA!BY11+TCHG!AO11+GMTU!BY11+PHLY!DF11 -> 12480 | DG11: =AJ11+BT11+DC11 -> 53 | DH11: =C11*DG11 -> 25440 | DI11: =D11*DG11 -> 30528 | DJ11: =E11*DG11 -> 5088 | DK11: 24 | DL11: =DG11*DK11 -> 1272 | DN11: =PARO!H11+HAA!AQ11+WANG!CA11+PUNA!CA11+GASA!AQ11+GELA!CA11+ZEMG!CA11+TRON!CA11+BUMA!CA11+SARA!CA11+TSIR!CA11+DGNA!CA11+PANG!CA11+DPLA!CA11+SJKA!CA11+TRAG!AQ11+MONA!H11+LUNT!CA11+TYSE!H11+PEMA!H11+KNLG!H11+RJNG!H11+WRMG!AQ11+DUSM!H11+GYPG!H11+NGLM!AQ11+SAMC!CA11+PHUA!CA11+TSMA!H11+GEDU!AQ11+SAMA!CA11+TCHG!AQ11+GMTU!CA11+LHAM!H11+PHLY!DH11 -> 0 | DO11: =PARO!I11+HAA!AR11+WANG!CB11+PUNA!CB11+GASA!AR11+GELA!CB11+ZEMG!CB11+TRON!CB11+BUMA!CB11+SARA!CB11+TSIR!CB11+DGNA!CB11+PANG!CB11+DPLA!CB11+SJKA!CB11+TRAG!AR11+MONA!I11+LUNT!CB11+TYSE!I11+PEMA!I11+KNLG!I11+RJNG!I11+WRMG!AR11+DUSM!I11+GYPG!I11+NGLM!AR11+SAMC!CB11+PHUA!CB11+TSMA!I11+GEDU!AR11+SAMA!CB11+TCHG!AR11+GMTU!CB11+LHAM!I11+PHLY!DI11 -> 0 | DP11: =PARO!J11+HAA!AS11+WANG!CC11+PUNA!CC11+GASA!AS11+GELA!CC11+ZEMG!CC11+TRON!CC11+BUMA!CC11+SARA!CC11+TSIR!CC11+DGNA!CC11+PANG!CC11+DPLA!CC11+SJKA!CC11+TRAG!AS11+MONA!J11+LUNT!CC11+TYSE!J11+PEMA!J11+KNLG!J11+RJNG!J11+WRMG!AS11+DUSM!J11+GYPG!J11+NGLM!AS11+SAMC!CC11+PHUA!CC11+TSMA!J11+GEDU!AS11+SAMA!CC11+TCHG!AS11+GMTU!CC11+LHAM!J11+PHLY!DJ11 -> 0 | DQ11: =PARO!K11+HAA!AT11+WANG!CD11+PUNA!CD11+GASA!AT11+GELA!CD11+ZEMG!CD11+TRON!CD11+BUMA!CD11+SARA!CD11+TSIR!CD11+DGNA!CD11+PANG!CD11+DPLA!CD11+SJKA!CD11+TRAG!AT11+MONA!K11+LUNT!CD11+TYSE!K11+PEMA!K11+KNLG!K11+RJNG!K11+WRMG!AT11+DUSM!K11+GYPG!K11+NGLM!AT11+SAMC!CD11+PHUA!CD11+TSMA!K11+GEDU!AT11+SAMA!CD11+TCHG!AT11+GMTU!CD11+LHAM!K11+PHLY!DK11 -> 0 | DR11: =PARO!L11+HAA!AU11+WANG!CE11+PUNA!CE11+GASA!AU11+GELA!CE11+ZEMG!CE11+TRON!CE11+BUMA!CE11+SARA!CE11+TSIR!CE11+DGNA!CE11+PANG!CE11+DPLA!CE11+SJKA!CE11+TRAG!AU11+MONA!L11+LUNT!CE11+TYSE!L11+PEMA!L11+KNLG!L11+RJNG!L11+WRMG!AU11+DUSM!L11+GYPG!L11+NGLM!AU11+SAMC!CE11+PHUA!CE11+TSMA!L11+GEDU!AU11+SAMA!CE11+TCHG!AU11+GMTU!CE11+LHAM!L11+PHLY!DL11 -> 0 | DS11: =PARO!M11+HAA!AV11+WANG!CF11+PUNA!CF11+GASA!AV11+GELA!CF11+ZEMG!CF11+TRON!CF11+BUMA!CF11+SARA!CF11+TSIR!CF11+DGNA!CF11+PANG!CF11+DPLA!CF11+SJKA!CF11+TRAG!AV11+MONA!M11+LUNT!CF11+TYSE!M11+PEMA!M11+KNLG!M11+RJNG!M11+WRMG!AV11+DUSM!M11+GYPG!M11+NGLM!AV11+SAMC!CF11+PHUA!CF11+TSMA!M11+GEDU!AV11+SAMA!CF11+TCHG!AV11+GMTU!CF11+LHAM!M11+PHLY!DM11 -> 1 | DT11: =PARO!N11+HAA!AW11+WANG!CG11+PUNA!CG11+GASA!AW11+GELA!CG11+ZEMG!CG11+TRON!CG11+BUMA!CG11+SARA!CG11+TSIR!CG11+DGNA!CG11+PANG!CG11+DPLA!CG11+SJKA!CG11+TRAG!AW11+MONA!N11+LUNT!CG11+TYSE!N11+PEMA!N11+KNLG!N11+RJNG!N11+WRMG!AW11+DUSM!N11+GYPG!N11+NGLM!AW11+SAMC!CG11+PHUA!CG11+TSMA!N11+GEDU!AW11+SAMA!CG11+TCHG!AW11+GMTU!CG11+LHAM!N11+PHLY!DN11 -> 0 | DU11: =PARO!O11+HAA!AX11+WANG!CH11+PUNA!CH11+GASA!AX11+GELA!CH11+ZEMG!CH11+TRON!CH11+BUMA!CH11+SARA!CH11+TSIR!CH11+DGNA!CH11+PANG!CH11+DPLA!CH11+SJKA!CH11+TRAG!AX11+MONA!O11+LUNT!CH11+TYSE!O11+PEMA!O11+KNLG!O11+RJNG!O11+WRMG!AX11+DUSM!O11+GYPG!O11+NGLM!AX11+SAMC!CH11+PHUA!CH11+TSMA!O11+GEDU!AX11+SAMA!CH11+TCHG!AX11+GMTU!CH11+LHAM!O11+PHLY!DO11 -> 1 | ... EV11: =PARO!AP11+HAA!BY11+WANG!DI11+PUNA!DI11+GASA!BY11+GELA!DI11+ZEMG!DI11+TRON!DI11+BUMA!DI11+SARA!DI11+TSIR!DI11+DGNA!DI11+PANG!DI11+DPLA!DI11+SJKA!DI11+TRAG!BY11+MONA!AP11+LUNT!DI11+TYSE!AP11+PEMA!AP11+KNLG!AP11+RJNG!AP11+WRMG!BY11+DUSM!AP11+GYPG!AP11+NGLM!BY11+SAMC!DI11+PHUA!DI11+TSMA!AP11+GEDU!BY11+SAMA!DI11+TCHG!BY11+GMTU!DI11+LHAM!AP11+PHLY!EP11 -> 3360 | EX11: =PARO!AR11+HAA!CA11+WANG!DK11+PUNA!DK11+GASA!CA11+GELA!DK11+ZEMG!DK11+TRON!DK11+BUMA!DK11+SARA!DK11+TSIR!DK11+DGNA!DK11+PANG!DK11+DPLA!DK11+SJKA!DK11+TRAG!CA11+MONA!AR11+LUNT!DK11+TYSE!AR11+PEMA!AR11+KNLG!AR11+RJNG!AR11+WRMG!CA11+DUSM!AR11+GYPG!AR11+NGLM!CA11+SAMC!DK11+PHUA!DK11+TSMA!AR11+GEDU!CA11+SAMA!DK11+TCHG!CA11+GMTU!DK11+LHAM!AR11+PHLY!ER11 -> 0 | EY11: =PARO!AS11+HAA!CB11+WANG!DL11+PUNA!DL11+GASA!CB11+GELA!DL11+ZEMG!DL11+TRON!DL11+BUMA!DL11+SARA!DL11+TSIR!DL11+DGNA!DL11+PANG!DL11+DPLA!DL11+SJKA!DL11+TRAG!CB11+MONA!AS11+LUNT!DL11+TYSE!AS11+PEMA!AS11+KNLG!AS11+RJNG!AS11+WRMG!CB11+DUSM!AS11+GYPG!AS11+NGLM!CB11+SAMC!DL11+PHUA!DL11+TSMA!AS11+GEDU!CB11+SAMA!DL11+TCHG!CB11+GMTU!DL11+LHAM!AS11+PHLY!ES11 -> 0 | EZ11: =PARO!AT11+HAA!CC11+WANG!DM11+PUNA!DM11+GASA!CC11+GELA!DM11+ZEMG!DM11+TRON!DM11+BUMA!DM11+SARA!DM11+TSIR!DM11+DGNA!DM11+PANG!DM11+DPLA!DM11+SJKA!DM11+TRAG!CC11+MONA!AT11+LUNT!DM11+TYSE!AT11+PEMA!AT11+KNLG!AT11+RJNG!AT11+WRMG!CC11+DUSM!AT11+GYPG!AT11+NGLM!CC11+SAMC!DM11+PHUA!DM11+TSMA!AT11+GEDU!CC11+SAMA!DM11+TCHG!CC11+GMTU!DM11+LHAM!AT11+PHLY!ET11 -> 0 | FA11: =PARO!AU11+HAA!CD11+WANG!DN11+PUNA!DN11+GASA!CD11+GELA!DN11+ZEMG!DN11+TRON!DN11+BUMA!DN11+SARA!DN11+TSIR!DN11+DGNA!DN11+PANG!DN11+DPLA!DN11+SJKA!DN11+TRAG!CD11+MONA!AU11+LUNT!DN11+TYSE!AU11+PEMA!AU11+KNLG!AU11+RJNG!AU11+WRMG!CD11+DUSM!AU11+GYPG!AU11+NGLM!CD11+SAMC!DN11+PHUA!DN11+TSMA!AU11+GEDU!CD11+SAMA!DN11+TCHG!CD11+GMTU!DN11+LHAM!AU11+PHLY!EU11 -> 0 | FB11: =PARO!AV11+HAA!CE11+WANG!DO11+PUNA!DO11+GASA!CE11+GELA!DO11+ZEMG!DO11+TRON!DO11+BUMA!DO11+SARA!DO11+TSIR!DO11+DGNA!DO11+PANG!DO11+DPLA!DO11+SJKA!DO11+TRAG!CE11+MONA!AV11+LUNT!DO11+TYSE!AV11+PEMA!AV11+KNLG!AV11+RJNG!AV11+WRMG!CE11+DUSM!AV11+GYPG!AV11+NGLM!CE11+SAMC!DO11+PHUA!DO11+TSMA!AV11+GEDU!CE11+SAMA!DO11+TCHG!CE11+GMTU!DO11+LHAM!AV11+PHLY!EV11 -> 1 | FC11: =PARO!AW11+HAA!CF11+WANG!DP11+PUNA!DP11+GASA!CF11+GELA!DP11+ZEMG!DP11+TRON!DP11+BUMA!DP11+SARA!DP11+TSIR!DP11+DGNA!DP11+PANG!DP11+DPLA!DP11+SJKA!DP11+TRAG!CF11+MONA!AW11+LUNT!DP11+TYSE!AW11+PEMA!AW11+KNLG!AW11+RJNG!AW11+WRMG!CF11+DUSM!AW11+GYPG!AW11+NGLM!CF11+SAMC!DP11+PHUA!DP11+TSMA!AW11+GEDU!CF11+SAMA!DP11+TCHG!CF11+GMTU!DP11+LHAM!AW11+PHLY!EW11 -> 0 | FD11: =PARO!AX11+HAA!CG11+WANG!DQ11+PUNA!DQ11+GASA!CG11+GELA!DQ11+ZEMG!DQ11+TRON!DQ11+BUMA!DQ11+SARA!DQ11+TSIR!DQ11+DGNA!DQ11+PANG!DQ11+DPLA!DQ11+SJKA!DQ11+TRAG!CG11+MONA!AX11+LUNT!DQ11+TYSE!AX11+PEMA!AX11+KNLG!AX11+RJNG!AX11+WRMG!CG11+DUSM!AX11+GYPG!AX11+NGLM!CG11+SAMC!DQ11+PHUA!DQ11+TSMA!AX11+GEDU!CG11+SAMA!DQ11+TCHG!CG11+GMTU!DQ11+LHAM!AX11+PHLY!EX11 -> 1 | FE11: =PARO!AY11+HAA!CH11+WANG!DR11+PUNA!DR11+GASA!CH11+GELA!DR11+ZEMG!DR11+TRON!DR11+BUMA!DR11+SARA!DR11+TSIR!DR11+DGNA!DR11+PANG!DR11+DPLA!DR11+SJKA!DR11+TRAG!CH11+MONA!AY11+LUNT!DR11+TYSE!AY11+PEMA!AY11+KNLG!AY11+RJNG!AY11+WRMG!CH11+DUSM!AY11+GYPG!AY11+NGLM!CH11+SAMC!DR11+PHUA!DR11+TSMA!AY11+GEDU!CH11+SAMA!DR11+TCHG!CH11+GMTU!DR11+LHAM!AY11+PHLY!EY11 -> 0 | ... GA11: =PARO!BU11+HAA!DD11+WANG!EN11+PUNA!EN11+GASA!DD11+GELA!EN11+ZEMG!EN11+TRON!EN11+BUMA!EN11+SARA!EN11+TSIR!EN11+DGNA!EN11+PANG!EN11+DPLA!EN11+SJKA!EN11+TRAG!DD11+MONA!BU11+LUNT!EN11+TYSE!BU11+PEMA!BU11+KNLG!BU11+RJNG!BU11+WRMG!DD11+DUSM!BU11+GYPG!BU11+NGLM!DD11+SAMC!EN11+PHUA!EN11+TSMA!BU11+GEDU!DD11+SAMA!EN11+TCHG!DD11+GMTU!EN11+LHAM!BU11+PHLY!FU11 -> 0 | GB11: =PARO!BV11+HAA!DE11+WANG!EO11+PUNA!EO11+GASA!DE11+GELA!EO11+ZEMG!EO11+TRON!EO11+BUMA!EO11+SARA!EO11+TSIR!EO11+DGNA!EO11+PANG!EO11+DPLA!EO11+SJKA!EO11+TRAG!DE11+MONA!BW11+LUNT!EO11+TYSE!BW11+PEMA!BW11+KNLG!BW11+RJNG!BV11+WRMG!DE11+DUSM!BW11+GYPG!BW11+NGLM!DE11+SAMC!EO11+PHUA!EO11+TSMA!BV11+GEDU!DE11+SAMA!EO11+TCHG!DE11+GMTU!EO11+LHAM!BV11+PHLY!FV11 -> 13 | GC11: =PARO!BW11+HAA!DF11+WANG!EP11+PUNA!EP11+GASA!DF11+GELA!EP11+ZEMG!EP11+TRON!EP11+BUMA!EP11+SARA!EP11+TSIR!EP11+DGNA!EP11+PANG!EP11+DPLA!EP11+SJKA!EP11+TRAG!DF11+MONA!BX11+LUNT!EP11+TYSE!BX11+PEMA!BX11+KNLG!BX11+RJNG!BW11+WRMG!DF11+DUSM!BX11+GYPG!BX11+NGLM!DF11+SAMC!EP11+PHUA!EP11+TSMA!BW11+GEDU!DF11+SAMA!EP11+TCHG!DF11+GMTU!EP11+LHAM!BW11+PHLY!FW11 -> 7488 | GD11: =PARO!BX11+HAA!DG11+WANG!EQ11+PUNA!EQ11+GASA!DG11+GELA!EQ11+ZEMG!EQ11+TRON!EQ11+BUMA!EQ11+SARA!EQ11+TSIR!EQ11+DGNA!EQ11+PANG!EQ11+DPLA!EQ11+SJKA!EQ11+TRAG!DG11+MONA!BY11+LUNT!EQ11+TYSE!BY11+PEMA!BY11+KNLG!BY11+RJNG!BX11+WRMG!DG11+DUSM!BY11+GYPG!BY11+NGLM!DG11+SAMC!EQ11+PHUA!EQ11+TSMA!BX11+GEDU!DG11+SAMA!EQ11+TCHG!DG11+GMTU!EQ11+LHAM!BX11+PHLY!FX11 -> 1248 | GE11: =PARO!BY11+HAA!DH11+WANG!ER11+PUNA!ER11+GASA!DH11+GELA!ER11+ZEMG!ER11+TRON!ER11+BUMA!ER11+SARA!ER11+TSIR!ER11+DGNA!ER11+PANG!ER11+DPLA!ER11+SJKA!ER11+TRAG!DH11+MONA!BZ11+LUNT!ER11+TYSE!BZ11+PEMA!BZ11+KNLG!BZ11+RJNG!BY11+WRMG!DH11+DUSM!BZ11+GYPG!BZ11+NGLM!DH11+SAMC!ER11+PHUA!ER11+TSMA!BY11+GEDU!DH11+SAMA!ER11+TCHG!DH11+GMTU!ER11+LHAM!BY11+PHLY!FY11 -> 6240 | GG11: =PARO!CA11+HAA!DJ11+WANG!ET11+PUNA!ET11+GASA!DJ11+GELA!ET11+ZEMG!ET11+TRON!ET11+BUMA!ET11+SARA!ET11+TSIR!ET11+DGNA!ET11+PANG!ET11+DPLA!ET11+SJKA!ET11+TRAG!DJ11+MONA!CB11+LUNT!ET11+TYSE!CB11+PEMA!CB11+KNLG!CB11+RJNG!CA11+WRMG!DJ11+DUSM!CB11+GYPG!CB11+NGLM!DJ11+SAMC!ET11+PHUA!ET11+TSMA!CA11+GEDU!DJ11+SAMA!ET11+TCHG!DJ11+GMTU!ET11+LHAM!CA11+PHLY!GA11 -> 1 | GH11: =PARO!CB11+HAA!DK11+WANG!EU11+PUNA!EU11+GASA!DK11+GELA!EU11+ZEMG!EU11+TRON!EU11+BUMA!EU11+SARA!EU11+TSIR!EU11+DGNA!EU11+PANG!EU11+DPLA!EU11+SJKA!EU11+TRAG!DK11+MONA!CC11+LUNT!EU11+TYSE!CC11+PEMA!CC11+KNLG!CC11+RJNG!CB11+WRMG!DK11+DUSM!CC11+GYPG!CC11+NGLM!DK11+SAMC!EU11+PHUA!EU11+TSMA!CB11+GEDU!DK11+SAMA!EU11+TCHG!DK11+GMTU!EU11+LHAM!CB11+PHLY!GB11 -> 0 | GI11: =PARO!CC11+HAA!DL11+WANG!EV11+PUNA!EV11+GASA!DL11+GELA!EV11+ZEMG!EV11+TRON!EV11+BUMA!EV11+SARA!EV11+TSIR!EV11+DGNA!EV11+PANG!EV11+DPLA!EV11+SJKA!EV11+TRAG!DL11+MONA!CD11+LUNT!EV11+TYSE!CD11+PEMA!CD11+KNLG!CD11+RJNG!CC11+WRMG!DL11+DUSM!CD11+GYPG!CD11+NGLM!DL11+SAMC!EV11+PHUA!EV11+TSMA!CC11+GEDU!DL11+SAMA!EV11+TCHG!DL11+GMTU!EV11+LHAM!CC11+PHLY!GC11 -> 1 | GJ11: =PARO!CD11+HAA!DM11+WANG!EW11+PUNA!EW11+GASA!DM11+GELA!EW11+ZEMG!EW11+TRON!EW11+BUMA!EW11+SARA!EW11+TSIR!EW11+DGNA!EW11+PANG!EW11+DPLA!EW11+SJKA!EW11+TRAG!DM11+MONA!CE11+LUNT!EW11+TYSE!CE11+PEMA!CE11+KNLG!CE11+RJNG!CD11+WRMG!DM11+DUSM!CE11+GYPG!CE11+NGLM!DM11+SAMC!EW11+PHUA!EW11+TSMA!CD11+GEDU!DM11+SAMA!EW11+TCHG!DM11+GMTU!EW11+LHAM!CD11+PHLY!GD11 -> 2 | GK11: =PARO!CE11+HAA!DN11+WANG!EX11+PUNA!EX11+GASA!DN11+GELA!EX11+ZEMG!EX11+TRON!EX11+BUMA!EX11+SARA!EX11+TSIR!EX11+DGNA!EX11+PANG!EX11+DPLA!EX11+SJKA!EX11+TRAG!DN11+MONA!CF11+LUNT!EX11+TYSE!CF11+PEMA!CF11+KNLG!CF11+RJNG!CE11+WRMG!DN11+DUSM!CF11+GYPG!CF11+NGLM!DN11+SAMC!EX11+PHUA!EX11+TSMA!CE11+GEDU!DN11+SAMA!EX11+TCHG!DN11+GMTU!EX11+LHAM!CE11+PHLY!GE11 -> 0 | GL11: =PARO!CF11+HAA!DO11+WANG!EY11+PUNA!EY11+GASA!DO11+GELA!EY11+ZEMG!EY11+TRON!EY11+BUMA!EY11+SARA!EY11+TSIR!EY11+DGNA!EY11+PANG!EY11+DPLA!EY11+SJKA!EY11+TRAG!DO11+MONA!CG11+LUNT!EY11+TYSE!CG11+PEMA!CG11+KNLG!CG11+RJNG!CF11+WRMG!DO11+DUSM!CG11+GYPG!CG11+NGLM!DO11+SAMC!EY11+PHUA!EY11+TSMA!CF11+GEDU!DO11+SAMA!EY11+TCHG!DO11+GMTU!EY11+LHAM!CF11+PHLY!GF11 -> 0 | GM11: =PARO!CG11+HAA!DP11+WANG!EZ11+PUNA!EZ11+GASA!DP11+GELA!EZ11+ZEMG!EZ11+TRON!EZ11+BUMA!EZ11+SARA!EZ11+TSIR!EZ11+DGNA!EZ11+PANG!EZ11+DPLA!EZ11+SJKA!EZ11+TRAG!DP11+MONA!CH11+LUNT!EZ11+TYSE!CH11+PEMA!CH11+KNLG!CH11+RJNG!CG11+WRMG!DP11+DUSM!CH11+GYPG!CH11+NGLM!DP11+SAMC!EZ11+PHUA!EZ11+TSMA!CG11+GEDU!DP11+SAMA!EZ11+TCHG!DP11+GMTU!EZ11+LHAM!CG11+PHLY!GG11 -> 0 | GN11: =PARO!CH11+HAA!DQ11+WANG!FA11+PUNA!FA11+GASA!DQ11+GELA!FA11+ZEMG!FA11+TRON!FA11+BUMA!FA11+SARA!FA11+TSIR!FA11+DGNA!FA11+PANG!FA11+DPLA!FA11+SJKA!FA11+TRAG!DQ11+MONA!CI11+LUNT!FA11+TYSE!CI11+PEMA!CI11+KNLG!CI11+RJNG!CH11+WRMG!DQ11+DUSM!CI11+GYPG!CI11+NGLM!DQ11+SAMC!FA11+PHUA!FA11+TSMA!CH11+GEDU!DQ11+SAMA!FA11+TCHG!DQ11+GMTU!FA11+LHAM!CH11+PHLY!GH11 -> 0 | ... HO11: =PARO!DI11+HAA!ER11+WANG!GB11+PUNA!GB11+GASA!ER11+GELA!GB11+ZEMG!GB11+TRON!GB11+BUMA!GB11+SARA!GB11+TSIR!GB11+DGNA!GB11+PANG!GB11+DPLA!GB11+SJKA!GB11+TRAG!ER11+MONA!DJ11+LUNT!GB11+TYSE!DJ11+PEMA!DJ11+KNLG!DJ11+RJNG!DI11+WRMG!ER11+DUSM!DJ11+GYPG!DJ11+NGLM!ER11+SAMC!GB11+PHUA!GB11+TSMA!DI11+GEDU!ER11+SAMA!GB11+TCHG!ER11+GMTU!GB11+LHAM!DI11+PHLY!HI11 -> 2880 | HQ11: =ES11+GB11+HL11 -> 26 | HR11: =C11*HQ11 -> 12480 | HS11: =D11*HQ11 -> 14976 | HT11: =E11*HQ11 -> 2496 | HU11: 24 | HV11: =HQ11*HU11 -> 624 | IN11: =AJ11+BT11+DC11+ES11+GB11+HL11 -> 79 | IO11: =AK11+BU11+DD11+ET11+GC11+HM11 -> 45504 | IP11: =AL11+BV11+DE11+EU11+GD11+HN11 -> 7584 | IQ11: =AM11+BW11+DF11+EV11+GE11+HO11 -> 37920
A12: 10 | B12: Ginseng Honey | C12: 650 | D12: 780 | E12: =D12-C12 -> 130 | F12: No Discount | H12: =PHLY!H12 -> 0 | I12: =PHLY!I12 -> 0 | J12: =PHLY!J12 -> 0 | K12: =PHLY!K12 -> 0 | L12: =PHLY!L12 -> 0 | M12: =PHLY!M12 -> 0 | N12: =PHLY!N12 -> 0 | O12: =PHLY!O12 -> 0 | ... AM12: =PHLY!AM12 -> 0 | AO12: =WANG!H12+PUNA!H12+GELA!H12+ZEMG!H12+TRON!H12+BUMA!H12+SARA!H12+TSIR!H12+DGNA!H12+PANG!H12+DPLA!H12+SJKA!H12+LUNT!H12+SAMC!H12+PHUA!H12+SAMA!H12+GMTU!H12+PHLY!AO12 -> 0 | AP12: =WANG!I12+PUNA!I12+GELA!I12+ZEMG!I12+TRON!I12+BUMA!I12+SARA!I12+TSIR!I12+DGNA!I12+PANG!I12+DPLA!I12+SJKA!I12+LUNT!I12+SAMC!I12+PHUA!I12+SAMA!I12+GMTU!I12+PHLY!AP12 -> 0 | AQ12: =WANG!J12+PUNA!J12+GELA!J12+ZEMG!J12+TRON!J12+BUMA!J12+SARA!J12+TSIR!J12+DGNA!J12+PANG!J12+DPLA!J12+SJKA!J12+LUNT!J12+SAMC!J12+PHUA!J12+SAMA!J12+GMTU!J12+PHLY!AQ12 -> 0 | AR12: =WANG!K12+PUNA!K12+GELA!K12+ZEMG!K12+TRON!K12+BUMA!K12+SARA!K12+TSIR!K12+DGNA!K12+PANG!K12+DPLA!K12+SJKA!K12+LUNT!K12+SAMC!K12+PHUA!K12+SAMA!K12+GMTU!K12+PHLY!AR12 -> 0 | AS12: =WANG!L12+PUNA!L12+GELA!L12+ZEMG!L12+TRON!L12+BUMA!L12+SARA!L12+TSIR!L12+DGNA!L12+PANG!L12+DPLA!L12+SJKA!L12+LUNT!L12+SAMC!L12+PHUA!L12+SAMA!L12+GMTU!L12+PHLY!AS12 -> 0 | AT12: =WANG!M12+PUNA!M12+GELA!M12+ZEMG!M12+TRON!M12+BUMA!M12+SARA!M12+TSIR!M12+DGNA!M12+PANG!M12+DPLA!M12+SJKA!M12+LUNT!M12+SAMC!M12+PHUA!M12+SAMA!M12+GMTU!M12+PHLY!AT12 -> 0 | AU12: =WANG!N12+PUNA!N12+GELA!N12+ZEMG!N12+TRON!N12+BUMA!N12+SARA!N12+TSIR!N12+DGNA!N12+PANG!N12+DPLA!N12+SJKA!N12+LUNT!N12+SAMC!N12+PHUA!N12+SAMA!N12+GMTU!N12+PHLY!AU12 -> 0 | AV12: =WANG!O12+PUNA!O12+GELA!O12+ZEMG!O12+TRON!O12+BUMA!O12+SARA!O12+TSIR!O12+DGNA!O12+PANG!O12+DPLA!O12+SJKA!O12+LUNT!O12+SAMC!O12+PHUA!O12+SAMA!O12+GMTU!O12+PHLY!AV12 -> 0 | ... BW12: =WANG!AP12+PUNA!AP12+GELA!AP12+ZEMG!AP12+TRON!AP12+BUMA!AP12+SARA!AP12+TSIR!AP12+DGNA!AP12+PANG!AP12+DPLA!AP12+SJKA!AP12+LUNT!AP12+SAMC!AP12+PHUA!AP12+SAMA!AP12+GMTU!AP12+PHLY!BW12 -> 0 | BY12: =HAA!H12+WANG!AR12+PUNA!AR12+GASA!H12+GELA!AR12+ZEMG!AR12+TRON!AR12+BUMA!AR12+SARA!AR12+TSIR!AR12+DGNA!AR12+PANG!AR12+DPLA!AR12+SJKA!AR12+TRAG!H12+LUNT!AR12+WRMG!H12+NGLM!H12+SAMC!AR12+PHUA!AR12+GEDU!H12+SAMA!AR12+TCHG!H12+GMTU!AR12+PHLY!BY12 -> 0 | BZ12: =HAA!I12+WANG!AS12+PUNA!AS12+GASA!I12+GELA!AS12+ZEMG!AS12+TRON!AS12+BUMA!AS12+SARA!AS12+TSIR!AS12+DGNA!AS12+PANG!AS12+DPLA!AS12+SJKA!AS12+TRAG!I12+LUNT!AS12+WRMG!I12+NGLM!I12+SAMC!AS12+PHUA!AS12+GEDU!I12+SAMA!AS12+TCHG!I12+GMTU!AS12+PHLY!BZ12 -> 0 | CA12: =HAA!J12+WANG!AT12+PUNA!AT12+GASA!J12+GELA!AT12+ZEMG!AT12+TRON!AT12+BUMA!AT12+SARA!AT12+TSIR!AT12+DGNA!AT12+PANG!AT12+DPLA!AT12+SJKA!AT12+TRAG!J12+LUNT!AT12+WRMG!J12+NGLM!J12+SAMC!AT12+PHUA!AT12+GEDU!J12+SAMA!AT12+TCHG!J12+GMTU!AT12+PHLY!CA12 -> 0 | CB12: =HAA!K12+WANG!AU12+PUNA!AU12+GASA!K12+GELA!AU12+ZEMG!AU12+TRON!AU12+BUMA!AU12+SARA!AU12+TSIR!AU12+DGNA!AU12+PANG!AU12+DPLA!AU12+SJKA!AU12+TRAG!K12+LUNT!AU12+WRMG!K12+NGLM!K12+SAMC!AU12+PHUA!AU12+GEDU!K12+SAMA!AU12+TCHG!K12+GMTU!AU12+PHLY!CB12 -> 0 | CC12: =HAA!L12+WANG!AV12+PUNA!AV12+GASA!L12+GELA!AV12+ZEMG!AV12+TRON!AV12+BUMA!AV12+SARA!AV12+TSIR!AV12+DGNA!AV12+PANG!AV12+DPLA!AV12+SJKA!AV12+TRAG!L12+LUNT!AV12+WRMG!L12+NGLM!L12+SAMC!AV12+PHUA!AV12+GEDU!L12+SAMA!AV12+TCHG!L12+GMTU!AV12+PHLY!CC12 -> 0 | CD12: =HAA!M12+WANG!AW12+PUNA!AW12+GASA!M12+GELA!AW12+ZEMG!AW12+TRON!AW12+BUMA!AW12+SARA!AW12+TSIR!AW12+DGNA!AW12+PANG!AW12+DPLA!AW12+SJKA!AW12+TRAG!M12+LUNT!AW12+WRMG!M12+NGLM!M12+SAMC!AW12+PHUA!AW12+GEDU!M12+SAMA!AW12+TCHG!M12+GMTU!AW12+PHLY!CD12 -> 0 | CE12: =HAA!N12+WANG!AX12+PUNA!AX12+GASA!N12+GELA!AX12+ZEMG!AX12+TRON!AX12+BUMA!AX12+SARA!AX12+TSIR!AX12+DGNA!AX12+PANG!AX12+DPLA!AX12+SJKA!AX12+TRAG!N12+LUNT!AX12+WRMG!N12+NGLM!N12+SAMC!AX12+PHUA!AX12+GEDU!N12+SAMA!AX12+TCHG!N12+GMTU!AX12+PHLY!CE12 -> 0 | CF12: =HAA!O12+WANG!AY12+PUNA!AY12+GASA!O12+GELA!AY12+ZEMG!AY12+TRON!AY12+BUMA!AY12+SARA!AY12+TSIR!AY12+DGNA!AY12+PANG!AY12+DPLA!AY12+SJKA!AY12+TRAG!O12+LUNT!AY12+WRMG!O12+NGLM!O12+SAMC!AY12+PHUA!AY12+GEDU!O12+SAMA!AY12+TCHG!O12+GMTU!AY12+PHLY!CF12 -> 0 | ... DF12: =HAA!AO12+WANG!BY12+PUNA!BY12+GASA!AO12+GELA!BY12+ZEMG!BY12+TRON!BY12+BUMA!BY12+SARA!BY12+TSIR!BY12+DGNA!BY12+PANG!BY12+DPLA!BY12+SJKA!BY12+TRAG!AO12+LUNT!BY12+WRMG!AO12+NGLM!AO12+SAMC!BY12+PHUA!BY12+GEDU!AO12+SAMA!BY12+TCHG!AO12+GMTU!BY12+PHLY!DF12 -> 5200 | DG12: =AJ12+BT12+DC12 -> 8 | DH12: =C12*DG12 -> 5200 | DI12: =D12*DG12 -> 6240 | DJ12: =E12*DG12 -> 1040 | DN12: =PARO!H12+HAA!AQ12+WANG!CA12+PUNA!CA12+GASA!AQ12+GELA!CA12+ZEMG!CA12+TRON!CA12+BUMA!CA12+SARA!CA12+TSIR!CA12+DGNA!CA12+PANG!CA12+DPLA!CA12+SJKA!CA12+TRAG!AQ12+MONA!H12+LUNT!CA12+TYSE!H12+PEMA!H12+KNLG!H12+RJNG!H12+WRMG!AQ12+DUSM!H12+GYPG!H12+NGLM!AQ12+SAMC!CA12+PHUA!CA12+TSMA!H12+GEDU!AQ12+SAMA!CA12+TCHG!AQ12+GMTU!CA12+LHAM!H12+PHLY!DH12 -> 0 | DO12: =PARO!I12+HAA!AR12+WANG!CB12+PUNA!CB12+GASA!AR12+GELA!CB12+ZEMG!CB12+TRON!CB12+BUMA!CB12+SARA!CB12+TSIR!CB12+DGNA!CB12+PANG!CB12+DPLA!CB12+SJKA!CB12+TRAG!AR12+MONA!I12+LUNT!CB12+TYSE!I12+PEMA!I12+KNLG!I12+RJNG!I12+WRMG!AR12+DUSM!I12+GYPG!I12+NGLM!AR12+SAMC!CB12+PHUA!CB12+TSMA!I12+GEDU!AR12+SAMA!CB12+TCHG!AR12+GMTU!CB12+LHAM!I12+PHLY!DI12 -> 0 | DP12: =PARO!J12+HAA!AS12+WANG!CC12+PUNA!CC12+GASA!AS12+GELA!CC12+ZEMG!CC12+TRON!CC12+BUMA!CC12+SARA!CC12+TSIR!CC12+DGNA!CC12+PANG!CC12+DPLA!CC12+SJKA!CC12+TRAG!AS12+MONA!J12+LUNT!CC12+TYSE!J12+PEMA!J12+KNLG!J12+RJNG!J12+WRMG!AS12+DUSM!J12+GYPG!J12+NGLM!AS12+SAMC!CC12+PHUA!CC12+TSMA!J12+GEDU!AS12+SAMA!CC12+TCHG!AS12+GMTU!CC12+LHAM!J12+PHLY!DJ12 -> 0 | DQ12: =PARO!K12+HAA!AT12+WANG!CD12+PUNA!CD12+GASA!AT12+GELA!CD12+ZEMG!CD12+TRON!CD12+BUMA!CD12+SARA!CD12+TSIR!CD12+DGNA!CD12+PANG!CD12+DPLA!CD12+SJKA!CD12+TRAG!AT12+MONA!K12+LUNT!CD12+TYSE!K12+PEMA!K12+KNLG!K12+RJNG!K12+WRMG!AT12+DUSM!K12+GYPG!K12+NGLM!AT12+SAMC!CD12+PHUA!CD12+TSMA!K12+GEDU!AT12+SAMA!CD12+TCHG!AT12+GMTU!CD12+LHAM!K12+PHLY!DK12 -> 0 | DR12: =PARO!L12+HAA!AU12+WANG!CE12+PUNA!CE12+GASA!AU12+GELA!CE12+ZEMG!CE12+TRON!CE12+BUMA!CE12+SARA!CE12+TSIR!CE12+DGNA!CE12+PANG!CE12+DPLA!CE12+SJKA!CE12+TRAG!AU12+MONA!L12+LUNT!CE12+TYSE!L12+PEMA!L12+KNLG!L12+RJNG!L12+WRMG!AU12+DUSM!L12+GYPG!L12+NGLM!AU12+SAMC!CE12+PHUA!CE12+TSMA!L12+GEDU!AU12+SAMA!CE12+TCHG!AU12+GMTU!CE12+LHAM!L12+PHLY!DL12 -> 0 | DS12: =PARO!M12+HAA!AV12+WANG!CF12+PUNA!CF12+GASA!AV12+GELA!CF12+ZEMG!CF12+TRON!CF12+BUMA!CF12+SARA!CF12+TSIR!CF12+DGNA!CF12+PANG!CF12+DPLA!CF12+SJKA!CF12+TRAG!AV12+MONA!M12+LUNT!CF12+TYSE!M12+PEMA!M12+KNLG!M12+RJNG!M12+WRMG!AV12+DUSM!M12+GYPG!M12+NGLM!AV12+SAMC!CF12+PHUA!CF12+TSMA!M12+GEDU!AV12+SAMA!CF12+TCHG!AV12+GMTU!CF12+LHAM!M12+PHLY!DM12 -> 0 | DT12: =PARO!N12+HAA!AW12+WANG!CG12+PUNA!CG12+GASA!AW12+GELA!CG12+ZEMG!CG12+TRON!CG12+BUMA!CG12+SARA!CG12+TSIR!CG12+DGNA!CG12+PANG!CG12+DPLA!CG12+SJKA!CG12+TRAG!AW12+MONA!N12+LUNT!CG12+TYSE!N12+PEMA!N12+KNLG!N12+RJNG!N12+WRMG!AW12+DUSM!N12+GYPG!N12+NGLM!AW12+SAMC!CG12+PHUA!CG12+TSMA!N12+GEDU!AW12+SAMA!CG12+TCHG!AW12+GMTU!CG12+LHAM!N12+PHLY!DN12 -> 0 | DU12: =PARO!O12+HAA!AX12+WANG!CH12+PUNA!CH12+GASA!AX12+GELA!CH12+ZEMG!CH12+TRON!CH12+BUMA!CH12+SARA!CH12+TSIR!CH12+DGNA!CH12+PANG!CH12+DPLA!CH12+SJKA!CH12+TRAG!AX12+MONA!O12+LUNT!CH12+TYSE!O12+PEMA!O12+KNLG!O12+RJNG!O12+WRMG!AX12+DUSM!O12+GYPG!O12+NGLM!AX12+SAMC!CH12+PHUA!CH12+TSMA!O12+GEDU!AX12+SAMA!CH12+TCHG!AX12+GMTU!CH12+LHAM!O12+PHLY!DO12 -> 0 | ... EV12: =PARO!AP12+HAA!BY12+WANG!DI12+PUNA!DI12+GASA!BY12+GELA!DI12+ZEMG!DI12+TRON!DI12+BUMA!DI12+SARA!DI12+TSIR!DI12+DGNA!DI12+PANG!DI12+DPLA!DI12+SJKA!DI12+TRAG!BY12+MONA!AP12+LUNT!DI12+TYSE!AP12+PEMA!AP12+KNLG!AP12+RJNG!AP12+WRMG!BY12+DUSM!AP12+GYPG!AP12+NGLM!BY12+SAMC!DI12+PHUA!DI12+TSMA!AP12+GEDU!BY12+SAMA!DI12+TCHG!BY12+GMTU!DI12+LHAM!AP12+PHLY!EP12 -> 0 | EX12: =PARO!AR12+HAA!CA12+WANG!DK12+PUNA!DK12+GASA!CA12+GELA!DK12+ZEMG!DK12+TRON!DK12+BUMA!DK12+SARA!DK12+TSIR!DK12+DGNA!DK12+PANG!DK12+DPLA!DK12+SJKA!DK12+TRAG!CA12+MONA!AR12+LUNT!DK12+TYSE!AR12+PEMA!AR12+KNLG!AR12+RJNG!AR12+WRMG!CA12+DUSM!AR12+GYPG!AR12+NGLM!CA12+SAMC!DK12+PHUA!DK12+TSMA!AR12+GEDU!CA12+SAMA!DK12+TCHG!CA12+GMTU!DK12+LHAM!AR12+PHLY!ER12 -> 0 | EY12: =PARO!AS12+HAA!CB12+WANG!DL12+PUNA!DL12+GASA!CB12+GELA!DL12+ZEMG!DL12+TRON!DL12+BUMA!DL12+SARA!DL12+TSIR!DL12+DGNA!DL12+PANG!DL12+DPLA!DL12+SJKA!DL12+TRAG!CB12+MONA!AS12+LUNT!DL12+TYSE!AS12+PEMA!AS12+KNLG!AS12+RJNG!AS12+WRMG!CB12+DUSM!AS12+GYPG!AS12+NGLM!CB12+SAMC!DL12+PHUA!DL12+TSMA!AS12+GEDU!CB12+SAMA!DL12+TCHG!CB12+GMTU!DL12+LHAM!AS12+PHLY!ES12 -> 0 | EZ12: =PARO!AT12+HAA!CC12+WANG!DM12+PUNA!DM12+GASA!CC12+GELA!DM12+ZEMG!DM12+TRON!DM12+BUMA!DM12+SARA!DM12+TSIR!DM12+DGNA!DM12+PANG!DM12+DPLA!DM12+SJKA!DM12+TRAG!CC12+MONA!AT12+LUNT!DM12+TYSE!AT12+PEMA!AT12+KNLG!AT12+RJNG!AT12+WRMG!CC12+DUSM!AT12+GYPG!AT12+NGLM!CC12+SAMC!DM12+PHUA!DM12+TSMA!AT12+GEDU!CC12+SAMA!DM12+TCHG!CC12+GMTU!DM12+LHAM!AT12+PHLY!ET12 -> 0 | FA12: =PARO!AU12+HAA!CD12+WANG!DN12+PUNA!DN12+GASA!CD12+GELA!DN12+ZEMG!DN12+TRON!DN12+BUMA!DN12+SARA!DN12+TSIR!DN12+DGNA!DN12+PANG!DN12+DPLA!DN12+SJKA!DN12+TRAG!CD12+MONA!AU12+LUNT!DN12+TYSE!AU12+PEMA!AU12+KNLG!AU12+RJNG!AU12+WRMG!CD12+DUSM!AU12+GYPG!AU12+NGLM!CD12+SAMC!DN12+PHUA!DN12+TSMA!AU12+GEDU!CD12+SAMA!DN12+TCHG!CD12+GMTU!DN12+LHAM!AU12+PHLY!EU12 -> 0 | FB12: =PARO!AV12+HAA!CE12+WANG!DO12+PUNA!DO12+GASA!CE12+GELA!DO12+ZEMG!DO12+TRON!DO12+BUMA!DO12+SARA!DO12+TSIR!DO12+DGNA!DO12+PANG!DO12+DPLA!DO12+SJKA!DO12+TRAG!CE12+MONA!AV12+LUNT!DO12+TYSE!AV12+PEMA!AV12+KNLG!AV12+RJNG!AV12+WRMG!CE12+DUSM!AV12+GYPG!AV12+NGLM!CE12+SAMC!DO12+PHUA!DO12+TSMA!AV12+GEDU!CE12+SAMA!DO12+TCHG!CE12+GMTU!DO12+LHAM!AV12+PHLY!EV12 -> 0 | FC12: =PARO!AW12+HAA!CF12+WANG!DP12+PUNA!DP12+GASA!CF12+GELA!DP12+ZEMG!DP12+TRON!DP12+BUMA!DP12+SARA!DP12+TSIR!DP12+DGNA!DP12+PANG!DP12+DPLA!DP12+SJKA!DP12+TRAG!CF12+MONA!AW12+LUNT!DP12+TYSE!AW12+PEMA!AW12+KNLG!AW12+RJNG!AW12+WRMG!CF12+DUSM!AW12+GYPG!AW12+NGLM!CF12+SAMC!DP12+PHUA!DP12+TSMA!AW12+GEDU!CF12+SAMA!DP12+TCHG!CF12+GMTU!DP12+LHAM!AW12+PHLY!EW12 -> 0 | FD12: =PARO!AX12+HAA!CG12+WANG!DQ12+PUNA!DQ12+GASA!CG12+GELA!DQ12+ZEMG!DQ12+TRON!DQ12+BUMA!DQ12+SARA!DQ12+TSIR!DQ12+DGNA!DQ12+PANG!DQ12+DPLA!DQ12+SJKA!DQ12+TRAG!CG12+MONA!AX12+LUNT!DQ12+TYSE!AX12+PEMA!AX12+KNLG!AX12+RJNG!AX12+WRMG!CG12+DUSM!AX12+GYPG!AX12+NGLM!CG12+SAMC!DQ12+PHUA!DQ12+TSMA!AX12+GEDU!CG12+SAMA!DQ12+TCHG!CG12+GMTU!DQ12+LHAM!AX12+PHLY!EX12 -> 0 | FE12: =PARO!AY12+HAA!CH12+WANG!DR12+PUNA!DR12+GASA!CH12+GELA!DR12+ZEMG!DR12+TRON!DR12+BUMA!DR12+SARA!DR12+TSIR!DR12+DGNA!DR12+PANG!DR12+DPLA!DR12+SJKA!DR12+TRAG!CH12+MONA!AY12+LUNT!DR12+TYSE!AY12+PEMA!AY12+KNLG!AY12+RJNG!AY12+WRMG!CH12+DUSM!AY12+GYPG!AY12+NGLM!CH12+SAMC!DR12+PHUA!DR12+TSMA!AY12+GEDU!CH12+SAMA!DR12+TCHG!CH12+GMTU!DR12+LHAM!AY12+PHLY!EY12 -> 0 | ... GA12: =PARO!BU12+HAA!DD12+WANG!EN12+PUNA!EN12+GASA!DD12+GELA!EN12+ZEMG!EN12+TRON!EN12+BUMA!EN12+SARA!EN12+TSIR!EN12+DGNA!EN12+PANG!EN12+DPLA!EN12+SJKA!EN12+TRAG!DD12+MONA!BU12+LUNT!EN12+TYSE!BU12+PEMA!BU12+KNLG!BU12+RJNG!BU12+WRMG!DD12+DUSM!BU12+GYPG!BU12+NGLM!DD12+SAMC!EN12+PHUA!EN12+TSMA!BU12+GEDU!DD12+SAMA!EN12+TCHG!DD12+GMTU!EN12+LHAM!BU12+PHLY!FU12 -> 0 | GB12: =PARO!BV12+HAA!DE12+WANG!EO12+PUNA!EO12+GASA!DE12+GELA!EO12+ZEMG!EO12+TRON!EO12+BUMA!EO12+SARA!EO12+TSIR!EO12+DGNA!EO12+PANG!EO12+DPLA!EO12+SJKA!EO12+TRAG!DE12+MONA!BW12+LUNT!EO12+TYSE!BW12+PEMA!BW12+KNLG!BW12+RJNG!BV12+WRMG!DE12+DUSM!BW12+GYPG!BW12+NGLM!DE12+SAMC!EO12+PHUA!EO12+TSMA!BV12+GEDU!DE12+SAMA!EO12+TCHG!DE12+GMTU!EO12+LHAM!BV12+PHLY!FV12 -> 3 | GC12: =PARO!BW12+HAA!DF12+WANG!EP12+PUNA!EP12+GASA!DF12+GELA!EP12+ZEMG!EP12+TRON!EP12+BUMA!EP12+SARA!EP12+TSIR!EP12+DGNA!EP12+PANG!EP12+DPLA!EP12+SJKA!EP12+TRAG!DF12+MONA!BX12+LUNT!EP12+TYSE!BX12+PEMA!BX12+KNLG!BX12+RJNG!BW12+WRMG!DF12+DUSM!BX12+GYPG!BX12+NGLM!DF12+SAMC!EP12+PHUA!EP12+TSMA!BW12+GEDU!DF12+SAMA!EP12+TCHG!DF12+GMTU!EP12+LHAM!BW12+PHLY!FW12 -> 2340 | GD12: =PARO!BX12+HAA!DG12+WANG!EQ12+PUNA!EQ12+GASA!DG12+GELA!EQ12+ZEMG!EQ12+TRON!EQ12+BUMA!EQ12+SARA!EQ12+TSIR!EQ12+DGNA!EQ12+PANG!EQ12+DPLA!EQ12+SJKA!EQ12+TRAG!DG12+MONA!BY12+LUNT!EQ12+TYSE!BY12+PEMA!BY12+KNLG!BY12+RJNG!BX12+WRMG!DG12+DUSM!BY12+GYPG!BY12+NGLM!DG12+SAMC!EQ12+PHUA!EQ12+TSMA!BX12+GEDU!DG12+SAMA!EQ12+TCHG!DG12+GMTU!EQ12+LHAM!BX12+PHLY!FX12 -> 390 | GE12: =PARO!BY12+HAA!DH12+WANG!ER12+PUNA!ER12+GASA!DH12+GELA!ER12+ZEMG!ER12+TRON!ER12+BUMA!ER12+SARA!ER12+TSIR!ER12+DGNA!ER12+PANG!ER12+DPLA!ER12+SJKA!ER12+TRAG!DH12+MONA!BZ12+LUNT!ER12+TYSE!BZ12+PEMA!BZ12+KNLG!BZ12+RJNG!BY12+WRMG!DH12+DUSM!BZ12+GYPG!BZ12+NGLM!DH12+SAMC!ER12+PHUA!ER12+TSMA!BY12+GEDU!DH12+SAMA!ER12+TCHG!DH12+GMTU!ER12+LHAM!BY12+PHLY!FY12 -> 1950 | GG12: =PARO!CA12+HAA!DJ12+WANG!ET12+PUNA!ET12+GASA!DJ12+GELA!ET12+ZEMG!ET12+TRON!ET12+BUMA!ET12+SARA!ET12+TSIR!ET12+DGNA!ET12+PANG!ET12+DPLA!ET12+SJKA!ET12+TRAG!DJ12+MONA!CB12+LUNT!ET12+TYSE!CB12+PEMA!CB12+KNLG!CB12+RJNG!CA12+WRMG!DJ12+DUSM!CB12+GYPG!CB12+NGLM!DJ12+SAMC!ET12+PHUA!ET12+TSMA!CA12+GEDU!DJ12+SAMA!ET12+TCHG!DJ12+GMTU!ET12+LHAM!CA12+PHLY!GA12 -> 0 | GH12: =PARO!CB12+HAA!DK12+WANG!EU12+PUNA!EU12+GASA!DK12+GELA!EU12+ZEMG!EU12+TRON!EU12+BUMA!EU12+SARA!EU12+TSIR!EU12+DGNA!EU12+PANG!EU12+DPLA!EU12+SJKA!EU12+TRAG!DK12+MONA!CC12+LUNT!EU12+TYSE!CC12+PEMA!CC12+KNLG!CC12+RJNG!CB12+WRMG!DK12+DUSM!CC12+GYPG!CC12+NGLM!DK12+SAMC!EU12+PHUA!EU12+TSMA!CB12+GEDU!DK12+SAMA!EU12+TCHG!DK12+GMTU!EU12+LHAM!CB12+PHLY!GB12 -> 0 | GI12: =PARO!CC12+HAA!DL12+WANG!EV12+PUNA!EV12+GASA!DL12+GELA!EV12+ZEMG!EV12+TRON!EV12+BUMA!EV12+SARA!EV12+TSIR!EV12+DGNA!EV12+PANG!EV12+DPLA!EV12+SJKA!EV12+TRAG!DL12+MONA!CD12+LUNT!EV12+TYSE!CD12+PEMA!CD12+KNLG!CD12+RJNG!CC12+WRMG!DL12+DUSM!CD12+GYPG!CD12+NGLM!DL12+SAMC!EV12+PHUA!EV12+TSMA!CC12+GEDU!DL12+SAMA!EV12+TCHG!DL12+GMTU!EV12+LHAM!CC12+PHLY!GC12 -> 0 | GJ12: =PARO!CD12+HAA!DM12+WANG!EW12+PUNA!EW12+GASA!DM12+GELA!EW12+ZEMG!EW12+TRON!EW12+BUMA!EW12+SARA!EW12+TSIR!EW12+DGNA!EW12+PANG!EW12+DPLA!EW12+SJKA!EW12+TRAG!DM12+MONA!CE12+LUNT!EW12+TYSE!CE12+PEMA!CE12+KNLG!CE12+RJNG!CD12+WRMG!DM12+DUSM!CE12+GYPG!CE12+NGLM!DM12+SAMC!EW12+PHUA!EW12+TSMA!CD12+GEDU!DM12+SAMA!EW12+TCHG!DM12+GMTU!EW12+LHAM!CD12+PHLY!GD12 -> 0 | GK12: =PARO!CE12+HAA!DN12+WANG!EX12+PUNA!EX12+GASA!DN12+GELA!EX12+ZEMG!EX12+TRON!EX12+BUMA!EX12+SARA!EX12+TSIR!EX12+DGNA!EX12+PANG!EX12+DPLA!EX12+SJKA!EX12+TRAG!DN12+MONA!CF12+LUNT!EX12+TYSE!CF12+PEMA!CF12+KNLG!CF12+RJNG!CE12+WRMG!DN12+DUSM!CF12+GYPG!CF12+NGLM!DN12+SAMC!EX12+PHUA!EX12+TSMA!CE12+GEDU!DN12+SAMA!EX12+TCHG!DN12+GMTU!EX12+LHAM!CE12+PHLY!GE12 -> 0 | GL12: =PARO!CF12+HAA!DO12+WANG!EY12+PUNA!EY12+GASA!DO12+GELA!EY12+ZEMG!EY12+TRON!EY12+BUMA!EY12+SARA!EY12+TSIR!EY12+DGNA!EY12+PANG!EY12+DPLA!EY12+SJKA!EY12+TRAG!DO12+MONA!CG12+LUNT!EY12+TYSE!CG12+PEMA!CG12+KNLG!CG12+RJNG!CF12+WRMG!DO12+DUSM!CG12+GYPG!CG12+NGLM!DO12+SAMC!EY12+PHUA!EY12+TSMA!CF12+GEDU!DO12+SAMA!EY12+TCHG!DO12+GMTU!EY12+LHAM!CF12+PHLY!GF12 -> 0 | GM12: =PARO!CG12+HAA!DP12+WANG!EZ12+PUNA!EZ12+GASA!DP12+GELA!EZ12+ZEMG!EZ12+TRON!EZ12+BUMA!EZ12+SARA!EZ12+TSIR!EZ12+DGNA!EZ12+PANG!EZ12+DPLA!EZ12+SJKA!EZ12+TRAG!DP12+MONA!CH12+LUNT!EZ12+TYSE!CH12+PEMA!CH12+KNLG!CH12+RJNG!CG12+WRMG!DP12+DUSM!CH12+GYPG!CH12+NGLM!DP12+SAMC!EZ12+PHUA!EZ12+TSMA!CG12+GEDU!DP12+SAMA!EZ12+TCHG!DP12+GMTU!EZ12+LHAM!CG12+PHLY!GG12 -> 0 | GN12: =PARO!CH12+HAA!DQ12+WANG!FA12+PUNA!FA12+GASA!DQ12+GELA!FA12+ZEMG!FA12+TRON!FA12+BUMA!FA12+SARA!FA12+TSIR!FA12+DGNA!FA12+PANG!FA12+DPLA!FA12+SJKA!FA12+TRAG!DQ12+MONA!CI12+LUNT!FA12+TYSE!CI12+PEMA!CI12+KNLG!CI12+RJNG!CH12+WRMG!DQ12+DUSM!CI12+GYPG!CI12+NGLM!DQ12+SAMC!FA12+PHUA!FA12+TSMA!CH12+GEDU!DQ12+SAMA!FA12+TCHG!DQ12+GMTU!FA12+LHAM!CH12+PHLY!GH12 -> 0 | ... HO12: =PARO!DI12+HAA!ER12+WANG!GB12+PUNA!GB12+GASA!ER12+GELA!GB12+ZEMG!GB12+TRON!GB12+BUMA!GB12+SARA!GB12+TSIR!GB12+DGNA!GB12+PANG!GB12+DPLA!GB12+SJKA!GB12+TRAG!ER12+MONA!DJ12+LUNT!GB12+TYSE!DJ12+PEMA!DJ12+KNLG!DJ12+RJNG!DI12+WRMG!ER12+DUSM!DJ12+GYPG!DJ12+NGLM!ER12+SAMC!GB12+PHUA!GB12+TSMA!DI12+GEDU!ER12+SAMA!GB12+TCHG!ER12+GMTU!GB12+LHAM!DI12+PHLY!HI12 -> 0 | HQ12: =ES12+GB12+HL12 -> 3 | HR12: =C12*HQ12 -> 1950 | HS12: =D12*HQ12 -> 2340 | HT12: =E12*HQ12 -> 390 | IN12: =AJ12+BT12+DC12+ES12+GB12+HL12 -> 11 | IO12: =AK12+BU12+DD12+ET12+GC12+HM12 -> 8580 | IP12: =AL12+BV12+DE12+EU12+GD12+HN12 -> 1430 | IQ12: =AM12+BW12+DF12+EV12+GE12+HO12 -> 7150
A13: 11 | B13: Cordyceps capsule (cordyCAPS) | C13: 13890 | D13: 16668 | E13: =D13-C13 -> 2778 | H13: =PHLY!H13 -> 0 | I13: =PHLY!I13 -> 0 | J13: =PHLY!J13 -> 0 | K13: =PHLY!K13 -> 0 | L13: =PHLY!L13 -> 0 | M13: =PHLY!M13 -> 0 | N13: =PHLY!N13 -> 0 | O13: =PHLY!O13 -> 0 | ... AM13: =PHLY!AM13 -> 0 | AO13: =WANG!H13+PUNA!H13+GELA!H13+ZEMG!H13+TRON!H13+BUMA!H13+SARA!H13+TSIR!H13+DGNA!H13+PANG!H13+DPLA!H13+SJKA!H13+LUNT!H13+SAMC!H13+PHUA!H13+SAMA!H13+GMTU!H13+PHLY!AO13 -> 0 | AP13: =WANG!I13+PUNA!I13+GELA!I13+ZEMG!I13+TRON!I13+BUMA!I13+SARA!I13+TSIR!I13+DGNA!I13+PANG!I13+DPLA!I13+SJKA!I13+LUNT!I13+SAMC!I13+PHUA!I13+SAMA!I13+GMTU!I13+PHLY!AP13 -> 0 | AQ13: =WANG!J13+PUNA!J13+GELA!J13+ZEMG!J13+TRON!J13+BUMA!J13+SARA!J13+TSIR!J13+DGNA!J13+PANG!J13+DPLA!J13+SJKA!J13+LUNT!J13+SAMC!J13+PHUA!J13+SAMA!J13+GMTU!J13+PHLY!AQ13 -> 0 | AR13: =WANG!K13+PUNA!K13+GELA!K13+ZEMG!K13+TRON!K13+BUMA!K13+SARA!K13+TSIR!K13+DGNA!K13+PANG!K13+DPLA!K13+SJKA!K13+LUNT!K13+SAMC!K13+PHUA!K13+SAMA!K13+GMTU!K13+PHLY!AR13 -> 0 | AS13: =WANG!L13+PUNA!L13+GELA!L13+ZEMG!L13+TRON!L13+BUMA!L13+SARA!L13+TSIR!L13+DGNA!L13+PANG!L13+DPLA!L13+SJKA!L13+LUNT!L13+SAMC!L13+PHUA!L13+SAMA!L13+GMTU!L13+PHLY!AS13 -> 0 | AT13: =WANG!M13+PUNA!M13+GELA!M13+ZEMG!M13+TRON!M13+BUMA!M13+SARA!M13+TSIR!M13+DGNA!M13+PANG!M13+DPLA!M13+SJKA!M13+LUNT!M13+SAMC!M13+PHUA!M13+SAMA!M13+GMTU!M13+PHLY!AT13 -> 0 | AU13: =WANG!N13+PUNA!N13+GELA!N13+ZEMG!N13+TRON!N13+BUMA!N13+SARA!N13+TSIR!N13+DGNA!N13+PANG!N13+DPLA!N13+SJKA!N13+LUNT!N13+SAMC!N13+PHUA!N13+SAMA!N13+GMTU!N13+PHLY!AU13 -> 0 | AV13: =WANG!O13+PUNA!O13+GELA!O13+ZEMG!O13+TRON!O13+BUMA!O13+SARA!O13+TSIR!O13+DGNA!O13+PANG!O13+DPLA!O13+SJKA!O13+LUNT!O13+SAMC!O13+PHUA!O13+SAMA!O13+GMTU!O13+PHLY!AV13 -> 0 | ... BW13: =WANG!AP13+PUNA!AP13+GELA!AP13+ZEMG!AP13+TRON!AP13+BUMA!AP13+SARA!AP13+TSIR!AP13+DGNA!AP13+PANG!AP13+DPLA!AP13+SJKA!AP13+LUNT!AP13+SAMC!AP13+PHUA!AP13+SAMA!AP13+GMTU!AP13+PHLY!BW13 -> 0 | BY13: =HAA!H13+WANG!AR13+PUNA!AR13+GASA!H13+GELA!AR13+ZEMG!AR13+TRON!AR13+BUMA!AR13+SARA!AR13+TSIR!AR13+DGNA!AR13+PANG!AR13+DPLA!AR13+SJKA!AR13+TRAG!H13+LUNT!AR13+WRMG!H13+NGLM!H13+SAMC!AR13+PHUA!AR13+GEDU!H13+SAMA!AR13+TCHG!H13+GMTU!AR13+PHLY!BY13 -> 0 | BZ13: =HAA!I13+WANG!AS13+PUNA!AS13+GASA!I13+GELA!AS13+ZEMG!AS13+TRON!AS13+BUMA!AS13+SARA!AS13+TSIR!AS13+DGNA!AS13+PANG!AS13+DPLA!AS13+SJKA!AS13+TRAG!I13+LUNT!AS13+WRMG!I13+NGLM!I13+SAMC!AS13+PHUA!AS13+GEDU!I13+SAMA!AS13+TCHG!I13+GMTU!AS13+PHLY!BZ13 -> 0 | CA13: =HAA!J13+WANG!AT13+PUNA!AT13+GASA!J13+GELA!AT13+ZEMG!AT13+TRON!AT13+BUMA!AT13+SARA!AT13+TSIR!AT13+DGNA!AT13+PANG!AT13+DPLA!AT13+SJKA!AT13+TRAG!J13+LUNT!AT13+WRMG!J13+NGLM!J13+SAMC!AT13+PHUA!AT13+GEDU!J13+SAMA!AT13+TCHG!J13+GMTU!AT13+PHLY!CA13 -> 0 | CB13: =HAA!K13+WANG!AU13+PUNA!AU13+GASA!K13+GELA!AU13+ZEMG!AU13+TRON!AU13+BUMA!AU13+SARA!AU13+TSIR!AU13+DGNA!AU13+PANG!AU13+DPLA!AU13+SJKA!AU13+TRAG!K13+LUNT!AU13+WRMG!K13+NGLM!K13+SAMC!AU13+PHUA!AU13+GEDU!K13+SAMA!AU13+TCHG!K13+GMTU!AU13+PHLY!CB13 -> 0 | CC13: =HAA!L13+WANG!AV13+PUNA!AV13+GASA!L13+GELA!AV13+ZEMG!AV13+TRON!AV13+BUMA!AV13+SARA!AV13+TSIR!AV13+DGNA!AV13+PANG!AV13+DPLA!AV13+SJKA!AV13+TRAG!L13+LUNT!AV13+WRMG!L13+NGLM!L13+SAMC!AV13+PHUA!AV13+GEDU!L13+SAMA!AV13+TCHG!L13+GMTU!AV13+PHLY!CC13 -> 0 | CD13: =HAA!M13+WANG!AW13+PUNA!AW13+GASA!M13+GELA!AW13+ZEMG!AW13+TRON!AW13+BUMA!AW13+SARA!AW13+TSIR!AW13+DGNA!AW13+PANG!AW13+DPLA!AW13+SJKA!AW13+TRAG!M13+LUNT!AW13+WRMG!M13+NGLM!M13+SAMC!AW13+PHUA!AW13+GEDU!M13+SAMA!AW13+TCHG!M13+GMTU!AW13+PHLY!CD13 -> 0 | CE13: =HAA!N13+WANG!AX13+PUNA!AX13+GASA!N13+GELA!AX13+ZEMG!AX13+TRON!AX13+BUMA!AX13+SARA!AX13+TSIR!AX13+DGNA!AX13+PANG!AX13+DPLA!AX13+SJKA!AX13+TRAG!N13+LUNT!AX13+WRMG!N13+NGLM!N13+SAMC!AX13+PHUA!AX13+GEDU!N13+SAMA!AX13+TCHG!N13+GMTU!AX13+PHLY!CE13 -> 0 | CF13: =HAA!O13+WANG!AY13+PUNA!AY13+GASA!O13+GELA!AY13+ZEMG!AY13+TRON!AY13+BUMA!AY13+SARA!AY13+TSIR!AY13+DGNA!AY13+PANG!AY13+DPLA!AY13+SJKA!AY13+TRAG!O13+LUNT!AY13+WRMG!O13+NGLM!O13+SAMC!AY13+PHUA!AY13+GEDU!O13+SAMA!AY13+TCHG!O13+GMTU!AY13+PHLY!CF13 -> 0 | ... DF13: =HAA!AO13+WANG!BY13+PUNA!BY13+GASA!AO13+GELA!BY13+ZEMG!BY13+TRON!BY13+BUMA!BY13+SARA!BY13+TSIR!BY13+DGNA!BY13+PANG!BY13+DPLA!BY13+SJKA!BY13+TRAG!AO13+LUNT!BY13+WRMG!AO13+NGLM!AO13+SAMC!BY13+PHUA!BY13+GEDU!AO13+SAMA!BY13+TCHG!AO13+GMTU!BY13+PHLY!DF13 -> 0 | DG13: =AJ13+BT13+DC13 -> 0 | DH13: =C13*DG13 -> 0 | DI13: =D13*DG13 -> 0 | DJ13: =E13*DG13 -> 0 | DN13: =PARO!H13+HAA!AQ13+WANG!CA13+PUNA!CA13+GASA!AQ13+GELA!CA13+ZEMG!CA13+TRON!CA13+BUMA!CA13+SARA!CA13+TSIR!CA13+DGNA!CA13+PANG!CA13+DPLA!CA13+SJKA!CA13+TRAG!AQ13+MONA!H13+LUNT!CA13+TYSE!H13+PEMA!H13+KNLG!H13+RJNG!H13+WRMG!AQ13+DUSM!H13+GYPG!H13+NGLM!AQ13+SAMC!CA13+PHUA!CA13+TSMA!H13+GEDU!AQ13+SAMA!CA13+TCHG!AQ13+GMTU!CA13+LHAM!H13+PHLY!DH13 -> 0 | DO13: =PARO!I13+HAA!AR13+WANG!CB13+PUNA!CB13+GASA!AR13+GELA!CB13+ZEMG!CB13+TRON!CB13+BUMA!CB13+SARA!CB13+TSIR!CB13+DGNA!CB13+PANG!CB13+DPLA!CB13+SJKA!CB13+TRAG!AR13+MONA!I13+LUNT!CB13+TYSE!I13+PEMA!I13+KNLG!I13+RJNG!I13+WRMG!AR13+DUSM!I13+GYPG!I13+NGLM!AR13+SAMC!CB13+PHUA!CB13+TSMA!I13+GEDU!AR13+SAMA!CB13+TCHG!AR13+GMTU!CB13+LHAM!I13+PHLY!DI13 -> 0 | DP13: =PARO!J13+HAA!AS13+WANG!CC13+PUNA!CC13+GASA!AS13+GELA!CC13+ZEMG!CC13+TRON!CC13+BUMA!CC13+SARA!CC13+TSIR!CC13+DGNA!CC13+PANG!CC13+DPLA!CC13+SJKA!CC13+TRAG!AS13+MONA!J13+LUNT!CC13+TYSE!J13+PEMA!J13+KNLG!J13+RJNG!J13+WRMG!AS13+DUSM!J13+GYPG!J13+NGLM!AS13+SAMC!CC13+PHUA!CC13+TSMA!J13+GEDU!AS13+SAMA!CC13+TCHG!AS13+GMTU!CC13+LHAM!J13+PHLY!DJ13 -> 0 | DQ13: =PARO!K13+HAA!AT13+WANG!CD13+PUNA!CD13+GASA!AT13+GELA!CD13+ZEMG!CD13+TRON!CD13+BUMA!CD13+SARA!CD13+TSIR!CD13+DGNA!CD13+PANG!CD13+DPLA!CD13+SJKA!CD13+TRAG!AT13+MONA!K13+LUNT!CD13+TYSE!K13+PEMA!K13+KNLG!K13+RJNG!K13+WRMG!AT13+DUSM!K13+GYPG!K13+NGLM!AT13+SAMC!CD13+PHUA!CD13+TSMA!K13+GEDU!AT13+SAMA!CD13+TCHG!AT13+GMTU!CD13+LHAM!K13+PHLY!DK13 -> 0 | DR13: =PARO!L13+HAA!AU13+WANG!CE13+PUNA!CE13+GASA!AU13+GELA!CE13+ZEMG!CE13+TRON!CE13+BUMA!CE13+SARA!CE13+TSIR!CE13+DGNA!CE13+PANG!CE13+DPLA!CE13+SJKA!CE13+TRAG!AU13+MONA!L13+LUNT!CE13+TYSE!L13+PEMA!L13+KNLG!L13+RJNG!L13+WRMG!AU13+DUSM!L13+GYPG!L13+NGLM!AU13+SAMC!CE13+PHUA!CE13+TSMA!L13+GEDU!AU13+SAMA!CE13+TCHG!AU13+GMTU!CE13+LHAM!L13+PHLY!DL13 -> 0 | DS13: =PARO!M13+HAA!AV13+WANG!CF13+PUNA!CF13+GASA!AV13+GELA!CF13+ZEMG!CF13+TRON!CF13+BUMA!CF13+SARA!CF13+TSIR!CF13+DGNA!CF13+PANG!CF13+DPLA!CF13+SJKA!CF13+TRAG!AV13+MONA!M13+LUNT!CF13+TYSE!M13+PEMA!M13+KNLG!M13+RJNG!M13+WRMG!AV13+DUSM!M13+GYPG!M13+NGLM!AV13+SAMC!CF13+PHUA!CF13+TSMA!M13+GEDU!AV13+SAMA!CF13+TCHG!AV13+GMTU!CF13+LHAM!M13+PHLY!DM13 -> 0 | DT13: =PARO!N13+HAA!AW13+WANG!CG13+PUNA!CG13+GASA!AW13+GELA!CG13+ZEMG!CG13+TRON!CG13+BUMA!CG13+SARA!CG13+TSIR!CG13+DGNA!CG13+PANG!CG13+DPLA!CG13+SJKA!CG13+TRAG!AW13+MONA!N13+LUNT!CG13+TYSE!N13+PEMA!N13+KNLG!N13+RJNG!N13+WRMG!AW13+DUSM!N13+GYPG!N13+NGLM!AW13+SAMC!CG13+PHUA!CG13+TSMA!N13+GEDU!AW13+SAMA!CG13+TCHG!AW13+GMTU!CG13+LHAM!N13+PHLY!DN13 -> 0 | DU13: =PARO!O13+HAA!AX13+WANG!CH13+PUNA!CH13+GASA!AX13+GELA!CH13+ZEMG!CH13+TRON!CH13+BUMA!CH13+SARA!CH13+TSIR!CH13+DGNA!CH13+PANG!CH13+DPLA!CH13+SJKA!CH13+TRAG!AX13+MONA!O13+LUNT!CH13+TYSE!O13+PEMA!O13+KNLG!O13+RJNG!O13+WRMG!AX13+DUSM!O13+GYPG!O13+NGLM!AX13+SAMC!CH13+PHUA!CH13+TSMA!O13+GEDU!AX13+SAMA!CH13+TCHG!AX13+GMTU!CH13+LHAM!O13+PHLY!DO13 -> 0 | ... EV13: =PARO!AP13+HAA!BY13+WANG!DI13+PUNA!DI13+GASA!BY13+GELA!DI13+ZEMG!DI13+TRON!DI13+BUMA!DI13+SARA!DI13+TSIR!DI13+DGNA!DI13+PANG!DI13+DPLA!DI13+SJKA!DI13+TRAG!BY13+MONA!AP13+LUNT!DI13+TYSE!AP13+PEMA!AP13+KNLG!AP13+RJNG!AP13+WRMG!BY13+DUSM!AP13+GYPG!AP13+NGLM!BY13+SAMC!DI13+PHUA!DI13+TSMA!AP13+GEDU!BY13+SAMA!DI13+TCHG!BY13+GMTU!DI13+LHAM!AP13+PHLY!EP13 -> 0 | EX13: =PARO!AR13+HAA!CA13+WANG!DK13+PUNA!DK13+GASA!CA13+GELA!DK13+ZEMG!DK13+TRON!DK13+BUMA!DK13+SARA!DK13+TSIR!DK13+DGNA!DK13+PANG!DK13+DPLA!DK13+SJKA!DK13+TRAG!CA13+MONA!AR13+LUNT!DK13+TYSE!AR13+PEMA!AR13+KNLG!AR13+RJNG!AR13+WRMG!CA13+DUSM!AR13+GYPG!AR13+NGLM!CA13+SAMC!DK13+PHUA!DK13+TSMA!AR13+GEDU!CA13+SAMA!DK13+TCHG!CA13+GMTU!DK13+LHAM!AR13+PHLY!ER13 -> 0 | EY13: =PARO!AS13+HAA!CB13+WANG!DL13+PUNA!DL13+GASA!CB13+GELA!DL13+ZEMG!DL13+TRON!DL13+BUMA!DL13+SARA!DL13+TSIR!DL13+DGNA!DL13+PANG!DL13+DPLA!DL13+SJKA!DL13+TRAG!CB13+MONA!AS13+LUNT!DL13+TYSE!AS13+PEMA!AS13+KNLG!AS13+RJNG!AS13+WRMG!CB13+DUSM!AS13+GYPG!AS13+NGLM!CB13+SAMC!DL13+PHUA!DL13+TSMA!AS13+GEDU!CB13+SAMA!DL13+TCHG!CB13+GMTU!DL13+LHAM!AS13+PHLY!ES13 -> 0 | EZ13: =PARO!AT13+HAA!CC13+WANG!DM13+PUNA!DM13+GASA!CC13+GELA!DM13+ZEMG!DM13+TRON!DM13+BUMA!DM13+SARA!DM13+TSIR!DM13+DGNA!DM13+PANG!DM13+DPLA!DM13+SJKA!DM13+TRAG!CC13+MONA!AT13+LUNT!DM13+TYSE!AT13+PEMA!AT13+KNLG!AT13+RJNG!AT13+WRMG!CC13+DUSM!AT13+GYPG!AT13+NGLM!CC13+SAMC!DM13+PHUA!DM13+TSMA!AT13+GEDU!CC13+SAMA!DM13+TCHG!CC13+GMTU!DM13+LHAM!AT13+PHLY!ET13 -> 0 | FA13: =PARO!AU13+HAA!CD13+WANG!DN13+PUNA!DN13+GASA!CD13+GELA!DN13+ZEMG!DN13+TRON!DN13+BUMA!DN13+SARA!DN13+TSIR!DN13+DGNA!DN13+PANG!DN13+DPLA!DN13+SJKA!DN13+TRAG!CD13+MONA!AU13+LUNT!DN13+TYSE!AU13+PEMA!AU13+KNLG!AU13+RJNG!AU13+WRMG!CD13+DUSM!AU13+GYPG!AU13+NGLM!CD13+SAMC!DN13+PHUA!DN13+TSMA!AU13+GEDU!CD13+SAMA!DN13+TCHG!CD13+GMTU!DN13+LHAM!AU13+PHLY!EU13 -> 0 | FB13: =PARO!AV13+HAA!CE13+WANG!DO13+PUNA!DO13+GASA!CE13+GELA!DO13+ZEMG!DO13+TRON!DO13+BUMA!DO13+SARA!DO13+TSIR!DO13+DGNA!DO13+PANG!DO13+DPLA!DO13+SJKA!DO13+TRAG!CE13+MONA!AV13+LUNT!DO13+TYSE!AV13+PEMA!AV13+KNLG!AV13+RJNG!AV13+WRMG!CE13+DUSM!AV13+GYPG!AV13+NGLM!CE13+SAMC!DO13+PHUA!DO13+TSMA!AV13+GEDU!CE13+SAMA!DO13+TCHG!CE13+GMTU!DO13+LHAM!AV13+PHLY!EV13 -> 0 | FC13: =PARO!AW13+HAA!CF13+WANG!DP13+PUNA!DP13+GASA!CF13+GELA!DP13+ZEMG!DP13+TRON!DP13+BUMA!DP13+SARA!DP13+TSIR!DP13+DGNA!DP13+PANG!DP13+DPLA!DP13+SJKA!DP13+TRAG!CF13+MONA!AW13+LUNT!DP13+TYSE!AW13+PEMA!AW13+KNLG!AW13+RJNG!AW13+WRMG!CF13+DUSM!AW13+GYPG!AW13+NGLM!CF13+SAMC!DP13+PHUA!DP13+TSMA!AW13+GEDU!CF13+SAMA!DP13+TCHG!CF13+GMTU!DP13+LHAM!AW13+PHLY!EW13 -> 0 | FD13: =PARO!AX13+HAA!CG13+WANG!DQ13+PUNA!DQ13+GASA!CG13+GELA!DQ13+ZEMG!DQ13+TRON!DQ13+BUMA!DQ13+SARA!DQ13+TSIR!DQ13+DGNA!DQ13+PANG!DQ13+DPLA!DQ13+SJKA!DQ13+TRAG!CG13+MONA!AX13+LUNT!DQ13+TYSE!AX13+PEMA!AX13+KNLG!AX13+RJNG!AX13+WRMG!CG13+DUSM!AX13+GYPG!AX13+NGLM!CG13+SAMC!DQ13+PHUA!DQ13+TSMA!AX13+GEDU!CG13+SAMA!DQ13+TCHG!CG13+GMTU!DQ13+LHAM!AX13+PHLY!EX13 -> 0 | FE13: =PARO!AY13+HAA!CH13+WANG!DR13+PUNA!DR13+GASA!CH13+GELA!DR13+ZEMG!DR13+TRON!DR13+BUMA!DR13+SARA!DR13+TSIR!DR13+DGNA!DR13+PANG!DR13+DPLA!DR13+SJKA!DR13+TRAG!CH13+MONA!AY13+LUNT!DR13+TYSE!AY13+PEMA!AY13+KNLG!AY13+RJNG!AY13+WRMG!CH13+DUSM!AY13+GYPG!AY13+NGLM!CH13+SAMC!DR13+PHUA!DR13+TSMA!AY13+GEDU!CH13+SAMA!DR13+TCHG!CH13+GMTU!DR13+LHAM!AY13+PHLY!EY13 -> 0 | ... GA13: =PARO!BU13+HAA!DD13+WANG!EN13+PUNA!EN13+GASA!DD13+GELA!EN13+ZEMG!EN13+TRON!EN13+BUMA!EN13+SARA!EN13+TSIR!EN13+DGNA!EN13+PANG!EN13+DPLA!EN13+SJKA!EN13+TRAG!DD13+MONA!BU13+LUNT!EN13+TYSE!BU13+PEMA!BU13+KNLG!BU13+RJNG!BU13+WRMG!DD13+DUSM!BU13+GYPG!BU13+NGLM!DD13+SAMC!EN13+PHUA!EN13+TSMA!BU13+GEDU!DD13+SAMA!EN13+TCHG!DD13+GMTU!EN13+LHAM!BU13+PHLY!FU13 -> 0 | GB13: =PARO!BV13+HAA!DE13+WANG!EO13+PUNA!EO13+GASA!DE13+GELA!EO13+ZEMG!EO13+TRON!EO13+BUMA!EO13+SARA!EO13+TSIR!EO13+DGNA!EO13+PANG!EO13+DPLA!EO13+SJKA!EO13+TRAG!DE13+MONA!BW13+LUNT!EO13+TYSE!BW13+PEMA!BW13+KNLG!BW13+RJNG!BV13+WRMG!DE13+DUSM!BW13+GYPG!BW13+NGLM!DE13+SAMC!EO13+PHUA!EO13+TSMA!BV13+GEDU!DE13+SAMA!EO13+TCHG!DE13+GMTU!EO13+LHAM!BV13+PHLY!FV13 -> 0 | GC13: =PARO!BW13+HAA!DF13+WANG!EP13+PUNA!EP13+GASA!DF13+GELA!EP13+ZEMG!EP13+TRON!EP13+BUMA!EP13+SARA!EP13+TSIR!EP13+DGNA!EP13+PANG!EP13+DPLA!EP13+SJKA!EP13+TRAG!DF13+MONA!BX13+LUNT!EP13+TYSE!BX13+PEMA!BX13+KNLG!BX13+RJNG!BW13+WRMG!DF13+DUSM!BX13+GYPG!BX13+NGLM!DF13+SAMC!EP13+PHUA!EP13+TSMA!BW13+GEDU!DF13+SAMA!EP13+TCHG!DF13+GMTU!EP13+LHAM!BW13+PHLY!FW13 -> 0 | GD13: =PARO!BX13+HAA!DG13+WANG!EQ13+PUNA!EQ13+GASA!DG13+GELA!EQ13+ZEMG!EQ13+TRON!EQ13+BUMA!EQ13+SARA!EQ13+TSIR!EQ13+DGNA!EQ13+PANG!EQ13+DPLA!EQ13+SJKA!EQ13+TRAG!DG13+MONA!BY13+LUNT!EQ13+TYSE!BY13+PEMA!BY13+KNLG!BY13+RJNG!BX13+WRMG!DG13+DUSM!BY13+GYPG!BY13+NGLM!DG13+SAMC!EQ13+PHUA!EQ13+TSMA!BX13+GEDU!DG13+SAMA!EQ13+TCHG!DG13+GMTU!EQ13+LHAM!BX13+PHLY!FX13 -> 0 | GE13: =PARO!BY13+HAA!DH13+WANG!ER13+PUNA!ER13+GASA!DH13+GELA!ER13+ZEMG!ER13+TRON!ER13+BUMA!ER13+SARA!ER13+TSIR!ER13+DGNA!ER13+PANG!ER13+DPLA!ER13+SJKA!ER13+TRAG!DH13+MONA!BZ13+LUNT!ER13+TYSE!BZ13+PEMA!BZ13+KNLG!BZ13+RJNG!BY13+WRMG!DH13+DUSM!BZ13+GYPG!BZ13+NGLM!DH13+SAMC!ER13+PHUA!ER13+TSMA!BY13+GEDU!DH13+SAMA!ER13+TCHG!DH13+GMTU!ER13+LHAM!BY13+PHLY!FY13 -> 0 | GG13: =PARO!CA13+HAA!DJ13+WANG!ET13+PUNA!ET13+GASA!DJ13+GELA!ET13+ZEMG!ET13+TRON!ET13+BUMA!ET13+SARA!ET13+TSIR!ET13+DGNA!ET13+PANG!ET13+DPLA!ET13+SJKA!ET13+TRAG!DJ13+MONA!CB13+LUNT!ET13+TYSE!CB13+PEMA!CB13+KNLG!CB13+RJNG!CA13+WRMG!DJ13+DUSM!CB13+GYPG!CB13+NGLM!DJ13+SAMC!ET13+PHUA!ET13+TSMA!CA13+GEDU!DJ13+SAMA!ET13+TCHG!DJ13+GMTU!ET13+LHAM!CA13+PHLY!GA13 -> 0 | GH13: =PARO!CB13+HAA!DK13+WANG!EU13+PUNA!EU13+GASA!DK13+GELA!EU13+ZEMG!EU13+TRON!EU13+BUMA!EU13+SARA!EU13+TSIR!EU13+DGNA!EU13+PANG!EU13+DPLA!EU13+SJKA!EU13+TRAG!DK13+MONA!CC13+LUNT!EU13+TYSE!CC13+PEMA!CC13+KNLG!CC13+RJNG!CB13+WRMG!DK13+DUSM!CC13+GYPG!CC13+NGLM!DK13+SAMC!EU13+PHUA!EU13+TSMA!CB13+GEDU!DK13+SAMA!EU13+TCHG!DK13+GMTU!EU13+LHAM!CB13+PHLY!GB13 -> 0 | GI13: =PARO!CC13+HAA!DL13+WANG!EV13+PUNA!EV13+GASA!DL13+GELA!EV13+ZEMG!EV13+TRON!EV13+BUMA!EV13+SARA!EV13+TSIR!EV13+DGNA!EV13+PANG!EV13+DPLA!EV13+SJKA!EV13+TRAG!DL13+MONA!CD13+LUNT!EV13+TYSE!CD13+PEMA!CD13+KNLG!CD13+RJNG!CC13+WRMG!DL13+DUSM!CD13+GYPG!CD13+NGLM!DL13+SAMC!EV13+PHUA!EV13+TSMA!CC13+GEDU!DL13+SAMA!EV13+TCHG!DL13+GMTU!EV13+LHAM!CC13+PHLY!GC13 -> 0 | GJ13: =PARO!CD13+HAA!DM13+WANG!EW13+PUNA!EW13+GASA!DM13+GELA!EW13+ZEMG!EW13+TRON!EW13+BUMA!EW13+SARA!EW13+TSIR!EW13+DGNA!EW13+PANG!EW13+DPLA!EW13+SJKA!EW13+TRAG!DM13+MONA!CE13+LUNT!EW13+TYSE!CE13+PEMA!CE13+KNLG!CE13+RJNG!CD13+WRMG!DM13+DUSM!CE13+GYPG!CE13+NGLM!DM13+SAMC!EW13+PHUA!EW13+TSMA!CD13+GEDU!DM13+SAMA!EW13+TCHG!DM13+GMTU!EW13+LHAM!CD13+PHLY!GD13 -> 0 | GK13: =PARO!CE13+HAA!DN13+WANG!EX13+PUNA!EX13+GASA!DN13+GELA!EX13+ZEMG!EX13+TRON!EX13+BUMA!EX13+SARA!EX13+TSIR!EX13+DGNA!EX13+PANG!EX13+DPLA!EX13+SJKA!EX13+TRAG!DN13+MONA!CF13+LUNT!EX13+TYSE!CF13+PEMA!CF13+KNLG!CF13+RJNG!CE13+WRMG!DN13+DUSM!CF13+GYPG!CF13+NGLM!DN13+SAMC!EX13+PHUA!EX13+TSMA!CE13+GEDU!DN13+SAMA!EX13+TCHG!DN13+GMTU!EX13+LHAM!CE13+PHLY!GE13 -> 0 | GL13: =PARO!CF13+HAA!DO13+WANG!EY13+PUNA!EY13+GASA!DO13+GELA!EY13+ZEMG!EY13+TRON!EY13+BUMA!EY13+SARA!EY13+TSIR!EY13+DGNA!EY13+PANG!EY13+DPLA!EY13+SJKA!EY13+TRAG!DO13+MONA!CG13+LUNT!EY13+TYSE!CG13+PEMA!CG13+KNLG!CG13+RJNG!CF13+WRMG!DO13+DUSM!CG13+GYPG!CG13+NGLM!DO13+SAMC!EY13+PHUA!EY13+TSMA!CF13+GEDU!DO13+SAMA!EY13+TCHG!DO13+GMTU!EY13+LHAM!CF13+PHLY!GF13 -> 0 | GM13: =PARO!CG13+HAA!DP13+WANG!EZ13+PUNA!EZ13+GASA!DP13+GELA!EZ13+ZEMG!EZ13+TRON!EZ13+BUMA!EZ13+SARA!EZ13+TSIR!EZ13+DGNA!EZ13+PANG!EZ13+DPLA!EZ13+SJKA!EZ13+TRAG!DP13+MONA!CH13+LUNT!EZ13+TYSE!CH13+PEMA!CH13+KNLG!CH13+RJNG!CG13+WRMG!DP13+DUSM!CH13+GYPG!CH13+NGLM!DP13+SAMC!EZ13+PHUA!EZ13+TSMA!CG13+GEDU!DP13+SAMA!EZ13+TCHG!DP13+GMTU!EZ13+LHAM!CG13+PHLY!GG13 -> 0 | GN13: =PARO!CH13+HAA!DQ13+WANG!FA13+PUNA!FA13+GASA!DQ13+GELA!FA13+ZEMG!FA13+TRON!FA13+BUMA!FA13+SARA!FA13+TSIR!FA13+DGNA!FA13+PANG!FA13+DPLA!FA13+SJKA!FA13+TRAG!DQ13+MONA!CI13+LUNT!FA13+TYSE!CI13+PEMA!CI13+KNLG!CI13+RJNG!CH13+WRMG!DQ13+DUSM!CI13+GYPG!CI13+NGLM!DQ13+SAMC!FA13+PHUA!FA13+TSMA!CH13+GEDU!DQ13+SAMA!FA13+TCHG!DQ13+GMTU!FA13+LHAM!CH13+PHLY!GH13 -> 0 | ... HO13: =PARO!DI13+HAA!ER13+WANG!GB13+PUNA!GB13+GASA!ER13+GELA!GB13+ZEMG!GB13+TRON!GB13+BUMA!GB13+SARA!GB13+TSIR!GB13+DGNA!GB13+PANG!GB13+DPLA!GB13+SJKA!GB13+TRAG!ER13+MONA!DJ13+LUNT!GB13+TYSE!DJ13+PEMA!DJ13+KNLG!DJ13+RJNG!DI13+WRMG!ER13+DUSM!DJ13+GYPG!DJ13+NGLM!ER13+SAMC!GB13+PHUA!GB13+TSMA!DI13+GEDU!ER13+SAMA!GB13+TCHG!ER13+GMTU!GB13+LHAM!DI13+PHLY!HI13 -> 0 | HQ13: =ES13+GB13+HL13 -> 0 | HR13: =C13*HQ13 -> 0 | HS13: =D13*HQ13 -> 0 | HT13: =E13*HQ13 -> 0 | IN13: =AJ13+BT13+DC13+ES13+GB13+HL13 -> 0 | IO13: =AK13+BU13+DD13+ET13+GC13+HM13 -> 0 | IP13: =AL13+BV13+DE13+EU13+GD13+HN13 -> 0 | IQ13: =AM13+BW13+DF13+EV13+GE13+HO13 -> 0
A14: 12 | B14: Mind soother | C14: 250 | D14: 300 | E14: =D14-C14 -> 50 | F14: 5% Discount on every 25 boxes / packets | H14: =PHLY!H14 -> 0 | I14: =PHLY!I14 -> 0 | J14: =PHLY!J14 -> 0 | K14: =PHLY!K14 -> 0 | L14: =PHLY!L14 -> 0 | M14: =PHLY!M14 -> 0 | N14: =PHLY!N14 -> 0 | O14: =PHLY!O14 -> 0 | ... AM14: =PHLY!AM14 -> 0 | AO14: =WANG!H14+PUNA!H14+GELA!H14+ZEMG!H14+TRON!H14+BUMA!H14+SARA!H14+TSIR!H14+DGNA!H14+PANG!H14+DPLA!H14+SJKA!H14+LUNT!H14+SAMC!H14+PHUA!H14+SAMA!H14+GMTU!H14+PHLY!AO14 -> 0 | AP14: =WANG!I14+PUNA!I14+GELA!I14+ZEMG!I14+TRON!I14+BUMA!I14+SARA!I14+TSIR!I14+DGNA!I14+PANG!I14+DPLA!I14+SJKA!I14+LUNT!I14+SAMC!I14+PHUA!I14+SAMA!I14+GMTU!I14+PHLY!AP14 -> 0 | AQ14: =WANG!J14+PUNA!J14+GELA!J14+ZEMG!J14+TRON!J14+BUMA!J14+SARA!J14+TSIR!J14+DGNA!J14+PANG!J14+DPLA!J14+SJKA!J14+LUNT!J14+SAMC!J14+PHUA!J14+SAMA!J14+GMTU!J14+PHLY!AQ14 -> 0 | AR14: =WANG!K14+PUNA!K14+GELA!K14+ZEMG!K14+TRON!K14+BUMA!K14+SARA!K14+TSIR!K14+DGNA!K14+PANG!K14+DPLA!K14+SJKA!K14+LUNT!K14+SAMC!K14+PHUA!K14+SAMA!K14+GMTU!K14+PHLY!AR14 -> 0 | AS14: =WANG!L14+PUNA!L14+GELA!L14+ZEMG!L14+TRON!L14+BUMA!L14+SARA!L14+TSIR!L14+DGNA!L14+PANG!L14+DPLA!L14+SJKA!L14+LUNT!L14+SAMC!L14+PHUA!L14+SAMA!L14+GMTU!L14+PHLY!AS14 -> 0 | AT14: =WANG!M14+PUNA!M14+GELA!M14+ZEMG!M14+TRON!M14+BUMA!M14+SARA!M14+TSIR!M14+DGNA!M14+PANG!M14+DPLA!M14+SJKA!M14+LUNT!M14+SAMC!M14+PHUA!M14+SAMA!M14+GMTU!M14+PHLY!AT14 -> 0 | AU14: =WANG!N14+PUNA!N14+GELA!N14+ZEMG!N14+TRON!N14+BUMA!N14+SARA!N14+TSIR!N14+DGNA!N14+PANG!N14+DPLA!N14+SJKA!N14+LUNT!N14+SAMC!N14+PHUA!N14+SAMA!N14+GMTU!N14+PHLY!AU14 -> 2 | AV14: =WANG!O14+PUNA!O14+GELA!O14+ZEMG!O14+TRON!O14+BUMA!O14+SARA!O14+TSIR!O14+DGNA!O14+PANG!O14+DPLA!O14+SJKA!O14+LUNT!O14+SAMC!O14+PHUA!O14+SAMA!O14+GMTU!O14+PHLY!AV14 -> 0 | ... BW14: =WANG!AP14+PUNA!AP14+GELA!AP14+ZEMG!AP14+TRON!AP14+BUMA!AP14+SARA!AP14+TSIR!AP14+DGNA!AP14+PANG!AP14+DPLA!AP14+SJKA!AP14+LUNT!AP14+SAMC!AP14+PHUA!AP14+SAMA!AP14+GMTU!AP14+PHLY!BW14 -> 2750 | BY14: =HAA!H14+WANG!AR14+PUNA!AR14+GASA!H14+GELA!AR14+ZEMG!AR14+TRON!AR14+BUMA!AR14+SARA!AR14+TSIR!AR14+DGNA!AR14+PANG!AR14+DPLA!AR14+SJKA!AR14+TRAG!H14+LUNT!AR14+WRMG!H14+NGLM!H14+SAMC!AR14+PHUA!AR14+GEDU!H14+SAMA!AR14+TCHG!H14+GMTU!AR14+PHLY!BY14 -> 0 | BZ14: =HAA!I14+WANG!AS14+PUNA!AS14+GASA!I14+GELA!AS14+ZEMG!AS14+TRON!AS14+BUMA!AS14+SARA!AS14+TSIR!AS14+DGNA!AS14+PANG!AS14+DPLA!AS14+SJKA!AS14+TRAG!I14+LUNT!AS14+WRMG!I14+NGLM!I14+SAMC!AS14+PHUA!AS14+GEDU!I14+SAMA!AS14+TCHG!I14+GMTU!AS14+PHLY!BZ14 -> 0 | CA14: =HAA!J14+WANG!AT14+PUNA!AT14+GASA!J14+GELA!AT14+ZEMG!AT14+TRON!AT14+BUMA!AT14+SARA!AT14+TSIR!AT14+DGNA!AT14+PANG!AT14+DPLA!AT14+SJKA!AT14+TRAG!J14+LUNT!AT14+WRMG!J14+NGLM!J14+SAMC!AT14+PHUA!AT14+GEDU!J14+SAMA!AT14+TCHG!J14+GMTU!AT14+PHLY!CA14 -> 1 | CB14: =HAA!K14+WANG!AU14+PUNA!AU14+GASA!K14+GELA!AU14+ZEMG!AU14+TRON!AU14+BUMA!AU14+SARA!AU14+TSIR!AU14+DGNA!AU14+PANG!AU14+DPLA!AU14+SJKA!AU14+TRAG!K14+LUNT!AU14+WRMG!K14+NGLM!K14+SAMC!AU14+PHUA!AU14+GEDU!K14+SAMA!AU14+TCHG!K14+GMTU!AU14+PHLY!CB14 -> 2 | CC14: =HAA!L14+WANG!AV14+PUNA!AV14+GASA!L14+GELA!AV14+ZEMG!AV14+TRON!AV14+BUMA!AV14+SARA!AV14+TSIR!AV14+DGNA!AV14+PANG!AV14+DPLA!AV14+SJKA!AV14+TRAG!L14+LUNT!AV14+WRMG!L14+NGLM!L14+SAMC!AV14+PHUA!AV14+GEDU!L14+SAMA!AV14+TCHG!L14+GMTU!AV14+PHLY!CC14 -> 2 | CD14: =HAA!M14+WANG!AW14+PUNA!AW14+GASA!M14+GELA!AW14+ZEMG!AW14+TRON!AW14+BUMA!AW14+SARA!AW14+TSIR!AW14+DGNA!AW14+PANG!AW14+DPLA!AW14+SJKA!AW14+TRAG!M14+LUNT!AW14+WRMG!M14+NGLM!M14+SAMC!AW14+PHUA!AW14+GEDU!M14+SAMA!AW14+TCHG!M14+GMTU!AW14+PHLY!CD14 -> 0 | CE14: =HAA!N14+WANG!AX14+PUNA!AX14+GASA!N14+GELA!AX14+ZEMG!AX14+TRON!AX14+BUMA!AX14+SARA!AX14+TSIR!AX14+DGNA!AX14+PANG!AX14+DPLA!AX14+SJKA!AX14+TRAG!N14+LUNT!AX14+WRMG!N14+NGLM!N14+SAMC!AX14+PHUA!AX14+GEDU!N14+SAMA!AX14+TCHG!N14+GMTU!AX14+PHLY!CE14 -> 0 | CF14: =HAA!O14+WANG!AY14+PUNA!AY14+GASA!O14+GELA!AY14+ZEMG!AY14+TRON!AY14+BUMA!AY14+SARA!AY14+TSIR!AY14+DGNA!AY14+PANG!AY14+DPLA!AY14+SJKA!AY14+TRAG!O14+LUNT!AY14+WRMG!O14+NGLM!O14+SAMC!AY14+PHUA!AY14+GEDU!O14+SAMA!AY14+TCHG!O14+GMTU!AY14+PHLY!CF14 -> 0 | ... DF14: =HAA!AO14+WANG!BY14+PUNA!BY14+GASA!AO14+GELA!BY14+ZEMG!BY14+TRON!BY14+BUMA!BY14+SARA!BY14+TSIR!BY14+DGNA!BY14+PANG!BY14+DPLA!BY14+SJKA!BY14+TRAG!AO14+LUNT!BY14+WRMG!AO14+NGLM!AO14+SAMC!BY14+PHUA!BY14+GEDU!AO14+SAMA!BY14+TCHG!AO14+GMTU!BY14+PHLY!DF14 -> 3250 | DG14: =AJ14+BT14+DC14 -> 24 | DH14: =C14*DG14 -> 6000 | DI14: =D14*DG14 -> 7200 | DJ14: =E14*DG14 -> 1200 | DK14: 12 | DL14: =DG14*DK14 -> 288 | DN14: =PARO!H14+HAA!AQ14+WANG!CA14+PUNA!CA14+GASA!AQ14+GELA!CA14+ZEMG!CA14+TRON!CA14+BUMA!CA14+SARA!CA14+TSIR!CA14+DGNA!CA14+PANG!CA14+DPLA!CA14+SJKA!CA14+TRAG!AQ14+MONA!H14+LUNT!CA14+TYSE!H14+PEMA!H14+KNLG!H14+RJNG!H14+WRMG!AQ14+DUSM!H14+GYPG!H14+NGLM!AQ14+SAMC!CA14+PHUA!CA14+TSMA!H14+GEDU!AQ14+SAMA!CA14+TCHG!AQ14+GMTU!CA14+LHAM!H14+PHLY!DH14 -> 1 | DO14: =PARO!I14+HAA!AR14+WANG!CB14+PUNA!CB14+GASA!AR14+GELA!CB14+ZEMG!CB14+TRON!CB14+BUMA!CB14+SARA!CB14+TSIR!CB14+DGNA!CB14+PANG!CB14+DPLA!CB14+SJKA!CB14+TRAG!AR14+MONA!I14+LUNT!CB14+TYSE!I14+PEMA!I14+KNLG!I14+RJNG!I14+WRMG!AR14+DUSM!I14+GYPG!I14+NGLM!AR14+SAMC!CB14+PHUA!CB14+TSMA!I14+GEDU!AR14+SAMA!CB14+TCHG!AR14+GMTU!CB14+LHAM!I14+PHLY!DI14 -> 0 | DP14: =PARO!J14+HAA!AS14+WANG!CC14+PUNA!CC14+GASA!AS14+GELA!CC14+ZEMG!CC14+TRON!CC14+BUMA!CC14+SARA!CC14+TSIR!CC14+DGNA!CC14+PANG!CC14+DPLA!CC14+SJKA!CC14+TRAG!AS14+MONA!J14+LUNT!CC14+TYSE!J14+PEMA!J14+KNLG!J14+RJNG!J14+WRMG!AS14+DUSM!J14+GYPG!J14+NGLM!AS14+SAMC!CC14+PHUA!CC14+TSMA!J14+GEDU!AS14+SAMA!CC14+TCHG!AS14+GMTU!CC14+LHAM!J14+PHLY!DJ14 -> 0 | DQ14: =PARO!K14+HAA!AT14+WANG!CD14+PUNA!CD14+GASA!AT14+GELA!CD14+ZEMG!CD14+TRON!CD14+BUMA!CD14+SARA!CD14+TSIR!CD14+DGNA!CD14+PANG!CD14+DPLA!CD14+SJKA!CD14+TRAG!AT14+MONA!K14+LUNT!CD14+TYSE!K14+PEMA!K14+KNLG!K14+RJNG!K14+WRMG!AT14+DUSM!K14+GYPG!K14+NGLM!AT14+SAMC!CD14+PHUA!CD14+TSMA!K14+GEDU!AT14+SAMA!CD14+TCHG!AT14+GMTU!CD14+LHAM!K14+PHLY!DK14 -> 0 | DR14: =PARO!L14+HAA!AU14+WANG!CE14+PUNA!CE14+GASA!AU14+GELA!CE14+ZEMG!CE14+TRON!CE14+BUMA!CE14+SARA!CE14+TSIR!CE14+DGNA!CE14+PANG!CE14+DPLA!CE14+SJKA!CE14+TRAG!AU14+MONA!L14+LUNT!CE14+TYSE!L14+PEMA!L14+KNLG!L14+RJNG!L14+WRMG!AU14+DUSM!L14+GYPG!L14+NGLM!AU14+SAMC!CE14+PHUA!CE14+TSMA!L14+GEDU!AU14+SAMA!CE14+TCHG!AU14+GMTU!CE14+LHAM!L14+PHLY!DL14 -> 0 | DS14: =PARO!M14+HAA!AV14+WANG!CF14+PUNA!CF14+GASA!AV14+GELA!CF14+ZEMG!CF14+TRON!CF14+BUMA!CF14+SARA!CF14+TSIR!CF14+DGNA!CF14+PANG!CF14+DPLA!CF14+SJKA!CF14+TRAG!AV14+MONA!M14+LUNT!CF14+TYSE!M14+PEMA!M14+KNLG!M14+RJNG!M14+WRMG!AV14+DUSM!M14+GYPG!M14+NGLM!AV14+SAMC!CF14+PHUA!CF14+TSMA!M14+GEDU!AV14+SAMA!CF14+TCHG!AV14+GMTU!CF14+LHAM!M14+PHLY!DM14 -> 3 | DT14: =PARO!N14+HAA!AW14+WANG!CG14+PUNA!CG14+GASA!AW14+GELA!CG14+ZEMG!CG14+TRON!CG14+BUMA!CG14+SARA!CG14+TSIR!CG14+DGNA!CG14+PANG!CG14+DPLA!CG14+SJKA!CG14+TRAG!AW14+MONA!N14+LUNT!CG14+TYSE!N14+PEMA!N14+KNLG!N14+RJNG!N14+WRMG!AW14+DUSM!N14+GYPG!N14+NGLM!AW14+SAMC!CG14+PHUA!CG14+TSMA!N14+GEDU!AW14+SAMA!CG14+TCHG!AW14+GMTU!CG14+LHAM!N14+PHLY!DN14 -> 0 | DU14: =PARO!O14+HAA!AX14+WANG!CH14+PUNA!CH14+GASA!AX14+GELA!CH14+ZEMG!CH14+TRON!CH14+BUMA!CH14+SARA!CH14+TSIR!CH14+DGNA!CH14+PANG!CH14+DPLA!CH14+SJKA!CH14+TRAG!AX14+MONA!O14+LUNT!CH14+TYSE!O14+PEMA!O14+KNLG!O14+RJNG!O14+WRMG!AX14+DUSM!O14+GYPG!O14+NGLM!AX14+SAMC!CH14+PHUA!CH14+TSMA!O14+GEDU!AX14+SAMA!CH14+TCHG!AX14+GMTU!CH14+LHAM!O14+PHLY!DO14 -> 0 | ... EV14: =PARO!AP14+HAA!BY14+WANG!DI14+PUNA!DI14+GASA!BY14+GELA!DI14+ZEMG!DI14+TRON!DI14+BUMA!DI14+SARA!DI14+TSIR!DI14+DGNA!DI14+PANG!DI14+DPLA!DI14+SJKA!DI14+TRAG!BY14+MONA!AP14+LUNT!DI14+TYSE!AP14+PEMA!AP14+KNLG!AP14+RJNG!AP14+WRMG!BY14+DUSM!AP14+GYPG!AP14+NGLM!BY14+SAMC!DI14+PHUA!DI14+TSMA!AP14+GEDU!BY14+SAMA!DI14+TCHG!BY14+GMTU!DI14+LHAM!AP14+PHLY!EP14 -> 1750 | EX14: =PARO!AR14+HAA!CA14+WANG!DK14+PUNA!DK14+GASA!CA14+GELA!DK14+ZEMG!DK14+TRON!DK14+BUMA!DK14+SARA!DK14+TSIR!DK14+DGNA!DK14+PANG!DK14+DPLA!DK14+SJKA!DK14+TRAG!CA14+MONA!AR14+LUNT!DK14+TYSE!AR14+PEMA!AR14+KNLG!AR14+RJNG!AR14+WRMG!CA14+DUSM!AR14+GYPG!AR14+NGLM!CA14+SAMC!DK14+PHUA!DK14+TSMA!AR14+GEDU!CA14+SAMA!DK14+TCHG!CA14+GMTU!DK14+LHAM!AR14+PHLY!ER14 -> 0 | EY14: =PARO!AS14+HAA!CB14+WANG!DL14+PUNA!DL14+GASA!CB14+GELA!DL14+ZEMG!DL14+TRON!DL14+BUMA!DL14+SARA!DL14+TSIR!DL14+DGNA!DL14+PANG!DL14+DPLA!DL14+SJKA!DL14+TRAG!CB14+MONA!AS14+LUNT!DL14+TYSE!AS14+PEMA!AS14+KNLG!AS14+RJNG!AS14+WRMG!CB14+DUSM!AS14+GYPG!AS14+NGLM!CB14+SAMC!DL14+PHUA!DL14+TSMA!AS14+GEDU!CB14+SAMA!DL14+TCHG!CB14+GMTU!DL14+LHAM!AS14+PHLY!ES14 -> 1 | EZ14: =PARO!AT14+HAA!CC14+WANG!DM14+PUNA!DM14+GASA!CC14+GELA!DM14+ZEMG!DM14+TRON!DM14+BUMA!DM14+SARA!DM14+TSIR!DM14+DGNA!DM14+PANG!DM14+DPLA!DM14+SJKA!DM14+TRAG!CC14+MONA!AT14+LUNT!DM14+TYSE!AT14+PEMA!AT14+KNLG!AT14+RJNG!AT14+WRMG!CC14+DUSM!AT14+GYPG!AT14+NGLM!CC14+SAMC!DM14+PHUA!DM14+TSMA!AT14+GEDU!CC14+SAMA!DM14+TCHG!CC14+GMTU!DM14+LHAM!AT14+PHLY!ET14 -> 1 | FA14: =PARO!AU14+HAA!CD14+WANG!DN14+PUNA!DN14+GASA!CD14+GELA!DN14+ZEMG!DN14+TRON!DN14+BUMA!DN14+SARA!DN14+TSIR!DN14+DGNA!DN14+PANG!DN14+DPLA!DN14+SJKA!DN14+TRAG!CD14+MONA!AU14+LUNT!DN14+TYSE!AU14+PEMA!AU14+KNLG!AU14+RJNG!AU14+WRMG!CD14+DUSM!AU14+GYPG!AU14+NGLM!CD14+SAMC!DN14+PHUA!DN14+TSMA!AU14+GEDU!CD14+SAMA!DN14+TCHG!CD14+GMTU!DN14+LHAM!AU14+PHLY!EU14 -> 0 | FB14: =PARO!AV14+HAA!CE14+WANG!DO14+PUNA!DO14+GASA!CE14+GELA!DO14+ZEMG!DO14+TRON!DO14+BUMA!DO14+SARA!DO14+TSIR!DO14+DGNA!DO14+PANG!DO14+DPLA!DO14+SJKA!DO14+TRAG!CE14+MONA!AV14+LUNT!DO14+TYSE!AV14+PEMA!AV14+KNLG!AV14+RJNG!AV14+WRMG!CE14+DUSM!AV14+GYPG!AV14+NGLM!CE14+SAMC!DO14+PHUA!DO14+TSMA!AV14+GEDU!CE14+SAMA!DO14+TCHG!CE14+GMTU!DO14+LHAM!AV14+PHLY!EV14 -> 0 | FC14: =PARO!AW14+HAA!CF14+WANG!DP14+PUNA!DP14+GASA!CF14+GELA!DP14+ZEMG!DP14+TRON!DP14+BUMA!DP14+SARA!DP14+TSIR!DP14+DGNA!DP14+PANG!DP14+DPLA!DP14+SJKA!DP14+TRAG!CF14+MONA!AW14+LUNT!DP14+TYSE!AW14+PEMA!AW14+KNLG!AW14+RJNG!AW14+WRMG!CF14+DUSM!AW14+GYPG!AW14+NGLM!CF14+SAMC!DP14+PHUA!DP14+TSMA!AW14+GEDU!CF14+SAMA!DP14+TCHG!CF14+GMTU!DP14+LHAM!AW14+PHLY!EW14 -> 1 | FD14: =PARO!AX14+HAA!CG14+WANG!DQ14+PUNA!DQ14+GASA!CG14+GELA!DQ14+ZEMG!DQ14+TRON!DQ14+BUMA!DQ14+SARA!DQ14+TSIR!DQ14+DGNA!DQ14+PANG!DQ14+DPLA!DQ14+SJKA!DQ14+TRAG!CG14+MONA!AX14+LUNT!DQ14+TYSE!AX14+PEMA!AX14+KNLG!AX14+RJNG!AX14+WRMG!CG14+DUSM!AX14+GYPG!AX14+NGLM!CG14+SAMC!DQ14+PHUA!DQ14+TSMA!AX14+GEDU!CG14+SAMA!DQ14+TCHG!CG14+GMTU!DQ14+LHAM!AX14+PHLY!EX14 -> 0 | FE14: =PARO!AY14+HAA!CH14+WANG!DR14+PUNA!DR14+GASA!CH14+GELA!DR14+ZEMG!DR14+TRON!DR14+BUMA!DR14+SARA!DR14+TSIR!DR14+DGNA!DR14+PANG!DR14+DPLA!DR14+SJKA!DR14+TRAG!CH14+MONA!AY14+LUNT!DR14+TYSE!AY14+PEMA!AY14+KNLG!AY14+RJNG!AY14+WRMG!CH14+DUSM!AY14+GYPG!AY14+NGLM!CH14+SAMC!DR14+PHUA!DR14+TSMA!AY14+GEDU!CH14+SAMA!DR14+TCHG!CH14+GMTU!DR14+LHAM!AY14+PHLY!EY14 -> 0 | ... GA14: =PARO!BU14+HAA!DD14+WANG!EN14+PUNA!EN14+GASA!DD14+GELA!EN14+ZEMG!EN14+TRON!EN14+BUMA!EN14+SARA!EN14+TSIR!EN14+DGNA!EN14+PANG!EN14+DPLA!EN14+SJKA!EN14+TRAG!DD14+MONA!BU14+LUNT!EN14+TYSE!BU14+PEMA!BU14+KNLG!BU14+RJNG!BU14+WRMG!DD14+DUSM!BU14+GYPG!BU14+NGLM!DD14+SAMC!EN14+PHUA!EN14+TSMA!BU14+GEDU!DD14+SAMA!EN14+TCHG!DD14+GMTU!EN14+LHAM!BU14+PHLY!FU14 -> 2 | GB14: =PARO!BV14+HAA!DE14+WANG!EO14+PUNA!EO14+GASA!DE14+GELA!EO14+ZEMG!EO14+TRON!EO14+BUMA!EO14+SARA!EO14+TSIR!EO14+DGNA!EO14+PANG!EO14+DPLA!EO14+SJKA!EO14+TRAG!DE14+MONA!BW14+LUNT!EO14+TYSE!BW14+PEMA!BW14+KNLG!BW14+RJNG!BV14+WRMG!DE14+DUSM!BW14+GYPG!BW14+NGLM!DE14+SAMC!EO14+PHUA!EO14+TSMA!BV14+GEDU!DE14+SAMA!EO14+TCHG!DE14+GMTU!EO14+LHAM!BV14+PHLY!FV14 -> 20 | GC14: =PARO!BW14+HAA!DF14+WANG!EP14+PUNA!EP14+GASA!DF14+GELA!EP14+ZEMG!EP14+TRON!EP14+BUMA!EP14+SARA!EP14+TSIR!EP14+DGNA!EP14+PANG!EP14+DPLA!EP14+SJKA!EP14+TRAG!DF14+MONA!BX14+LUNT!EP14+TYSE!BX14+PEMA!BX14+KNLG!BX14+RJNG!BW14+WRMG!DF14+DUSM!BX14+GYPG!BX14+NGLM!DF14+SAMC!EP14+PHUA!EP14+TSMA!BW14+GEDU!DF14+SAMA!EP14+TCHG!DF14+GMTU!EP14+LHAM!BW14+PHLY!FW14 -> 6000 | GD14: =PARO!BX14+HAA!DG14+WANG!EQ14+PUNA!EQ14+GASA!DG14+GELA!EQ14+ZEMG!EQ14+TRON!EQ14+BUMA!EQ14+SARA!EQ14+TSIR!EQ14+DGNA!EQ14+PANG!EQ14+DPLA!EQ14+SJKA!EQ14+TRAG!DG14+MONA!BY14+LUNT!EQ14+TYSE!BY14+PEMA!BY14+KNLG!BY14+RJNG!BX14+WRMG!DG14+DUSM!BY14+GYPG!BY14+NGLM!DG14+SAMC!EQ14+PHUA!EQ14+TSMA!BX14+GEDU!DG14+SAMA!EQ14+TCHG!DG14+GMTU!EQ14+LHAM!BX14+PHLY!FX14 -> 1000 | GE14: =PARO!BY14+HAA!DH14+WANG!ER14+PUNA!ER14+GASA!DH14+GELA!ER14+ZEMG!ER14+TRON!ER14+BUMA!ER14+SARA!ER14+TSIR!ER14+DGNA!ER14+PANG!ER14+DPLA!ER14+SJKA!ER14+TRAG!DH14+MONA!BZ14+LUNT!ER14+TYSE!BZ14+PEMA!BZ14+KNLG!BZ14+RJNG!BY14+WRMG!DH14+DUSM!BZ14+GYPG!BZ14+NGLM!DH14+SAMC!ER14+PHUA!ER14+TSMA!BY14+GEDU!DH14+SAMA!ER14+TCHG!DH14+GMTU!ER14+LHAM!BY14+PHLY!FY14 -> 5000 | GG14: =PARO!CA14+HAA!DJ14+WANG!ET14+PUNA!ET14+GASA!DJ14+GELA!ET14+ZEMG!ET14+TRON!ET14+BUMA!ET14+SARA!ET14+TSIR!ET14+DGNA!ET14+PANG!ET14+DPLA!ET14+SJKA!ET14+TRAG!DJ14+MONA!CB14+LUNT!ET14+TYSE!CB14+PEMA!CB14+KNLG!CB14+RJNG!CA14+WRMG!DJ14+DUSM!CB14+GYPG!CB14+NGLM!DJ14+SAMC!ET14+PHUA!ET14+TSMA!CA14+GEDU!DJ14+SAMA!ET14+TCHG!DJ14+GMTU!ET14+LHAM!CA14+PHLY!GA14 -> 0 | GH14: =PARO!CB14+HAA!DK14+WANG!EU14+PUNA!EU14+GASA!DK14+GELA!EU14+ZEMG!EU14+TRON!EU14+BUMA!EU14+SARA!EU14+TSIR!EU14+DGNA!EU14+PANG!EU14+DPLA!EU14+SJKA!EU14+TRAG!DK14+MONA!CC14+LUNT!EU14+TYSE!CC14+PEMA!CC14+KNLG!CC14+RJNG!CB14+WRMG!DK14+DUSM!CC14+GYPG!CC14+NGLM!DK14+SAMC!EU14+PHUA!EU14+TSMA!CB14+GEDU!DK14+SAMA!EU14+TCHG!DK14+GMTU!EU14+LHAM!CB14+PHLY!GB14 -> 2 | GI14: =PARO!CC14+HAA!DL14+WANG!EV14+PUNA!EV14+GASA!DL14+GELA!EV14+ZEMG!EV14+TRON!EV14+BUMA!EV14+SARA!EV14+TSIR!EV14+DGNA!EV14+PANG!EV14+DPLA!EV14+SJKA!EV14+TRAG!DL14+MONA!CD14+LUNT!EV14+TYSE!CD14+PEMA!CD14+KNLG!CD14+RJNG!CC14+WRMG!DL14+DUSM!CD14+GYPG!CD14+NGLM!DL14+SAMC!EV14+PHUA!EV14+TSMA!CC14+GEDU!DL14+SAMA!EV14+TCHG!DL14+GMTU!EV14+LHAM!CC14+PHLY!GC14 -> 1 | GJ14: =PARO!CD14+HAA!DM14+WANG!EW14+PUNA!EW14+GASA!DM14+GELA!EW14+ZEMG!EW14+TRON!EW14+BUMA!EW14+SARA!EW14+TSIR!EW14+DGNA!EW14+PANG!EW14+DPLA!EW14+SJKA!EW14+TRAG!DM14+MONA!CE14+LUNT!EW14+TYSE!CE14+PEMA!CE14+KNLG!CE14+RJNG!CD14+WRMG!DM14+DUSM!CE14+GYPG!CE14+NGLM!DM14+SAMC!EW14+PHUA!EW14+TSMA!CD14+GEDU!DM14+SAMA!EW14+TCHG!DM14+GMTU!EW14+LHAM!CD14+PHLY!GD14 -> 4 | GK14: =PARO!CE14+HAA!DN14+WANG!EX14+PUNA!EX14+GASA!DN14+GELA!EX14+ZEMG!EX14+TRON!EX14+BUMA!EX14+SARA!EX14+TSIR!EX14+DGNA!EX14+PANG!EX14+DPLA!EX14+SJKA!EX14+TRAG!DN14+MONA!CF14+LUNT!EX14+TYSE!CF14+PEMA!CF14+KNLG!CF14+RJNG!CE14+WRMG!DN14+DUSM!CF14+GYPG!CF14+NGLM!DN14+SAMC!EX14+PHUA!EX14+TSMA!CE14+GEDU!DN14+SAMA!EX14+TCHG!DN14+GMTU!EX14+LHAM!CE14+PHLY!GE14 -> 0 | GL14: =PARO!CF14+HAA!DO14+WANG!EY14+PUNA!EY14+GASA!DO14+GELA!EY14+ZEMG!EY14+TRON!EY14+BUMA!EY14+SARA!EY14+TSIR!EY14+DGNA!EY14+PANG!EY14+DPLA!EY14+SJKA!EY14+TRAG!DO14+MONA!CG14+LUNT!EY14+TYSE!CG14+PEMA!CG14+KNLG!CG14+RJNG!CF14+WRMG!DO14+DUSM!CG14+GYPG!CG14+NGLM!DO14+SAMC!EY14+PHUA!EY14+TSMA!CF14+GEDU!DO14+SAMA!EY14+TCHG!DO14+GMTU!EY14+LHAM!CF14+PHLY!GF14 -> 0 | GM14: =PARO!CG14+HAA!DP14+WANG!EZ14+PUNA!EZ14+GASA!DP14+GELA!EZ14+ZEMG!EZ14+TRON!EZ14+BUMA!EZ14+SARA!EZ14+TSIR!EZ14+DGNA!EZ14+PANG!EZ14+DPLA!EZ14+SJKA!EZ14+TRAG!DP14+MONA!CH14+LUNT!EZ14+TYSE!CH14+PEMA!CH14+KNLG!CH14+RJNG!CG14+WRMG!DP14+DUSM!CH14+GYPG!CH14+NGLM!DP14+SAMC!EZ14+PHUA!EZ14+TSMA!CG14+GEDU!DP14+SAMA!EZ14+TCHG!DP14+GMTU!EZ14+LHAM!CG14+PHLY!GG14 -> 0 | GN14: =PARO!CH14+HAA!DQ14+WANG!FA14+PUNA!FA14+GASA!DQ14+GELA!FA14+ZEMG!FA14+TRON!FA14+BUMA!FA14+SARA!FA14+TSIR!FA14+DGNA!FA14+PANG!FA14+DPLA!FA14+SJKA!FA14+TRAG!DQ14+MONA!CI14+LUNT!FA14+TYSE!CI14+PEMA!CI14+KNLG!CI14+RJNG!CH14+WRMG!DQ14+DUSM!CI14+GYPG!CI14+NGLM!DQ14+SAMC!FA14+PHUA!FA14+TSMA!CH14+GEDU!DQ14+SAMA!FA14+TCHG!DQ14+GMTU!FA14+LHAM!CH14+PHLY!GH14 -> 1 | ... HO14: =PARO!DI14+HAA!ER14+WANG!GB14+PUNA!GB14+GASA!ER14+GELA!GB14+ZEMG!GB14+TRON!GB14+BUMA!GB14+SARA!GB14+TSIR!GB14+DGNA!GB14+PANG!GB14+DPLA!GB14+SJKA!GB14+TRAG!ER14+MONA!DJ14+LUNT!GB14+TYSE!DJ14+PEMA!DJ14+KNLG!DJ14+RJNG!DI14+WRMG!ER14+DUSM!DJ14+GYPG!DJ14+NGLM!ER14+SAMC!GB14+PHUA!GB14+TSMA!DI14+GEDU!ER14+SAMA!GB14+TCHG!ER14+GMTU!GB14+LHAM!DI14+PHLY!HI14 -> 3250 | HQ14: =ES14+GB14+HL14 -> 40 | HR14: =C14*HQ14 -> 10000 | HS14: =D14*HQ14 -> 12000 | HT14: =E14*HQ14 -> 2000 | HU14: 12 | HV14: =HQ14*HU14 -> 480 | IN14: =AJ14+BT14+DC14+ES14+GB14+HL14 -> 64 | IO14: =AK14+BU14+DD14+ET14+GC14+HM14 -> 19200 | IP14: =AL14+BV14+DE14+EU14+GD14+HN14 -> 3200 | IQ14: =AM14+BW14+DF14+EV14+GE14+HO14 -> 16000
A15: 13 | B15: Natural soap- nut hand made soap | C15: 150 | D15: 180 | E15: =D15-C15 -> 30 | F15: No Discount | H15: =PHLY!H15 -> 0 | I15: =PHLY!I15 -> 0 | J15: =PHLY!J15 -> 0 | K15: =PHLY!K15 -> 0 | L15: =PHLY!L15 -> 0 | M15: =PHLY!M15 -> 0 | N15: =PHLY!N15 -> 0 | O15: =PHLY!O15 -> 0 | ... AM15: =PHLY!AM15 -> 0 | AO15: =WANG!H15+PUNA!H15+GELA!H15+ZEMG!H15+TRON!H15+BUMA!H15+SARA!H15+TSIR!H15+DGNA!H15+PANG!H15+DPLA!H15+SJKA!H15+LUNT!H15+SAMC!H15+PHUA!H15+SAMA!H15+GMTU!H15+PHLY!AO15 -> 0 | AP15: =WANG!I15+PUNA!I15+GELA!I15+ZEMG!I15+TRON!I15+BUMA!I15+SARA!I15+TSIR!I15+DGNA!I15+PANG!I15+DPLA!I15+SJKA!I15+LUNT!I15+SAMC!I15+PHUA!I15+SAMA!I15+GMTU!I15+PHLY!AP15 -> 0 | AQ15: =WANG!J15+PUNA!J15+GELA!J15+ZEMG!J15+TRON!J15+BUMA!J15+SARA!J15+TSIR!J15+DGNA!J15+PANG!J15+DPLA!J15+SJKA!J15+LUNT!J15+SAMC!J15+PHUA!J15+SAMA!J15+GMTU!J15+PHLY!AQ15 -> 0 | AR15: =WANG!K15+PUNA!K15+GELA!K15+ZEMG!K15+TRON!K15+BUMA!K15+SARA!K15+TSIR!K15+DGNA!K15+PANG!K15+DPLA!K15+SJKA!K15+LUNT!K15+SAMC!K15+PHUA!K15+SAMA!K15+GMTU!K15+PHLY!AR15 -> 0 | AS15: =WANG!L15+PUNA!L15+GELA!L15+ZEMG!L15+TRON!L15+BUMA!L15+SARA!L15+TSIR!L15+DGNA!L15+PANG!L15+DPLA!L15+SJKA!L15+LUNT!L15+SAMC!L15+PHUA!L15+SAMA!L15+GMTU!L15+PHLY!AS15 -> 1 | AT15: =WANG!M15+PUNA!M15+GELA!M15+ZEMG!M15+TRON!M15+BUMA!M15+SARA!M15+TSIR!M15+DGNA!M15+PANG!M15+DPLA!M15+SJKA!M15+LUNT!M15+SAMC!M15+PHUA!M15+SAMA!M15+GMTU!M15+PHLY!AT15 -> 0 | AU15: =WANG!N15+PUNA!N15+GELA!N15+ZEMG!N15+TRON!N15+BUMA!N15+SARA!N15+TSIR!N15+DGNA!N15+PANG!N15+DPLA!N15+SJKA!N15+LUNT!N15+SAMC!N15+PHUA!N15+SAMA!N15+GMTU!N15+PHLY!AU15 -> 0 | AV15: =WANG!O15+PUNA!O15+GELA!O15+ZEMG!O15+TRON!O15+BUMA!O15+SARA!O15+TSIR!O15+DGNA!O15+PANG!O15+DPLA!O15+SJKA!O15+LUNT!O15+SAMC!O15+PHUA!O15+SAMA!O15+GMTU!O15+PHLY!AV15 -> 0 | ... BW15: =WANG!AP15+PUNA!AP15+GELA!AP15+ZEMG!AP15+TRON!AP15+BUMA!AP15+SARA!AP15+TSIR!AP15+DGNA!AP15+PANG!AP15+DPLA!AP15+SJKA!AP15+LUNT!AP15+SAMC!AP15+PHUA!AP15+SAMA!AP15+GMTU!AP15+PHLY!BW15 -> 7650 | BY15: =HAA!H15+WANG!AR15+PUNA!AR15+GASA!H15+GELA!AR15+ZEMG!AR15+TRON!AR15+BUMA!AR15+SARA!AR15+TSIR!AR15+DGNA!AR15+PANG!AR15+DPLA!AR15+SJKA!AR15+TRAG!H15+LUNT!AR15+WRMG!H15+NGLM!H15+SAMC!AR15+PHUA!AR15+GEDU!H15+SAMA!AR15+TCHG!H15+GMTU!AR15+PHLY!BY15 -> 0 | BZ15: =HAA!I15+WANG!AS15+PUNA!AS15+GASA!I15+GELA!AS15+ZEMG!AS15+TRON!AS15+BUMA!AS15+SARA!AS15+TSIR!AS15+DGNA!AS15+PANG!AS15+DPLA!AS15+SJKA!AS15+TRAG!I15+LUNT!AS15+WRMG!I15+NGLM!I15+SAMC!AS15+PHUA!AS15+GEDU!I15+SAMA!AS15+TCHG!I15+GMTU!AS15+PHLY!BZ15 -> 0 | CA15: =HAA!J15+WANG!AT15+PUNA!AT15+GASA!J15+GELA!AT15+ZEMG!AT15+TRON!AT15+BUMA!AT15+SARA!AT15+TSIR!AT15+DGNA!AT15+PANG!AT15+DPLA!AT15+SJKA!AT15+TRAG!J15+LUNT!AT15+WRMG!J15+NGLM!J15+SAMC!AT15+PHUA!AT15+GEDU!J15+SAMA!AT15+TCHG!J15+GMTU!AT15+PHLY!CA15 -> 0 | CB15: =HAA!K15+WANG!AU15+PUNA!AU15+GASA!K15+GELA!AU15+ZEMG!AU15+TRON!AU15+BUMA!AU15+SARA!AU15+TSIR!AU15+DGNA!AU15+PANG!AU15+DPLA!AU15+SJKA!AU15+TRAG!K15+LUNT!AU15+WRMG!K15+NGLM!K15+SAMC!AU15+PHUA!AU15+GEDU!K15+SAMA!AU15+TCHG!K15+GMTU!AU15+PHLY!CB15 -> 8 | CC15: =HAA!L15+WANG!AV15+PUNA!AV15+GASA!L15+GELA!AV15+ZEMG!AV15+TRON!AV15+BUMA!AV15+SARA!AV15+TSIR!AV15+DGNA!AV15+PANG!AV15+DPLA!AV15+SJKA!AV15+TRAG!L15+LUNT!AV15+WRMG!L15+NGLM!L15+SAMC!AV15+PHUA!AV15+GEDU!L15+SAMA!AV15+TCHG!L15+GMTU!AV15+PHLY!CC15 -> 0 | CD15: =HAA!M15+WANG!AW15+PUNA!AW15+GASA!M15+GELA!AW15+ZEMG!AW15+TRON!AW15+BUMA!AW15+SARA!AW15+TSIR!AW15+DGNA!AW15+PANG!AW15+DPLA!AW15+SJKA!AW15+TRAG!M15+LUNT!AW15+WRMG!M15+NGLM!M15+SAMC!AW15+PHUA!AW15+GEDU!M15+SAMA!AW15+TCHG!M15+GMTU!AW15+PHLY!CD15 -> #VALUE! | CE15: =HAA!N15+WANG!AX15+PUNA!AX15+GASA!N15+GELA!AX15+ZEMG!AX15+TRON!AX15+BUMA!AX15+SARA!AX15+TSIR!AX15+DGNA!AX15+PANG!AX15+DPLA!AX15+SJKA!AX15+TRAG!N15+LUNT!AX15+WRMG!N15+NGLM!N15+SAMC!AX15+PHUA!AX15+GEDU!N15+SAMA!AX15+TCHG!N15+GMTU!AX15+PHLY!CE15 -> 1 | CF15: =HAA!O15+WANG!AY15+PUNA!AY15+GASA!O15+GELA!AY15+ZEMG!AY15+TRON!AY15+BUMA!AY15+SARA!AY15+TSIR!AY15+DGNA!AY15+PANG!AY15+DPLA!AY15+SJKA!AY15+TRAG!O15+LUNT!AY15+WRMG!O15+NGLM!O15+SAMC!AY15+PHUA!AY15+GEDU!O15+SAMA!AY15+TCHG!O15+GMTU!AY15+PHLY!CF15 -> 2 | ... DF15: =HAA!AO15+WANG!BY15+PUNA!BY15+GASA!AO15+GELA!BY15+ZEMG!BY15+TRON!BY15+BUMA!BY15+SARA!BY15+TSIR!BY15+DGNA!BY15+PANG!BY15+DPLA!BY15+SJKA!BY15+TRAG!AO15+LUNT!BY15+WRMG!AO15+NGLM!AO15+SAMC!BY15+PHUA!BY15+GEDU!AO15+SAMA!BY15+TCHG!AO15+GMTU!BY15+PHLY!DF15 -> 7800 | DG15: =AJ15+BT15+DC15 -> 103 | DH15: =C15*DG15 -> 15450 | DI15: =D15*DG15 -> 18540 | DJ15: =E15*DG15 -> 3090 | DN15: =PARO!H15+HAA!AQ15+WANG!CA15+PUNA!CA15+GASA!AQ15+GELA!CA15+ZEMG!CA15+TRON!CA15+BUMA!CA15+SARA!CA15+TSIR!CA15+DGNA!CA15+PANG!CA15+DPLA!CA15+SJKA!CA15+TRAG!AQ15+MONA!H15+LUNT!CA15+TYSE!H15+PEMA!H15+KNLG!H15+RJNG!H15+WRMG!AQ15+DUSM!H15+GYPG!H15+NGLM!AQ15+SAMC!CA15+PHUA!CA15+TSMA!H15+GEDU!AQ15+SAMA!CA15+TCHG!AQ15+GMTU!CA15+LHAM!H15+PHLY!DH15 -> 0 | DO15: =PARO!I15+HAA!AR15+WANG!CB15+PUNA!CB15+GASA!AR15+GELA!CB15+ZEMG!CB15+TRON!CB15+BUMA!CB15+SARA!CB15+TSIR!CB15+DGNA!CB15+PANG!CB15+DPLA!CB15+SJKA!CB15+TRAG!AR15+MONA!I15+LUNT!CB15+TYSE!I15+PEMA!I15+KNLG!I15+RJNG!I15+WRMG!AR15+DUSM!I15+GYPG!I15+NGLM!AR15+SAMC!CB15+PHUA!CB15+TSMA!I15+GEDU!AR15+SAMA!CB15+TCHG!AR15+GMTU!CB15+LHAM!I15+PHLY!DI15 -> 0 | DP15: =PARO!J15+HAA!AS15+WANG!CC15+PUNA!CC15+GASA!AS15+GELA!CC15+ZEMG!CC15+TRON!CC15+BUMA!CC15+SARA!CC15+TSIR!CC15+DGNA!CC15+PANG!CC15+DPLA!CC15+SJKA!CC15+TRAG!AS15+MONA!J15+LUNT!CC15+TYSE!J15+PEMA!J15+KNLG!J15+RJNG!J15+WRMG!AS15+DUSM!J15+GYPG!J15+NGLM!AS15+SAMC!CC15+PHUA!CC15+TSMA!J15+GEDU!AS15+SAMA!CC15+TCHG!AS15+GMTU!CC15+LHAM!J15+PHLY!DJ15 -> 0 | DQ15: =PARO!K15+HAA!AT15+WANG!CD15+PUNA!CD15+GASA!AT15+GELA!CD15+ZEMG!CD15+TRON!CD15+BUMA!CD15+SARA!CD15+TSIR!CD15+DGNA!CD15+PANG!CD15+DPLA!CD15+SJKA!CD15+TRAG!AT15+MONA!K15+LUNT!CD15+TYSE!K15+PEMA!K15+KNLG!K15+RJNG!K15+WRMG!AT15+DUSM!K15+GYPG!K15+NGLM!AT15+SAMC!CD15+PHUA!CD15+TSMA!K15+GEDU!AT15+SAMA!CD15+TCHG!AT15+GMTU!CD15+LHAM!K15+PHLY!DK15 -> 0 | DR15: =PARO!L15+HAA!AU15+WANG!CE15+PUNA!CE15+GASA!AU15+GELA!CE15+ZEMG!CE15+TRON!CE15+BUMA!CE15+SARA!CE15+TSIR!CE15+DGNA!CE15+PANG!CE15+DPLA!CE15+SJKA!CE15+TRAG!AU15+MONA!L15+LUNT!CE15+TYSE!L15+PEMA!L15+KNLG!L15+RJNG!L15+WRMG!AU15+DUSM!L15+GYPG!L15+NGLM!AU15+SAMC!CE15+PHUA!CE15+TSMA!L15+GEDU!AU15+SAMA!CE15+TCHG!AU15+GMTU!CE15+LHAM!L15+PHLY!DL15 -> 2 | DS15: =PARO!M15+HAA!AV15+WANG!CF15+PUNA!CF15+GASA!AV15+GELA!CF15+ZEMG!CF15+TRON!CF15+BUMA!CF15+SARA!CF15+TSIR!CF15+DGNA!CF15+PANG!CF15+DPLA!CF15+SJKA!CF15+TRAG!AV15+MONA!M15+LUNT!CF15+TYSE!M15+PEMA!M15+KNLG!M15+RJNG!M15+WRMG!AV15+DUSM!M15+GYPG!M15+NGLM!AV15+SAMC!CF15+PHUA!CF15+TSMA!M15+GEDU!AV15+SAMA!CF15+TCHG!AV15+GMTU!CF15+LHAM!M15+PHLY!DM15 -> 1 | DT15: =PARO!N15+HAA!AW15+WANG!CG15+PUNA!CG15+GASA!AW15+GELA!CG15+ZEMG!CG15+TRON!CG15+BUMA!CG15+SARA!CG15+TSIR!CG15+DGNA!CG15+PANG!CG15+DPLA!CG15+SJKA!CG15+TRAG!AW15+MONA!N15+LUNT!CG15+TYSE!N15+PEMA!N15+KNLG!N15+RJNG!N15+WRMG!AW15+DUSM!N15+GYPG!N15+NGLM!AW15+SAMC!CG15+PHUA!CG15+TSMA!N15+GEDU!AW15+SAMA!CG15+TCHG!AW15+GMTU!CG15+LHAM!N15+PHLY!DN15 -> 0 | DU15: =PARO!O15+HAA!AX15+WANG!CH15+PUNA!CH15+GASA!AX15+GELA!CH15+ZEMG!CH15+TRON!CH15+BUMA!CH15+SARA!CH15+TSIR!CH15+DGNA!CH15+PANG!CH15+DPLA!CH15+SJKA!CH15+TRAG!AX15+MONA!O15+LUNT!CH15+TYSE!O15+PEMA!O15+KNLG!O15+RJNG!O15+WRMG!AX15+DUSM!O15+GYPG!O15+NGLM!AX15+SAMC!CH15+PHUA!CH15+TSMA!O15+GEDU!AX15+SAMA!CH15+TCHG!AX15+GMTU!CH15+LHAM!O15+PHLY!DO15 -> 2 | ... EV15: =PARO!AP15+HAA!BY15+WANG!DI15+PUNA!DI15+GASA!BY15+GELA!DI15+ZEMG!DI15+TRON!DI15+BUMA!DI15+SARA!DI15+TSIR!DI15+DGNA!DI15+PANG!DI15+DPLA!DI15+SJKA!DI15+TRAG!BY15+MONA!AP15+LUNT!DI15+TYSE!AP15+PEMA!AP15+KNLG!AP15+RJNG!AP15+WRMG!BY15+DUSM!AP15+GYPG!AP15+NGLM!BY15+SAMC!DI15+PHUA!DI15+TSMA!AP15+GEDU!BY15+SAMA!DI15+TCHG!BY15+GMTU!DI15+LHAM!AP15+PHLY!EP15 -> 3300 | EX15: =PARO!AR15+HAA!CA15+WANG!DK15+PUNA!DK15+GASA!CA15+GELA!DK15+ZEMG!DK15+TRON!DK15+BUMA!DK15+SARA!DK15+TSIR!DK15+DGNA!DK15+PANG!DK15+DPLA!DK15+SJKA!DK15+TRAG!CA15+MONA!AR15+LUNT!DK15+TYSE!AR15+PEMA!AR15+KNLG!AR15+RJNG!AR15+WRMG!CA15+DUSM!AR15+GYPG!AR15+NGLM!CA15+SAMC!DK15+PHUA!DK15+TSMA!AR15+GEDU!CA15+SAMA!DK15+TCHG!CA15+GMTU!DK15+LHAM!AR15+PHLY!ER15 -> 0 | EY15: =PARO!AS15+HAA!CB15+WANG!DL15+PUNA!DL15+GASA!CB15+GELA!DL15+ZEMG!DL15+TRON!DL15+BUMA!DL15+SARA!DL15+TSIR!DL15+DGNA!DL15+PANG!DL15+DPLA!DL15+SJKA!DL15+TRAG!CB15+MONA!AS15+LUNT!DL15+TYSE!AS15+PEMA!AS15+KNLG!AS15+RJNG!AS15+WRMG!CB15+DUSM!AS15+GYPG!AS15+NGLM!CB15+SAMC!DL15+PHUA!DL15+TSMA!AS15+GEDU!CB15+SAMA!DL15+TCHG!CB15+GMTU!DL15+LHAM!AS15+PHLY!ES15 -> 4 | EZ15: =PARO!AT15+HAA!CC15+WANG!DM15+PUNA!DM15+GASA!CC15+GELA!DM15+ZEMG!DM15+TRON!DM15+BUMA!DM15+SARA!DM15+TSIR!DM15+DGNA!DM15+PANG!DM15+DPLA!DM15+SJKA!DM15+TRAG!CC15+MONA!AT15+LUNT!DM15+TYSE!AT15+PEMA!AT15+KNLG!AT15+RJNG!AT15+WRMG!CC15+DUSM!AT15+GYPG!AT15+NGLM!CC15+SAMC!DM15+PHUA!DM15+TSMA!AT15+GEDU!CC15+SAMA!DM15+TCHG!CC15+GMTU!DM15+LHAM!AT15+PHLY!ET15 -> 0 | FA15: =PARO!AU15+HAA!CD15+WANG!DN15+PUNA!DN15+GASA!CD15+GELA!DN15+ZEMG!DN15+TRON!DN15+BUMA!DN15+SARA!DN15+TSIR!DN15+DGNA!DN15+PANG!DN15+DPLA!DN15+SJKA!DN15+TRAG!CD15+MONA!AU15+LUNT!DN15+TYSE!AU15+PEMA!AU15+KNLG!AU15+RJNG!AU15+WRMG!CD15+DUSM!AU15+GYPG!AU15+NGLM!CD15+SAMC!DN15+PHUA!DN15+TSMA!AU15+GEDU!CD15+SAMA!DN15+TCHG!CD15+GMTU!DN15+LHAM!AU15+PHLY!EU15 -> 3 | FB15: =PARO!AV15+HAA!CE15+WANG!DO15+PUNA!DO15+GASA!CE15+GELA!DO15+ZEMG!DO15+TRON!DO15+BUMA!DO15+SARA!DO15+TSIR!DO15+DGNA!DO15+PANG!DO15+DPLA!DO15+SJKA!DO15+TRAG!CE15+MONA!AV15+LUNT!DO15+TYSE!AV15+PEMA!AV15+KNLG!AV15+RJNG!AV15+WRMG!CE15+DUSM!AV15+GYPG!AV15+NGLM!CE15+SAMC!DO15+PHUA!DO15+TSMA!AV15+GEDU!CE15+SAMA!DO15+TCHG!CE15+GMTU!DO15+LHAM!AV15+PHLY!EV15 -> 4 | FC15: =PARO!AW15+HAA!CF15+WANG!DP15+PUNA!DP15+GASA!CF15+GELA!DP15+ZEMG!DP15+TRON!DP15+BUMA!DP15+SARA!DP15+TSIR!DP15+DGNA!DP15+PANG!DP15+DPLA!DP15+SJKA!DP15+TRAG!CF15+MONA!AW15+LUNT!DP15+TYSE!AW15+PEMA!AW15+KNLG!AW15+RJNG!AW15+WRMG!CF15+DUSM!AW15+GYPG!AW15+NGLM!CF15+SAMC!DP15+PHUA!DP15+TSMA!AW15+GEDU!CF15+SAMA!DP15+TCHG!CF15+GMTU!DP15+LHAM!AW15+PHLY!EW15 -> 0 | FD15: =PARO!AX15+HAA!CG15+WANG!DQ15+PUNA!DQ15+GASA!CG15+GELA!DQ15+ZEMG!DQ15+TRON!DQ15+BUMA!DQ15+SARA!DQ15+TSIR!DQ15+DGNA!DQ15+PANG!DQ15+DPLA!DQ15+SJKA!DQ15+TRAG!CG15+MONA!AX15+LUNT!DQ15+TYSE!AX15+PEMA!AX15+KNLG!AX15+RJNG!AX15+WRMG!CG15+DUSM!AX15+GYPG!AX15+NGLM!CG15+SAMC!DQ15+PHUA!DQ15+TSMA!AX15+GEDU!CG15+SAMA!DQ15+TCHG!CG15+GMTU!DQ15+LHAM!AX15+PHLY!EX15 -> 5 | FE15: =PARO!AY15+HAA!CH15+WANG!DR15+PUNA!DR15+GASA!CH15+GELA!DR15+ZEMG!DR15+TRON!DR15+BUMA!DR15+SARA!DR15+TSIR!DR15+DGNA!DR15+PANG!DR15+DPLA!DR15+SJKA!DR15+TRAG!CH15+MONA!AY15+LUNT!DR15+TYSE!AY15+PEMA!AY15+KNLG!AY15+RJNG!AY15+WRMG!CH15+DUSM!AY15+GYPG!AY15+NGLM!CH15+SAMC!DR15+PHUA!DR15+TSMA!AY15+GEDU!CH15+SAMA!DR15+TCHG!CH15+GMTU!DR15+LHAM!AY15+PHLY!EY15 -> 0 | ... GA15: =PARO!BU15+HAA!DD15+WANG!EN15+PUNA!EN15+GASA!DD15+GELA!EN15+ZEMG!EN15+TRON!EN15+BUMA!EN15+SARA!EN15+TSIR!EN15+DGNA!EN15+PANG!EN15+DPLA!EN15+SJKA!EN15+TRAG!DD15+MONA!BU15+LUNT!EN15+TYSE!BU15+PEMA!BU15+KNLG!BU15+RJNG!BU15+WRMG!DD15+DUSM!BU15+GYPG!BU15+NGLM!DD15+SAMC!EN15+PHUA!EN15+TSMA!BU15+GEDU!DD15+SAMA!EN15+TCHG!DD15+GMTU!EN15+LHAM!BU15+PHLY!FU15 -> 0 | GB15: =PARO!BV15+HAA!DE15+WANG!EO15+PUNA!EO15+GASA!DE15+GELA!EO15+ZEMG!EO15+TRON!EO15+BUMA!EO15+SARA!EO15+TSIR!EO15+DGNA!EO15+PANG!EO15+DPLA!EO15+SJKA!EO15+TRAG!DE15+MONA!BW15+LUNT!EO15+TYSE!BW15+PEMA!BW15+KNLG!BW15+RJNG!BV15+WRMG!DE15+DUSM!BW15+GYPG!BW15+NGLM!DE15+SAMC!EO15+PHUA!EO15+TSMA!BV15+GEDU!DE15+SAMA!EO15+TCHG!DE15+GMTU!EO15+LHAM!BV15+PHLY!FV15 -> 26 | GC15: =PARO!BW15+HAA!DF15+WANG!EP15+PUNA!EP15+GASA!DF15+GELA!EP15+ZEMG!EP15+TRON!EP15+BUMA!EP15+SARA!EP15+TSIR!EP15+DGNA!EP15+PANG!EP15+DPLA!EP15+SJKA!EP15+TRAG!DF15+MONA!BX15+LUNT!EP15+TYSE!BX15+PEMA!BX15+KNLG!BX15+RJNG!BW15+WRMG!DF15+DUSM!BX15+GYPG!BX15+NGLM!DF15+SAMC!EP15+PHUA!EP15+TSMA!BW15+GEDU!DF15+SAMA!EP15+TCHG!DF15+GMTU!EP15+LHAM!BW15+PHLY!FW15 -> 4680 | GD15: =PARO!BX15+HAA!DG15+WANG!EQ15+PUNA!EQ15+GASA!DG15+GELA!EQ15+ZEMG!EQ15+TRON!EQ15+BUMA!EQ15+SARA!EQ15+TSIR!EQ15+DGNA!EQ15+PANG!EQ15+DPLA!EQ15+SJKA!EQ15+TRAG!DG15+MONA!BY15+LUNT!EQ15+TYSE!BY15+PEMA!BY15+KNLG!BY15+RJNG!BX15+WRMG!DG15+DUSM!BY15+GYPG!BY15+NGLM!DG15+SAMC!EQ15+PHUA!EQ15+TSMA!BX15+GEDU!DG15+SAMA!EQ15+TCHG!DG15+GMTU!EQ15+LHAM!BX15+PHLY!FX15 -> 780 | GE15: =PARO!BY15+HAA!DH15+WANG!ER15+PUNA!ER15+GASA!DH15+GELA!ER15+ZEMG!ER15+TRON!ER15+BUMA!ER15+SARA!ER15+TSIR!ER15+DGNA!ER15+PANG!ER15+DPLA!ER15+SJKA!ER15+TRAG!DH15+MONA!BZ15+LUNT!ER15+TYSE!BZ15+PEMA!BZ15+KNLG!BZ15+RJNG!BY15+WRMG!DH15+DUSM!BZ15+GYPG!BZ15+NGLM!DH15+SAMC!ER15+PHUA!ER15+TSMA!BY15+GEDU!DH15+SAMA!ER15+TCHG!DH15+GMTU!ER15+LHAM!BY15+PHLY!FY15 -> 3900 | GG15: =PARO!CA15+HAA!DJ15+WANG!ET15+PUNA!ET15+GASA!DJ15+GELA!ET15+ZEMG!ET15+TRON!ET15+BUMA!ET15+SARA!ET15+TSIR!ET15+DGNA!ET15+PANG!ET15+DPLA!ET15+SJKA!ET15+TRAG!DJ15+MONA!CB15+LUNT!ET15+TYSE!CB15+PEMA!CB15+KNLG!CB15+RJNG!CA15+WRMG!DJ15+DUSM!CB15+GYPG!CB15+NGLM!DJ15+SAMC!ET15+PHUA!ET15+TSMA!CA15+GEDU!DJ15+SAMA!ET15+TCHG!DJ15+GMTU!ET15+LHAM!CA15+PHLY!GA15 -> 1 | GH15: =PARO!CB15+HAA!DK15+WANG!EU15+PUNA!EU15+GASA!DK15+GELA!EU15+ZEMG!EU15+TRON!EU15+BUMA!EU15+SARA!EU15+TSIR!EU15+DGNA!EU15+PANG!EU15+DPLA!EU15+SJKA!EU15+TRAG!DK15+MONA!CC15+LUNT!EU15+TYSE!CC15+PEMA!CC15+KNLG!CC15+RJNG!CB15+WRMG!DK15+DUSM!CC15+GYPG!CC15+NGLM!DK15+SAMC!EU15+PHUA!EU15+TSMA!CB15+GEDU!DK15+SAMA!EU15+TCHG!DK15+GMTU!EU15+LHAM!CB15+PHLY!GB15 -> 0 | GI15: =PARO!CC15+HAA!DL15+WANG!EV15+PUNA!EV15+GASA!DL15+GELA!EV15+ZEMG!EV15+TRON!EV15+BUMA!EV15+SARA!EV15+TSIR!EV15+DGNA!EV15+PANG!EV15+DPLA!EV15+SJKA!EV15+TRAG!DL15+MONA!CD15+LUNT!EV15+TYSE!CD15+PEMA!CD15+KNLG!CD15+RJNG!CC15+WRMG!DL15+DUSM!CD15+GYPG!CD15+NGLM!DL15+SAMC!EV15+PHUA!EV15+TSMA!CC15+GEDU!DL15+SAMA!EV15+TCHG!DL15+GMTU!EV15+LHAM!CC15+PHLY!GC15 -> 0 | GJ15: =PARO!CD15+HAA!DM15+WANG!EW15+PUNA!EW15+GASA!DM15+GELA!EW15+ZEMG!EW15+TRON!EW15+BUMA!EW15+SARA!EW15+TSIR!EW15+DGNA!EW15+PANG!EW15+DPLA!EW15+SJKA!EW15+TRAG!DM15+MONA!CE15+LUNT!EW15+TYSE!CE15+PEMA!CE15+KNLG!CE15+RJNG!CD15+WRMG!DM15+DUSM!CE15+GYPG!CE15+NGLM!DM15+SAMC!EW15+PHUA!EW15+TSMA!CD15+GEDU!DM15+SAMA!EW15+TCHG!DM15+GMTU!EW15+LHAM!CD15+PHLY!GD15 -> 6 | GK15: =PARO!CE15+HAA!DN15+WANG!EX15+PUNA!EX15+GASA!DN15+GELA!EX15+ZEMG!EX15+TRON!EX15+BUMA!EX15+SARA!EX15+TSIR!EX15+DGNA!EX15+PANG!EX15+DPLA!EX15+SJKA!EX15+TRAG!DN15+MONA!CF15+LUNT!EX15+TYSE!CF15+PEMA!CF15+KNLG!CF15+RJNG!CE15+WRMG!DN15+DUSM!CF15+GYPG!CF15+NGLM!DN15+SAMC!EX15+PHUA!EX15+TSMA!CE15+GEDU!DN15+SAMA!EX15+TCHG!DN15+GMTU!EX15+LHAM!CE15+PHLY!GE15 -> 0 | GL15: =PARO!CF15+HAA!DO15+WANG!EY15+PUNA!EY15+GASA!DO15+GELA!EY15+ZEMG!EY15+TRON!EY15+BUMA!EY15+SARA!EY15+TSIR!EY15+DGNA!EY15+PANG!EY15+DPLA!EY15+SJKA!EY15+TRAG!DO15+MONA!CG15+LUNT!EY15+TYSE!CG15+PEMA!CG15+KNLG!CG15+RJNG!CF15+WRMG!DO15+DUSM!CG15+GYPG!CG15+NGLM!DO15+SAMC!EY15+PHUA!EY15+TSMA!CF15+GEDU!DO15+SAMA!EY15+TCHG!DO15+GMTU!EY15+LHAM!CF15+PHLY!GF15 -> 0 | GM15: =PARO!CG15+HAA!DP15+WANG!EZ15+PUNA!EZ15+GASA!DP15+GELA!EZ15+ZEMG!EZ15+TRON!EZ15+BUMA!EZ15+SARA!EZ15+TSIR!EZ15+DGNA!EZ15+PANG!EZ15+DPLA!EZ15+SJKA!EZ15+TRAG!DP15+MONA!CH15+LUNT!EZ15+TYSE!CH15+PEMA!CH15+KNLG!CH15+RJNG!CG15+WRMG!DP15+DUSM!CH15+GYPG!CH15+NGLM!DP15+SAMC!EZ15+PHUA!EZ15+TSMA!CG15+GEDU!DP15+SAMA!EZ15+TCHG!DP15+GMTU!EZ15+LHAM!CG15+PHLY!GG15 -> 0 | GN15: =PARO!CH15+HAA!DQ15+WANG!FA15+PUNA!FA15+GASA!DQ15+GELA!FA15+ZEMG!FA15+TRON!FA15+BUMA!FA15+SARA!FA15+TSIR!FA15+DGNA!FA15+PANG!FA15+DPLA!FA15+SJKA!FA15+TRAG!DQ15+MONA!CI15+LUNT!FA15+TYSE!CI15+PEMA!CI15+KNLG!CI15+RJNG!CH15+WRMG!DQ15+DUSM!CI15+GYPG!CI15+NGLM!DQ15+SAMC!FA15+PHUA!FA15+TSMA!CH15+GEDU!DQ15+SAMA!FA15+TCHG!DQ15+GMTU!FA15+LHAM!CH15+PHLY!GH15 -> 0 | ... HO15: =PARO!DI15+HAA!ER15+WANG!GB15+PUNA!GB15+GASA!ER15+GELA!GB15+ZEMG!GB15+TRON!GB15+BUMA!GB15+SARA!GB15+TSIR!GB15+DGNA!GB15+PANG!GB15+DPLA!GB15+SJKA!GB15+TRAG!ER15+MONA!DJ15+LUNT!GB15+TYSE!DJ15+PEMA!DJ15+KNLG!DJ15+RJNG!DI15+WRMG!ER15+DUSM!DJ15+GYPG!DJ15+NGLM!ER15+SAMC!GB15+PHUA!GB15+TSMA!DI15+GEDU!ER15+SAMA!GB15+TCHG!ER15+GMTU!GB15+LHAM!DI15+PHLY!HI15 -> 2850 | HQ15: =ES15+GB15+HL15 -> 67 | HR15: =C15*HQ15 -> 10050 | HS15: =D15*HQ15 -> 12060 | HT15: =E15*HQ15 -> 2010 | IN15: =AJ15+BT15+DC15+ES15+GB15+HL15 -> 170 | IO15: =AK15+BU15+DD15+ET15+GC15+HM15 -> 30600 | IP15: =AL15+BV15+DE15+EU15+GD15+HN15 -> 5100 | IQ15: =AM15+BW15+DF15+EV15+GE15+HO15 -> 25500
