Workbook

Sheet Summary
A1: Sl.No | B1: Particular | C1: Amount (Nu)
A2: 1 | B2: Rectified as New Asset
A3: a | B3: ='Annexure 1A FNF'!A1 -> FNF Physicall Available but not recorded in the system | C3: ='Annexure 1A FNF'!A63+'Annexure 1A FNF'!A156+'Annexure 1A FNF'!A184+'Annexure 1A FNF'!A202+'Annexure 1A FNF'!A226 -> 215
A4: b | B4: ='Annexure 1B EQP'!A1 -> EQP Physicall Available but not recorded in the system | C4: ='Annexure 1B EQP'!A6+'Annexure 1B EQP'!A12 -> 7
B5: Total | C5: =SUM(C3:C4) -> 222
A6: 2 | B6: For Disposal
A7: a | B7: ='Annex 2A Unserviceable items EQ'!A1 -> EQP items available and recorded in ERP system but Unserviceable | C7: ='Annex 2A Unserviceable items EQ'!O174 -> 27507.91
A8: b | B8: ='Annex 2B Unserviceable items FN'!B1 -> FNF items available and recorded in ERP system but Unserviceable | C8: ='Annex 2B Unserviceable items FN'!O62 -> 8985.68
A9: c | B9: ='Annexure 2C Unserviceable Grant'!A1 -> Unserviceable Grant | C9: ='Annexure 2C Unserviceable Grant'!O44 -> 8580.38
A10: d | B10: ='Annex 2D Surrendered EQP'!A1 -> Surrendered EQP Items | C10: ='Annex 2D Surrendered EQP'!N102 -> 35754.85
A11: e | B11: ='Annex 2E Surrendered FNF'!A1 -> Surrendered FNF Items | C11: ='Annex 2E Surrendered FNF'!N7 -> 190.6
A12: f | B12: ='Annex 2F Tally software for dis'!A1 -> Tally Software for disposal | C12: ='Annex 2F Tally software for dis'!O46 -> 52942.98
B13: Total | C13: =SUM(C7:C12) -> 133962.4
A14: 3 | B14: For Write Off
A15: a | B15: ='Annex 3A EQP Physical not avail'!A1 -> EQP Physicall not Available but recorded in the system | C15: ='Annex 3A EQP Physical not avail'!O13 -> 1384.37
A16: b | B16: ='Annex 3B Grant not ava but reco'!A1 -> FNF Physicall not Available but recorded in the system | C16: ='Annex 3B Grant not ava but reco'!O14 -> 5
A17: c | B17: ='Annex 3C Tally Software Writeof'!A1 -> Tally Software Writeoff | C17: ='Annex 3C Tally Software Writeof'!O36 -> 9956.98
B18: Total | C18: =SUM(C15:C17) -> 11346.35

Sheet Annexure 1A FNF
A1: FNF Physicall Available but not recorded in the system
A2: Sl No | B2: Asset Item | C2: ERP Codification | D2: Actual Codification | E2: Custodian | F2: Location
A3: HQ
A4: 1 | B4: BBPL Table | C4: Not recorded | D4: 2000/FNF/0136 | E4: Tek Brd Poudyel | F4: Finance Division
A5: 2 | B5: Half Back Revolving Chair old | C5: Not recorded | D5: no code | E5: Phurba Dorji | F5: PBAX
A6: 3 | B6: Goodraj Table old | C6: Not recorded | D6: no code | E6: Phurba Dorji | F6: PBAX
A7: 4 | B7: Steel Almirah Small old | C7: Not recorded | D7: no code | E7: Phurba Dorji | F7: PBAX
A8: 5 | B8: Chair Visiting with leather cusion | C8: Not recorded | D8: 2009/FNF/0011 | E8: Thinley Wangchuk | F8: Corporate
A9: 6 | B9: Chair Visiting with leather cusion | C9: Not recorded | D9: 2009/FNF/0012 | E9: Thinley Wangchuk | F9: Corporate
A10: 7 | B10: Chair Visiting with leather cusion | C10: Not recorded | D10: 2009/FNF/0013 | E10: Thinley Wangchuk | F10: Corporate
A11: 8 | B11: Steel Book Shelf | C11: Not recorded | D11: 1997/FNF/0008 | E11: Jamyang Phuntsho | F11: Postal Operation
A12: 9 | B12: Visiting Chair (Old) | C12: Not recorded | D12: BP/OF/VC/18 | E12: Wangmo Phuntsho Droenma | F12: Postal Operation
A13: 10 | B13: Visiting Chair (Old) | C13: Not recorded | D13: BP/OF/VC/19 | E13: Wangmo Phuntsho Droenma | F13: Postal Operation
A14: 11 | B14: Visiting Chair (Old) | C14: Not recorded | D14: BP/OF/VC/20 | E14: Wangmo Phuntsho Droenma | F14: Postal Operation
A15: 12 | B15: Woodcraft Table | C15: Not recorded | D15: no code | E15: Kezang Choden | F15: Postal Operation
... A156: 91 | B156: Table Wooden | C156: Not recorded | D156: 1977/FNF/0156 | E156: Ganesh Bdr Mongar | F156: Gedu PO
A158: WR
A159: 1 | B159: Half BAck Rewolving chair | C159: Not recorded | D159: No code | E159: Pema Yangchen | F159: Thimphu GPO
A160: 2 | B160: Drawer Cabinet WCCL | C160: Not recorded | D160: No code | E160: DECHEN WANGMO | F160: Thimphu GPO
A161: 3 | B161: Medium Working Table | C161: Not recorded | D161: 2013/FNF/0039 | E161: DECHEN WANGMO | F161: Thimphu GPO
A162: 4 | B162: Chair with cusion | C162: Not recorded | D162: No Code | E162: UGYEN WANGMO | F162: Wangdue PO
A163: 5 | B163: Chair with cusion | C163: Not recorded | D163: No Code | E163: UGYEN WANGMO | F163: Wangdue PO
A164: 6 | B164: wooden file rack | C164: Not recorded | D164: 2003/FNF/0028 | E164: UGYEN WANGMO | F164: Wangdue PO
A165: 7 | B165: Metal File rack | C165: Not recorded | D165: 1986/FNF/0087 | E165: UGYEN WANGMO | F165: Wangdue PO
A166: 8 | B166: Plastic Chair | C166: Not recorded | D166: No code | E166: UGYEN WANGMO | F166: Wangdue PO
A167: 9 | B167: Plastic Chair | D167: No code | E167: UGYEN WANGMO | F167: Wangdue PO
A168: 10 | B168: Plastic Chair | D168: No code | E168: UGYEN WANGMO | F168: Wangdue PO
A169: 11 | B169: Almirah Steel (Small) | C169: Not recorded | D169: No code | E169: Sonam | F169: Haa PO
A170: 12 | B170: Almirah Steel | C170: Not recorded | E170: Sonam Peldon | F170: Punakha PO
A171: 13 | B171: Post Box 1 | C171: Not recorded | D171: No Codification | E171: Karma Wangchuk | F171: Paro Airport
A172: 14 | B172: Chair with arm | C172: Not recorded | D172: No Codification | E172: Karma Wangchuk | F172: Paro Airport
A173: 15 | B173: P/box pegion Holes (26 holes) | C173: Not recorded | E173: Sangay Zangmo | F173: Paro PO
A174: 16 | B174: Rack pegion Holes Wooden | C174: Not recorded | E174: Sangay Zangmo | F174: Paro PO
A175: 17 | B175: Counter | C175: Not recorded | D175: 2005/FNF/0020 | E175: Sangay Zangmo | F175: Paro PO
A176: 18 | B176: Draw Cabinet | C176: Not recorded | D176: 2016/FNF/0071 | E176: Sangay Zangmo | F176: Paro PO
A177: 19 | B177: Drawer Cabinet | C177: Not recorded | D177: 2016/FNF/0072 | E177: Sangay Zangmo | F177: Paro PO
A178: 20 | B178: letter Box (Steel) 25 hole | C178: Not recorded | D178: No Codification | E178: Sangay Zangmo | F178: Paro PO
A179: 21 | B179: Almirah Steel (Small) | C179: Not recorded | D179: No code | E179: Thinley Yoezer | F179: Dzong PO
A180: 22 | B180: Wooden Table | C180: Not recorded | D180: No code | E180: Thinley Yoezer | F180: Dzong PO
A181: 23 | B181: Wooden Table | C181: Not recorded | D181: No code | E181: Thinley Yoezer | F181: Dzong PO
A182: 24 | B182: Wooden Table | C182: Not recorded | D182: No code | E182: Thinley Yoezer | F182: Dzong PO
A183: 25 | B183: Wooden Table | C183: Not recorded | D183: No code | E183: Thinley Yoezer | F183: Dzong PO
A184: 26 | B184: Sorting wooden Table | C184: Not recorded | D184: No code | E184: Thinley Yoezer | F184: Dzong PO
A186: CR
A187: 1 | B187: Post Box (110piegons holed) | C187: Not recorded | D187: 2004/FNF/0113 | E187: Hari Maya Gurung | F187: Gelephu GPO
A188: 2 | B188: Cash Box | C188: Not recorded | D188: BP/CR/PO/ZMG/SCB-01 | E188: Dechen Wangmo | F188: Gelephu GPO
A189: 3 | B189: Steel Box | C189: Not recorded | D189: 1993/EQP/0021 | E189: Maya Devi Baskota | F189: Tsirang PO
A190: 4 | B190: Table Half Secretrate | C190: Not recorded | D190: 1976/FNF/0015 | E190: Sonam Dorji | F190: Zhemgang PO
A191: 5 | B191: Computer Table BBPL | C191: Not recorded | D191: No Code | E191: Sonam Dorji | F191: Zhemgang PO
A192: 6 | B192: Computer Table BBPL | C192: Not recorded | D192: No Code | E192: Pema Chogay | F192: Zhemgang PO
A193: 7 | B193: Computer Table | C193: Not recorded | D193: No Code | E193: Sonam Dorji | F193: Zhemgang PO
A194: 8 | B194: Computer Table | C194: Not recorded
A195: 9 | B195: wooden arm chair with cushion | C195: Not recorded | D195: BP/CR/PO/ZMG/ACS-01/CIC | E195: Sonam Dorji | F195: Zhemgang PO
A196: 10 | B196: wooden arm chair with cushion | C196: Not recorded | D196: BP/CR/PO/ZMG/ACS-02/CIC | E196: Sonam Dorji | F196: Zhemgang PO
A197: 11 | B197: Chair Steel Armless | C197: Not recorded | D197: 1978/FNF/0017 | E197: Sonam Dorji | F197: Zhemgang PO
A198: 12 | B198: Chair Steel Armless | C198: Not recorded | D198: No Code | F198: Zhemgang PO
A199: 13 | B199: Chair Steel Armless | C199: Not recorded | D199: No code | F199: Zhemgang PO
A200: 14 | B200: Old sorting Counter | C200: Not recorded | D200: No code | F200: CHABI LAL
A201: 15 | B201: ALMIRAL STEEL(BIG) | C201: Not recorded | E201: SARPANG PO | F201: CHABI LAL
A202: 16 | B202: ALMIRAL STEEL(BIG) | C202: Not recorded | E202: SARPANG PO | F202: CHABI LAL
A204: ER
A205: 1 | B205: Table Computer | C205: Not recorded | D205: 2004/EQP/0063 | E205: Phurba tshering tamang | F205: Samdrupjongkhar GPO
A206: 2 | B206: Wooden Table | C206: Not recorded | D206: NO CODE | E206: Phurba tshering tamang | F206: Samdrupjongkhar GPO
A207: 3 | B207: Wooden Stool | C207: Not recorded | D207: BP/ER/PO/SJK/SS-02 | E207: Phurba tshering tamang | F207: Samdrupjongkhar GPO
A208: 4 | B208: Pegion Letter Box | C208: Not recorded | D208: 2000/FNF/0142 | E208: Phurba tshering tamang | F208: Samdrupjongkhar GPO
A209: 5 | B209: Letter Sorting Table | C209: Not recorded | D209: 2004/FNF/0080 | E209: Phurba tshering tamang | F209: Samdrupjongkhar GPO
A210: 6 | B210: Cash Box | C210: Not recorded | D210: BP/ER/PO/SJK/CB-04 | E210: Phurba tshering tamang | F210: Samdrupjongkhar GPO
A211: 7 | B211: Cash Box | C211: Not recorded | D211: BP/ER/PO/SJK/CB-01 | E211: Phurba tshering tamang | F211: Samdrupjongkhar GPO
A212: 8 | B212: Table Computer | C212: Not recorded | D212: 1984/FNF/0045 | E212: Tshering Chophel | F212: Samdrupjongkhar GPO
A213: 9 | B213: Aluminum Box | C213: Not recorded | D213: BP/ER/PO/PG/SAM-01 | E213: Phuntsho Dorji | F213: Pemagathsel PO
A214: 10 | B214: Sorting Case | C214: Not recorded | D214: 1979/FNF/0030 | E214: Phuntsho Dorji | F214: Pemagathsel PO
A215: 11 | B215: Steel Almeria (Medium) | C215: Not recorded | D215: 1998/FNF/0001 | E215: Norbu | F215: Nganglam PO
A216: 12 | B216: Letter Box ( Small) | C216: Not recorded | D216: Code 6 | E216: Norbu | F216: Nganglam PO
... A226: 22 | B226: Wooden Chair | C226: Not recorded | D226: Code-26 | E226: Kuenga Yeshi | F226: Gyelposhing PO

Sheet Annexure 1B EQP
A1: EQP Physicall Available but not recorded in the system
A2: Sl No | B2: Asset Item | C2: ERP Codification | D2: Actual Codification | E2: Custodian | F2: Location
A3: Southern Region
A4: 1 | B4: Telephone | C4: Not recorded | D4: 2001/EQP/0143 | E4: Chandra Bdr Subba | F4: Pling GPO
A5: 2 | B5: CPU | C5: Not recorded | D5: 2018/EQP/0128 | E5: Kelzang Tobgay | F5: Pling GPO
A6: 3 | B6: PCO Monitor | C6: Not recorded | D6: No code | E6: Tashi Yangden | F6: Pling GPO
B8: ER
A9: 1 | B9: CPU | C9: Not recorded | D9: 2008/EQP/0016 | E9: Tshering Chophel | F9: Samdrupjongkhar GPO
A10: 2 | B10: BIKE BG-2-A0489 | C10: Not recorded | E10: Kinzang Norbu | F10: Jomotshangkha GPO | G10: Purser Bike Received In 2020 but Model 2019
A11: 3 | B11: Fax Machine Panasonic | C11: Not recorded | D11: 2003/EQP/0036 | E11: Kuenga Yeshi | F11: Gyelposhing PO
A12: 4 | B12: Bike BG-2B-0490 | C12: Not recorded | E12: Cheten Norbu | F12: Duksum PO | G12: Purser Bike Received In 2020 but Model 2019

Sheet Annex 2A Unserviceable items EQ
A1: EQP items available and recorded in ERP system but Unserviceable
A2: Head Quarter
A3: Finance
A4: # | B4: Assets | C4: Asset ID | D4: Location | E4: Put-in Use Date | F4: Custodian | G4: Useful Life | H4: Gross Value | I4: Salvage Value | J4: Depreciable Amt | K4: Dep per Day | L4: Opening Dep | M4: Depreciation | N4: Net Value | O4: Selvage value + Net Value
A5: 1 | B5: Room Blower Heater | C5: 2016/EQP/0105 | D5: Finance & Investment | E5: 42733 | F5: HARI CHANDRA BAJGAI | G5: 5 | H5: 2750 | I5: 55 | J5: 2695 | K5: 1.48 | L5: 2694 | M5: 0 | N5: 1 | O5: =I5+N5 -> 56
A6: 2 | B6: Stabilizer | C6: 2016/EQP/0119 | D6: Finance & Investment | E6: 42565 | F6: THINLEY TOBGAY | G6: 5 | H6: 4990 | I6: 0 | J6: 4990 | K6: 2.73 | L6: 4989 | M6: 0 | N6: 1 | O6: =I6+N6 -> 1
A7: 3 | B7: Stabilizer | C7: 2016/EQP/0122 | D7: Finance & Investment | E7: 42565 | F7: THINLEY TOBGAY | G7: 5 | H7: 4990 | I7: 99.8 | J7: 4890.2 | K7: 2.68 | L7: 4889.2 | M7: 0 | N7: 1 | O7: =I7+N7 -> 100.8
A8: 4 | B8: Room Heater | C8: 2018/EQP/0132 | D8: Finance & Investment | E8: 43202 | F8: THINLEY TOBGAY | G8: 5 | H8: 2189 | I8: 43.78 | J8: 2145.22 | K8: 1.18 | L8: 1871.13 | M8: 250.16 | N8: 23.93 | O8: =I8+N8 -> 67.71
A9: 5 | B9: Room Blower Heater | C9: 2018/EQP/0167 | D9: Finance & Investment | E9: 43385 | F9: LUNGTEN PEMA | G9: 5 | H9: 2189 | I9: 43.78 | J9: 2145.22 | K9: 1.18 | L9: 1865.74 | M9: 250.16 | N9: 29.32 | O9: =I9+N9 -> 73.1
A10: 6 | B10: Stabilizer UPS | C10: 2016/EQP/0118 | D10: Finance & Investment | E10: 42565 | F10: UGYEN CHOPHEL | G10: 5 | H10: 4990 | I10: 99.8 | J10: 4890.2 | K10: 2.68 | L10: 4889.2 | M10: 0 | N10: 1 | O10: =I10+N10 -> 100.8
A12: HR
A13: 1 | B13: Water Boiler | C13: 2008/EQP/0133 | D13: Procurement | E13: 39673 | F13: UGYEN BIDA | G13: 5 | H13: 1250 | I13: 0 | J13: 1250 | K13: 0.68 | L13: 1249 | M13: 0 | N13: 1 | O13: =I13+N13 -> 1
A14: 2 | B14: Printer HP Laserjet M607 | C14: 2018/EQP/0024 | D14: Postal Service | E14: 43221 | F14: CHHIMI RINZIN | G14: 5 | H14: 65000 | I14: 1300 | J14: 63700 | K14: 34.9 | L14: 63699 | M14: 0 | N14: 1 | O14: =I14+N14 -> 1301
A15: 3 | B15: Camera Nicon Coolpix | C15: 2008/EQP/0001 | D15: Design & Production | E15: 39737 | F15: TASHI WANGCHUK | G15: 5 | H15: 11100 | I15: 0 | J15: 11100 | K15: 6.08 | L15: 11099 | M15: 0 | N15: 1 | O15: =I15+N15 -> 1
A16: 4 | B16: Room Blower Heater | C16: 2018/EQP/0137 | D16: Philately Sales | E16: 43202 | F16: TASHI WANGCHUK | G16: 5 | H16: 2189 | I16: 43.78 | J16: 2145.22 | K16: 1.18 | L16: 1871.13 | M16: 250.16 | N16: 23.93 | O16: =I16+N16 -> 67.71
A18: ICT
A19: 1 | B19: FAX MACHINE | C19: 2016/EQP/0223 | D19: ICT | E19: 42967 | F19: SONAM PELDON | G19: 5 | H19: 7900 | I19: 109.02 | J19: 7790.98 | K19: 4.27 | L19: 7789.98 | M19: 0 | N19: 1 | O19: =I19+N19 -> 110.02
A20: 2 | B20: FAX MACHINE | C20: 2016/EQP/0224 | D20: ICT | E20: 42602 | F20: SONAM PELDON | G20: 5 | H20: 7900 | I20: 109.02 | J20: 7790.98 | K20: 4.27 | L20: 7789.98 | M20: 0 | N20: 1 | O20: =I20+N20 -> 110.02
A21: 3 | B21: MUSLADY D2 | C21: 2019/EQP/0101 | D21: ICT | E21: 43664 | F21: SONAM PELDON | G21: 5 | H21: 18065.16 | I21: 361.3 | J21: 17703.86 | K21: 9.7 | L21: 15220.29 | M21: 2056.4 | N21: 427.17 | O21: =I21+N21 -> 788.47
A24: Western Region (Thimphu)
A25: Thimphu GPO
A26: 1 | B26: Printer HP | C26: 2008/EQP/0112 | D26: Thimphu GPO | E26: 39570 | F26: RINCHEN DORJI | G26: 5 | H26: 20999 | I26: 0 | J26: 20999 | K26: 11.51 | L26: 20998 | M26: 0 | N26: 1 | O26: =I26+N26 -> 1
A27: 2 | B27: Scanner Barcode | C27: 2013/EQP/0147 | D27: Thimphu GPO | E27: 41478 | F27: RINCHEN DORJI | G27: 5 | H27: 4950 | I27: 0 | J27: 4950 | K27: 2.71 | L27: 4949 | M27: 0 | N27: 1 | O27: =I27+N27 -> 1
A28: 3 | B28: Scanner Barcode | C28: 2013/EQP/0148 | D28: Thimphu GPO | E28: 41478 | F28: RINCHEN DORJI | G28: 5 | H28: 4950 | I28: 0 | J28: 4950 | K28: 2.71 | L28: 4949 | M28: 0 | N28: 1 | O28: =I28+N28 -> 1
A29: 4 | B29: Printer HP Laserjet | C29: 2013/EQP/0167 | D29: Thimphu GPO | E29: 41302 | F29: LHAM WANGCHUK | G29: 5 | H29: 7989 | I29: 0 | J29: 7989 | K29: 4.38 | L29: 7988 | M29: 0 | N29: 1 | O29: =I29+N29 -> 1
A30: 5 | B30: Cash Counting Machine | C30: 2016/EQP/0005 | D30: Thimphu GPO | E30: 42678 | F30: LHAM WANGCHUK | G30: 5 | H30: 20000 | I30: 400 | J30: 19600 | K30: 10.74 | L30: 19599 | M30: 0 | N30: 1 | O30: =I30+N30 -> 401
A31: 6 | B31: Printer | C31: 2017/EQP/0067 | D31: Thimphu GPO | E31: 43033 | F31: LHAM WANGCHUK | G31: 5 | H31: 12700 | I31: 254 | J31: 12446 | K31: 6.82 | L31: 12445 | M31: 211.42 | N31: -210.42 | O31: =I31+N31 -> 43.58
A32: 7 | B32: ROOM HEATER SINGLE ROD | C32: 2017/EQP/0002 | D32: Thimphu GPO | E32: 42751 | F32: LHAM WANGCHUK | G32: 5 | H32: 950 | I32: 65.75 | J32: 884.25 | K32: 0.49 | L32: 883.25 | M32: 0 | N32: 1 | O32: =I32+N32 -> 66.75
O33: =I33+N33 -> 0
A34: Wangdue | O34: =I34+N34 -> 0
A35: 1 | B35: Scanner Scan Jet 3500C | C35: 2004/EQP/0431 | D35: Wangdue PO | E35: 37987 | F35: UGYEN WANGMO | G35: 5 | H35: 6400 | I35: 0 | J35: 6400 | K35: 3.51 | L35: 6399 | M35: 0 | N35: 1 | O35: =I35+N35 -> 1
A36: 2 | B36: Room Heater Double Rod | C36: 2018/EQP/0109 | D36: Wangdue PO | E36: 43202 | F36: UGYEN WANGMO | G36: 5 | H36: 1499 | I36: 29.98 | J36: 1469.02 | K36: 0.81 | L36: 1282.03 | M36: 171.72 | N36: 15.27 | O36: =I36+N36 -> 45.25
A37: 3 | B37: Room Heater Double Rod | C37: 2018/EQP/0110 | D37: Wangdue PO | E37: 43202 | F37: UGYEN WANGMO | G37: 5 | H37: 1499 | I37: 29.98 | J37: 1469.02 | K37: 0.81 | L37: 1282.03 | M37: 171.72 | N37: 15.27 | O37: =I37+N37 -> 45.25
A38: 4 | B38: Weighing Digital Letter Scale | C38: 1993/EQP/0044 | D38: Postal Service | E38: 33970 | F38: YESHEY PALDEN | G38: 5 | H38: 1364.8 | I38: 0 | J38: 1364.8 | K38: 0.75 | L38: 1363.8 | M38: 0 | N38: 1 | O38: =I38+N38 -> 1
A39: 5 | B39: Weighing Digital Letter Scale 50kg | C39: 2017/EQP/0062 | D39: Wangdue PO | E39: 43006 | F39: UGYEN WANGMO | G39: 5 | H39: 11000 | I39: 220 | J39: 10780 | K39: 5.91 | L39: 10779 | M39: 0 | N39: 1 | O39: =I39+N39 -> 221
A40: 6 | B40: HP Laserjet P1108 Printer | C40: 2015/EQP/0012 | D40: Wangdue PO | E40: 42228 | F40: UGYEN WANGMO | G40: 5 | H40: 1800 | I40: 0 | J40: 1800 | K40: 0.99 | L40: 1799 | M40: 0 | N40: 1 | O40: =I40+N40 -> 1
A42: Haa
A43: 2 | B43: Room Heater Double Rod | C43: 2004/EQP/0323 | D43: Haa PO | E43: 38290 | F43: SONAM | G43: 5 | H43: 461.25 | I43: 0 | J43: 461.25 | K43: 0.25 | L43: 460.25 | M43: 0 | N43: 1 | O43: =I43+N43 -> 1
A44: 3 | B44: Room Heater Double Rod | C44: 2004/EQP/0324 | D44: Haa PO | E44: 38290 | F44: SONAM | G44: 5 | H44: 461.25 | I44: 0 | J44: 461.25 | K44: 0.25 | L44: 460.25 | M44: 0 | N44: 1 | O44: =I44+N44 -> 1
A45: 4 | B45: Stabilizer | C45: 2006/EQP/0081 | D45: Haa PO | E45: 38903 | F45: SONAM | G45: 5 | H45: 1040 | I45: 0 | J45: 1040 | K45: 0.57 | L45: 1039 | M45: 0 | N45: 1 | O45: =I45+N45 -> 1
A46: 5 | B46: Printer EPSON LQ 310 | C46: 2019/EQP/0003 | D46: Haa PO | E46: 43539 | F46: SONAM | G46: 5 | H46: 13790 | I46: 275.8 | J46: 13514.2 | K46: 7.41 | L46: 11620.4 | M46: 1570.92 | N46: 322.88 | O46: =I46+N46 -> 598.68
A47: 7 | B47: Printer EPSON LQ 310 | C47: 2018/EQP/0041 | D47: Haa PO | E47: 43339 | F47: SONAM | G47: 5 | H47: 13790 | I47: 275.8 | J47: 13514.2 | K47: 7.41 | L47: 12339.48 | M47: 1173.72 | N47: 1 | O47: =I47+N47 -> 276.8
A49: Punakha
A50: 1 | B50: Computer | C50: 2004/EQP/0061 | D50: Punakha PO | E50: 37987 | F50: SONAM PELDON | G50: 5 | H50: 69000 | I50: 0 | J50: 69000 | K50: 37.81 | L50: 68999 | M50: 0 | N50: 1 | O50: =I50+N50 -> 1
A51: 2 | B51: Scanner Scan Jet 3500C | C51: 2004/EQP/0429 | D51: Punakha PO | E51: 37987 | F51: SONAM PELDON | G51: 5 | H51: 6400 | I51: 0 | J51: 6400 | K51: 3.51 | L51: 6399 | M51: 0 | N51: 1 | O51: =I51+N51 -> 1
A52: 3 | B52: Printer HP laserjet 1022 | C52: 2008/EQP/0091 | D52: Punakha PO | E52: 39609 | F52: SONAM PELDON | G52: 5 | H52: 9636 | I52: 0 | J52: 9636 | K52: 5.28 | L52: 9635 | M52: 0 | N52: 1 | O52: =I52+N52 -> 1
A54: Paro
A55: 1 | B55: Room Heater Single Rod | C55: 2017/EQP/0004 | D55: Paro PO | E55: 42753 | F55: SANGAY ZANGMO | G55: 5 | H55: 700 | I55: 14 | J55: 686 | K55: 0.38 | L55: 685 | M55: 0 | N55: 1 | O55: =I55+N55 -> 15
A56: 2 | B56: Room Heater Double Rod | C56: 2018/EQP/0108 | D56: Paro PO | E56: 43202 | F56: SANGAY ZANGMO | G56: 5 | H56: 1499 | I56: 29.98 | J56: 1469.02 | K56: 0.81 | L56: 1282.03 | M56: 171.72 | N56: 15.27 | O56: =I56+N56 -> 45.25
A57: 3 | B57: Printer EPSON LQ 310 | C57: 2019/EQP/0137 | D57: Paro PO | E57: 43725 | F57: SANGAY ZANGMO | G57: 5 | H57: 13120 | I57: 262.4 | J57: 12857.6 | K57: 7.05 | L57: 11055.82 | M57: 1494.6 | N57: 307.18 | O57: =I57+N57 -> 569.58
A58: 4 | B58: Digital Weighing Machine 30kg | C58: 2020/EQP/0019 | D58: Paro PO | E58: 43992 | F58: SANGAY ZANGMO | G58: 5 | H58: 4500 | I58: 90 | J58: 4410 | K58: 2.42 | L58: 3278.61 | M58: 513.04 | N58: 618.35 | O58: =I58+N58 -> 708.35
A61: Dzong PO
A62: 1 | B62: Printer EPSON LQ 310 | C62: 2016/EQP/0251 | D62: Tashichodzong PO | E62: 42713 | F62: THINLEY YOEZER | G62: 5 | H62: 12390 | I62: 247.8 | J62: 12142.2 | K62: 6.65 | L62: 12141.2 | M62: 0 | N62: 1 | O62: =I62+N62 -> 248.8
A65: Southern Region
A66: Phuntsholing GPO
A67: 1 | B67: Printer EPSON LQ 310 | C67: 2019/EQP/0035 | D67: Phuntsholing GPO | E67: 43671 | F67: TASHI YANGDEN | G67: 5 | H67: 13120 | I67: 262.4 | J67: 12857.6 | K67: 7.05 | L67: 11055.82 | M67: 1494.6 | N67: 307.18 | O67: =I67+N67 -> 569.58
A68: 2 | B68: Telephone | C68: 2005/EQP/0092 | D68: Phuntsholing GPO | E68: 38420 | F68: YANGKI DEMA | G68: 5 | H68: 750 | I68: 0 | J68: 750 | K68: 0.41 | L68: 749 | M68: 0 | N68: 1 | O68: =I68+N68 -> 1
A69: 3 | B69: Telephone Beetel | C69: 2017/EQP/0015 | D69: Phuntsholing GPO | E69: 42824 | F69: PASSANG WAIBA | G69: 5 | H69: 1200 | I69: 24 | J69: 1176 | K69: 0.64 | L69: 1175 | M69: 0 | N69: 1 | O69: =I69+N69 -> 25
A70: 4 | B70: Water Boiler | C70: 2004/EQP/0450 | D70: Phuntsholing GPO | E70: 38105 | F70: KELZANG TOBGAY | G70: 5 | H70: 1490 | I70: 0 | J70: 1490 | K70: 0.82 | L70: 1489 | M70: 0 | N70: 1 | O70: =I70+N70 -> 1
A71: 5 | B71: Scanner Barcode | C71: 2007/EQP/0070 | D71: Phuntsholing GPO | E71: 39262 | F71: TASHI YANGDEN | G71: 5 | H71: 3320.83 | I71: 0 | J71: 3320.83 | K71: 1.82 | L71: 3319.83 | M71: 0 | N71: 1 | O71: =I71+N71 -> 1
A72: 6 | B72: Photo Copy Machine | C72: 2010/EQP/0030 | D72: Phuntsholing GPO | E72: 40188 | F72: TASHI YANGDEN | G72: 5 | H72: 59000 | I72: 0 | J72: 59000 | K72: 32.33 | L72: 58999 | M72: 0 | N72: 1 | O72: =I72+N72 -> 1
A73: 7 | B73: Stabilizer UPS | C73: 2016/EQP/0123 | D73: Phuntsholing GPO | E73: 42626 | F73: TASHI YANGDEN | G73: 5 | H73: 4990 | I73: 99.8 | J73: 4890.2 | K73: 2.68 | L73: 4889.2 | M73: 0 | N73: 1 | O73: =I73+N73 -> 100.8
A74: 8 | B74: Weighing Digital Letter Scale | C74: 1981/EQP/0005 | D74: Phuntsholing GPO | E74: 29587 | F74: TASHI YANGDEN | G74: 5 | H74: 261 | I74: 0 | J74: 261 | K74: 0.14 | L74: 260 | M74: 0 | N74: 1 | O74: =I74+N74 -> 1
A75: 9 | B75: Telephone | C75: 2003/EQP/0079 | D75: Phuntsholing GPO | E75: 37978 | F75: TASHI YANGDEN | G75: 5 | H75: 650 | I75: 0 | J75: 650 | K75: 0.36 | L75: 649 | M75: 0 | N75: 1 | O75: =I75+N75 -> 1
A76: 10 | B76: Scanner Barcode | C76: 2007/EQP/0069 | D76: Phuntsholing GPO | E76: 39262 | F76: TASHI YANGDEN | G76: 5 | H76: 3320.83 | I76: 0 | J76: 3320.83 | K76: 1.82 | L76: 3319.83 | M76: 0 | N76: 1 | O76: =I76+N76 -> 1
A77: 11 | B77: Computer | C77: 2010/EQP/0008 | D77: Phuntsholing GPO | E77: 40306 | F77: TASHI YANGDEN | G77: 5 | H77: 34827 | I77: 0 | J77: 34827 | K77: 19.08 | L77: 34826 | M77: 0 | N77: 1 | O77: =I77+N77 -> 1
A78: 12 | B78: Photo Copy Machine | C78: 2010/EQP/0029 | D78: Phuntsholing GPO | E78: 40188 | F78: TASHI YANGDEN | G78: 5 | H78: 59000 | I78: 0 | J78: 59000 | K78: 32.33 | L78: 58999 | M78: 0 | N78: 1 | O78: =I78+N78 -> 1
... A98: 32 | B98: Mobile Mircomak | C98: 2012/EQP/0077 | D98: Phuntsholing GPO | E98: 41235 | F98: TASHI YANGDEN | G98: 5 | H98: 3000 | I98: 0 | J98: 3000 | K98: 1.64 | L98: 2999 | M98: 0 | N98: 1 | O98: =I98+N98 -> 1
A100: Gedu
A101: 1 | B101: Telephone | C101: 2000/EQP/0039 | D101: Gedu PO | E101: 36684 | F101: SINGYE RINZIN | G101: 5 | H101: 500 | I101: 0 | J101: 500 | K101: 0.27 | L101: 499 | M101: 0 | N101: 1 | O101: =I101+N101 -> 1
A102: 5 | B102: Weighing Digital Letter Scale | C102: 1978/EQP/0003 | D102: Gomtu PO | E102: 28491 | F102: THARKA MAN BISWA | G102: 5 | H102: 6860 | I102: 0 | J102: 6860 | K102: 3.76 | L102: 6859 | M102: 0 | N102: 1 | O102: =I102+N102 -> 1
A103: 2 | B103: Room Blower Heater | C103: 2018/EQP/0129 | D103: Gedu PO | E103: 43202 | F103: SINGYE RINZIN | G103: 5 | H103: 2189 | I103: 43.78 | J103: 2145.22 | K103: 1.18 | L103: 1871.13 | M103: 250.16 | N103: 23.93 | O103: =I103+N103 -> 67.71
A106: Centrel Region
A107: Gelephu GPO
A108: 1 | B108: Computer | C108: 2009/EQP/0007 | D108: Gelephu GPO | E108: 39902 | F108: SARMILLA CHHETRI | G108: 5 | H108: 34999 | I108: 0 | J108: 34999 | K108: 19.18 | L108: 34998 | M108: 0 | N108: 1 | O108: =I108+N108 -> 1
A109: 2 | B109: UPS | C109: 2009/EQP/0060 | D109: Gelephu GPO | E109: 40111 | F109: SARMILLA CHHETRI | G109: 5 | H109: 4600 | I109: 0 | J109: 4600 | K109: 2.52 | L109: 4599 | M109: 0 | N109: 1 | O109: =I109+N109 -> 1
A110: 3 | B110: Photo Copy Machine | C110: 2016/EQP/0068 | D110: Gelephu GPO | E110: 42478 | F110: SARMILLA CHHETRI | G110: 5 | H110: 37000 | I110: 740 | J110: 36260 | K110: 19.87 | L110: 36259 | M110: 0 | N110: 1 | O110: =I110+N110 -> 741
A111: 4 | B111: Stabilizer | C111: 2016/EQP/0137 | D111: Gelephu GPO | E111: 42626 | F111: SARMILLA CHHETRI | G111: 5 | H111: 4990 | I111: 99.8 | J111: 4890.2 | K111: 2.68 | L111: 4889.2 | M111: 0 | N111: 1 | O111: =I111+N111 -> 100.8
A112: 5 | B112: Scanner Barcode | C112: 2018/EQP/0045 | D112: Gelephu GPO | E112: 43229 | F112: SARMILLA CHHETRI | G112: 5 | H112: 2990 | I112: 59.8 | J112: 2930.2 | K112: 1.61 | L112: 2665.63 | M112: 263.57 | N112: 1 | O112: =I112+N112 -> 60.8
A113: 6 | B113: Water Boiler | C113: 2001/EQP/0159 | D113: Gelephu GPO | E113: 37008 | F113: NGAWANG LHAMO | G113: 5 | H113: 2000 | I113: 0 | J113: 2000 | K113: 1.1 | L113: 1999 | M113: 0 | N113: 1 | O113: =I113+N113 -> 1
A114: 7 | B114: Printer EPSON LQ G3110 | C114: 2015/EQP/0018 | D114: Gelephu GPO | E114: 42177 | F114: HARI MAYA GURUNG | G114: 5 | H114: 12960 | I114: 0 | J114: 12960 | K114: 7.1 | L114: 12959 | M114: 0 | N114: 1 | O114: =I114+N114 -> 1
A115: 8 | B115: Scanner Barcode | C115: 2018/EQP/0045 | D115: Gelephu GPO | E115: 43229 | F115: SARMILLA CHHETRI | G115: 5 | H115: 2990 | I115: 59.8 | J115: 2930.2 | K115: 1.61 | L115: 2665.63 | M115: 263.57 | N115: 1 | O115: =I115+N115 -> 60.8
A116: 9 | B116: Printer EPSON | C116: 2013/EQP/0185 | D116: Bumthang PO | E116: 41516 | F116: DAWA GYELPO | G116: 5 | H116: 9890 | I116: 0 | J116: 9890 | K116: 5.42 | L116: 9889 | M116: 0 | N116: 1 | O116: =I116+N116 -> 1
A117: 10 | B117: Printer EPSON P1108 | C117: 2018/EQP/0173 | D117: Samtse PO | E117: 43339 | F117: SAN BDR GURUNG | G117: 5 | H117: 13790 | I117: 275.8 | J117: 13514.2 | K117: 7.41 | L117: 12339.48 | M117: 1173.72 | N117: 1 | O117: =I117+N117 -> 276.8
A118: 11 | B118: Computer | C118: 2016/EQP/0015 | D118: Trongsa PO | E118: 42387 | F118: TSHECHEY WANGMO | G118: 5 | H118: 39790 | I118: 795.8 | J118: 38994.2 | K118: 21.37 | L118: 38993.2 | M118: 0 | N118: 1 | O118: =I118+N118 -> 796.8
A119: 12 | B119: Printer EPSON LQ 310 | C119: 2016/EQP/0094 | D119: Trongsa PO | E119: 42593 | F119: TSHECHEY WANGMO | G119: 5 | H119: 12390 | I119: 247.8 | J119: 12142.2 | K119: 6.65 | L119: 12141.2 | M119: 0 | N119: 1 | O119: =I119+N119 -> 248.8
... A135: 28 | B135: Room Heater Double Rod | C135: 2018/EQP/0099 | D135: Dagapela PO | E135: 43202 | F135: INDRA BDR DHITAL | G135: 5 | H135: 1499 | I135: 29.98 | J135: 1469.02 | K135: 0.81 | L135: 1282.03 | M135: 171.72 | N135: 15.27 | O135: =I135+N135 -> 45.25
A138: Central Region
A139: Sandrup Jongkhar GPO
A140: 1 | B140: Weighing Digital Letter Scale | C140: 1993/EQP/0039 | D140: Samdrup Jongkhar GPO | E140: 33970 | F140: PEMA DEKI | G140: 5 | H140: 1364.8 | I140: 0 | J140: 1364.8 | K140: 0.75 | L140: 1363.8 | M140: 0 | N140: 1 | O140: =I140+N140 -> 1
A141: 2 | B141: Laptop | C141: 2016/EQP/0054 | D141: Samdrup Jongkhar GPO | E141: 42621 | F141: PEMA DEKI | G141: 5 | H141: 38790 | I141: 775.8 | J141: 38014.2 | K141: 20.83 | L141: 38013.2 | M141: 0 | N141: 1 | O141: =I141+N141 -> 776.8
A142: 3 | B142: Stabilizer | C142: 2016/EQP/0145 | D142: Samdrup Jongkhar GPO | E142: 42626 | F142: PEMA DEKI | G142: 5 | H142: 4990 | I142: 99.8 | J142: 4890.2 | K142: 2.68 | L142: 4889.2 | M142: 0 | N142: 1 | O142: =I142+N142 -> 100.8
A143: 4 | B143: Computer | C143: 2018/EQP/0027 | D143: Samdrup Jongkhar GPO | E143: 43328 | F143: PEMA DEKI | G143: 5 | H143: 42000 | I143: 840 | J143: 41160 | K143: 22.55 | L143: 37765.19 | M143: 3393.81 | N143: 1 | O143: =I143+N143 -> 841
A144: 5 | B144: STABILIZER | C144: 2018/EQP/0163 | D144: Samdrup Jongkhar GPO | E144: 43459 | F144: PEMA DEKI | G144: 5 | H144: 5400 | I144: 108 | J144: 5292 | K144: 2.9 | L144: 4565.32 | M144: 614.8 | N144: 111.88 | O144: =I144+N144 -> 219.88
A145: 6 | B145: Photo Copy Machine | C145: 2019/EQP/0039 | D145: Samdrup Jongkhar GPO | E145: 43671 | F145: PEMA DEKI | G145: 5 | H145: 39000 | I145: 780 | J145: 38220 | K145: 20.94 | L145: 32858.04 | M145: 4439.28 | N145: 922.68 | O145: =I145+N145 -> 1702.68
A146: 7 | B146: UPS | C146: 2019/EQP/0045 | D146: Samdrup Jongkhar GPO | E146: 43671 | F146: DORJI CHOZOM | G146: 5 | H146: 5897 | I146: 117.94 | J146: 5779.06 | K146: 3.17 | L146: 4969.68 | M146: 672.04 | N146: 137.34 | O146: =I146+N146 -> 255.28
A147: 8 | B147: Telephone | C147: 2001/EQP/0169 | D147: Trashigang PO | E147: 36939 | F147: THINLEY ZANGMO | G147: 5 | H147: 800 | I147: 0 | J147: 800 | K147: 0.44 | L147: 799 | M147: 0 | N147: 1 | O147: =I147+N147 -> 1
A148: 9 | B148: Telephone | C148: 2009/EQP/0065 | D148: Trashigang PO | E148: 39998 | F148: THINLEY ZANGMO | G148: 5 | H148: 550 | I148: 0 | J148: 550 | K148: 0.3 | L148: 549 | M148: 0 | N148: 1 | O148: =I148+N148 -> 1
A149: 10 | B149: Printer HP laserjet M12A | C149: 2018/EQP/0082 | D149: Trashigang PO | E149: 43443 | F149: THINLEY ZANGMO | G149: 5 | H149: 8490 | I149: 169.8 | J149: 8320.2 | K149: 4.56 | L149: 7540.42 | M149: 778.78 | N149: 1 | O149: =I149+N149 -> 170.8
A150: 11 | B150: Scanner Barcode | C150: 2009/EQP/0047 | D150: Trashigang PO | E150: 40160 | F150: THINLEY ZANGMO | G150: 5 | H150: 8800 | I150: 0 | J150: 8800 | K150: 4.82 | L150: 8799 | M150: 0 | N150: 1 | O150: =I150+N150 -> 1
...

Sheet Annex 2B Unserviceable items FN
B1: FNF items available and recorded in ERP system but Unserviceable
A2: Western Region
A3: # | B3: Assets | C3: Asset ID | D3: Location | E3: Put-in Use Date | F3: Custodian | G3: Useful Life | H3: Gross Value | I3: Salvage Value | J3: Depreciable Amt | K3: Dep per Day | L3: Opening Dep | M3: Depreciation | N3: Net Value | O3: Selvage value + Net Value
A4: 1 | B4: Table Date Stamp | C4: 1979/FNF/0028 | D4: Wangdue PO | E4: 28856 | F4: UGYEN WANGMO | G4: 10 | H4: 55 | I4: 0 | J4: 55 | K4: 0.02 | L4: 54 | M4: 0 | N4: 1 | O4: =I4+N4 -> 1
A5: 2 | B5: Chair | C5: 1980/FNF/0005 | D5: Wangdue PO | E5: 29221 | F5: UGYEN WANGMO | G5: 5 | H5: 60 | I5: 0 | J5: 60 | K5: 0.03 | L5: 59 | M5: 0 | N5: 1 | O5: =I5+N5 -> 1
A6: 3 | B6: Table Half Secretrate | C6: 1980/FNF/0029 | D6: Wangdue PO | E6: 29221 | F6: UGYEN WANGMO | G6: 10 | H6: 197 | I6: 0 | J6: 197 | K6: 0.05 | L6: 196 | M6: 0 | N6: 1 | O6: =I6+N6 -> 1
A7: 4 | B7: Table Half Secretrate | C7: 1981/FNF/0014 | D7: Wangdue PO | E7: 29587 | F7: UGYEN WANGMO | G7: 10 | H7: 485 | I7: 0 | J7: 485 | K7: 0.13 | L7: 484 | M7: 0 | N7: 1 | O7: =I7+N7 -> 1
A8: 5 | B8: Almirah Steel | C8: 1984/FNF/0016 | D8: Wangdue PO | E8: 30682 | F8: UGYEN WANGMO | G8: 12 | H8: 2275 | I8: 0 | J8: 2275 | K8: 0.52 | L8: 2274 | M8: 0 | N8: 1 | O8: =I8+N8 -> 1
A9: 6 | B9: Rack File | C9: 1985/FNF/0018 | D9: Wangdue PO | E9: 31048 | F9: UGYEN WANGMO | G9: 10 | H9: 525 | I9: 0 | J9: 525 | K9: 0.14 | L9: 524 | M9: 0 | N9: 1 | O9: =I9+N9 -> 1
A10: 7 | B10: Chair | C10: 1987/FNF/0003 | D10: Wangdue PO | E10: 31778 | F10: UGYEN WANGMO | G10: 5 | H10: 120 | I10: 0 | J10: 120 | K10: 0.07 | L10: 119 | M10: 0 | N10: 1 | O10: =I10+N10 -> 1
A11: 8 | B11: Chair Revolving | C11: 2002/FNF/0017 | D11: Wangdue PO | E11: 37428 | F11: UGYEN WANGMO | G11: 5 | H11: 3675 | I11: 0 | J11: 3675 | K11: 2.01 | L11: 3674 | M11: 0 | N11: 1 | O11: =I11+N11 -> 1
A12: 9 | B12: Chair Revolving Half Back | C12: 2015/FNF/0047 | D12: Wangdue PO | E12: 42233 | F12: UGYEN WANGMO | G12: 5 | H12: 4690 | I12: 93.8 | J12: 4596.2 | K12: 2.52 | L12: 4595.2 | M12: 0 | N12: 1 | O12: =I12+N12 -> 94.8
A13: 10 | B13: Table | C13: 1983/FNF/0017 | D13: Haa PO | E13: 30317 | F13: SONAM | G13: 10 | H13: 650 | I13: 0 | J13: 650 | K13: 0.18 | L13: 649 | M13: 0 | N13: 1 | O13: =I13+N13 -> 1
A14: 11 | B14: Chair | C14: 2009/FNF/0005 | D14: Punakha PO | E14: 40172 | F14: SONAM PELDON | G14: 5 | H14: 1400 | I14: 0 | J14: 1400 | K14: 0.77 | L14: 1399 | M14: 0 | N14: 1 | O14: =I14+N14 -> 1
A15: 12 | B15: Chair Half Back Revolving | C15: 2017/FNF/0055 | D15: Punakha PO | E15: 42978 | F15: SONAM PELDON | G15: 5 | H15: 4950 | I15: 99 | J15: 4851 | K15: 2.66 | L15: 4850 | M15: 0 | N15: 1 | O15: =I15+N15 -> 100
... A19: 16 | B19: Chair Revolving Full Back | C19: 2018/FNF/0100 | D19: Gasa PO | E19: 43317 | F19: UGYEN PHUNTSHO | G19: 5 | H19: 5150 | I19: 103 | J19: 5047 | K19: 2.77 | L19: 4843.92 | M19: 202.08 | N19: 1 | O19: =I19+N19 -> 104
A23: Southern Region
A24: 1 | B24: Trolly Steel | C24: 2020/FNF/0002 | D24: Phuntsholing GPO | E24: 43909 | F24: TASHI YANGDEN | G24: 6 | H24: 13490 | I24: 269.8 | J24: 13220.2 | K24: 6.04 | L24: 10057.63 | M24: 1280.48 | N24: 1882.09 | O24: =I24+N24 -> 2151.89
A25: 2 | B25: Trolly Steel | C25: 2020/FNF/0003 | D25: Phuntsholing GPO | E25: 43909 | F25: TASHI YANGDEN | G25: 6 | H25: 13490 | I25: 269.8 | J25: 13220.2 | K25: 6.04 | L25: 10057.63 | M25: 1280.48 | N25: 1882.09 | O25: =I25+N25 -> 2151.89
A26: 3 | B26: Counter | C26: 2003/FNF/0010 | D26: Tsimasham PO | E26: 37725 | F26: TASHI DORJI | G26: 10 | H26: 18675 | I26: 0 | J26: 18675 | K26: 5.12 | L26: 18674 | M26: 0 | N26: 1 | O26: =I26+N26 -> 1
A27: 4 | B27: Chair Revolving | C27: 2020/FNF/0061 | D27: Lhamoizingkha PO | E27: 43914 | F27: SARAN KUMAR GURUNG | G27: 10 | H27: 3990 | I27: 79.8 | J27: 3910.2 | K27: 1.07 | L27: 2443.68 | M27: 226.84 | N27: 1239.68 | O27: =I27+N27 -> 1319.48
A28: 5 | B28: File Rack | C28: 2018/FNF/0132 | D28: Thimphu GPO | E28: 43179 | F28: DECHEN WANGMO | G28: 5 | H28: 4243 | I28: 84.86 | J28: 4158.14 | K28: 2.28 | L28: 4075.37 | M28: 81.77 | N28: 1 | O28: =I28+N28 -> 85.86
A29: 6 | B29: Chair Revolving | C29: 2018/FNF/0147 | D29: Gomtu PO | E29: 43317 | F29: THARKA MAN BISWA | G29: 5 | H29: 4950 | I29: 99 | J29: 4851 | K29: 2.66 | L29: 4654.91 | M29: 195.09 | N29: 1 | O29: =I29+N29 -> 100
A33: Central Region
A34: 1 | B34: Chair | C34: 1983/FNF/0023 | D34: Sarpang PO | E34: 30317 | F34: CHABILAL CHAPAGAI | G34: 5 | H34: 1075 | I34: 0 | J34: 1075 | K34: 0.59 | L34: 1074 | M34: 0 | N34: 1 | O34: =I34+N34 -> 1
A35: 2 | B35: Table Wooden | C35: 1979/FNF/0041 | D35: Gelephu GPO | E35: 28856 | F35: HARI MAYA GURUNG | G35: 10 | H35: 280 | I35: 0 | J35: 280 | K35: 0.08 | L35: 279 | M35: 0 | N35: 1 | O35: =I35+N35 -> 1
A36: 3 | B36: Chair Steel | C36: 2005/FNF/0004 | D36: Bumthang PO | E36: 38570 | F36: DAWA GYELPO | G36: 6 | H36: 3919.2 | I36: 0 | J36: 3919.2 | K36: 1.79 | L36: 3918.2 | M36: 0 | N36: 1 | O36: =I36+N36 -> 1
A37: 4 | B37: Table Steel | C37: 1984/FNF/0042 | D37: Dagapela PO | E37: 30682 | F37: INDRA BDR DHITAL | G37: 12 | H37: 280 | I37: 0 | J37: 280 | K37: 0.06 | L37: 279 | M37: 0 | N37: 1 | O37: =I37+N37 -> 1
A40: Southern Region
A41: 1 | B41: Table Sorting | C41: 1978/FNF/0037 | D41: Samdrup Jongkhar GPO | E41: 28491 | F41: PEMA DEKI | G41: 10 | H41: 340 | I41: 0 | J41: 340 | K41: 0.09 | L41: 339 | M41: 0 | N41: 1 | O41: =I41+N41 -> 1
A42: 2 | B42: Almirah Steel | C42: 1984/FNF/0002 | D42: Samdrup Jongkhar GPO | E42: 30682 | F42: PEMA DEKI | G42: 12 | H42: 1350 | I42: 0 | J42: 1350 | K42: 0.31 | L42: 1349 | M42: 0 | N42: 1 | O42: =I42+N42 -> 1
A43: 3 | B43: Rack Show Case | C43: 1998/FNF/0026 | D43: Samdrup Jongkhar GPO | E43: 35961 | F43: PEMA DEKI | G43: 12 | H43: 2955 | I43: 0 | J43: 2955 | K43: 0.67 | L43: 2954 | M43: 0 | N43: 1 | O43: =I43+N43 -> 1
A44: 4 | B44: Table Half Secretrate | C44: 2015/FNF/0092 | D44: Samdrup Jongkhar GPO | E44: 42276 | F44: PEMA DEKI | G44: 10 | H44: 4787 | I44: 95.74 | J44: 4691.26 | K44: 1.29 | L44: 4690.26 | M44: 0 | N44: 1 | O44: =I44+N44 -> 96.74
A45: 5 | B45: Table | C45: 2017/FNF/0097 | D45: Samdrup Jongkhar GPO | E45: 42978 | F45: PEMA DEKI | G45: 10 | H45: 15830 | I45: 316.6 | J45: 15513.4 | K45: 4.25 | L45: 13402.79 | M45: 901 | N45: 1209.61 | O45: =I45+N45 -> 1526.21
A46: 6 | B46: Chair Half Back Revolving | C46: 2020/FNF/0046 | D46: Trashigang PO | E46: 43909 | F46: TSHERING CHOPHEL | G46: 5 | H46: 3890 | I46: 77.8 | J46: 3812.2 | K46: 2.09 | L46: 3154.79 | M46: 443.08 | N46: 214.33 | O46: =I46+N46 -> 292.13
A47: 7 | B47: Almirah Steel | C47: 1984/FNF/0021 | D47: Samdrup Jongkhar GPO | E47: 30682 | F47: TSHERING CHOPHEL | G47: 12 | H47: 1350 | I47: 0 | J47: 1350 | K47: 0.31 | L47: 1349 | M47: 0 | N47: 1 | O47: =I47+N47 -> 1
A48: 8 | B48: Chair Revolving | C48: 2014/FNF/0021 | D48: Samdrupcholing PO | E48: 41951 | F48: RINCHEN TSHERING | G48: 5 | H48: 4980 | I48: 0 | J48: 4980 | K48: 2.73 | L48: 4979 | M48: 0 | N48: 1 | O48: =I48+N48 -> 1
A49: 9 | B49: Chair Half Back Revolving | C49: 2021/FNF/0001 | D49: Jomotshangkha PO | E49: 44244 | F49: KINZANG NORBU | G49: 5 | H49: 3890 | I49: 77.8 | J49: 3812.2 | K49: 2.09 | L49: 2619.24 | M49: 443.08 | N49: 749.88 | O49: =I49+N49 -> 827.68
A50: 10 | B50: Table Wooden | C50: 1979/FNF/0045 | D50: Pemagatshel PO | E50: 28856 | F50: PHUNTSHO DORJI | G50: 10 | H50: 100 | I50: 0 | J50: 100 | K50: 0.03 | L50: 99 | M50: 0 | N50: 1 | O50: =I50+N50 -> 1
A51: 11 | B51: Chair Revolving | C51: 2015/FNF/0041 | D51: Nganglam PO | E51: 42325 | F51: NORBU | G51: 5 | H51: 5000 | I51: 100 | J51: 4900 | K51: 2.68 | L51: 4899 | M51: 0 | N51: 1 | O51: =I51+N51 -> 101
A52: 12 | B52: Chair Revolving | C52: 1993/FNF/0003 | D52: Rangjung PO | E52: 33970 | F52: KINZANG THINLEY | G52: 5 | H52: 390 | I52: 0 | J52: 390 | K52: 0.21 | L52: 389 | M52: 0 | N52: 1 | O52: =I52+N52 -> 1
... A61: 21 | B61: Rack File | C61: 1998/FNF/0030 | D61: Wamrong PO | E61: 36134 | F61: NETEN DORJI | G61: 10 | H61: 1709.92 | I61: 0 | J61: 1709.92 | K61: 0.47 | L61: 1708.92 | M61: 0 | N61: 1 | O61: =I61+N61 -> 1
O62: =SUM(O4:O61) -> 8985.68

Sheet Annexure 2C Unserviceable Grant
A1: Unserviceable Grant
A2: # | B2: Assets | C2: Asset ID | D2: Location | E2: Put-in Use Date | F2: Custodian | G2: Useful Life | H2: Gross Value | I2: Salvage Value | J2: Depreciable Amt | K2: Dep per Day | L2: Opening Dep | M2: Depreciation | N2: Net Value | O2: Selvage value + Net Value
A3: Thimphu GPO
A4: 1 | B4: Barcode Reader | C4: 2016/GRA/0006 | D4: Thimphu GPO | E4: 42555 | F4: LHAM WANGCHUK | G4: 5 | H4: 11220 | I4: 0 | J4: 11220 | K4: 6.15 | L4: 11219 | M4: 0 | N4: 1 | O4: =I4+N4 -> 1
A5: 2 | B5: EMERGENCY FLASH LIGHT | C5: 2020/GRA/0096 | D5: Wangdue PO | E5: 44196 | F5: UGYEN WANGMO | G5: 5 | H5: 5353 | I5: 0 | J5: 5353 | K5: 2.93 | L5: 4280.73 | M5: 621.16 | N5: 451.11 | O5: =I5+N5 -> 451.11
A6: 3 | B6: FIRST AID KITS | C6: 2020/GRA/0146 | D6: Wangdue PO | E6: 44196 | F6: UGYEN WANGMO | G6: 5 | H6: 6231 | I6: 0 | J6: 6231 | K6: 3.41 | L6: 4982.01 | M6: 722.92 | N6: 526.07 | O6: =I6+N6 -> 526.07
A7: 4 | B7: EMERGENCY FLASH LIGHT | C7: 2020/GRA/0097 | D7: Haa PO | E7: 44196 | F7: SONAM | G7: 5 | H7: 5353 | I7: 0 | J7: 5353 | K7: 2.93 | L7: 4280.73 | M7: 621.16 | N7: 451.11 | O7: =I7+N7 -> 451.11
A8: 5 | B8: EMERGENCY FLASH LIGHT | C8: 2020/GRA/0095 | D8: Punakha PO | E8: 44196 | F8: SONAM PELDON | G8: 5 | H8: 5353 | I8: 0 | J8: 5353 | K8: 2.93 | L8: 4280.73 | M8: 621.16 | N8: 451.11 | O8: =I8+N8 -> 451.11
A11: Southern Region
A12: 1 | B12: Barcode Reader | C12: 2016/GRA/0020 | D12: Phuntsholing GPO | E12: 42555 | F12: LHAMO | G12: 5 | H12: 11220 | I12: 0 | J12: 11220 | K12: 6.15 | L12: 11219 | M12: 0 | N12: 1 | O12: =I12+N12 -> 1
A13: 2 | B13: UPS | C13: 2018/GRA/0031 | D13: Gedu PO | E13: 43441 | F13: SINGYE RINZIN | G13: 5 | H13: 3950 | I13: 79 | J13: 3871 | K13: 2.12 | L13: 3870 | M13: 0 | N13: 1 | O13: =I13+N13 -> 80
A16: Central Region
A17: 1 | B17: Barcode Reader | C17: 2016/GRA/0015 | D17: Gelephu GPO | E17: 42555 | F17: SARMILLA CHHETRI | G17: 5 | H17: 11220 | I17: 0 | J17: 11220 | K17: 6.15 | L17: 11219 | M17: 0 | N17: 1 | O17: =I17+N17 -> 1
A18: 2 | B18: Computer | C18: 2016/GRA/0060 | D18: Gelephu GPO | E18: 42600 | F18: SARMILLA CHHETRI | G18: 5 | H18: 37490 | I18: 749.8 | J18: 36740.2 | K18: 0 | L18: 36739.2 | M18: 0 | N18: 1 | O18: =I18+N18 -> 750.8
A19: 3 | B19: UPS | C19: 2018/GRA/0025 | D19: Trongsa PO | E19: 43347 | F19: TSHECHEY WANGMO | G19: 5 | H19: 3950 | I19: 79 | J19: 3871 | K19: 2.12 | L19: 3870 | M19: 0 | N19: 1 | O19: =I19+N19 -> 80
A20: 4 | B20: Computer | C20: 2016/GRA/0071 | D20: Trongsa PO | E20: 42600 | F20: TSHECHEY WANGMO | G20: 5 | H20: 37490 | I20: 749.8 | J20: 36740.2 | K20: 20.13 | L20: 36739.2 | M20: 0 | N20: 1 | O20: =I20+N20 -> 750.8
A21: 5 | B21: UPS | C21: 2018/GRA/0020 | D21: Panbang PO | E21: 43347 | F21: RINCHEN CHODA | G21: 5 | H21: 3950 | I21: 79 | J21: 3871 | K21: 2.12 | L21: 3870 | M21: 0 | N21: 1 | O21: =I21+N21 -> 80
A22: 6 | B22: EMERGENCY FLASH LIGHT | C22: 2020/GRA/0114 | D22: Panbang PO | E22: 44196 | F22: RINCHEN CHODA | G22: 5 | H22: 5353 | I22: 0 | J22: 5353 | K22: 2.93 | L22: 4280.73 | M22: 621.16 | N22: 451.11 | O22: =I22+N22 -> 451.11
A23: 7 | B23: Barcode Reader | C23: 2016/GRA/0003 | D23: Sarpang PO | E23: 42555 | F23: CHABILAL CHAPAGAI | G23: 5 | H23: 11220 | I23: 0 | J23: 11220 | K23: 6.15 | L23: 11219 | M23: 0 | N23: 1 | O23: =I23+N23 -> 1
A24: 8 | B24: EMERGENCY FLASH LIGHT | C24: 2020/GRA/0107 | D24: Dagana PO | E24: 44196 | F24: SANGAY CHOZOM | G24: 5 | H24: 5353 | I24: 0 | J24: 5353 | K24: 2.93 | L24: 4280.73 | M24: 621.16 | N24: 451.11 | O24: =I24+N24 -> 451.11
A27: Eastern Region
A28: 1 | B28: UPS | C28: 2016/GRA/0009 | D28: Samdrup Jongkhar GPO | E28: 42555 | F28: PEMA DEKI | G28: 5 | H28: 11220 | I28: 224.4 | J28: 10995.6 | K28: 6.02 | L28: 10994.6 | M28: 0 | N28: 1 | O28: =I28+N28 -> 225.4
A29: 2 | B29: UPS | C29: 2016/GRA/0011 | D29: Samdrup Jongkhar GPO | E29: 42555 | F29: PEMA DEKI | G29: 5 | H29: 11220 | I29: 224.4 | J29: 10995.6 | K29: 6.02 | L29: 10994.6 | M29: 0 | N29: 1 | O29: =I29+N29 -> 225.4
A30: 3 | B30: USP | C30: 2016/GRA/0017 | D30: Samdrup Jongkhar GPO | E30: 42555 | F30: PEMA DEKI | G30: 5 | H30: 11220 | I30: 224.4 | J30: 10995.6 | K30: 6.02 | L30: 10994.6 | M30: 0 | N30: 1 | O30: =I30+N30 -> 225.4
A31: 4 | B31: Barcode Reader | C31: 2016/GRA/0018 | D31: Samdrup Jongkhar GPO | E31: 42555 | F31: PEMA DEKI | G31: 5 | H31: 11220 | I31: 0 | J31: 11220 | K31: 6.15 | L31: 11219 | M31: 0 | N31: 1 | O31: =I31+N31 -> 1
A32: 5 | B32: UPS | C32: 2018/GRA/0013 | D32: Samdrup Jongkhar GPO | E32: 43347 | F32: PEMA DEKI | G32: 5 | H32: 3950 | I32: 79 | J32: 3871 | K32: 2.12 | L32: 3870 | M32: 0 | N32: 1 | O32: =I32+N32 -> 80
A33: 6 | B33: UPS | C33: 2018/GRA/0015 | D33: Samdrup Jongkhar GPO | E33: 43347 | F33: PEMA DEKI | G33: 5 | H33: 3950 | I33: 79 | J33: 3871 | K33: 2.12 | L33: 3870 | M33: 0 | N33: 1 | O33: =I33+N33 -> 80
A34: 7 | B34: EMERGENCY FLASH LIGHT | C34: 2020/GRA/0121 | D34: Trashigang PO | E34: 44196 | F34: THINLEY ZANGMO | G34: 5 | H34: 5353 | I34: 0 | J34: 5353 | K34: 2.93 | L34: 4280.73 | M34: 621.16 | N34: 451.11 | O34: =I34+N34 -> 451.11
A35: 8 | B35: FIRST AID KITS | C35: 2020/GRA/0171 | D35: Trashigang PO | E35: 44196 | F35: THINLEY ZANGMO | G35: 5 | H35: 6231 | I35: 0 | J35: 6231 | K35: 3.41 | L35: 4982.01 | M35: 722.92 | N35: 526.07 | O35: =I35+N35 -> 526.07
A36: 9 | B36: Barcode Reader | C36: 2016/GRA/0039 | D36: Trashigang PO | E36: 42555 | F36: THINLEY ZANGMO | G36: 5 | H36: 11220 | I36: 0 | J36: 11220 | K36: 6.15 | L36: 11219 | M36: 0 | N36: 1 | O36: =I36+N36 -> 1
A37: 10 | B37: UPS | C37: 2018/GRA/0014 | D37: Jomotshangkha PO | E37: 43347 | F37: KINZANG NORBU | G37: 5 | H37: 3950 | I37: 79 | J37: 3871 | K37: 2.12 | L37: 3870 | M37: 0 | N37: 1 | O37: =I37+N37 -> 80
A38: 11 | B38: EMERGENCY FLASH LIGHT | C38: 2020/GRA/0126 | D38: Pemagatshel PO | E38: 44196 | F38: PHUNTSHO DORJI | G38: 5 | H38: 5353 | I38: 0 | J38: 5353 | K38: 2.93 | L38: 4280.73 | M38: 621.16 | N38: 451.11 | O38: =I38+N38 -> 451.11
A39: 12 | B39: FIRST AID KITS | C39: 2020/GRA/0176 | D39: Pemagatshel PO | E39: 44196 | F39: PHUNTSHO DORJI | G39: 5 | H39: 6231 | I39: 0 | J39: 6231 | K39: 3.41 | L39: 4982.01 | M39: 722.92 | N39: 526.07 | O39: =I39+N39 -> 526.07
... A43: 16 | B43: Zebra Printer | C43: 2016/GRA/0047 | D43: Gyelposhing PO | E43: 42600 | F43: KUENGA YESHI | G43: 5 | H43: 17390 | I43: 347.8 | J43: 17042.2 | K43: 9.34 | L43: 17041.2 | M43: 0 | N43: 1 | O43: =I43+N43 -> 348.8
O44: =SUM(O4:O43) -> 8580.38

Sheet Annex 2D Surrendered EQP
A1: Surrendered EQP Items
A2: # | B2: Assets | C2: Asset ID | D2: Location | E2: Put-in Use Date | F2: Useful Life | G2: Gross Value | H2: Salvage Value | I2: Depreciable Amt | J2: Dep per Day | K2: Opening Dep | L2: Depreciation | M2: Net Value | N2: Salvage + Net Value | O2: Status
A3: 1 | B3: Fax Machine | C3: 1994/EQP/0029 | D3: ICT | E3: 34335 | F3: 5 | G3: 49360 | H3: 0 | I3: 49360 | J3: 27.05 | K3: 49359 | L3: 0 | M3: 1 | N3: =H3+M3 -> 1 | O3: Surrender
A4: 2 | B4: Computer | C4: 2000/EQP/0026 | D4: ICT | E4: 36795 | F4: 5 | G4: 67911.2 | H4: 0 | I4: 67911.2 | J4: 37.21 | K4: 67910.2 | L4: 0 | M4: 1 | N4: =H4+M4 -> 1 | O4: Surrender
A5: 3 | B5: Room Heater Double Rod | C5: 2001/EQP/0100 | D5: ICT | E5: 37222 | F5: 5 | G5: 800 | H5: 0 | I5: 800 | J5: 0.44 | K5: 799 | L5: 0 | M5: 1 | N5: =H5+M5 -> 1 | O5: Surrender
A6: 4 | B6: Weighing Digital Letter Scale | C6: 2001/EQP/0160 | D6: ICT | E6: 37057 | F6: 5 | G6: 1800 | H6: 0 | I6: 1800 | J6: 0.99 | K6: 1799 | L6: 0 | M6: 1 | N6: =H6+M6 -> 1 | O6: Surrender
A7: 5 | B7: Computer | C7: 2003/EQP/0018 | D7: ICT | E7: 37918 | F7: 5 | G7: 33500 | H7: 0 | I7: 33500 | J7: 18.36 | K7: 33499 | L7: 0 | M7: 1 | N7: =H7+M7 -> 1 | O7: Surrender
A8: 6 | B8: Scanner Scan Jet 3500C | C8: 2004/EQP/0424 | D8: ICT | E8: 37987 | F8: 5 | G8: 6400 | H8: 0 | I8: 6400 | J8: 3.51 | K8: 6399 | L8: 0 | M8: 1 | N8: =H8+M8 -> 1 | O8: Surrender
A9: 7 | B9: Computer | C9: 2005/EQP/0043 | D9: ICT | E9: 38441 | F9: 5 | G9: 47800 | H9: 0 | I9: 47800 | J9: 26.19 | K9: 47799 | L9: 0 | M9: 1 | N9: =H9+M9 -> 1 | O9: Surrender
A10: 8 | B10: Scanner Barcode | C10: 2007/EQP/0060 | D10: ICT | E10: 39262 | F10: 5 | G10: 3320.83 | H10: 0 | I10: 3320.83 | J10: 1.82 | K10: 3319.83 | L10: 0 | M10: 1 | N10: =H10+M10 -> 1 | O10: Surrender
A11: 9 | B11: Computer | C11: 2008/EQP/0018 | D11: ICT | E11: 39570 | F11: 5 | G11: 40999 | H11: 0 | I11: 40999 | J11: 22.47 | K11: 40998 | L11: 0 | M11: 1 | N11: =H11+M11 -> 1 | O11: Surrender
A12: 10 | B12: Fax Machine | C12: 2008/EQP/0066 | D12: ICT | E12: 39609 | F12: 5 | G12: 6351 | H12: 0 | I12: 6351 | J12: 3.48 | K12: 6350 | L12: 0 | M12: 1 | N12: =H12+M12 -> 1 | O12: Surrender
A13: 11 | B13: Fax Machine | C13: 2009/EQP/0013 | D13: ICT | E13: 39951 | F13: 5 | G13: 6351 | H13: 0 | I13: 6351 | J13: 3.48 | K13: 6350 | L13: 0 | M13: 1 | N13: =H13+M13 -> 1 | O13: Surrender
A14: 12 | B14: Room Blower Heater | C14: 2009/EQP/0026 | D14: ICT | E14: 40148 | F14: 5 | G14: 1195 | H14: 0 | I14: 1195 | J14: 0.66 | K14: 1194 | L14: 0 | M14: 1 | N14: =H14+M14 -> 1 | O14: Surrender
... A101: 99 | B101: UPS | C101: 2018/GRA/0019 | D101: ICT | E101: 43347 | F101: 5 | G101: 3950 | H101: 79 | I101: 3871 | J101: 2.12 | K101: 3870 | L101: 0 | M101: 1 | N101: =H101+M101 -> 80 | O101: Surrender
N102: =SUM(N3:N101) -> 35754.85

Sheet Annex 2E Surrendered FNF
A1: Surrendered FNF Items
A2: # | B2: Assets | C2: Asset ID | D2: Location | E2: Put-in Use Date | F2: Useful Life | G2: Gross Value | H2: Salvage Value | I2: Depreciable Amt | J2: Dep per Day | K2: Opening Dep | L2: Depreciation | M2: Net Value | N2: Salvage + Net Value | O2: Status
A3: 1 | B3: Table Wooden | C3: 1986/FNF/0010 | D3: Procurement | E3: 31413 | F3: 5 | G3: 1875 | H3: 0 | I3: 1875 | J3: 1.03 | K3: 1874 | L3: 0 | M3: 1 | N3: =H3+M3 -> 1 | O3: Surrender
A4: 2 | B4: Table Wooden | C4: 1995/FNF/0019 | D4: Procurement | E4: 34700 | F4: 10 | G4: 2000 | H4: 0 | I4: 2000 | J4: 0.55 | K4: 1999 | L4: 0 | M4: 1 | N4: =H4+M4 -> 1 | O4: Surrender
A5: 3 | B5: Table Computer | C5: 2006/FNF/0065 | D5: Procurement | E5: 39030 | F5: 10 | G5: 2350 | H5: 0 | I5: 2350 | J5: 0.64 | K5: 2349 | L5: 0 | M5: 1 | N5: =H5+M5 -> 1 | O5: Surrender
A6: 4 | B6: Full Back Chair Revolving | C6: 2016/FNF/0046 | D6: Procurement | E6: 42660 | F6: 5 | G6: 9330 | H6: 186.6 | I6: 9143.4 | J6: 5.01 | K6: 9142.4 | L6: 0 | M6: 1 | N6: =H6+M6 -> 187.6 | O6: Surrender
N7: =SUM(N3:N6) -> 190.6

Sheet Annex 2F Tally software for dis
A1: Tally Software for disposal
A2: Sl. No. | B2: Assets | C2: Asset ID | D2: Location | E2: Put-in Use Date | F2: Custodian | G2: Useful Life | H2: Gross Value | I2: Salvage Value | J2: Depreciable Amt | K2: Dep per Day | L2: Opening Dep | M2: Depreciation | N2: Net Value | O2: Salvage + Net Value
A3: 1 | B3: Software Tally PARO Serial No. 755550945 | C3: 2017/SOF/0004 | D3: Paro PO | E3: 23/06/2017 | F3: SANGAY ZANGMO | G3: 5 | H3: 292720 | I3: 1 | J3: 292719 | K3: 160.39 | L3: 292718 | M3: 0 | N3: 1 | O3: =I3+N3 -> 2
A4: 2 | B4: Software Tally PHUA Serial No. 765028584 | C4: 2018/SOF/0001 | D4: Phuntsholing GPO | E4: 16/08/2018 | F4: DAWA | G4: 5 | H4: 125000 | I4: 1 | J4: 124999 | K4: 68.49 | L4: 124998 | M4: 0 | N4: 1 | O4: =I4+N4 -> 2
A5: 3 | B5: Software Tally GEDU Serial No. 756621090 | C5: 2019/SOF/0001 | D5: Gedu PO | E5: 26/06/2019 | F5: GANESH BDR. MONGAR | G5: 5 | H5: 16992 | I5: 1 | J5: 16991 | K5: 9.31 | L5: 16990 | M5: 0 | N5: 1 | O5: =I5+N5 -> 2
A6: 4 | B6: Software Tally GMTU Serial No. 746621091 | C6: 2019/SOF/0002 | D6: Gomtu PO | E6: 26/06/2019 | F6: THARKA MAN BISWA | G6: 5 | H6: 16992 | I6: 1 | J6: 16991 | K6: 9.31 | L6: 16990 | M6: 0 | N6: 1 | O6: =I6+N6 -> 2
A7: 5 | B7: Software Tally LHAM Serial No. 736621092 | C7: 2019/SOF/0003 | D7: Lhamoizingkha PO | E7: 26/06/2019 | F7: SARAN KUMAR GURUNG | G7: 5 | H7: 16992 | I7: 1 | J7: 16991 | K7: 9.31 | L7: 16990 | M7: 0 | N7: 1 | O7: =I7+N7 -> 2
A8: 6 | B8: Software Tally SAMA Serial No. 726621093 | C8: 2019/SOF/0004 | D8: Samtse PO | E8: 26/06/2019 | F8: SAN BDR GURUNG | G8: 5 | H8: 16992 | I8: 1 | J8: 16991 | K8: 9.31 | L8: 16990 | M8: 0 | N8: 1 | O8: =I8+N8 -> 2
A9: 7 | B9: Software Tally TCHG Serial No. 716621094 | C9: 2019/SOF/0005 | D9: Trashicholing PO | E9: 26/06/2019 | F9: UGYEN TSHERING | G9: 5 | H9: 16992 | I9: 1 | J9: 16991 | K9: 9.31 | L9: 16990 | M9: 0 | N9: 1 | O9: =I9+N9 -> 2
A10: 8 | B10: Software Tally TSMA Serial No. 796621095 | C10: 2019/SOF/0006 | D10: Tsimasham PO | E10: 26/06/2019 | F10: TASHI DORJI | G10: 5 | H10: 16992 | I10: 1 | J10: 16991 | K10: 9.31 | L10: 16990 | M10: 0 | N10: 1 | O10: =I10+N10 -> 2
A11: 9 | B11: Software Tally JOMO Serial No. 796653018 | C11: 2019/SOF/0007 | D11: Jomotshangkha PO | E11: 43713 | F11: KINZANG NORBU | G11: 5 | H11: 16498 | I11: 1 | J11: 16497 | K11: 9.04 | L11: 15630.8 | M11: 865.2 | N11: 1 | O11: =I11+N11 -> 2
A12: 10 | B12: Software Tally NGLM Serial No. 786653019 | C12: 2019/SOF/0008 | D12: Nganglam PO | E12: 43717 | F12: NORBU | G12: 5 | H12: 16498 | I12: 1 | J12: 16497 | K12: 9.04 | L12: 15576.6 | M12: 919.4 | N12: 1 | O12: =I12+N12 -> 2
A13: 11 | B13: Software Tally DEOT Serial No. 776653020 | C13: 2019/SOF/0009 | D13: Samdrup Jongkhar GPO | E13: 43718 | F13: PEMA DEKI | G13: 5 | H13: 16498 | I13: 1 | J13: 16497 | K13: 9.04 | L13: 15563.06 | M13: 932.94 | N13: 1 | O13: =I13+N13 -> 2
A14: 12 | B14: Software Tally SAMC Serial No. 766653021 | C14: 2019/SOF/0010 | D14: Samdrupcholing PO | E14: 43808 | F14: RINCHEN TSHERING | G14: 5 | H14: 16498 | I14: 1 | J14: 16497 | K14: 9.04 | L14: 15535.96 | M14: 960.04 | N14: 1 | O14: =I14+N14 -> 2
A15: 13 | B15: Software Tally PEMA Serial no. 756653022 | C15: 2019/SOF/0011 | D15: Pemagatshel PO | E15: 14/09/2019 | F15: PHUNTSHO DORJI | G15: 5 | H15: 16498 | I15: 1 | J15: 16497 | K15: 9.04 | L15: 15508.86 | M15: 987.14 | N15: 1 | O15: =I15+N15 -> 2
A16: 14 | B16: Software Tally GYPG Serial No. 746653023 | C16: 2019/SOF/0012 | D16: Gyelposhing PO | E16: 17/10/2019 | F16: KUENGA YESHI | G16: 5 | H16: 16498 | I16: 1 | J16: 16497 | K16: 9.04 | L16: 15061.78 | M16: 1434.22 | N16: 1 | O16: =I16+N16 -> 2
A17: 15 | B17: Software Tally MONA Serial No. 736653024 | C17: 2019/SOF/0013 | D17: Mongar PO | E17: 19/10/2019 | F17: PEMA YANGDON | G17: 5 | H17: 16498 | I17: 1 | J17: 16497 | K17: 9.04 | L17: 15034.7 | M17: 1461.3 | N17: 1 | O17: =I17+N17 -> 2
A18: 16 | B18: Software Tally LUNT Serial No. 726653025 | C18: 2019/SOF/0014 | D18: Lhuntse PO | E18: 19/10/2019 | F18: UGYEN | G18: 5 | H18: 16498 | I18: 1 | J18: 16497 | K18: 9.04 | L18: 15034.7 | M18: 1461.3 | N18: 1 | O18: =I18+N18 -> 2
A19: 17 | B19: Software Tally TRAG Serial no. 716653026 | C19: 2019/SOF/0015 | D19: Trashigang PO | E19: 20/10/2019 | F19: THINLEY ZANGMO | G19: 5 | H19: 16498 | I19: 1 | J19: 16497 | K19: 9.04 | L19: 15021.14 | M19: 1474.86 | N19: 1 | O19: =I19+N19 -> 2
A20: 18 | B20: Software Tally TYSE Serial No. 796653027 | C20: 2019/SOF/0016 | D20: Trashiyangtse PO | E20: 20/10/2019 | F20: PEMA DORJI | G20: 5 | H20: 16498 | I20: 1 | J20: 16497 | K20: 9.04 | L20: 15021.14 | M20: 1474.86 | N20: 1 | O20: =I20+N20 -> 2
A21: 19 | B21: Software Tally DUSM Serial No. 786653028 | C21: 2019/SOF/0017 | D21: Doksum PO | E21: 20/10/2019 | F21: CHETEN NORBU | G21: 5 | H21: 16498 | I21: 1 | J21: 16497 | K21: 9.04 | L21: 15021.14 | M21: 1474.86 | N21: 1 | O21: =I21+N21 -> 2
A22: 20 | B22: Software Tally WRMG Serial No. 776653029 | C22: 2019/SOF/0018 | D22: Wamrong PO | E22: 20/10/2019 | F22: NETEN DORJI | G22: 5 | H22: 16498 | I22: 1 | J22: 16497 | K22: 9.04 | L22: 15021.14 | M22: 1474.86 | N22: 1 | O22: =I22+N22 -> 2
A23: 21 | B23: Software Tally KNLG Serial No. 766653030 | C23: 2019/SOF/0019 | D23: Kanglung PO | E23: 20/10/2019 | F23: CHUNDU DORJI | G23: 5 | H23: 16498 | I23: 1 | J23: 16497 | K23: 9.04 | L23: 15021.14 | M23: 1474.86 | N23: 1 | O23: =I23+N23 -> 2
A24: 22 | B24: Software Tally HAA Serial No. 756653031 | C24: 2019/SOF/0020 | D24: Haa PO | E24: 27/11/2019 | F24: SONAM | G24: 5 | H24: 16498 | I24: 1 | J24: 16497 | K24: 9.04 | L24: 14506.32 | M24: 1636.24 | N24: 354.44 | O24: =I24+N24 -> 355.44
A25: 23 | B25: Software Tally SJKA Serial No. 785559816 | C25: 2019/SOF/0035 | D25: Samdrupcholing PO | E25: 43505 | F25: PEMA DEKI | G25: 5 | H25: 50976 | I25: 1 | J25: 50975 | K25: 27.93 | L25: 48421.96 | M25: 2552.04 | N25: 1 | O25: =I25+N25 -> 2
A26: 24 | B26: Software Tally PUNA Serial No. 786621096 | C26: 2019/SOF/0036 | D26: Punakha PO | E26: 25/11/2019 | F26: SONAM PELDON | G26: 5 | H26: 16992 | I26: 1 | J26: 16991 | K26: 9.31 | L26: 14968.34 | M26: 1685.11 | N26: 337.55 | O26: =I26+N26 -> 338.55
A27: 25 | B27: Software Tally WANG Serial No. 776621097 | C27: 2019/SOF/0037 | D27: Wangdue PO | E27: 26/11/2019 | F27: UGYEN WANGMO | G27: 5 | H27: 16992 | I27: 1 | J27: 16991 | K27: 9.31 | L27: 14954.4 | M27: 1685.11 | N27: 351.49 | O27: =I27+N27 -> 352.49
A28: 26 | B28: Software Tally GELA Serial No. 775559817 | C28: 2020/SOF/0001 | D28: Gelephu GPO | E28: 20/01/2019 | F28: SARMILLA CHHETRI | G28: 5 | H28: 50976 | I28: 1 | J28: 50975 | K28: 27.93 | L28: 42979.5 | M28: 5055.33 | N28: 2940.17 | O28: =I28+N28 -> 2941.17
A29: 27 | B29: Software Tally DGNA Serial No. 746653086 | C29: 2020/SOF/0002 | D29: Dagana PO | E29: 15/01/2020 | F29: SANGAY CHOZOM | G29: 5 | H29: 19950 | I29: 1 | J29: 19949 | K29: 10.93 | L29: 16861.1 | M29: 1978.33 | N29: 1109.57 | O29: =I29+N29 -> 1110.57
A30: 28 | B30: Software Tally TSIR Serial No. 736653087 | C30: 2020/SOF/0004 | D30: Tsirang PO | E30: 17/01/2020 | F30: MAYA DEVI BASKOTA | G30: 5 | H30: 19950 | I30: 1 | J30: 19949 | K30: 10.93 | L30: 16844.7 | M30: 1978.33 | N30: 1125.97 | O30: =I30+N30 -> 1126.97
A31: 29 | B31: Software Tally SARA Serial No. 726653088 | C31: 2020/SOF/0006 | D31: Sarpang PO | E31: 18/01/2020 | F31: CHABILAL CHAPAGAI | G31: 5 | H31: 19950 | I31: 1 | J31: 19949 | K31: 10.93 | L31: 16836.5 | M31: 1978.33 | N31: 1134.17 | O31: =I31+N31 -> 1135.17
A32: 30 | B32: Software Tally PANG Serial No. 716653089 | C32: 2020/SOF/0008 | D32: Panbang PO | E32: 24/01/2020 | F32: RINCHEN CHODA | G32: 5 | H32: 19950 | I32: 1 | J32: 19949 | K32: 10.93 | L32: 16787.31 | M32: 1978.33 | N32: 1183.36 | O32: =I32+N32 -> 1184.36
A33: 31 | B33: Software Tally ZEMG Serial No. 796653090 | C33: 2020/SOF/0010 | D33: Zhemgang PO | E33: 25/01/2020 | F33: SONAM DORJI | G33: 5 | H33: 19950 | I33: 1 | J33: 19949 | K33: 10.93 | L33: 16779.11 | M33: 1978.33 | N33: 1191.56 | O33: =I33+N33 -> 1192.56
A34: 32 | B34: Software Tally TRON Serial No. 786653091 | C34: 2020/SOF/0012 | D34: Trongsa PO | E34: 26/01/2020 | F34: TSHECHEY WANGMO | G34: 5 | H34: 19950 | I34: 1 | J34: 19949 | K34: 10.93 | L34: 16770.91 | M34: 1978.33 | N34: 1199.76 | O34: =I34+N34 -> 1200.76
A35: 33 | B35: Software Tally CHMY Serial No. 776653092 | C35: 2020/SOF/0014 | D35: Bumthang PO | E35: 27/01/2020 | F35: DAWA GYELPO | G35: 5 | H35: 19950 | I35: 1 | J35: 19949 | K35: 10.93 | L35: 16762.71 | M35: 1978.33 | N35: 1207.96 | O35: =I35+N35 -> 1208.96
A36: 34 | B36: Software Tally BUMA Serial No. 766653093 | C36: 2020/SOF/0016 | D36: Bumthang PO | E36: 43894 | F36: DAWA GYELPO | G36: 5 | H36: 19950 | I36: 1 | J36: 19949 | K36: 10.93 | L36: 16213.41 | M36: 1978.33 | N36: 1757.26 | O36: =I36+N36 -> 1758.26
A37: 35 | B37: Software Tally TING Serial No. 746653095 | C37: 2020/SOF/0018 | D37: Zhemgang PO | E37: 36710 | F37: SONAM DORJI | G37: 5 | H37: 19950 | I37: 1 | J37: 19949 | K37: 10.93 | L37: 16180.61 | M37: 1978.33 | N37: 1790.06 | O37: =I37+N37 -> 1791.06
A38: 36 | B38: Software Tally GASA Serial No. 736653096 | C38: 2020/SOF/0020 | D38: Gasa PO | E38: 22/04/2020 | F38: UGYEN PHUNTSHO | G38: 5 | H38: 19950 | I38: 1 | J38: 19949 | K38: 10.93 | L38: 16057.63 | M38: 1978.33 | N38: 1913.04 | O38: =I38+N38 -> 1914.04
A39: 37 | B39: Software Tally DPLA Serial No. 726653097 | C39: 2020/SOF/0022 | D39: Dagapela PO | E39: 43835 | F39: INDRA BDR DHITAL | G39: 5 | H39: 19950 | I39: 1 | J39: 19949 | K39: 10.93 | L39: 15983.84 | M39: 1978.33 | N39: 1986.83 | O39: =I39+N39 -> 1987.83
A40: 38 | B40: Software Tally KHAI Serial No. 786653100 | C40: 2020/SOF/0024 | D40: Samdrupcholing PO | E40: 30/04/2020 | F40: PEMA DEKI | G40: 5 | H40: 19950 | I40: 1 | J40: 19949 | K40: 10.93 | L40: 15992.04 | M40: 1978.33 | N40: 1978.63 | O40: =I40+N40 -> 1979.63
A41: 39 | B41: Software Tally RJNG Serial No. 756653094 | C41: 2020/SOF/0026 | D41: Rangjung PO | E41: 43894 | F41: KINZANG THINLEY | G41: 5 | H41: 19950 | I41: 1 | J41: 19949 | K41: 10.93 | L41: 16213.41 | M41: 1978.33 | N41: 1757.26 | O41: =I41+N41 -> 1758.26
A42: 40 | B42: Software Tally PARO Airport Serial No. 796653099 | C42: 2022/SOF/0001 | D42: Paro PO | E42: 18/04/2021 | F42: KARMA WANGCHUK | G42: 5 | H42: 19950 | I42: 1 | J42: 19949 | K42: 10.93 | L42: 9908.66 | M42: 1978.33 | N42: 8062.01 | O42: =I42+N42 -> 8063.01
A43: 41 | B43: Software Tally CNF PKHA Serial No. 726653079 | C43: 2022/SOF/0003 | D43: Phuntsholing GPO | E43: 44900 | F43: DAWA | G43: 5 | H43: 19950 | I43: 1 | J43: 19949 | K43: 10.93 | L43: 9908.66 | M43: 1978.33 | N43: 8062.01 | O43: =I43+N43 -> 8063.01
A44: 42 | B44: Software Tally CNF PHUA Serial No. 716653080 | C44: 2022/SOF/0005 | D44: Phuntsholing GPO | E44: 44900 | F44: DAWA | G44: 5 | H44: 19950 | I44: 1 | J44: 19949 | K44: 10.93 | L44: 9908.65 | M44: 1978.33 | N44: 8062.02 | O44: =I44+N44 -> 8063.02
A45: 43 | B45: Software Tally DZNG Serial No. 716653098 | C45: 2021/SOF/0002 | D45: Tashichodzong PO | E45: 16/07/2021 | F45: RUIS KUMAR GHALLEY | G45: 5 | H45: 19950 | I45: 1 | J45: 19949 | K45: 10.93 | L45: 12597.81 | M45: 1978.33 | N45: 5372.86 | O45: =I45+N45 -> 5373.86
H46: =sum(H3:H45) -> 1225730 | J46: =sum(J3:J45) -> 1225687 | L46: =sum(L3:L45) -> 1110145.7 | M46: =sum(M3:M45) -> 62641.28 | N46: =sum(N3:N45) -> 52899.98 | O46: =SUM(O3:O45) -> 52942.98

Sheet Annex 3A EQP Physical not avail
A1: EQP Physicall not Available but recorded in the system
A2: HQ
A3: # | B3: Assets | C3: Asset ID | D3: Location | E3: Put-in Use Date | F3: Custodian | G3: Useful Life | H3: Gross Value | I3: Salvage Value | J3: Depreciable Amt | K3: Dep per Day | L3: Opening Dep | M3: Depreciation | N3: Net Value | O3: Salvage + net value
A4: 1 | B4: Laptop | C4: 2016/EQP/0064 | D4: Postal Service | E4: 42606 | F4: KEZANG CHODEN | G4: 5 | H4: 38790 | I4: 0 | J4: 38790 | K4: 21.25 | L4: 38789 | M4: 0 | N4: 1 | O4: =I4+N4 -> 1
A5: 2 | B5: Computer | C5: 2010/EQP/0013 | D5: Philately Sales | E5: 40389 | F5: NIMA ZANGMO | G5: 5 | H5: 34827 | I5: 0 | J5: 34827 | K5: 19.08 | L5: 34826 | M5: 0 | N5: 1 | O5: =I5+N5 -> 1
O6: =I6+N6 -> 0
A7: WR | O7: =I7+N7 -> 0
A8: 1 | B8: Tracker Device | C8: 2018/EQP/0176 | D8: Thimphu GPO | E8: 43458 | F8: LHAM WANGCHUK | G8: 5 | H8: 11400 | I8: 228 | J8: 11172 | K8: 6.12 | L8: 9641.77 | M8: 1297.44 | N8: 232.79 | O8: =I8+N8 -> 460.79
A9: 2 | B9: Tracker Device | C9: 2018/EQP/0177 | D9: Thimphu GPO | E9: 43458 | F9: LHAM WANGCHUK | G9: 5 | H9: 11400 | I9: 228 | J9: 11172 | K9: 6.12 | L9: 9641.77 | M9: 1297.44 | N9: 232.79 | O9: =I9+N9 -> 460.79
O10: =I10+N10 -> 0
A11: SR | O11: =I11+N11 -> 0
A12: 1 | B12: Tracker Device | C12: 2018/EQP/0179 | D12: Phuntsholing GPO | E12: 43458 | F12: CHANDRA BAHADUR SUBBA | G12: 5 | H12: 11400 | I12: 228 | J12: 11172 | K12: 6.12 | L12: 9641.77 | M12: 1297.44 | N12: 232.79 | O12: =I12+N12 -> 460.79
O13: =SUM(O4:O12) -> 1384.37

Sheet Annex 3B Grant not ava but reco
A1: FNF Physicall not Available but recorded in the system
A3: # | B3: Assets | C3: Asset ID | D3: Location | E3: Put-in Use Date | F3: Custodian | G3: Useful Life | H3: Gross Value | I3: Salvage Value | J3: Depreciable Amt | K3: Dep per Day | L3: Opening Dep | M3: Depreciation | N3: Net Value | O3: Salvage + net value
A4: SR | O4: =I4+N4 -> 0
A5: 1 | B5: BIKE BG-29172 | C5: 2010/GRA/0002 | D5: Samtse PO | E5: 40499 | F5: JIT BDR RAI | G5: 6 | H5: 62932.14 | I5: 0 | J5: 62932.14 | K5: 28.74 | L5: 62931.14 | M5: 0 | N5: 1 | O5: =I5+N5 -> 1
O6: =I6+N6 -> 0
A7: CR | O7: =I7+N7 -> 0
A8: 1 | B8: BIKE BG-2A-0396 | C8: 2010/GRA/0003 | D8: Zhemgang PO | E8: 40499 | F8: SONAM DORJI | G8: 6 | H8: 62932.14 | I8: 0 | J8: 62932.14 | K8: 28.74 | L8: 62931.14 | M8: 0 | N8: 1 | O8: =I8+N8 -> 1
O9: =I9+N9 -> 0
A10: ER | O10: =I10+N10 -> 0
A11: 1 | B11: BIKE BG-2A-0394 | C11: 2010/GRA/0005 | D11: Trashigang PO | E11: 40499 | F11: KARMA DUPCHU | G11: 6 | H11: 62932.14 | I11: 0 | J11: 62932.14 | K11: 28.74 | L11: 62931.14 | M11: 0 | N11: 1 | O11: =I11+N11 -> 1
A12: 2 | B12: BIKE BG-2-A0489 | C12: 2010/GRA/0008 | D12: Jomotshangkha PO | E12: 40499 | F12: KINZANG NORBU | G12: 6 | H12: 62932.14 | I12: 0 | J12: 62932.14 | K12: 28.74 | L12: 62931.14 | M12: 0 | N12: 1 | O12: =I12+N12 -> 1
A13: 3 | B13: BIKE BG-2A-0490 | C13: 2010/GRA/0007 | D13: Doksum PO | E13: 40499 | F13: CHETEN NORBU | G13: 6 | H13: 62932.14 | I13: 0 | J13: 62932.14 | K13: 28.74 | L13: 62931.14 | M13: 0 | N13: 1 | O13: =I13+N13 -> 1
O14: =SUM(O4:O13) -> 5

Sheet Annex 3C Tally Software Writeof
A1: Tally Software Writeoff
A2: Sl. No. | B2: Assets | C2: Asset ID | D2: Location | E2: Put-in Use Date | F2: Custodian | G2: Useful Life | H2: Gross Value | I2: Salvage Value | J2: Depreciable Amt | K2: Dep per Day | L2: Opening Dep | M2: Depreciation | N2: Net Value | O2: Salvage + Net Value
A3: 1 | B3: Software Customization & Implementation | C3: 2017/SOF/0001 | D3: Finance & Investment | E3: 27/11/2017 | F3: UGYEN CHOPHEL | G3: 5 | H3: 754800 | I3: 1 | J3: 754799 | K3: 413.59 | L3: 721061.3 | M3: 33736.7 | N3: 1 | O3: =I3+N3 -> 2
A4: 2 | B4: Software Tally User Licence Connectivity | C4: 2017/SOF/0005 | D4: Finance & Investment | E4: 42948 | F4: THINLEY TOBGAY | G4: 5 | H4: 17900 | I4: 1 | J4: 17899 | K4: 9.81 | L4: 17898 | M4: 0 | N4: 1 | O4: =I4+N4 -> 2
A5: 3 | B5: Software Tally User Licence Connectivity | C5: 2019/SOF/0021 | D5: Jomotshangkha PO | E5: 43594 | F5: KINZANG NORBU | G5: 5 | H5: 2750 | I5: 1 | J5: 2749 | K5: 1.51 | L5: 2606.36 | M5: 141.64 | N5: 1 | O5: =I5+N5 -> 2
A6: 4 | B6: Software Tally User Licence Connectivity | C6: 2019/SOF/0022 | D6: Nganglam PO | E6: 43717 | F6: NORBU | G6: 5 | H6: 2750 | I6: 1 | J6: 2749 | K6: 1.51 | L6: 2597.32 | M6: 150.68 | N6: 1 | O6: =I6+N6 -> 2
A7: 5 | B7: Software Tally User Licence Connectivity | C7: 2019/SOF/0023 | D7: Samdrup Jongkhar GPO | E7: 43747 | F7: PEMA DEKI | G7: 5 | H7: 2750 | I7: 1 | J7: 2749 | K7: 1.51 | L7: 2595.06 | M7: 152.94 | N7: 1 | O7: =I7+N7 -> 2
A8: 6 | B8: Software Tally User Licence Connectivity | C8: 2019/SOF/0024 | D8: Samdrupcholing PO | E8: 43808 | F8: RINCHEN TSHERING | G8: 5 | H8: 2750 | I8: 1 | J8: 2749 | K8: 1.51 | L8: 2590.56 | M8: 157.44 | N8: 1 | O8: =I8+N8 -> 2
A9: 7 | B9: Software Tally User Licence Connectivity | C9: 2019/SOF/0025 | D9: Pemagatshel PO | E9: 14/09/2019 | F9: PHUNTSHO DORJI | G9: 5 | H9: 2750 | I9: 1 | J9: 2749 | K9: 1.51 | L9: 2586.04 | M9: 161.96 | N9: 1 | O9: =I9+N9 -> 2
A10: 8 | B10: Software Tally User Licence Connectivity | C10: 2019/SOF/0026 | D10: Gyelposhing PO | E10: 17/10/2019 | F10: KUENGA YESHI | G10: 5 | H10: 2750 | I10: 1 | J10: 2749 | K10: 1.51 | L10: 2511.54 | M10: 236.46 | N10: 1 | O10: =I10+N10 -> 2
A11: 9 | B11: Software Tally User Licence Connectivity | C11: 2019/SOF/0027 | D11: Mongar PO | E11: 19/10/2019 | F11: PEMA YANGDON | G11: 5 | H11: 2750 | I11: 1 | J11: 2749 | K11: 1.51 | L11: 2507.02 | M11: 240.98 | N11: 1 | O11: =I11+N11 -> 2
A12: 10 | B12: Software Tally User Licence Connectivity | C12: 2019/SOF/0028 | D12: Lhuntse PO | E12: 19/10/2019 | F12: UGYEN | G12: 5 | H12: 2750 | I12: 1 | J12: 2749 | K12: 1.51 | L12: 2507.02 | M12: 240.98 | N12: 1 | O12: =I12+N12 -> 2
A13: 11 | B13: Software Tally User Licence Connectivity | C13: 2019/SOF/0029 | D13: Trashigang PO | E13: 20/10/2019 | F13: THINLEY ZANGMO | G13: 5 | H13: 2750 | I13: 1 | J13: 2749 | K13: 1.51 | L13: 2504.76 | M13: 243.24 | N13: 1 | O13: =I13+N13 -> 2
A14: 12 | B14: Software Tally User Licence Connectivity | C14: 2019/SOF/0030 | D14: Trashiyangtse PO | E14: 20/10/2019 | F14: PEMA DORJI | G14: 5 | H14: 2750 | I14: 1 | J14: 2749 | K14: 1.51 | L14: 2504.76 | M14: 243.24 | N14: 1 | O14: =I14+N14 -> 2
A15: 13 | B15: Software Tally User Licence Connectivity | C15: 2019/SOF/0031 | D15: Doksum PO | E15: 20/10/2019 | F15: CHETEN NORBU | G15: 5 | H15: 2750 | I15: 1 | J15: 2749 | K15: 1.51 | L15: 2504.76 | M15: 243.24 | N15: 1 | O15: =I15+N15 -> 2
A16: 14 | B16: Software Tally User Licence Connectivity | C16: 2019/SOF/0032 | D16: Wamrong PO | E16: 20/10/2019 | F16: NETEN DORJI | G16: 5 | H16: 2750 | I16: 1 | J16: 2749 | K16: 1.51 | L16: 2504.76 | M16: 243.24 | N16: 1 | O16: =I16+N16 -> 2
A17: 15 | B17: Software Tally User Licence Connectivity | C17: 2019/SOF/0033 | D17: Kanglung PO | E17: 20/10/2019 | F17: CHUNDU DORJI | G17: 5 | H17: 2750 | I17: 1 | J17: 2749 | K17: 1.51 | L17: 2504.76 | M17: 243.24 | N17: 1 | O17: =I17+N17 -> 2
A18: 16 | B18: Software Tally User Licence Connectivity | C18: 2019/SOF/0034 | D18: Haa PO | E18: 27/11/2019 | F18: SONAM | G18: 5 | H18: 2750 | I18: 1 | J18: 2749 | K18: 1.51 | L18: 2418.98 | M18: 273.31 | N18: 56.71 | O18: =I18+N18 -> 57.71
A19: 17 | B19: Software Tally User Licence Connectivity | C19: 2020/SOF/0003 | D19: Dagana PO | E19: 15/01/2020 | F19: SANGAY CHOZOM | G19: 5 | H19: 4000 | I19: 1 | J19: 3999 | K19: 2.19 | L19: 3379.97 | M19: 396.39 | N19: 222.64 | O19: =I19+N19 -> 223.64
A20: 18 | B20: Software Tally User Licence Connectivity | C20: 2020/SOF/0005 | D20: Tsirang PO | E20: 17/01/2020 | F20: MAYA DEVI BASKOTA | G20: 5 | H20: 4000 | I20: 1 | J20: 3999 | K20: 2.19 | L20: 3376.68 | M20: 396.39 | N20: 225.93 | O20: =I20+N20 -> 226.93
... A25: 23 | B25: Software Tally User Licence Connectivity | C25: 2020/SOF/0015 | D25: Bumthang PO | E25: 27/01/2020 | F25: DAWA GYELPO | G25: 5 | H25: 4000 | I25: 1 | J25: 3999 | K25: 2.19 | L25: 3360.24 | M25: 396.39 | N25: 242.37 | O25: =I25+N25 -> 243.37
A26: 24 | B26: Software Tally User Licence Connectivity | C26: 2020/SOF/0017 | D26: Bumthang PO | E26: 43924 | F26: DAWA GYELPO | G26: 5 | H26: 4000 | I26: 1 | J26: 3999 | K26: 2.19 | L26: 3250.11 | M26: 396.39 | N26: 352.5 | O26: =I26+N26 -> 353.5
A27: 25 | B27: Software Tally User Licence Connectivity | C27: 2020/SOF/0019 | D27: Zhemgang PO | E27: 44016 | F27: SONAM DORJI | G27: 5 | H27: 4000 | I27: 1 | J27: 3999 | K27: 2.19 | L27: 3243.53 | M27: 396.39 | N27: 359.08 | O27: =I27+N27 -> 360.08
A28: 26 | B28: Software Tally User Licence Connectivity | C28: 2020/SOF/0021 | D28: Gasa PO | E28: 22/04/2020 | F28: UGYEN PHUNTSHO | G28: 5 | H28: 4000 | I28: 1 | J28: 3999 | K28: 2.19 | L28: 3218.87 | M28: 396.39 | N28: 383.74 | O28: =I28+N28 -> 384.74
A29: 27 | B29: Software Tally User Licence Connectivity | C29: 2020/SOF/0023 | D29: Dagapela PO | E29: 43835 | F29: INDRA BDR DHITAL | G29: 5 | H29: 4000 | I29: 1 | J29: 3999 | K29: 2.19 | L29: 3204.08 | M29: 396.39 | N29: 398.53 | O29: =I29+N29 -> 399.53
A30: 28 | B30: Software Tally User Licence Connectivity | C30: 2020/SOF/0025 | D30: Samdrupcholing PO | E30: 30/04/2022 | F30: PEMA DEKI | G30: 5 | H30: 4000 | I30: 1 | J30: 3999 | K30: 2.19 | L30: 3205.72 | M30: 396.39 | N30: 396.89 | O30: =I30+N30 -> 397.89
A31: 29 | B31: Software Tally User Licence Connectivity | C31: 2020/SOF/0027 | D31: Rangjung PO | E31: 43894 | F31: KINZANG THINLEY | G31: 5 | H31: 4000 | I31: 1 | J31: 3999 | K31: 2.19 | L31: 3250.11 | M31: 396.39 | N31: 352.5 | O31: =I31+N31 -> 353.5
A32: 30 | B32: Software Tally User Licence Connectivity | C32: 2022/SOF/0002 | D32: Paro PO | E32: 16/06/2021 | F32: KARMA WANGCHUK | G32: 5 | H32: 4000 | I32: 1 | J32: 3999 | K32: 2.19 | L32: 1986 | M32: 396.39 | N32: 1616.61 | O32: =I32+N32 -> 1617.61
A33: 31 | B33: Software Tally User Licence Connectivity | C33: 2022/SOF/0004 | D33: Phuntsholing GPO | E33: 44900 | F33: DAWA | G33: 5 | H33: 4000 | I33: 1 | J33: 3999 | K33: 2.19 | L33: 1986 | M33: 396.39 | N33: 1616.61 | O33: =I33+N33 -> 1617.61
A34: 32 | B34: Software Tally User Licence Connectivity | C34: 2022/SOF/0006 | D34: Phuntsholing GPO | E34: 44900 | F34: DAWA | G34: 5 | H34: 4000 | I34: 1 | J34: 3999 | K34: 2.19 | L34: 1986 | M34: 396.39 | N34: 1616.61 | O34: =I34+N34 -> 1617.61
A35: 33 | B35: Software Tally User Licence Connectivity | C35: 2021/SOF/0003 | D35: Tashichodzong PO | E35: 21/07/2021 | F35: RUIS KUMAR GHALLEY | G35: 5 | H35: 4000 | I35: 1 | J35: 3999 | K35: 2.19 | L35: 2479.15 | M35: 396.39 | N35: 1123.46 | O35: =I35+N35 -> 1124.46
H36: =sum(H3:H35) -> 879200 | J36: =sum(J3:J35) -> 879167 | L36: =sum(L3:L35) -> 825795.1 | M36: =sum(M3:M35) -> 43447.92 | N36: =sum(N3:N35) -> 9923.98 | O36: =SUM(O3:O35) -> 9956.98
